Workbook

Sheet 总览
A1: ShellStorm2 游戏内容数据库 v0.1
A2: 设计、内容与实现状态的中央索引｜最后校对：2026-08-27｜正式入口：TowerDescent3D.tscn
A3: 绿色字体=已实装；蓝色字体=用户设计；橙色字体=Codex补充。条目存在不等于全部表现与数值已通过最终QA。
A5: 工作表 | B5: 当前条目 | C5: 已实装 | D5: 用户设计 | E5: Codex补充 | F5: 对应系统 | G5: 主要用途 | H5: 维护提示
A6: 武器 | B6: 24 | C6: 24 | D6: 0 | E6: 0 | F6: 系统2/5 | G6: 7远程枪身、3近战、8子弹、6配件、数值、价格和产出 | H6: WeaponInstance统一承载远近战；六公共枪械配件位置固定、兼容子集禁用、单拆/整枪随行；棒球棍为基地初级近战
A7: 命运卡 | B7: 78 | C7: 48 | D7: 30 | E7: 0 | F7: 系统2/6 | G7: 78张塔罗命运：22大+56小阿尔卡那；正/逆位功能、概率和翻牌UI设计 | H7: 目标分布36星星/21月亮/21太阳。48张现有卡已完成塔罗命名、正逆位效果快照和代码翻牌；30张新增卡执行器待施工
A8: 怪物与Boss | B8: =COUNTA('怪物与Boss'!$A$5:$A$204) | C8: =COUNTIF('怪物与Boss'!$L$5:$L$204,"[已实装]") | D8: =COUNTIF('怪物与Boss'!$L$5:$L$204,"[用户设计]") | E8: =COUNTIF('怪物与Boss'!$L$5:$L$204,"[Codex补充]") | F8: 系统3/4 | G8: 正式3D敌人基线、技能与刷新 | H8: 不要混入旧2D生命基线
A9: 精英怪 | B9: 12 | C9: 1 | D9: 11 | E9: 0 | F9: 系统4/7 | G9: 12只唯一精英定义；当前正式内容1/12 | H9: 首只背枪的裂口爬虫已投放98—96F并完成残血逃脱、击杀玩家归因、12级成长、副枪频率、夺械转译和悬赏兑现；其余11只design_only
A10: 掉落物品 | B10: 45 | C10: 38 | D10: 7 | E10: 0 | F10: 系统2/3/5/7 | G10: 物品、价格、稀有度和掉落池 | H10: 武器成品保留实例构筑；新增基地初级棒球棍；3种背包装备提供2/4/8扩展格；电池与贩卖机ID已对齐
A12: 七大系统与文档定位
A13: 编号 | B13: 核心系统 | C13: 主内容表 | D13: 设计状态 | E13: 实现状态 | F13: P0焦点 | G13: 主施工文档 | H13: 备注
A14: 1 | B14: 玩家状态机与操作 | C14: — | D14: 已冻结 | E14: 正式3D较完整 | F14: 交互仲裁/状态诊断 | G14: 03_技术施工_玩家与操作.md | H14: 视觉根与玩法根分离
A15: 2 | B15: 战斗/武器/子弹/命运卡 | C15: 武器/命运卡 | D15: 已冻结 | E15: 正式3D核心闭环已验收（含3近战/统一配件槽） | F15: 最终近战武器美术/配件专属模型/逐卡表现QA | G15: 04_技术施工_战斗与局内成长.md | H15: 构筑随具体武器实例；7远程+3近战；六公共配件位置固定，枪型开放兼容子集
A16: 3 | B16: 关卡生成与爬楼 | C16: 怪物/掉落 | D16: Boss路线新设定已冻结 | E16: 当前生成可用 | F16: 专钥匙/专门门/Boss后电梯 | G16: 05_技术施工_关卡生成与爬楼.md | H16: 整层一次冻结
A17: 4 | B17: 怪物/精英/Boss | C17: 怪物/精英怪 | D17: 12精英已冻结 | E17: 唯一系统完成；正式精英内容1/12 | F17: 剩余11只独立内容与投放 | G17: 06_技术施工_怪物精英与Boss.md | H17: 定义/档案/表现已解耦；未完成精英不进入随机池
A18: 5 | B18: 基地设施 | C18: 多表引用 | D18: 已冻结 | E18: 八设施可用 | F18: 精英档案/设施服务化 | G18: 07_技术施工_基地设施.md | H18: UI不直接写存档
A19: 6 | B19: 剧情触发 | C19: 后续剧情表 | D19: 系统边界已冻结 | E19: 基础NPC/事件 | F19: 独立触发服务 | G19: 08_技术施工_剧情触发.md | H19: 不擅自补写主线
A20: 7 | B20: 存档/结算/复活 | C20: 精英/掉落 | D20: 边界已冻结 | E20: 基地/结算与武器实例迁移可用 | F20: 结算幂等/复活策略 | G20: 09_技术施工_存档结算与复活.md | H20: 复活政策尚未冻结
A22: 发布前检查：稳定ID唯一｜78张卡名唯一｜22大+56小｜36/21/21作用域｜正/逆各50%｜逆位整卡倒置｜旧存档不重投｜实现状态真实

Sheet 武器
A1: ShellStorm2 游戏内容数据库｜武器
A2: 正式注册：7远程枪身、2大型近战武器、8子弹、6配件。独立WeaponInstance与普通武器8命运槽已实装；近战四态/三段/命中闭环已验收，逐条最终美术与专属音频继续QA。
A3: 字体颜色：绿色=已实装；蓝色=用户设计；橙色=Codex补充。实现状态需结合事实源判断。
A4: 内容ID | B4: 类别 | C4: 名称 | D4: 蓝图Tier | E4: 稀有度 | F4: 价格 | G4: 核心数值 | H4: 功能 | I4: 特殊效果/标签 | J4: 产出与掉落 | K4: 状态来源 | L4: 实现状态 | M4: 事实源 | N4: 备注 | O4: 基础命运槽 | P4: 实例/装配规则 | Q4: 新设计实现状态 | R4: 功能UI提示 | S4: 武器/战斗表现 | T4: 表现实现状态 | U4: 基地购买价 | V4: 基地出售价 | W4: 基地商店上架 | X4: 基地库存规则 | Y4: 基地货架顺序
A5: attach_big_mag | B5: 配件 | C5: 肉质弹匣 | D5: 1 | E5: uncommon | F5: 80 | G5: magazine_size=15 | H5: 装配后提供magazine_size=15；修饰方向：heal、capacity | I5: 标签：magazine、heal、capacity | J5: combat_floor_1×2.5；combat_floor_2×3；loot_abyss×2；loot_floor_3_4×2；loot_floor_5×2.5；scavenge_floor_3×2；scavenge_floor_4×2.5；scavenge_floor_5×2 | K5: [已实装] | L5: 正式注册；具体行为与表现仍需逐项QA | M5: src/base/BlueprintRegistry.gd；src/base/ItemRegistry.gd | P5: 可拆卸、可替换、可交易；不占命运槽；安装结果写入目标weapon_instance_id | Q5: [已实装] 可换装、不占命运槽，并随目标WeaponInstance完整保存/恢复 | R5: 弹匣槽显示容量/换弹差值与治疗触发说明；安装前后对比，注明可拆卸、不占命运槽 | S5: 更大弹匣实体与换弹动作同步；治疗触发时弹匣图标和绿色脉冲同时出现 | T5: [部分完成] 实例尾号、槽位、已装配件与命运刻印已可视；逐条专属VFX/音频仍待QA | U5: =IF(F5>0,F5,0) | V5: =IF(F5>0,ROUND(F5*0.5,0),0) | W5: FALSE | X5: not_listed | Y5: 0
A6: attach_copy_sticker | B6: 配件 | C6: 复制贴纸 | D6: 2 | E6: epic | F6: 200 | G6: copy_chance=0.25 | H6: 装配后提供copy_chance=0.25；修饰方向：copy、duplicate | I6: 标签：mutator、copy、duplicate | J6: boss_floor_1×3；boss_floor_2×4；combat_floor_3×1；combat_floor_4×1.5；combat_floor_5×2；loot_abyss×2；scavenge_floor_4×2；scavenge_floor_5×3 | K6: [已实装] | L6: 正式注册；具体行为与表现仍需逐项QA | M6: src/base/BlueprintRegistry.gd；src/base/ItemRegistry.gd | P6: 可拆卸、可替换、可交易；不占命运槽；安装结果写入目标weapon_instance_id | Q6: [已实装] 可换装、不占命运槽，并随目标WeaponInstance完整保存/恢复 | R6: 外接槽显示复制概率、可复制对象和触发条件；触发链显示来源与限制 | S6: 枪身出现实体贴纸；触发复制时产生对象残影、专属图标脉冲和短音效 | T6: [部分完成] 实例尾号、槽位、已装配件与命运刻印已可视；逐条专属VFX/音频仍待QA | U6: =IF(F6>0,F6,0) | V6: =IF(F6>0,ROUND(F6*0.5,0),0) | W6: FALSE | X6: not_listed | Y6: 0
A7: attach_fan | B7: 配件 | C7: 小风扇 | D7: 2 | E7: epic | F7: 150 | G7: pull_strength=0.5 | H7: 装配后提供pull_strength=0.5；修饰方向：pull、wind | I7: 标签：external、pull、wind | J7: boss_floor_1×3；combat_floor_3×1.5；combat_floor_4×2；combat_floor_5×2.5；loot_abyss×2.5；loot_floor_5×2；scavenge_floor_4×2；scavenge_floor_5×2.5 | K7: [已实装] | L7: 正式注册；具体行为与表现仍需逐项QA | M7: src/base/BlueprintRegistry.gd；src/base/ItemRegistry.gd | P7: 可拆卸、可替换、可交易；不占命运槽；安装结果写入目标weapon_instance_id | Q7: [已实装] 可换装、不占命运槽，并随目标WeaponInstance完整保存/恢复 | R7: 外接槽显示拉力强度、作用对象和范围；战斗HUD保留吸附行为图标 | S7: 小风扇叶片持续转动；受力对象显示朝向流线，触发点播放吸附短音 | T7: [部分完成] 实例尾号、槽位、已装配件与命运刻印已可视；逐条专属VFX/音频仍待QA | U7: =IF(F7>0,F7,0) | V7: =IF(F7>0,ROUND(F7*0.5,0),0) | W7: FALSE | X7: not_listed | Y7: 0
A8: attach_rubber_stock | B8: 配件 | C8: 橡皮枪托 | D8: 0 | E8: common | F8: 45 | G8: spread=-0.04 | H8: 装配后提供spread=-0.04；修饰方向：bounce | I8: 标签：stock、bounce | J8: combat_floor_1×2.5；combat_floor_2×2；loot_abyss×1.5；loot_floor_1_2×3；loot_floor_3_4×2.5；loot_floor_5×2；scavenge_floor_1×3；scavenge_floor_2×2.5；scavenge_floor_3×2；scavenge_floor_4×1.5；spawn_starter×3 | K8: [已实装] | L8: 正式注册；具体行为与表现仍需逐项QA | M8: src/base/BlueprintRegistry.gd；src/base/ItemRegistry.gd | P8: 可拆卸、可替换、可交易；不占命运槽；安装结果写入目标weapon_instance_id | Q8: [已实装] 可换装、不占命运槽，并随目标WeaponInstance完整保存/恢复 | R8: 枪托槽显示扩散变化和弹跳行为；提供准星散布前后对比 | S8: 橡胶枪托实体挂接；后坐/准星收束可见，弹跳命中显示方向折线 | T8: [部分完成] 实例尾号、槽位、已装配件与命运刻印已可视；逐条专属VFX/音频仍待QA | U8: =IF(F8>0,F8,0) | V8: =IF(F8>0,ROUND(F8*0.5,0),0) | W8: FALSE | X8: not_listed | Y8: 0
A9: attach_scope | B9: 配件 | C9: 放大镜瞄具 | D9: 1 | E9: rare | F9: 100 | G9: damage=5；spread=-0.05 | H9: 装配后提供damage=5；spread=-0.05；修饰方向：crit、accuracy | I9: 标签：scope、crit、accuracy | J9: combat_floor_2×1.5；combat_floor_3×2.5；loot_abyss×3；loot_floor_3_4×2；loot_floor_5×2.5；scavenge_floor_3×2；scavenge_floor_4×2.5；scavenge_floor_5×3 | K9: [已实装] | L9: 正式注册；具体行为与表现仍需逐项QA | M9: src/base/BlueprintRegistry.gd；src/base/ItemRegistry.gd | P9: 可拆卸、可替换、可交易；不占命运槽；安装结果写入目标weapon_instance_id | Q9: [已实装] 可换装、不占命运槽，并随目标WeaponInstance完整保存/恢复 | R9: 瞄具槽显示伤害、扩散/暴击来源和瞄准差值；注明兼容枪型 | S9: 实际瞄具模型、瞄准姿态与准星同步变化；暴击命中使用高亮反馈 | T9: [部分完成] 实例尾号、槽位、已装配件与命运刻印已可视；逐条专属VFX/音频仍待QA | U9: =IF(F9>0,F9,0) | V9: =IF(F9>0,ROUND(F9*0.5,0),0) | W9: FALSE | X9: not_listed | Y9: 0
A10: attach_triple_muzzle | B10: 配件 | C10: 三叉枪口 | D10: 0 | E10: uncommon | F10: 70 | G10: bullet_count=2；spread=0.08 | H10: 装配后提供bullet_count=2；spread=0.08；修饰方向：multi_shot | I10: 标签：muzzle、multi_shot | J10: combat_floor_1×2；combat_floor_2×1.5；loot_abyss×1；loot_floor_1_2×2.5；loot_floor_3_4×2；loot_floor_5×1.5；scavenge_floor_1×2.5；scavenge_floor_2×2；scavenge_floor_3×1.5；scavenge_floor_4×1；spawn_starter×2.5 | K10: [已实装] | L10: 正式注册；具体行为与表现仍需逐项QA | M10: src/base/BlueprintRegistry.gd；src/base/ItemRegistry.gd | P10: 可拆卸、可替换、可交易；不占命运槽；安装结果写入目标weapon_instance_id | Q10: [已实装] 可换装、不占命运槽，并随目标WeaponInstance完整保存/恢复 | R10: 枪口槽显示弹丸数与扩散差值，并预览弹道扇形 | S10: 三叉枪口实体；开火时多枪口火焰、多弹道和声层同步 | T10: [部分完成] 实例尾号、槽位、已装配件与命运刻印已可视；逐条专属VFX/音频仍待QA | U10: =IF(F10>0,F10,0) | V10: =IF(F10>0,ROUND(F10*0.5,0),0) | W10: FALSE | X10: not_listed | Y10: 0
A11: mod_bullet_balloon | B11: 子弹 | C11: 气球弹模块 | D11: 1 | E11: rare | F11: 90 | G11: bullet_damage=18；bullet_speed=0.5 | H11: 提供bullet_damage=18；bullet_speed=0.5；弹道/命中行为：balloon、slow、big | I11: 标签：bullet、balloon、slow、big | J11: combat_floor_3×1；combat_floor_4×1.5；loot_abyss×2；loot_floor_3_4×1.5；loot_floor_5×2；scavenge_floor_3×1.5；scavenge_floor_4×2；scavenge_floor_5×2 | K11: [已实装] | L11: 正式注册；具体行为与表现仍需逐项QA | M11: src/base/BlueprintRegistry.gd；src/base/ItemRegistry.gd | P11: 可更换子弹模块；不占命运槽；弹道配置写入目标weapon_instance_id | Q11: [已实装] 可换装、不占命运槽，并随目标WeaponInstance完整保存/恢复 | R11: 子弹页显示体积、伤害、速度差值和大型弹体标签 | S11: 膨胀弹体、较重尾迹与命中体积一致，不能只改伤害数值 | T11: [部分完成] 实例尾号、槽位、已装配件与命运刻印已可视；逐条专属VFX/音频仍待QA | U11: =IF(F11>0,F11,0) | V11: =IF(F11>0,ROUND(F11*0.5,0),0) | W11: FALSE | X11: not_listed | Y11: 0
A12: mod_bullet_blackhole | B12: 子弹 | C12: 黑洞弹模块 | D12: 2 | E12: epic | F12: 180 | G12: bullet_damage=12；bullet_speed=0.6 | H12: 提供bullet_damage=12；bullet_speed=0.6；弹道/命中行为：blackhole、pull | I12: 标签：bullet、blackhole、pull | J12: boss_floor_1×3；boss_floor_2×4；combat_floor_4×2；combat_floor_5×3；loot_abyss×2.5；scavenge_floor_4×2.5；scavenge_floor_5×4 | K12: [已实装] | L12: 正式注册；具体行为与表现仍需逐项QA | M12: src/base/BlueprintRegistry.gd；src/base/ItemRegistry.gd | P12: 可更换子弹模块；不占命运槽；弹道配置写入目标weapon_instance_id | Q12: [已实装] 可换装、不占命运槽，并随目标WeaponInstance完整保存/恢复 | R12: 显示伤害、速度、牵引范围/强度和受影响对象 | S12: 黑洞核心、吸入流线和范围边界清晰；命中/结束有收束反馈 | T12: [部分完成] 实例尾号、槽位、已装配件与命运刻印已可视；逐条专属VFX/音频仍待QA | U12: =IF(F12>0,F12,0) | V12: =IF(F12>0,ROUND(F12*0.5,0),0) | W12: FALSE | X12: not_listed | Y12: 0
A13: mod_bullet_bounce | B13: 子弹 | C13: 回旋镖弹模块 | D13: 0 | E13: uncommon | F13: 60 | G13: bullet_damage=7；bullet_speed=1.1 | H13: 提供bullet_damage=7；bullet_speed=1.1；弹道/命中行为：bounce、ricochet | I13: 标签：bullet、bounce、ricochet | J13: combat_floor_1×1.5；combat_floor_2×2；loot_abyss×2；loot_floor_1_2×1.5；loot_floor_3_4×2；loot_floor_5×2.5；scavenge_floor_1×1.5；scavenge_floor_2×2；spawn_starter×1.5 | K13: [已实装] | L13: 正式注册；具体行为与表现仍需逐项QA | M13: src/base/BlueprintRegistry.gd；src/base/ItemRegistry.gd | P13: 可更换子弹模块；不占命运槽；弹道配置写入目标weapon_instance_id | Q13: [已实装] 可换装、不占命运槽，并随目标WeaponInstance完整保存/恢复 | R13: 显示弹跳次数、可反弹表面和剩余次数 | S13: 反弹点有折线闪光与计数递减，飞行方向变化清楚可读 | T13: [部分完成] 实例尾号、槽位、已装配件与命运刻印已可视；逐条专属VFX/音频仍待QA | U13: =IF(F13>0,F13,0) | V13: =IF(F13>0,ROUND(F13*0.5,0),0) | W13: FALSE | X13: not_listed | Y13: 0
A14: mod_bullet_explosive | B14: 子弹 | C14: 爆炸弹模块 | D14: 1 | E14: rare | F14: 100 | G14: bullet_damage=28；bullet_speed=0.75 | H14: 提供bullet_damage=28；bullet_speed=0.75；弹道/命中行为：explosive、area | I14: 标签：bullet、explosive、area | J14: combat_floor_3×1；loot_abyss×2.5；loot_floor_3_4×1.5；loot_floor_5×2；scavenge_floor_3×1.5；scavenge_floor_4×2；scavenge_floor_5×2.5 | K14: [已实装] | L14: 正式注册；具体行为与表现仍需逐项QA | M14: src/base/BlueprintRegistry.gd；src/base/ItemRegistry.gd | P14: 可更换子弹模块；不占命运槽；弹道配置写入目标weapon_instance_id | Q14: [已实装] 可换装、不占命运槽，并随目标WeaponInstance完整保存/恢复 | R14: 显示爆炸伤害、半径和触发时机；地面预览危险圈 | S14: 弹体、尾迹、爆炸半径与伤害时点同步，低特效下保留轮廓圈 | T14: [部分完成] 实例尾号、槽位、已装配件与命运刻印已可视；逐条专属VFX/音频仍待QA | U14: =IF(F14>0,F14,0) | V14: =IF(F14>0,ROUND(F14*0.5,0),0) | W14: FALSE | X14: not_listed | Y14: 0
A15: mod_bullet_homing | B15: 子弹 | C15: 蜂卵弹模块 | D15: 2 | E15: epic | F15: 150 | G15: bullet_damage=10；bullet_speed=0.9 | H15: 提供bullet_damage=10；bullet_speed=0.9；弹道/命中行为：homing、summon | I15: 标签：bullet、homing、summon | J15: boss_floor_1×4；combat_floor_4×1.5；combat_floor_5×2.5；loot_abyss×3；loot_floor_5×2；scavenge_floor_4×2；scavenge_floor_5×3 | K15: [已实装] | L15: 正式注册；具体行为与表现仍需逐项QA | M15: src/base/BlueprintRegistry.gd；src/base/ItemRegistry.gd | P15: 可更换子弹模块；不占命运槽；弹道配置写入目标weapon_instance_id | Q15: [已实装] 可换装、不占命运槽，并随目标WeaponInstance完整保存/恢复 | R15: 显示追踪强度、锁定条件和当前目标标记 | S15: 锁定框、弯曲尾迹和转向动作一致；目标丢失有解除提示 | T15: [部分完成] 实例尾号、槽位、已装配件与命运刻印已可视；逐条专属VFX/音频仍待QA | U15: =IF(F15>0,F15,0) | V15: =IF(F15>0,ROUND(F15*0.5,0),0) | W15: FALSE | X15: not_listed | Y15: 0
A16: mod_bullet_piercing | B16: 子弹 | C16: 穿甲弹模块 | D16: 1 | E16: rare | F16: 80 | G16: bullet_damage=14；bullet_speed=1.4 | H16: 提供bullet_damage=14；bullet_speed=1.4；弹道/命中行为：piercing、armor | I16: 标签：bullet、piercing、armor | J16: combat_floor_3×1.5；loot_abyss×3；loot_floor_3_4×2；loot_floor_5×2.5；scavenge_floor_3×2；scavenge_floor_4×2.5；scavenge_floor_5×3 | K16: [已实装] | L16: 正式注册；具体行为与表现仍需逐项QA | M16: src/base/BlueprintRegistry.gd；src/base/ItemRegistry.gd | P16: 可更换子弹模块；不占命运槽；弹道配置写入目标weapon_instance_id | Q16: [已实装] 可换装、不占命运槽，并随目标WeaponInstance完整保存/恢复 | R16: 显示穿透等级、可穿对象和命中衰减规则 | S16: 穿透命中显示连续贯穿线与剩余层数，不在首个目标处假性消失 | T16: [部分完成] 实例尾号、槽位、已装配件与命运刻印已可视；逐条专属VFX/音频仍待QA | U16: =IF(F16>0,F16,0) | V16: =IF(F16>0,ROUND(F16*0.5,0),0) | W16: FALSE | X16: not_listed | Y16: 0
... A18: mod_bullet_sticky | B18: 子弹 | C18: 黏黏弹模块 | D18: 0 | E18: uncommon | F18: 50 | G18: bullet_damage=6；bullet_speed=0.8 | H18: 提供bullet_damage=6；bullet_speed=0.8；弹道/命中行为：sticky、dot | I18: 标签：bullet、sticky、dot | J18: combat_floor_1×2；combat_floor_2×2.5；loot_abyss×1.5；loot_floor_1_2×2；loot_floor_3_4×2.5；loot_floor_5×2；scavenge_floor_1×2；scavenge_floor_2×2.5；spawn_starter×2 | K18: [已实装] | L18: 正式注册；具体行为与表现仍需逐项QA | M18: src/base/BlueprintRegistry.gd；src/base/ItemRegistry.gd | P18: 可更换子弹模块；不占命运槽；弹道配置写入目标weapon_instance_id | Q18: [已实装] 可换装、不占命运槽，并随目标WeaponInstance完整保存/恢复 | R18: 显示黏附对象、持续/引爆条件与每秒效果 | S18: 命中后弹体留在表面并显示倒计时/状态，结束时反馈与结算同步 | T18: [部分完成] 实例尾号、槽位、已装配件与命运刻印已可视；逐条专属VFX/音频仍待QA | U18: =IF(F18>0,F18,0) | V18: =IF(F18>0,ROUND(F18*0.5,0),0) | W18: FALSE | X18: not_listed | Y18: 0
A19: bp_charge | B19: 枪身 | C19: 蓄力萝卜炮 | D19: 3 | E19: epic | F19: 350 | G19: bullet_count=1；charge_time=1.2；damage=30；fire_rate=1.5；magazine_size=4；reload_time=3；spread=0.05 | H19: 蓄力时间越长伤害越高，超蓄力后弹体变大并附带穿透。左键装备为当前主武器。 | I19: 标签：charge、蓄力、high_damage | J19: 成品：boss_floor_2×4；combat_floor_4×0.5；combat_floor_5×1；elite_floor_2×3；loot_abyss×2；loot_floor_5×0.8；scavenge_floor_4×0.4；scavenge_floor_5×1 蓝图：boss_floor_2×4；combat_floor_4×0.5；combat_floor_5×1；loot_abyss×2；scavenge_floor_5×0.5 | K19: [已实装] | L19: 正式注册；具体行为与表现仍需逐项QA | M19: src/base/BlueprintRegistry.gd；src/base/ItemRegistry.gd | N19: 装配ID=bp_charge；成品物品ID=weapon_charge；蓝图物品ID=bp_charge | O19: 8 | P19: 成品生成永久weapon_instance_id；命运槽、子弹模块与配件随实例在装备/背包/地面/商店/保险/存档间移动 | Q19: [已实装] 唯一实例ID、8槽基线、完整构筑/弹药/命运记录随枪转移与存档 | R19: HUD和详情显示蓄力阶段、当前倍率、超蓄力风险、弹量和换弹 | S19: 枪身能量逐级充盈、音高与震动递增；释放弹体大小和穿透随阶段变化 | T19: [部分完成] 实例尾号、槽位、已装配件与命运刻印已可视；逐条专属VFX/音频仍待QA | U19: =IF(F19>0,F19,0) | V19: =IF(F19>0,ROUND(F19*0.5,0),0) | W19: FALSE | X19: not_listed | Y19: 0
A20: bp_launcher | B20: 枪身 | C20: 反胃榴弹筒 | D20: 2 | E20: rare | F20: 250 | G20: bullet_count=1；damage=38；fire_rate=0.8；magazine_size=3；reload_time=4；spread=0.1 | H20: 发射爆炸弹，抛物线弹道，大范围AOE。左键装备为当前主武器。 | I20: 标签：launcher、explosive、slow | J20: 成品：boss_floor_1×2.5；boss_floor_2×4；combat_floor_3×0.8；combat_floor_4×0.5；combat_floor_5×1；elite_floor_2×3；loot_abyss×2.5；loot_floor_3_4×1；loot_floor_5×1.5；scavenge_floor_3×0.5；scavenge_floor_4×1；scavenge_floor_5×2 蓝图：boss_floor_1×3；boss_floor_2×4；combat_floor_3×0.5；combat_floor_4×0.3；loot_abyss×2.5；scavenge_floor_5×1 | K20: [已实装] | L20: 正式注册；具体行为与表现仍需逐项QA | M20: src/base/BlueprintRegistry.gd；src/base/ItemRegistry.gd | N20: 装配ID=bp_launcher；成品物品ID=weapon_launcher；蓝图物品ID=bp_launcher | O20: 8 | P20: 成品生成永久weapon_instance_id；命运槽、子弹模块与配件随实例在装备/背包/地面/商店/保险/存档间移动 | Q20: [已实装] 唯一实例ID、8槽基线、完整构筑/弹药/命运记录随枪转移与存档 | R20: 显示抛物线、爆炸半径、弹量与安全距离；瞄准时给落点预览 | S20: 发射器抬升动作、弧线弹道、落点圈和爆炸反馈一致 | T20: [部分完成] 实例尾号、槽位、已装配件与命运刻印已可视；逐条专属VFX/音频仍待QA | U20: =IF(F20>0,F20,0) | V20: =IF(F20>0,ROUND(F20*0.5,0),0) | W20: FALSE | X20: not_listed | Y20: 0
A21: bp_machinegun | B21: 枪身 | C21: 蜂窝机枪 | D21: 1 | E21: uncommon | F21: 180 | G21: bullet_count=1；damage=15；fire_rate=12；magazine_size=60；reload_time=2.8；spread=0.15 | H21: 高射速压制武器，适合清群怪。左键装备为当前主武器。 | I21: 标签：auto、high_rate、spray | J21: 成品：combat_floor_1×0.8；combat_floor_2×1.2；combat_floor_3×1.5；elite_floor_1×1.5；elite_floor_2×2.5；loot_abyss×2.5；loot_floor_1_2×1；loot_floor_3_4×1.5；loot_floor_5×2；scavenge_floor_1×0.5；scavenge_floor_2×1；scavenge_floor_3×1.2；scavenge_floor_4×1.5；scavenge_floor_5×2.5 蓝图：combat_floor_1×0.8；combat_floor_2×0.5；loot_abyss×2.5；loot_floor_3_4×1.5；loot_floor_5×2；scavenge_floor_3×1.5；scavenge_floor_4×2；scavenge_floor_5×2.5 | K21: [已实装] | L21: 正式注册；具体行为与表现仍需逐项QA | M21: src/base/BlueprintRegistry.gd；src/base/ItemRegistry.gd | N21: 装配ID=bp_machinegun；成品物品ID=weapon_machinegun；蓝图物品ID=bp_machinegun | O21: 8 | P21: 成品生成永久weapon_instance_id；命运槽、子弹模块与配件随实例在装备/背包/地面/商店/保险/存档间移动 | Q21: [已实装] 唯一实例ID、8槽基线、完整构筑/弹药/命运记录随枪转移与存档 | R21: 显示高射速、弹量、扩散与持续射击节奏；低弹药警告明显 | S21: 连续枪口焰、机械循环和后坐累积可读，不能用单发动画冒充连射 | T21: [部分完成] 实例尾号、槽位、已装配件与命运刻印已可视；逐条专属VFX/音频仍待QA | U21: =IF(F21>0,F21,0) | V21: =IF(F21>0,ROUND(F21*0.5,0),0) | W21: FALSE | X21: not_listed | Y21: 0
A22: bp_pistol | B22: 枪身 | C22: 豌豆手枪 | D22: 0 | E22: common | F22: 70 | G22: bullet_count=1；damage=18；fire_rate=3.5；magazine_size=12；reload_time=1.5；spread=0.03 | H22: 可靠的基础半自动武器。左键装备为当前主武器。 | I22: 标签：pistol、semi_auto、sidearm | J22: 成品：combat_floor_1×0.5；combat_floor_2×0.8；loot_floor_1_2×0.8；scavenge_floor_1×0.8；scavenge_floor_2×1.4 蓝图：combat_floor_1×1.5；combat_floor_2×1；loot_abyss×1.5；loot_common×1；loot_floor_1_2×3；loot_floor_3_4×2.5；loot_floor_5×2；scavenge_floor_1×2.5；scavenge_floor_2×1.8；spawn_starter×4 | K22: [已实装] | L22: 正式注册；具体行为与表现仍需逐项QA | M22: src/base/BlueprintRegistry.gd；src/base/ItemRegistry.gd | N22: 装配ID=bp_pistol；成品物品ID=weapon_pistol；蓝图物品ID=bp_pistol | O22: 8 | P22: 生成永久weapon_instance_id；六个公共配件位置固定，枪型仅开放兼容子集；单拆配件，整枪移动时完整装配树随实例转移 | Q22: [已实装并验收] WeaponInstance schema v2、主副武器独立配件、兼容禁用、替换回滚与旧快照迁移 | R22: 显示半自动节奏、伤害、弹量与精准度，作为轻型基准枪比较 | S22: 每次点击有清晰单发后坐、枪口焰与复位，轮廓轻巧 | T22: [部分完成] 实例尾号、槽位、已装配件与命运刻印已可视；逐条专属VFX/音频仍待QA | U22: =IF(F22>0,F22,0) | V22: =IF(F22>0,ROUND(F22*0.5,0),0) | W22: TRUE | X22: unlimited | Y22: 2
A23: bp_rifle | B23: 枪身 | C23: 步枪 | D23: 1 | E23: rare | F23: 150 | G23: bullet_count=1；damage=22；fire_rate=6；magazine_size=30；reload_time=2.2；spread=0.07 | H23: 稳定连发的中距离武器。左键装备为当前主武器。 | I23: 标签：rifle、automatic、assault | J23: 成品：boss_floor_1×2；boss_floor_2×3；combat_floor_1×0.5；combat_floor_2×1；combat_floor_3×1.5；elite_floor_1×1.5；elite_floor_2×2；loot_abyss×2.5；loot_floor_1_2×0.3；loot_floor_3_4×1.5；loot_floor_5×2；scavenge_floor_3×1；scavenge_floor_4×1.5；scavenge_floor_5×2 蓝图：boss_floor_1×3；combat_floor_1×1.5；combat_floor_2×1；combat_floor_3×0.8；loot_abyss×3；loot_common×1；loot_floor_3_4×2；loot_floor_5×2.5；scavenge_floor_3×1.5；scavenge_floor_4×2；spawn_starter×2 | K23: [已实装] | L23: 正式注册；具体行为与表现仍需逐项QA | M23: src/base/BlueprintRegistry.gd；src/base/ItemRegistry.gd | N23: 装配ID=bp_rifle；成品物品ID=weapon_rifle；蓝图物品ID=bp_rifle | O23: 8 | P23: 生成永久weapon_instance_id；六个公共配件位置固定，枪型仅开放兼容子集；单拆配件，整枪移动时完整装配树随实例转移 | Q23: [已实装并验收] WeaponInstance schema v2、主副武器独立配件、兼容禁用、替换回滚与旧快照迁移 | R23: 显示中距离连发、伤害、射速、弹量和扩散的平衡定位 | S23: 连发节奏、枪身动作和中等后坐一致，弹道辨识稳定 | T23: [部分完成] 实例尾号、槽位、已装配件与命运刻印已可视；逐条专属VFX/音频仍待QA | U23: =IF(F23>0,F23,0) | V23: =IF(F23>0,ROUND(F23*0.5,0),0) | W23: TRUE | X23: unlimited | Y23: 4
A24: bp_shotgun | B24: 枪身 | C24: 散射喷壶 | D24: 0 | E24: uncommon | F24: 110 | G24: bullet_count=5；damage=12；fire_rate=1.2；magazine_size=6；reload_time=3；spread=0.35 | H24: 近距离多弹丸散射武器。左键装备为当前主武器。 | I24: 标签：shotgun、close_range、burst | J24: 成品：combat_floor_1×0.8；combat_floor_2×1.2；loot_floor_1_2×1；scavenge_floor_1×1.4；scavenge_floor_2×2；spawn_starter×3 蓝图：combat_floor_1×1；combat_floor_2×0.5；loot_abyss×1；loot_common×1；loot_floor_1_2×2.5；loot_floor_3_4×2；loot_floor_5×1.5；scavenge_floor_1×2；scavenge_floor_2×1.5；spawn_starter×3.5 | K24: [已实装] | L24: 正式注册；具体行为与表现仍需逐项QA | M24: src/base/BlueprintRegistry.gd；src/base/ItemRegistry.gd | N24: 装配ID=bp_shotgun；成品物品ID=weapon_shotgun；蓝图物品ID=bp_shotgun | O24: 8 | P24: 生成永久weapon_instance_id；六个公共配件位置固定，枪型仅开放兼容子集；单拆配件，整枪移动时完整装配树随实例转移 | Q24: [已实装并验收] WeaponInstance schema v2、主副武器独立配件、兼容禁用、替换回滚与旧快照迁移 | R24: 显示每发弹丸数、散布锥、近距收益、弹量与换弹 | S24: 多弹丸扇形、强后坐和近距命中层次同步；命中数量可读 | T24: [部分完成] 实例尾号、槽位、已装配件与命运刻印已可视；逐条专属VFX/音频仍待QA | U24: =IF(F24>0,F24,0) | V24: =IF(F24>0,ROUND(F24*0.5,0),0) | W24: TRUE | X24: unlimited | Y24: 3
A25: bp_sniper | B25: 枪身 | C25: 弹弓狙击 | D25: 2 | E25: rare | F25: 220 | G25: bullet_count=1；damage=55；fire_rate=1；magazine_size=5；reload_time=3.5；spread=0.01 | H25: 低射速高伤害，穿透力强，适合精准打击。左键装备为当前主武器。 | I25: 标签：sniper、precision、high_damage | J25: 成品：boss_floor_1×2；boss_floor_2×4；combat_floor_2×0.3；combat_floor_3×0.8；elite_floor_1×1.5；elite_floor_2×2；loot_abyss×2.5；loot_floor_3_4×0.5；loot_floor_5×1.5；scavenge_floor_3×0.5；scavenge_floor_4×1；scavenge_floor_5×2 蓝图：boss_floor_1×4；boss_floor_2×5；combat_floor_3×1.5；combat_floor_4×2；combat_floor_5×2.5；loot_abyss×3；loot_common×0.5；loot_floor_5×2；scavenge_floor_5×1.5；spawn_starter×1 | K25: [已实装] | L25: 正式注册；具体行为与表现仍需逐项QA | M25: src/base/BlueprintRegistry.gd；src/base/ItemRegistry.gd | N25: 装配ID=bp_sniper；成品物品ID=weapon_sniper；蓝图物品ID=bp_sniper | O25: 8 | P25: 成品生成永久weapon_instance_id；命运槽、子弹模块与配件随实例在装备/背包/地面/商店/保险/存档间移动 | Q25: [已实装] 唯一实例ID、8槽基线、完整构筑/弹药/命运记录随枪转移与存档 | R25: 显示高伤害、低射速、精准/穿透与瞄准状态；提供远距比较 | S25: 长枪轮廓、瞄准准星、强单发反馈和贯穿线一致，射击时点明确 | T25: [部分完成] 实例尾号、槽位、已装配件与命运刻印已可视；逐条专属VFX/音频仍待QA | U25: =IF(F25>0,F25,0) | V25: =IF(F25>0,ROUND(F25*0.5,0),0) | W25: FALSE | X25: not_listed | Y25: 0
A26: bp_greatblade | B26: 近战武器 | C26: 巨型工业断刃 | D26: 0 | E26: uncommon | F26: 165 | G26: damage=34；reach=2.65m；arc=115°；knockback=5.4；combo=3 | H26: 左横斩→右回斩→过顶重劈；每段前摇/命中/后摇；无弹药与换弹 | I26: 标签：melee、heavy_melee、greatblade、wide_arc；第三段1.48×伤害/1.55×击退 | J26: 成品：spawn_starter×1.2；loot_floor_1_2×0.75；loot_floor_3_4×1.2；scavenge_floor_1×0.65；scavenge_floor_2×1.1；combat_floor_1×0.5；combat_floor_2×0.9 | K26: [已实装] | L26: 正式注册；近战专项验收通过 | M26: src/base/BlueprintRegistry.gd；src/base/ItemRegistry.gd；src/player3d/melee/PlayerMeleeCombat3D.gd | N26: 装配ID=bp_greatblade；成品物品ID=weapon_greatblade；程序原型总长2.42m | O26: 8 | P26: 生成永久weapon_instance_id；无子弹槽；命运/主副槽/背负/地面/背包/保险/存档随实例移动 | Q26: [已实装并验收] 四态动作机、三段缓存、扇区/墙体/去重、伤害/击退/中断与反馈闭环 | R26: HUD显示近战·三段；动作快照显示阶段、进度、攻击ID；挥空有弧光/切风声，命中有爆点/冲击声 | S26: 双手重型持握；青色能量断刃；三段弧光方向可辨，第三段尺寸与冲击最强 | T26: [核心已验收] 程序模型/三段动作/参数化VFX/专属音频完成；最终模型与低特效模式待替换/复验 | W26: 0 | X26: not_listed | Y26: 0
A27: bp_waraxe | B27: 近战武器 | C27: 攻城裂甲斧 | D27: 1 | E27: rare | F27: 240 | G27: damage=46；reach=2.85m；arc=100°；knockback=7.2；combo=3 | H27: 上挑斩→交叉斩→砸地裂斩；高伤高击退；无弹药与换弹 | I27: 标签：melee、heavy_melee、waraxe、high_knockback；第三段1.62×伤害/1.70×击退 | J27: 成品：loot_floor_1_2×0.18；loot_floor_3_4×0.95；loot_floor_5×1.45；loot_abyss×1.8；scavenge_floor_3×0.8；combat_floor_3×0.72；elite_floor_1×1.2；elite_floor_2×1.8 | K27: [已实装] | L27: 正式注册；近战专项验收通过 | M27: src/base/BlueprintRegistry.gd；src/base/ItemRegistry.gd；src/player3d/melee/PlayerMeleeCombat3D.gd | N27: 装配ID=bp_waraxe；成品物品ID=weapon_waraxe；程序原型总长2.62m | O27: 8 | P27: 生成永久weapon_instance_id；无子弹槽；命运/主副槽/背负/地面/背包/保险/存档随实例移动 | Q27: [已实装并验收] 四态动作机、三段缓存、扇区/墙体/去重、伤害/击退/中断与反馈闭环 | R27: HUD显示近战·三段；动作快照显示阶段、进度、攻击ID；挥空有弧光/切风声，命中有爆点/冲击声 | S27: 双手长柄持握；橙色冲击核心；第三段最大过顶弧光，音高更低、冲击更重 | T27: [核心已验收] 程序模型/三段动作/参数化VFX/专属音频完成；最终模型与低特效模式待替换/复验 | W27: 0 | X27: not_listed | Y27: 0
A28: bp_baseball_bat | B28: 近战武器 | C28: 废土棒球棍 | D28: 0 | E28: common | F28: 45 | G28: damage=20；reach=2.05m；arc=105°；knockback=3.2；combo=3 | H28: 左横扫→右回扫→蓄力重挥；初级快速近战；无弹药与换弹 | I28: 标签：melee、light_melee、baseball_bat、starter_melee；第三段1.28×伤害/1.35×击退 | J28: 成品：spawn_starter×2.2；loot_floor_1_2×1.6；scavenge_floor_1×1.8；scavenge_floor_2×1.2；combat_floor_1×1.0；基地贩卖机无限库存 | K28: [已实装] | L28: 正式注册；基地贩卖、近战专项与配件系统专项验收通过 | M28: src/base/BlueprintRegistry.gd；src/base/ItemRegistry.gd；src/player3d/melee/PlayerMeleeCombat3D.gd；tests/verification/verify_weapon_attachment_inventory_flow.gd | N28: 装配ID=bp_baseball_bat；成品物品ID=weapon_baseball_bat；程序原型总长1.48m | O28: 8 | P28: 生成永久weapon_instance_id；无子弹/普通枪械配件槽；命运/主副槽/背负/地面/背包/保险/存档随实例移动 | Q28: [已实装并验收] 复用ready/windup/active/recovery四态、三段缓存、扇区/遮挡/去重、伤害/击退/中断与反馈闭环 | R28: HUD显示近战·三段；第三段反馈增强；基地货架明确初级定位 | S28: 双手挥击；木质粗大轮廓、金属加固环；沿local -Z延伸，背负/手持轮廓清晰 | T28: [核心已验收] 程序模型/三段动作/VFX/音频完成；最终模型待替换 | U28: 45 | V28: 23 | W28: 1 | X28: unlimited | Y28: 1

Sheet 命运卡
A1: ShellStorm2 游戏内容数据库｜命运塔罗
A2: 78张完整牌组：48张现有卡已接入塔罗名称、正/逆位效果快照、50%/50%方位与代码翻牌；新增30张须完成独立玩法执行器后再进入正式池。
A3: 每张卡先抽身份，再以50%/50%独立抽正位或逆位；同名、同稳定ID、同收藏条目。逆位只倒置图案/框体，名称、说明、数值和目标文字始终正向。
A4: 稳定卡ID | B4: 塔罗名称 | C4: 类型 | D4: 品质 | E4: 正位短说明 | F4: 正位完整功能 | G4: 背景介绍 | H4: 背景来源 | I4: 目标规则 | J4: 当前/正位效果参数 | K4: 获得方式 | L4: 状态来源 | M4: 实现状态 | N4: 事实源 | O4: 备注 | P4: 作用域 | Q4: 槽位/所有者规则 | R4: 塔罗实现状态 | S4: 选择/槽位UI提示 | T4: 触发/战斗/世界表现 | U4: 表现实现状态 | V4: 旧名/迁移别名 | W4: 塔罗编号 | X4: 阿尔卡那 | Y4: 花色 | Z4: 正位概率 | AA4: 逆位概率 | AB4: 正位功能说明 | AC4: 正位效果参数 | AD4: 逆位功能说明 | AE4: 逆位效果参数 | AF4: 翻转/UI表现 | AG4: 塔罗设计状态
A5: fate_mark_enemy | B5: 愚者 | C5: 规则 | D5: 传说 | E5: 击杀第10个敌人获得随机命卡 | F5: 每击杀 10 个敌人，有 50% 概率获得一张随机命运卡片 | G5: 第十个倒下者会留下短暂印记，偶尔把一张新的规则卡交给胜者。 | H5: [Codex补充] | J5: action=GRANT_RANDOM_CARD；grant_probability=0.5；kill_threshold=10 | K5: 玩家卡池；也可由地图阈值事件触发 | L5: [已实装] | M5: [部分实装] 塔罗名称、正/逆位效果快照与通用执行已接入；复杂逆位专属行为继续逐卡QA | N5: src/weapons/FateCard.gd；src/weapons/FateCardPresets.gd；src/weapons/FateCardEngine.gd；src/game/FateCardGameBridge.gd；docs/v0.1/14_技术施工_命运塔罗牌组.md；src/weapons/TarotFateCatalog.gd；tests/verification/verify_tarot_fate_runtime.gd | O5: 迁移前名称：命运标记；稳定ID不变，旧存档迁移为正位，不重投方位 | P5: CHARACTER | Q5: 不占武器槽；写入角色局内规则状态 | R5: [已实装] 塔罗名称、50/50方位、正逆位同ID、代码翻牌、整卡倒置、逆位描述替换与方位持久化已接入 | S5: ☾ 月亮命运｜愚者｜翻牌后显示正位/逆位、目标、槽位与对应功能 | T5: 卡背绕Y轴翻面；逆位整张正面卡牌（含边框、图案、文字与布局）收束180°，并显示逆位效果描述；目标头顶出现可读标记；达成条件时角色HUD进度完成，枪械外观不变 | U5: [部分实装] 通用卡背/翻牌/逆位倒置已验收；逐卡逆位专属VFX与音效继续QA | V5: 命运标记 | W5: 0 | X5: MAJOR | Y5: MAJOR | Z5: 0.5 | AA5: 0.5 | AB5: 每击杀 10 个敌人，有 50% 概率获得一张随机命运卡片 | AC5: action=GRANT_RANDOM_CARD；grant_probability=0.5；kill_threshold=10 | AD5: 每10击杀必得随机命运，但失去30魂 | AE5: action=GRANT_RANDOM_CARD; kill_threshold=10; grant_probability=1; currency_cost=30 | AF5: 0.00s卡背→0.24s薄边换面→0.42s收束；逆位图案/框体180°，卡名、天体、方位标签和说明文字0°；0.62s后可点 | AG5: [设计完成/数据已入表/运行时待施工]
A6: fate_gun_on_gun | B6: 魔术师 | C6: 组合 | D6: 传说 | E6: 副枪跟随主枪一起开火 | F6: 选择一个枪身，将其挂到当前枪身上，副枪跟随射击 | G6: 当一个扳机不够时，就让第二把枪把第一把枪的节奏当成命令。 | H6: [Codex补充] | J6: action=ATTACH_GUN_TO_GUN；damage_scale=0.5；fire_rate_scale=0.6；follow_probability=1 | K6: 门后命运/三选一/工作台共用卡池 | L6: [已实装] | M6: [部分实装] 塔罗名称、正/逆位效果快照与通用执行已接入；复杂逆位专属行为继续逐卡QA | N6: src/weapons/FateCard.gd；src/weapons/FateCardPresets.gd；src/weapons/FateCardEngine.gd；src/game/FateCardGameBridge.gd；docs/v0.1/14_技术施工_命运塔罗牌组.md；src/weapons/TarotFateCatalog.gd；tests/verification/verify_tarot_fate_runtime.gd | O6: 迁移前名称：枪上加枪；稳定ID不变，旧存档迁移为正位，不重投方位 | P6: WEAPON | Q6: 占目标枪械下一个永久命运槽；按序追加、不可拆卸/替换/回退 | R6: [已实装] 塔罗名称、50/50方位、正逆位同ID、代码翻牌、整卡倒置、逆位描述替换与方位持久化已接入 | S6: ★ 星星命运｜魔术师｜翻牌后显示正位/逆位、目标、槽位与对应功能 | T6: 卡背绕Y轴翻面；逆位整张正面卡牌（含边框、图案、文字与布局）收束180°，并显示逆位效果描述；主枪上出现副枪实体/能量轮廓；同步或派生开火用不同声层区分 | U6: [部分实装] 通用卡背/翻牌/逆位倒置已验收；逐卡逆位专属VFX与音效继续QA | V6: 枪上加枪 | W6: I | X6: MAJOR | Y6: MAJOR | Z6: 0.5 | AA6: 0.5 | AB6: 选择一个枪身，将其挂到当前枪身上，副枪跟随射击 | AC6: action=ATTACH_GUN_TO_GUN；damage_scale=0.5；fire_rate_scale=0.6；follow_probability=1 | AD6: 主副枪交替开火，单发更强但主枪变慢 | AE6: action=ATTACH_GUN_TO_GUN; alternate_fire=true; damage_scale=0.85; main_fire_rate_scale=0.85 | AF6: 0.00s卡背→0.24s薄边换面→0.42s收束；逆位图案/框体180°，卡名、天体、方位标签和说明文字0°；0.62s后可点 | AG6: [设计完成/数据已入表/运行时待施工]
A7: fate_moon_vitality | B7: 女祭司 | C7: 强化 | D7: 稀有 | E7: 生命上限+20 | F7: 最大生命提升20，并立刻恢复20生命 | G7: 月光让受损躯体重新生长，把本局的生存空间向上推高。 | H7: [用户设计] | J7: action=APPLY_SCOPED_MODIFIER；modifier=max_hp；amount=20 | K7: 门后命运/三选一/工作台共用正式卡池 | L7: [已实装] | M7: [部分实装] 塔罗名称、正/逆位效果快照与通用执行已接入；复杂逆位专属行为继续逐卡QA | N7: src/weapons/FateCard.gd；src/weapons/FateCardPresets.gd；src/weapons/FateCardEngine.gd；src/game/FateCardGameBridge.gd；src/player3d/Player3D.gd；src/world3d/Dungeon3D.gd；docs/v0.1/14_技术施工_命运塔罗牌组.md；src/weapons/TarotFateCatalog.gd；tests/verification/verify_tarot_fate_runtime.gd | O7: 迁移前名称：月相增生；稳定ID不变，旧存档迁移为正位，不重投方位 | P7: CHARACTER | Q7: 不占武器槽；写入角色局内规则状态 | R7: [已实装] 塔罗名称、50/50方位、正逆位同ID、代码翻牌、整卡倒置、逆位描述替换与方位持久化已接入 | S7: ☾ 月亮命运｜女祭司｜翻牌后显示正位/逆位、目标、槽位与对应功能 | T7: 卡背绕Y轴翻面；逆位整张正面卡牌（含边框、图案、文字与布局）收束180°，并显示逆位效果描述；角色生命上限与当前生命同步增加，红色生命条立即扩容 | U7: [部分实装] 通用卡背/翻牌/逆位倒置已验收；逐卡逆位专属VFX与音效继续QA | V7: 月相增生 | W7: II | X7: MAJOR | Y7: MAJOR | Z7: 0.5 | AA7: 0.5 | AB7: 最大生命提升20，并立刻恢复20生命 | AC7: action=APPLY_SCOPED_MODIFIER；modifier=max_hp；amount=20 | AD7: 生命上限-10，立即恢复50生命 | AE7: action=APPLY_SCOPED_MODIFIER; modifier=max_hp_trade; max_hp_delta=-10; heal=50 | AF7: 0.00s卡背→0.24s薄边换面→0.42s收束；逆位图案/框体180°，卡名、天体、方位标签和说明文字0°；0.62s后可点 | AG7: [设计完成/数据已入表/运行时待施工]
A8: fate_sun_extra_loot | B8: 皇后 | C8: 规则 | D8: 史诗 | E8: 下箱追加2抽，保留最佳 | F8: 下一个容器追加2次候选抽取并保留最高品质结果，地面仍只掉落1件 | G8: 太阳延长了这一日的收成，但只让猎人带走其中最值得的一件。 | H8: [用户设计] | J8: action=APPLY_SCOPED_MODIFIER；modifier=next_chest_extra；count=2 | K8: 门后命运/三选一/工作台共用正式卡池 | L8: [已实装] | M8: [部分实装] 塔罗名称、正/逆位效果快照与通用执行已接入；复杂逆位专属行为继续逐卡QA | N8: src/weapons/FateCard.gd；src/weapons/FateCardPresets.gd；src/weapons/FateCardEngine.gd；src/game/FateCardGameBridge.gd；src/player3d/Player3D.gd；src/world3d/Dungeon3D.gd；docs/v0.1/14_技术施工_命运塔罗牌组.md；src/weapons/TarotFateCatalog.gd；tests/verification/verify_tarot_fate_runtime.gd | O8: 迁移前名称：丰收日；稳定ID不变，旧存档迁移为正位，不重投方位 | P8: WORLD | Q8: 不占武器槽；写入行动/房间/掉落/撤离规则状态 | R8: [已实装] 塔罗名称、50/50方位、正逆位同ID、代码翻牌、整卡倒置、逆位描述替换与方位持久化已接入 | S8: ☀ 太阳命运｜皇后｜翻牌后显示正位/逆位、目标、槽位与对应功能 | T8: 开箱时追加2次候选扫描，界面闪过候选后只生成1个最高品质地面实体并清空计数 | U8: [部分实装] 通用卡背/翻牌/逆位倒置已验收；逐卡逆位专属VFX与音效继续QA | V8: 丰收日 | W8: III | X8: MAJOR | Y8: MAJOR | Z8: 0.5 | AA8: 0.5 | AB8: 下一个容器追加2次候选抽取并保留最高品质结果，地面仍只掉落1件 | AC8: action=APPLY_SCOPED_MODIFIER；modifier=next_chest_extra；count=2 | AD8: 下一容器追加4次候选抽取并保留最佳，品质上限为稀有，地面仍只掉落1件 | AE8: action=APPLY_SCOPED_MODIFIER; modifier=next_chest_extra_capped; count=4; rarity_cap=RARE | AF8: 0.00s卡背→0.24s薄边换面→0.42s收束；逆位图案/框体180°，卡名、天体、方位标签和说明文字0°；0.62s后可点 | AG8: [设计完成/数据已入表/运行时待施工]
A9: fate_sun_reinforce | B9: 皇帝 | C9: 规则 | D9: 史诗 | E9: 下房敌人+3 | F9: 下一个敌对房间额外出现3名敌人 | G9: 日冕暴露了行动路线，下一间敌对区域会提前集结增援。 | H9: [用户设计] | J9: action=APPLY_SCOPED_MODIFIER；modifier=next_room_enemy_count；count=3 | K9: 门后命运/三选一/工作台共用正式卡池 | L9: [已实装] | M9: [部分实装] 塔罗名称、正/逆位效果快照与通用执行已接入；复杂逆位专属行为继续逐卡QA | N9: src/weapons/FateCard.gd；src/weapons/FateCardPresets.gd；src/weapons/FateCardEngine.gd；src/game/FateCardGameBridge.gd；src/player3d/Player3D.gd；src/world3d/Dungeon3D.gd；docs/v0.1/14_技术施工_命运塔罗牌组.md；src/weapons/TarotFateCatalog.gd；tests/verification/verify_tarot_fate_runtime.gd | O9: 迁移前名称：日冕增援；稳定ID不变，旧存档迁移为正位，不重投方位 | P9: WORLD | Q9: 不占武器槽；写入行动/房间/掉落/撤离规则状态 | R9: [已实装] 塔罗名称、50/50方位、正逆位同ID、代码翻牌、整卡倒置、逆位描述替换与方位持久化已接入 | S9: ☀ 太阳命运｜皇帝｜翻牌后显示正位/逆位、目标、槽位与对应功能 | T9: 卡背绕Y轴翻面；逆位整张正面卡牌（含边框、图案、文字与布局）收束180°，并显示逆位效果描述；下一敌对房间生成表追加3名敌人后消费状态 | U9: [部分实装] 通用卡背/翻牌/逆位倒置已验收；逐卡逆位专属VFX与音效继续QA | V9: 日冕增援 | W9: IV | X9: MAJOR | Y9: MAJOR | Z9: 0.5 | AA9: 0.5 | AB9: 下一个敌对房间额外出现3名敌人 | AC9: action=APPLY_SCOPED_MODIFIER；modifier=next_room_enemy_count；count=3 | AD9: 下一敌对房增加1精英，清理后+50魂 | AE9: action=APPLY_SCOPED_MODIFIER; modifier=next_room_elite_reward; elite_count=1; currency_reward=50 | AF9: 0.00s卡背→0.24s薄边换面→0.42s收束；逆位图案/框体180°，卡名、天体、方位标签和说明文字0°；0.62s后可点 | AG9: [设计完成/数据已入表/运行时待施工]
A10: fate_sun_key | B10: 教皇 | C10: 强化 | D10: 稀有 | E10: 获得房间钥匙 | F10: 立即获得1把普通房间钥匙 | G10: 灼热印记在掌心凝成一把只属于本次行动的房间钥匙。 | H10: [用户设计] | J10: action=APPLY_SCOPED_MODIFIER；modifier=grant_room_key；count=1 | K10: 门后命运/三选一/工作台共用正式卡池 | L10: [已实装] | M10: [部分实装] 塔罗名称、正/逆位效果快照与通用执行已接入；复杂逆位专属行为继续逐卡QA | N10: src/weapons/FateCard.gd；src/weapons/FateCardPresets.gd；src/weapons/FateCardEngine.gd；src/game/FateCardGameBridge.gd；src/player3d/Player3D.gd；src/world3d/Dungeon3D.gd；docs/v0.1/14_技术施工_命运塔罗牌组.md；src/weapons/TarotFateCatalog.gd；tests/verification/verify_tarot_fate_runtime.gd | O10: 迁移前名称：太阳钥印；稳定ID不变，旧存档迁移为正位，不重投方位 | P10: WORLD | Q10: 不占武器槽；写入行动/房间/掉落/撤离规则状态 | R10: [已实装] 塔罗名称、50/50方位、正逆位同ID、代码翻牌、整卡倒置、逆位描述替换与方位持久化已接入 | S10: ☀ 太阳命运｜教皇｜翻牌后显示正位/逆位、目标、槽位与对应功能 | T10: 卡背绕Y轴翻面；逆位整张正面卡牌（含边框、图案、文字与布局）收束180°，并显示逆位效果描述；普通房间钥匙计数立即+1，HUD同步刷新 | U10: [部分实装] 通用卡背/翻牌/逆位倒置已验收；逐卡逆位专属VFX与音效继续QA | V10: 太阳钥印 | W10: V | X10: MAJOR | Y10: MAJOR | Z10: 0.5 | AA10: 0.5 | AB10: 立即获得1把普通房间钥匙 | AC10: action=APPLY_SCOPED_MODIFIER；modifier=grant_room_key；count=1 | AD10: 获得2把临时钥匙，离开当层失效 | AE10: action=APPLY_SCOPED_MODIFIER; modifier=grant_temporary_keys; count=2; expires=FLOOR_EXIT | AF10: 0.00s卡背→0.24s薄边换面→0.42s收束；逆位图案/框体180°，卡名、天体、方位标签和说明文字0°；0.62s后可点 | AG10: [设计完成/数据已入表/运行时待施工]
A11: fate_moon_power | B11: 恋人 | C11: 强化 | D11: 史诗 | E11: 枪伤+12% | F11: 本局角色造成的枪械伤害提升12% | G11: 月刃不改写枪械本体，却让持有者的每次射击更有力量。 | H11: [用户设计] | J11: action=APPLY_SCOPED_MODIFIER；modifier=weapon_damage；multiplier=1.12 | K11: 门后命运/三选一/工作台共用正式卡池 | L11: [已实装] | M11: [部分实装] 塔罗名称、正/逆位效果快照与通用执行已接入；复杂逆位专属行为继续逐卡QA | N11: src/weapons/FateCard.gd；src/weapons/FateCardPresets.gd；src/weapons/FateCardEngine.gd；src/game/FateCardGameBridge.gd；src/player3d/Player3D.gd；src/world3d/Dungeon3D.gd；docs/v0.1/14_技术施工_命运塔罗牌组.md；src/weapons/TarotFateCatalog.gd；tests/verification/verify_tarot_fate_runtime.gd | O11: 迁移前名称：月刃共鸣；稳定ID不变，旧存档迁移为正位，不重投方位 | P11: CHARACTER | Q11: 不占武器槽；写入角色局内规则状态 | R11: [已实装] 塔罗名称、50/50方位、正逆位同ID、代码翻牌、整卡倒置、逆位描述替换与方位持久化已接入 | S11: ☾ 月亮命运｜恋人｜翻牌后显示正位/逆位、目标、槽位与对应功能 | T11: 卡背绕Y轴翻面；逆位整张正面卡牌（含边框、图案、文字与布局）收束180°，并显示逆位效果描述；角色伤害乘区生效；换枪后加成仍随角色，不随枪转移 | U11: [部分实装] 通用卡背/翻牌/逆位倒置已验收；逐卡逆位专属VFX与音效继续QA | V11: 月刃共鸣 | W11: VI | X11: MAJOR | Y11: MAJOR | Z11: 0.5 | AA11: 0.5 | AB11: 本局角色造成的枪械伤害提升12% | AC11: action=APPLY_SCOPED_MODIFIER；modifier=weapon_damage；multiplier=1.12 | AD11: 枪伤-8%，暴击率+15% | AE11: action=APPLY_SCOPED_MODIFIER; modifier=weapon_damage_crit_trade; damage_multiplier=0.92; crit_chance_add=0.15 | AF11: 0.00s卡背→0.24s薄边换面→0.42s收束；逆位图案/框体180°，卡名、天体、方位标签和说明文字0°；0.62s后可点 | AG11: [设计完成/数据已入表/运行时待施工]
A12: fate_bullet_carry_gun | B12: 战车 | C12: 组合 | D12: 史诗 | E12: 子弹飞出去时自动开枪 | F12: 选择一个子弹和一个枪身，该子弹将携带枪身并自动射击 | G12: 有人把整把枪绑在弹头上，荒唐的结构在命运规则下反而可以边飞边射。 | H12: [Codex补充] | J12: action=ATTACH_GUN_TO_BULLET；damage_scale=0.45；fire_rate_scale=0.6；max_attached_gun=1 | K12: 门后命运/三选一/工作台共用卡池 | L12: [已实装] | M12: [部分实装] 塔罗名称、正/逆位效果快照与通用执行已接入；复杂逆位专属行为继续逐卡QA | N12: src/weapons/FateCard.gd；src/weapons/FateCardPresets.gd；src/weapons/FateCardEngine.gd；src/game/FateCardGameBridge.gd；docs/v0.1/14_技术施工_命运塔罗牌组.md；src/weapons/TarotFateCatalog.gd；tests/verification/verify_tarot_fate_runtime.gd | O12: 迁移前名称：子弹背枪；稳定ID不变，旧存档迁移为正位，不重投方位 | P12: WEAPON | Q12: 占目标枪械下一个永久命运槽；按序追加、不可拆卸/替换/回退 | R12: [已实装] 塔罗名称、50/50方位、正逆位同ID、代码翻牌、整卡倒置、逆位描述替换与方位持久化已接入 | S12: ★ 星星命运｜战车｜翻牌后显示正位/逆位、目标、槽位与对应功能 | T12: 卡背绕Y轴翻面；逆位整张正面卡牌（含边框、图案、文字与布局）收束180°，并显示逆位效果描述；投射物上可见微型枪械或等价轮廓；派生开火有独立枪口焰且来源可追溯 | U12: [部分实装] 通用卡背/翻牌/逆位倒置已验收；逐卡逆位专属VFX与音效继续QA | V12: 子弹背枪 | W12: VII | X12: MAJOR | Y12: MAJOR | Z12: 0.5 | AA12: 0.5 | AB12: 选择一个子弹和一个枪身，该子弹将携带枪身并自动射击 | AC12: action=ATTACH_GUN_TO_BULLET；damage_scale=0.45；fire_rate_scale=0.6；max_attached_gun=1 | AD12: 携枪子弹只在命中时开一次高伤射击 | AE12: action=ATTACH_GUN_TO_BULLET; trigger=ON_HIT; shots=1; damage_scale=0.75 | AF12: 0.00s卡背→0.24s薄边换面→0.42s收束；逆位图案/框体180°，卡名、天体、方位标签和说明文字0°；0.62s后可点 | AG12: [设计完成/数据已入表/运行时待施工]
A13: fate_armor_pierce | B13: 力量 | C13: 强化 | D13: 稀有 | E13: 伤害提升 50%，无视护盾 | F13: 选择一个节点，伤害提升 50%，无视护盾减伤效果 | G13: 废弃军械库留下的硬芯工艺，专门教子弹绕过壳甲最自信的角度。 | H13: [Codex补充] | J13: action=ADD_DAMAGE；damage_scale=1.5；pierce_shield=true | K13: 门后命运/三选一/工作台共用卡池 | L13: [已实装] | M13: [部分实装] 塔罗名称、正/逆位效果快照与通用执行已接入；复杂逆位专属行为继续逐卡QA | N13: src/weapons/FateCard.gd；src/weapons/FateCardPresets.gd；src/weapons/FateCardEngine.gd；src/game/FateCardGameBridge.gd；docs/v0.1/14_技术施工_命运塔罗牌组.md；src/weapons/TarotFateCatalog.gd；tests/verification/verify_tarot_fate_runtime.gd | O13: 迁移前名称：穿甲强化；稳定ID不变，旧存档迁移为正位，不重投方位 | P13: WEAPON | Q13: 占目标枪械下一个永久命运槽；按序追加、不可拆卸/替换/回退 | R13: [已实装] 塔罗名称、50/50方位、正逆位同ID、代码翻牌、整卡倒置、逆位描述替换与方位持久化已接入 | S13: ★ 星星命运｜力量｜翻牌后显示正位/逆位、目标、槽位与对应功能 | T13: 卡背绕Y轴翻面；逆位整张正面卡牌（含边框、图案、文字与布局）收束180°，并显示逆位效果描述；弹体使用贯穿线；护甲命中出现破盾裂纹与剩余穿透提示 | U13: [部分实装] 通用卡背/翻牌/逆位倒置已验收；逐卡逆位专属VFX与音效继续QA | V13: 穿甲强化 | W13: VIII | X13: MAJOR | Y13: MAJOR | Z13: 0.5 | AA13: 0.5 | AB13: 选择一个节点，伤害提升 50%，无视护盾减伤效果 | AC13: action=ADD_DAMAGE；damage_scale=1.5；pierce_shield=true | AD13: 伤害+15%，不穿盾但对护盾×2 | AE13: action=ADD_DAMAGE; damage_scale=1.15; pierce_shield=false; shield_damage_scale=2 | AF13: 0.00s卡背→0.24s薄边换面→0.42s收束；逆位图案/框体180°，卡名、天体、方位标签和说明文字0°；0.62s后可点 | AG13: [设计完成/数据已入表/运行时待施工]
A14: fate_moon_stride | B14: 隐者 | C14: 强化 | D14: 稀有 | E14: 移速+12% | F14: 本局角色移动速度提升12% | G14: 月影贴着脚步移动，让角色更快穿过火力空隙。 | H14: [用户设计] | J14: action=APPLY_SCOPED_MODIFIER；modifier=move_speed；multiplier=1.12 | K14: 门后命运/三选一/工作台共用正式卡池 | L14: [已实装] | M14: [部分实装] 塔罗名称、正/逆位效果快照与通用执行已接入；复杂逆位专属行为继续逐卡QA | N14: src/weapons/FateCard.gd；src/weapons/FateCardPresets.gd；src/weapons/FateCardEngine.gd；src/game/FateCardGameBridge.gd；src/player3d/Player3D.gd；src/world3d/Dungeon3D.gd；docs/v0.1/14_技术施工_命运塔罗牌组.md；src/weapons/TarotFateCatalog.gd；tests/verification/verify_tarot_fate_runtime.gd | O14: 迁移前名称：月影疾行；稳定ID不变，旧存档迁移为正位，不重投方位 | P14: CHARACTER | Q14: 不占武器槽；写入角色局内规则状态 | R14: [已实装] 塔罗名称、50/50方位、正逆位同ID、代码翻牌、整卡倒置、逆位描述替换与方位持久化已接入 | S14: ☾ 月亮命运｜隐者｜翻牌后显示正位/逆位、目标、槽位与对应功能 | T14: 卡背绕Y轴翻面；逆位整张正面卡牌（含边框、图案、文字与布局）收束180°，并显示逆位效果描述；角色实际移动速度提高，月亮命运常驻栏可追溯 | U14: [部分实装] 通用卡背/翻牌/逆位倒置已验收；逐卡逆位专属VFX与音效继续QA | V14: 月影疾行 | W14: IX | X14: MAJOR | Y14: MAJOR | Z14: 0.5 | AA14: 0.5 | AB14: 本局角色移动速度提升12% | AC14: action=APPLY_SCOPED_MODIFIER；modifier=move_speed；multiplier=1.12 | AD14: 移速-8%，冲刺无敌+0.12秒 | AE14: action=APPLY_SCOPED_MODIFIER; modifier=stride_invulnerability_trade; move_multiplier=0.92; invulnerability_add=0.12 | AF14: 0.00s卡背→0.24s薄边换面→0.42s收束；逆位图案/框体180°，卡名、天体、方位标签和说明文字0°；0.62s后可点 | AG14: [设计完成/数据已入表/运行时待施工]
A15: fate_every_seventh | B15: 命运之轮 | C15: 规则 | D15: 稀有 | E15: 第7发子弹触发额外效果 | F15: 选择一个枪身，第 7 发子弹伤害翻倍并引发小爆炸 | G15: 塔内旧式计数器只承认第七次脉冲，并把那一发标记为异常。 | H15: [Codex补充] | I15: select=GUNBODY | J15: action=EVERY_NTH_FIRE；bonus_effect=small_explosion；damage_multiplier=2；nth=7 | K15: 门后命运/三选一/工作台共用卡池 | L15: [已实装] | M15: [部分实装] 塔罗名称、正/逆位效果快照与通用执行已接入；复杂逆位专属行为继续逐卡QA | N15: src/weapons/FateCard.gd；src/weapons/FateCardPresets.gd；src/weapons/FateCardEngine.gd；src/game/FateCardGameBridge.gd；docs/v0.1/14_技术施工_命运塔罗牌组.md；src/weapons/TarotFateCatalog.gd；tests/verification/verify_tarot_fate_runtime.gd | O15: 迁移前名称：每第七发；稳定ID不变，旧存档迁移为正位，不重投方位 | P15: WEAPON | Q15: 占目标枪械下一个永久命运槽；按序追加、不可拆卸/替换/回退 | R15: [已实装] 塔罗名称、50/50方位、正逆位同ID、代码翻牌、整卡倒置、逆位描述替换与方位持久化已接入 | S15: ★ 星星命运｜命运之轮｜翻牌后显示正位/逆位、目标、槽位与对应功能 | T15: 卡背绕Y轴翻面；逆位整张正面卡牌（含边框、图案、文字与布局）收束180°，并显示逆位效果描述；第7发枪身、弹体和枪口焰同时高亮，命中使用专属反馈 | U15: [部分实装] 通用卡背/翻牌/逆位倒置已验收；逐卡逆位专属VFX与音效继续QA | V15: 每第七发 | W15: X | X15: MAJOR | Y15: MAJOR | Z15: 0.5 | AA15: 0.5 | AB15: 选择一个枪身，第 7 发子弹伤害翻倍并引发小爆炸 | AC15: action=EVERY_NTH_FIRE；bonus_effect=small_explosion；damage_multiplier=2；nth=7 | AD15: 每次换弹后第1发×2.5，弹匣-20% | AE15: action=EVERY_RELOAD_FIRST; damage_multiplier=2.5; magazine_multiplier=0.8 | AF15: 0.00s卡背→0.24s薄边换面→0.42s收束；逆位图案/框体180°，卡名、天体、方位标签和说明文字0°；0.62s后可点 | AG15: [设计完成/数据已入表/运行时待施工]
A16: fate_sun_trial | B16: 正义 | C16: 诅咒 | D16: 传说 | E16: 强敌双倍魂 | F16: 下一个敌对房间敌人伤害+25%，其魂掉落×2 | G16: 烈日要求用更危险的一战证明资格，并用双倍魂回报胜者。 | H16: [用户设计] | J16: action=APPLY_SCOPED_MODIFIER；modifier=next_room_trial；damage_multiplier=1.25；currency_multiplier=2 | K16: 门后命运/三选一/工作台共用正式卡池 | L16: [已实装] | M16: [部分实装] 塔罗名称、正/逆位效果快照与通用执行已接入；复杂逆位专属行为继续逐卡QA | N16: src/weapons/FateCard.gd；src/weapons/FateCardPresets.gd；src/weapons/FateCardEngine.gd；src/game/FateCardGameBridge.gd；src/player3d/Player3D.gd；src/world3d/Dungeon3D.gd；docs/v0.1/14_技术施工_命运塔罗牌组.md；src/weapons/TarotFateCatalog.gd；tests/verification/verify_tarot_fate_runtime.gd | O16: 迁移前名称：烈日试炼；稳定ID不变，旧存档迁移为正位，不重投方位 | P16: WORLD | Q16: 不占武器槽；写入行动/房间/掉落/撤离规则状态 | R16: [已实装] 塔罗名称、50/50方位、正逆位同ID、代码翻牌、整卡倒置、逆位描述替换与方位持久化已接入 | S16: ☀ 太阳命运｜正义｜翻牌后显示正位/逆位、目标、槽位与对应功能 | T16: 卡背绕Y轴翻面；逆位整张正面卡牌（含边框、图案、文字与布局）收束180°，并显示逆位效果描述；下一敌对房敌伤乘1.25、魂乘2；风险与收益同时消费 | U16: [部分实装] 通用卡背/翻牌/逆位倒置已验收；逐卡逆位专属VFX与音效继续QA | V16: 烈日试炼 | W16: XI | X16: MAJOR | Y16: MAJOR | Z16: 0.5 | AA16: 0.5 | AB16: 下一个敌对房间敌人伤害+25%，其魂掉落×2 | AC16: action=APPLY_SCOPED_MODIFIER；modifier=next_room_trial；damage_multiplier=1.25；currency_multiplier=2 | AD16: 下房敌伤-20%、魂×0.5 | AE16: action=APPLY_SCOPED_MODIFIER; modifier=next_room_safe_trial; damage_multiplier=0.8; currency_multiplier=0.5 | AF16: 0.00s卡背→0.24s薄边换面→0.42s收束；逆位图案/框体180°，卡名、天体、方位标签和说明文字0°；0.62s后可点 | AG16: [设计完成/数据已入表/运行时待施工]
A17: fate_moon_guard | B17: 倒吊人 | C17: 强化 | D17: 史诗 | E17: 受伤-12% | F17: 本局角色受到的伤害降低12% | G17: 银色月壳在冲击抵达前分走一部分力量。 | H17: [用户设计] | J17: action=APPLY_SCOPED_MODIFIER；modifier=damage_taken；multiplier=0.88 | K17: 门后命运/三选一/工作台共用正式卡池 | L17: [已实装] | M17: [部分实装] 塔罗名称、正/逆位效果快照与通用执行已接入；复杂逆位专属行为继续逐卡QA | N17: src/weapons/FateCard.gd；src/weapons/FateCardPresets.gd；src/weapons/FateCardEngine.gd；src/game/FateCardGameBridge.gd；src/player3d/Player3D.gd；src/world3d/Dungeon3D.gd；docs/v0.1/14_技术施工_命运塔罗牌组.md；src/weapons/TarotFateCatalog.gd；tests/verification/verify_tarot_fate_runtime.gd | O17: 迁移前名称：银月护体；稳定ID不变，旧存档迁移为正位，不重投方位 | P17: CHARACTER | Q17: 不占武器槽；写入角色局内规则状态 | R17: [已实装] 塔罗名称、50/50方位、正逆位同ID、代码翻牌、整卡倒置、逆位描述替换与方位持久化已接入 | S17: ☾ 月亮命运｜倒吊人｜翻牌后显示正位/逆位、目标、槽位与对应功能 | T17: 卡背绕Y轴翻面；逆位整张正面卡牌（含边框、图案、文字与布局）收束180°，并显示逆位效果描述；受击结算乘以0.88，角色状态常驻可见 | U17: [部分实装] 通用卡背/翻牌/逆位倒置已验收；逐卡逆位专属VFX与音效继续QA | V17: 银月护体 | W17: XII | X17: MAJOR | Y17: MAJOR | Z17: 0.5 | AA17: 0.5 | AB17: 本局角色受到的伤害降低12% | AC17: action=APPLY_SCOPED_MODIFIER；modifier=damage_taken；multiplier=0.88 | AD17: 受伤+8%，反射15%实际伤害 | AE17: action=APPLY_SCOPED_MODIFIER; modifier=damage_reflect_trade; damage_taken_multiplier=1.08; reflect_ratio=0.15 | AF17: 0.00s卡背→0.24s薄边换面→0.42s收束；逆位图案/框体180°，卡名、天体、方位标签和说明文字0°；0.62s后可点 | AG17: [设计完成/数据已入表/运行时待施工]
A18: fate_gluttony | B18: 死神 | C18: 诅咒 | D18: 禁忌 | E18: 每次命中子弹变大，伤害变高 | F18: 选择一个子弹，每次命中敌人后子弹伤害和体积增加 15%，最大可叠加 5 次 | G18: 每次命中都让弹体吞下一部分猎物，直到体积与力量达到极限。 | H18: [Codex补充] | I18: select=BULLET | J18: action=SIZE_GROWTH；damage_per_hit=0.15；max_stacks=5；scale_per_hit=0.12 | K18: 门后命运/三选一/工作台共用卡池 | L18: [已实装] | M18: [部分实装] 塔罗名称、正/逆位效果快照与通用执行已接入；复杂逆位专属行为继续逐卡QA | N18: src/weapons/FateCard.gd；src/weapons/FateCardPresets.gd；src/weapons/FateCardEngine.gd；src/game/FateCardGameBridge.gd；docs/v0.1/14_技术施工_命运塔罗牌组.md；src/weapons/TarotFateCatalog.gd；tests/verification/verify_tarot_fate_runtime.gd | O18: 迁移前名称：火力暴食；稳定ID不变，旧存档迁移为正位，不重投方位 | P18: WEAPON | Q18: 占目标枪械下一个永久命运槽；按序追加、不可拆卸/替换/回退 | R18: [已实装] 塔罗名称、50/50方位、正逆位同ID、代码翻牌、整卡倒置、逆位描述替换与方位持久化已接入 | S18: ★ 星星命运｜死神｜翻牌后显示正位/逆位、目标、槽位与对应功能 | T18: 卡背绕Y轴翻面；逆位整张正面卡牌（含边框、图案、文字与布局）收束180°，并显示逆位效果描述；弹体或节点随层数渐进增大；HUD层数与尺寸变化同步，满层明显收束 | U18: [部分实装] 通用卡背/翻牌/逆位倒置已验收；逐卡逆位专属VFX与音效继续QA | V18: 火力暴食 | W18: XIII | X18: MAJOR | Y18: MAJOR | Z18: 0.5 | AA18: 0.5 | AB18: 选择一个子弹，每次命中敌人后子弹伤害和体积增加 15%，最大可叠加 5 次 | AC18: action=SIZE_GROWTH；damage_per_hit=0.15；max_stacks=5；scale_per_hit=0.12 | AD18: 未命中时成长，下次命中消耗全部层数 | AE18: action=SIZE_GROWTH_ON_MISS; damage_per_stack=0.15; scale_per_stack=0.12; max_stacks=5; consume_on_hit=true | AF18: 0.00s卡背→0.24s薄边换面→0.42s收束；逆位图案/框体180°，卡名、天体、方位标签和说明文字0°；0.62s后可点 | AG18: [设计完成/数据已入表/运行时待施工]
A19: fate_sun_scorch | B19: 节制 | C19: 规则 | D19: 史诗 | E19: 下房敌血-20% | F19: 下一个敌对房间的敌人最大生命降低20% | G19: 天火先扫过下一战区，让尚未现身的敌群带着灼伤入场。 | H19: [用户设计] | J19: action=APPLY_SCOPED_MODIFIER；modifier=next_room_enemy_hp；multiplier=0.8 | K19: 门后命运/三选一/工作台共用正式卡池 | L19: [已实装] | M19: [部分实装] 塔罗名称、正/逆位效果快照与通用执行已接入；复杂逆位专属行为继续逐卡QA | N19: src/weapons/FateCard.gd；src/weapons/FateCardPresets.gd；src/weapons/FateCardEngine.gd；src/game/FateCardGameBridge.gd；src/player3d/Player3D.gd；src/world3d/Dungeon3D.gd；docs/v0.1/14_技术施工_命运塔罗牌组.md；src/weapons/TarotFateCatalog.gd；tests/verification/verify_tarot_fate_runtime.gd | O19: 迁移前名称：天火灼地；稳定ID不变，旧存档迁移为正位，不重投方位 | P19: WORLD | Q19: 不占武器槽；写入行动/房间/掉落/撤离规则状态 | R19: [已实装] 塔罗名称、50/50方位、正逆位同ID、代码翻牌、整卡倒置、逆位描述替换与方位持久化已接入 | S19: ☀ 太阳命运｜节制｜翻牌后显示正位/逆位、目标、槽位与对应功能 | T19: 卡背绕Y轴翻面；逆位整张正面卡牌（含边框、图案、文字与布局）收束180°，并显示逆位效果描述；下一敌对房所有波次按0.8最大生命生成，随后清除待用状态 | U19: [部分实装] 通用卡背/翻牌/逆位倒置已验收；逐卡逆位专属VFX与音效继续QA | V19: 天火灼地 | W19: XIV | X19: MAJOR | Y19: MAJOR | Z19: 0.5 | AA19: 0.5 | AB19: 下一个敌对房间的敌人最大生命降低20% | AC19: action=APPLY_SCOPED_MODIFIER；modifier=next_room_enemy_hp；multiplier=0.8 | AD19: 下房敌血+20%，敌伤-20% | AE19: action=APPLY_SCOPED_MODIFIER; modifier=next_room_endurance; hp_multiplier=1.2; damage_multiplier=0.8 | AF19: 0.00s卡背→0.24s薄边换面→0.42s收束；逆位图案/框体180°，卡名、天体、方位标签和说明文字0°；0.62s后可点 | AG19: [设计完成/数据已入表/运行时待施工]
A20: fate_out_of_control | B20: 恶魔 | C20: 诅咒 | D20: 禁忌 | E20: 子弹上的枪随机乱射 | F20: 选择一个子弹，携带的枪会随机乱射，射击方向完全随机，伤害提升 30% | G20: 失控的附属枪不再等待瞄准，用更高伤害换取完全不可预测的方向。 | H20: [Codex补充] | I20: require_gun=true；select=BULLET | J20: action=OUT_OF_CONTROL；damage_scale=1.3；fire_rate_scale=2；spread_angle=360 | K20: 门后命运/三选一/工作台共用卡池 | L20: [已实装] | M20: [部分实装] 塔罗名称、正/逆位效果快照与通用执行已接入；复杂逆位专属行为继续逐卡QA | N20: src/weapons/FateCard.gd；src/weapons/FateCardPresets.gd；src/weapons/FateCardEngine.gd；src/game/FateCardGameBridge.gd；docs/v0.1/14_技术施工_命运塔罗牌组.md；src/weapons/TarotFateCatalog.gd；tests/verification/verify_tarot_fate_runtime.gd | O20: 迁移前名称：管不住了；稳定ID不变，旧存档迁移为正位，不重投方位 | P20: WEAPON | Q20: 占目标枪械下一个永久命运槽；按序追加、不可拆卸/替换/回退 | R20: [已实装] 塔罗名称、50/50方位、正逆位同ID、代码翻牌、整卡倒置、逆位描述替换与方位持久化已接入 | S20: ★ 星星命运｜恶魔｜翻牌后显示正位/逆位、目标、槽位与对应功能 | T20: 卡背绕Y轴翻面；逆位整张正面卡牌（含边框、图案、文字与布局）收束180°，并显示逆位效果描述；枪身警示脉冲、异常后坐/弹道与危险音色对应真实失控规则 | U20: [部分实装] 通用卡背/翻牌/逆位倒置已验收；逐卡逆位专属VFX与音效继续QA | V20: 管不住了 | W20: XV | X20: MAJOR | Y20: MAJOR | Z20: 0.5 | AA20: 0.5 | AB20: 选择一个子弹，携带的枪会随机乱射，射击方向完全随机，伤害提升 30% | AC20: action=OUT_OF_CONTROL；damage_scale=1.3；fire_rate_scale=2；spread_angle=360 | AD20: 乱射收束为90°锥形，射速更高但后坐增大 | AE20: action=OUT_OF_CONTROL; spread_angle=90; fire_rate_scale=2.5; damage_scale=1.15; recoil_scale=1.5 | AF20: 0.00s卡背→0.24s薄边换面→0.42s收束；逆位图案/框体180°，卡名、天体、方位标签和说明文字0°；0.62s后可点 | AG20: [设计完成/数据已入表/运行时待施工]
A21: fate_explode_reload | B21: 高塔 | C21: 诅咒 | D21: 禁忌 | E21: 换弹时对周围造成爆炸伤害 | F21: 选择一个枪身，换弹时对周围 150 范围内的敌人造成 80% 伤害的爆炸，但换弹时间增加 0.5 秒 | G21: 被排出的热量在换弹瞬间释放，保护了空窗，也延长了空窗。 | H21: [Codex补充] | I21: select=GUNBODY | J21: action=EXPLODE_ON_RELOAD；explosion_damage=0.8；explosion_radius=150；reload_penalty=0.5 | K21: 门后命运/三选一/工作台共用卡池 | L21: [已实装] | M21: [部分实装] 塔罗名称、正/逆位效果快照与通用执行已接入；复杂逆位专属行为继续逐卡QA | N21: src/weapons/FateCard.gd；src/weapons/FateCardPresets.gd；src/weapons/FateCardEngine.gd；src/game/FateCardGameBridge.gd；docs/v0.1/14_技术施工_命运塔罗牌组.md；src/weapons/TarotFateCatalog.gd；tests/verification/verify_tarot_fate_runtime.gd | O21: 迁移前名称：换弹爆炸；稳定ID不变，旧存档迁移为正位，不重投方位 | P21: WEAPON | Q21: 占目标枪械下一个永久命运槽；按序追加、不可拆卸/替换/回退 | R21: [已实装] 塔罗名称、50/50方位、正逆位同ID、代码翻牌、整卡倒置、逆位描述替换与方位持久化已接入 | S21: ★ 星星命运｜高塔｜翻牌后显示正位/逆位、目标、槽位与对应功能 | T21: 卡背绕Y轴翻面；逆位整张正面卡牌（含边框、图案、文字与布局）收束180°，并显示逆位效果描述；换弹开始显示范围圈与充能，结算时爆炸VFX/音效和伤害时点一致 | U21: [部分实装] 通用卡背/翻牌/逆位倒置已验收；逐卡逆位专属VFX与音效继续QA | V21: 换弹爆炸 | W21: XVI | X21: MAJOR | Y21: MAJOR | Z21: 0.5 | AA21: 0.5 | AB21: 选择一个枪身，换弹时对周围 150 范围内的敌人造成 80% 伤害的爆炸，但换弹时间增加 0.5 秒 | AC21: action=EXPLODE_ON_RELOAD；explosion_damage=0.8；explosion_radius=150；reload_penalty=0.5 | AD21: 换弹产生低伤吸引爆炸，换弹+0.2秒 | AE21: action=IMPLODE_ON_RELOAD; explosion_damage=0.5; radius=180; pull_strength=1; reload_penalty=0.2 | AF21: 0.00s卡背→0.24s薄边换面→0.42s收束；逆位图案/框体180°，卡名、天体、方位标签和说明文字0°；0.62s后可点 | AG21: [设计完成/数据已入表/运行时待施工]
A22: fate_living_bullet | B22: 星星 | C22: 变种 | D22: 稀有 | E22: 子弹会追踪最近的敌人 | F22: 选择一个子弹，使其变成追踪弹，自动飞向最近的敌人 | G22: 弹体长出了辨认敌意的本能，它不再服从直线，只服从最近的猎物。 | H22: [Codex补充] | I22: select=BULLET | J22: action=MUTATE_TO_HOMING；homing_strength=0.6；turn_rate=3 | K22: 门后命运/三选一/工作台共用卡池 | L22: [已实装] | M22: [部分实装] 塔罗名称、正/逆位效果快照与通用执行已接入；复杂逆位专属行为继续逐卡QA | N22: src/weapons/FateCard.gd；src/weapons/FateCardPresets.gd；src/weapons/FateCardEngine.gd；src/game/FateCardGameBridge.gd；docs/v0.1/14_技术施工_命运塔罗牌组.md；src/weapons/TarotFateCatalog.gd；tests/verification/verify_tarot_fate_runtime.gd | O22: 迁移前名称：活过来；稳定ID不变，旧存档迁移为正位，不重投方位 | P22: WEAPON | Q22: 占目标枪械下一个永久命运槽；按序追加、不可拆卸/替换/回退 | R22: [已实装] 塔罗名称、50/50方位、正逆位同ID、代码翻牌、整卡倒置、逆位描述替换与方位持久化已接入 | S22: ★ 星星命运｜星星｜翻牌后显示正位/逆位、目标、槽位与对应功能 | T22: 卡背绕Y轴翻面；逆位整张正面卡牌（含边框、图案、文字与布局）收束180°，并显示逆位效果描述；弹体获得生命化轮廓与转向动作，尾迹表现主动寻敌而非普通追踪 | U22: [部分实装] 通用卡背/翻牌/逆位倒置已验收；逐卡逆位专属VFX与音效继续QA | V22: 活过来 | W22: XVII | X22: MAJOR | Y22: MAJOR | Z22: 0.5 | AA22: 0.5 | AB22: 选择一个子弹，使其变成追踪弹，自动飞向最近的敌人 | AC22: action=MUTATE_TO_HOMING；homing_strength=0.6；turn_rate=3 | AD22: 子弹追踪最远可见敌人，伤害+25% | AE22: action=MUTATE_TO_HOMING; target_policy=FARTHEST_VISIBLE; homing_strength=0.35; damage_scale=1.25 | AF22: 0.00s卡背→0.24s薄边换面→0.42s收束；逆位图案/框体180°，卡名、天体、方位标签和说明文字0°；0.62s后可点 | AG22: [设计完成/数据已入表/运行时待施工]
A23: fate_moon_first_hit | B23: 月亮 | C23: 规则 | D23: 传说 | E23: 首次受伤减半 | F23: 每个房间第一次受到的伤害降低50% | G23: 静夜只替进入者挡下第一记冲击，随后屏障沉寂。 | H23: [用户设计] | J23: action=APPLY_SCOPED_MODIFIER；modifier=first_hit_guard；multiplier=0.5 | K23: 门后命运/三选一/工作台共用正式卡池 | L23: [已实装] | M23: [部分实装] 塔罗名称、正/逆位效果快照与通用执行已接入；复杂逆位专属行为继续逐卡QA | N23: src/weapons/FateCard.gd；src/weapons/FateCardPresets.gd；src/weapons/FateCardEngine.gd；src/game/FateCardGameBridge.gd；src/player3d/Player3D.gd；src/world3d/Dungeon3D.gd；docs/v0.1/14_技术施工_命运塔罗牌组.md；src/weapons/TarotFateCatalog.gd；tests/verification/verify_tarot_fate_runtime.gd | O23: 迁移前名称：静夜屏障；稳定ID不变，旧存档迁移为正位，不重投方位 | P23: CHARACTER | Q23: 不占武器槽；写入角色局内规则状态 | R23: [已实装] 塔罗名称、50/50方位、正逆位同ID、代码翻牌、整卡倒置、逆位描述替换与方位持久化已接入 | S23: ☾ 月亮命运｜月亮｜翻牌后显示正位/逆位、目标、槽位与对应功能 | T23: 卡背绕Y轴翻面；逆位整张正面卡牌（含边框、图案、文字与布局）收束180°，并显示逆位效果描述；首次进入房间重置屏障；第一次受伤后立即消耗 | U23: [部分实装] 通用卡背/翻牌/逆位倒置已验收；逐卡逆位专属VFX与音效继续QA | V23: 静夜屏障 | W23: XVIII | X23: MAJOR | Y23: MAJOR | Z23: 0.5 | AA23: 0.5 | AB23: 每个房间第一次受到的伤害降低50% | AC23: action=APPLY_SCOPED_MODIFIER；modifier=first_hit_guard；multiplier=0.5 | AD23: 首次受伤不减免，随后3次受伤-20% | AE23: action=APPLY_SCOPED_MODIFIER; modifier=delayed_guard; first_hit_multiplier=1; next_hits=3; next_hit_multiplier=0.8 | AF23: 0.00s卡背→0.24s薄边换面→0.42s收束；逆位图案/框体180°，卡名、天体、方位标签和说明文字0°；0.62s后可点 | AG23: [设计完成/数据已入表/运行时待施工]
A24: fate_sun_currency | B24: 太阳 | C24: 强化 | D24: 史诗 | E24: 魂获取+30% | F24: 本局之后获得的魂数量提升30% | G24: 太阳把敌人遗留的魂染成金色，让之后的收获更丰厚。 | H24: [用户设计] | J24: action=APPLY_SCOPED_MODIFIER；modifier=currency_gain；multiplier=1.3 | K24: 门后命运/三选一/工作台共用正式卡池 | L24: [已实装] | M24: [部分实装] 塔罗名称、正/逆位效果快照与通用执行已接入；复杂逆位专属行为继续逐卡QA | N24: src/weapons/FateCard.gd；src/weapons/FateCardPresets.gd；src/weapons/FateCardEngine.gd；src/game/FateCardGameBridge.gd；src/player3d/Player3D.gd；src/world3d/Dungeon3D.gd；docs/v0.1/14_技术施工_命运塔罗牌组.md；src/weapons/TarotFateCatalog.gd；tests/verification/verify_tarot_fate_runtime.gd | O24: 迁移前名称：黄金潮汐；稳定ID不变，旧存档迁移为正位，不重投方位 | P24: WORLD | Q24: 不占武器槽；写入行动/房间/掉落/撤离规则状态 | R24: [已实装] 塔罗名称、50/50方位、正逆位同ID、代码翻牌、整卡倒置、逆位描述替换与方位持久化已接入 | S24: ☀ 太阳命运｜太阳｜翻牌后显示正位/逆位、目标、槽位与对应功能 | T24: 卡背绕Y轴翻面；逆位整张正面卡牌（含边框、图案、文字与布局）收束180°，并显示逆位效果描述；之后敌人魂掉落乘以1.3；太阳命运常驻栏显示来源 | U24: [部分实装] 通用卡背/翻牌/逆位倒置已验收；逐卡逆位专属VFX与音效继续QA | V24: 黄金潮汐 | W24: XIX | X24: MAJOR | Y24: MAJOR | Z24: 0.5 | AA24: 0.5 | AB24: 本局之后获得的魂数量提升30% | AC24: action=APPLY_SCOPED_MODIFIER；modifier=currency_gain；multiplier=1.3 | AD24: 魂获取-15%，每第3件掉落品质+1 | AE24: action=APPLY_SCOPED_MODIFIER; modifier=currency_quality_trade; currency_multiplier=0.85; every_nth_drop=3; rarity_tiers=1 | AF24: 0.00s卡背→0.24s薄边换面→0.42s收束；逆位图案/框体180°，卡名、天体、方位标签和说明文字0°；0.62s后可点 | AG24: [设计完成/数据已入表/运行时待施工]
A25: fate_moon_last_stand | B25: 审判 | C25: 规则 | D25: 传说 | E25: 致命伤保留1血 | F25: 致命伤改为保留1生命；每张牌提供1次 | G25: 残月不会阻止伤害，只在生命归零前留下最后一道弧光。 | H25: [用户设计] | J25: action=APPLY_SCOPED_MODIFIER；modifier=last_stand；charges=1 | K25: 门后命运/三选一/工作台共用正式卡池 | L25: [已实装] | M25: [部分实装] 塔罗名称、正/逆位效果快照与通用执行已接入；复杂逆位专属行为继续逐卡QA | N25: src/weapons/FateCard.gd；src/weapons/FateCardPresets.gd；src/weapons/FateCardEngine.gd；src/game/FateCardGameBridge.gd；src/player3d/Player3D.gd；src/world3d/Dungeon3D.gd；docs/v0.1/14_技术施工_命运塔罗牌组.md；src/weapons/TarotFateCatalog.gd；tests/verification/verify_tarot_fate_runtime.gd | O25: 迁移前名称：残月不灭；稳定ID不变，旧存档迁移为正位，不重投方位 | P25: CHARACTER | Q25: 不占武器槽；写入角色局内规则状态 | R25: [已实装] 塔罗名称、50/50方位、正逆位同ID、代码翻牌、整卡倒置、逆位描述替换与方位持久化已接入 | S25: ☾ 月亮命运｜审判｜翻牌后显示正位/逆位、目标、槽位与对应功能 | T25: 卡背绕Y轴翻面；逆位整张正面卡牌（含边框、图案、文字与布局）收束180°，并显示逆位效果描述；致命伤结算保留1血并消费1次；剩余次数保存在角色状态 | U25: [部分实装] 通用卡背/翻牌/逆位倒置已验收；逐卡逆位专属VFX与音效继续QA | V25: 残月不灭 | W25: XX | X25: MAJOR | Y25: MAJOR | Z25: 0.5 | AA25: 0.5 | AB25: 致命伤改为保留1生命；每张牌提供1次 | AC25: action=APPLY_SCOPED_MODIFIER；modifier=last_stand；charges=1 | AD25: 致命时消耗50魂并恢复25%生命，每张1次 | AE25: action=APPLY_SCOPED_MODIFIER; modifier=paid_last_stand; currency_cost=50; restore_ratio=0.25; charges=1 | AF25: 0.00s卡背→0.24s薄边换面→0.42s收束；逆位图案/框体180°，卡名、天体、方位标签和说明文字0°；0.62s后可点 | AG25: [设计完成/数据已入表/运行时待施工]
A26: fate_sun_extraction | B26: 世界 | C26: 规则 | D26: 传说 | E26: 撤离时间-20% | F26: 本局所有撤离同步时间缩短20% | G26: 日落前留下的短暂通道压缩了所有撤离信标的同步过程。 | H26: [用户设计] | J26: action=APPLY_SCOPED_MODIFIER；modifier=extraction_time；multiplier=0.8 | K26: 门后命运/三选一/工作台共用正式卡池 | L26: [已实装] | M26: [部分实装] 塔罗名称、正/逆位效果快照与通用执行已接入；复杂逆位专属行为继续逐卡QA | N26: src/weapons/FateCard.gd；src/weapons/FateCardPresets.gd；src/weapons/FateCardEngine.gd；src/game/FateCardGameBridge.gd；src/player3d/Player3D.gd；src/world3d/Dungeon3D.gd；docs/v0.1/14_技术施工_命运塔罗牌组.md；src/weapons/TarotFateCatalog.gd；tests/verification/verify_tarot_fate_runtime.gd | O26: 迁移前名称：日落捷径；稳定ID不变，旧存档迁移为正位，不重投方位 | P26: WORLD | Q26: 不占武器槽；写入行动/房间/掉落/撤离规则状态 | R26: [已实装] 塔罗名称、50/50方位、正逆位同ID、代码翻牌、整卡倒置、逆位描述替换与方位持久化已接入 | S26: ☀ 太阳命运｜世界｜翻牌后显示正位/逆位、目标、槽位与对应功能 | T26: 卡背绕Y轴翻面；逆位整张正面卡牌（含边框、图案、文字与布局）收束180°，并显示逆位效果描述；现有与后续撤离信标时长乘0.8，撤离HUD使用新时长 | U26: [部分实装] 通用卡背/翻牌/逆位倒置已验收；逐卡逆位专属VFX与音效继续QA | V26: 日落捷径 | W26: XXI | X26: MAJOR | Y26: MAJOR | Z26: 0.5 | AA26: 0.5 | AB26: 本局所有撤离同步时间缩短20% | AC26: action=APPLY_SCOPED_MODIFIER；modifier=extraction_time；multiplier=0.8 | AD26: 撤离时间+30%，同步区内敌人移速-50% | AE26: action=APPLY_SCOPED_MODIFIER; modifier=slow_extraction; time_multiplier=1.3; enemy_speed_multiplier=0.5 | AF26: 0.00s卡背→0.24s薄边换面→0.42s收束；逆位图案/框体180°，卡名、天体、方位标签和说明文字0°；0.62s后可点 | AG26: [设计完成/数据已入表/运行时待施工]
A27: fate_scale_node | B27: 权杖·王牌 | C27: 强化 | D27: 普通 | E27: 体型与碰撞范围增加 | F27: 选择一个节点，体型与碰撞范围增加，伤害提升 30%，速度降低 20% | G27: 塔内的尺度并不可信；一枚被命运放大的零件，会用迟缓交换压倒性的体积。 | H27: [Codex补充] | J27: action=SCALE_NODE；damage_scale=1.3；scale=1.4；speed_scale=0.8 | K27: 门后命运/三选一/工作台共用卡池 | L27: [已实装] | M27: [部分实装] 塔罗名称、正/逆位效果快照与通用执行已接入；复杂逆位专属行为继续逐卡QA | N27: src/weapons/FateCard.gd；src/weapons/FateCardPresets.gd；src/weapons/FateCardEngine.gd；src/game/FateCardGameBridge.gd；docs/v0.1/14_技术施工_命运塔罗牌组.md；src/weapons/TarotFateCatalog.gd；tests/verification/verify_tarot_fate_runtime.gd | O27: 迁移前名称：变大了；稳定ID不变，旧存档迁移为正位，不重投方位 | P27: WEAPON | Q27: 占目标枪械下一个永久命运槽；按序追加、不可拆卸/替换/回退 | R27: [已实装] 塔罗名称、50/50方位、正逆位同ID、代码翻牌、整卡倒置、逆位描述替换与方位持久化已接入 | S27: ★ 星星命运｜权杖·王牌｜翻牌后显示正位/逆位、目标、槽位与对应功能 | T27: 卡背绕Y轴翻面；逆位整张正面卡牌（含边框、图案、文字与布局）收束180°，并显示逆位效果描述；被放大的枪体/挂件/弹体同步改变轮廓、动作重量和尾迹，命中体积与规则一致 | U27: [部分实装] 通用卡背/翻牌/逆位倒置已验收；逐卡逆位专属VFX与音效继续QA | V27: 变大了 | W27: ACE | X27: MINOR | Y27: WANDS | Z27: 0.5 | AA27: 0.5 | AB27: 选择一个节点，体型与碰撞范围增加，伤害提升 30%，速度降低 20% | AC27: action=SCALE_NODE；damage_scale=1.3；scale=1.4；speed_scale=0.8 | AD27: 体积×0.75、伤害-20%、速度+25% | AE27: action=SCALE_NODE; scale=0.75; damage_scale=0.8; speed_scale=1.25 | AF27: 0.00s卡背→0.24s薄边换面→0.42s收束；逆位图案/框体180°，卡名、天体、方位标签和说明文字0°；0.62s后可点 | AG27: [设计完成/数据已入表/运行时待施工]
A28: fate_overclock | B28: 权杖·二 | C28: 强化 | D28: 稀有 | E28: 射速提升 80% | F28: 选择一个枪身，射速提升 80%，但每次射击后累计受击伤害倍率（overheat_penalty=1.5：射击越多，受伤越痛） | G28: 把供能旋钮拧过红线的人通常只记得火力，却忘了过热会把每次受击放大。 | H28: [Codex补充] | J28: action=MULTIPLY_FIRE_RATE；fire_rate_scale=1.8；overheat_penalty=1.5 | K28: 门后命运/三选一/工作台共用卡池 | L28: [已实装] | M28: [部分实装] 塔罗名称、正/逆位效果快照与通用执行已接入；复杂逆位专属行为继续逐卡QA | N28: src/weapons/FateCard.gd；src/weapons/FateCardPresets.gd；src/weapons/FateCardEngine.gd；src/game/FateCardGameBridge.gd；docs/v0.1/14_技术施工_命运塔罗牌组.md；src/weapons/TarotFateCatalog.gd；tests/verification/verify_tarot_fate_runtime.gd | O28: 迁移前名称：超频；稳定ID不变，旧存档迁移为正位，不重投方位 | P28: WEAPON | Q28: 占目标枪械下一个永久命运槽；按序追加、不可拆卸/替换/回退 | R28: [已实装] 塔罗名称、50/50方位、正逆位同ID、代码翻牌、整卡倒置、逆位描述替换与方位持久化已接入 | S28: ★ 星星命运｜权杖·二｜翻牌后显示正位/逆位、目标、槽位与对应功能 | T28: 卡背绕Y轴翻面；逆位整张正面卡牌（含边框、图案、文字与布局）收束180°，并显示逆位效果描述；枪管热色、机械循环、枪口节奏和过热反馈同步，不能只让数值变快 | U28: [部分实装] 通用卡背/翻牌/逆位倒置已验收；逐卡逆位专属VFX与音效继续QA | V28: 超频 | W28: 2 | X28: MINOR | Y28: WANDS | Z28: 0.5 | AA28: 0.5 | AB28: 选择一个枪身，射速提升 80%，但每次射击后累计受击伤害倍率（overheat_penalty=1.5：射击越多，受伤越痛） | AC28: action=MULTIPLY_FIRE_RATE；fire_rate_scale=1.8；overheat_penalty=1.5 | AD28: 射速-25%，单发伤害+55% | AE28: action=MULTIPLY_FIRE_RATE; fire_rate_scale=0.75; damage_scale=1.55 | AF28: 0.00s卡背→0.24s薄边换面→0.42s收束；逆位图案/框体180°，卡名、天体、方位标签和说明文字0°；0.62s后可点 | AG28: [设计完成/数据已入表/运行时待施工]
A29: fate_attachment_parasite | B29: 权杖·三 | C29: 组合 | D29: 史诗 | E29: 配件附在子弹上，命中时触发效果 | F29: 选择一个配件使其寄生到子弹上，命中时触发配件效果 | G29: 活化配件会抓住弹体，把原本静止的功能带到每一次命中现场。 | H29: [Codex补充] | I29: select=BULLET | J29: action=ATTACH_TO_MOUNT；target_slot=MUZZLE；trigger_on_hit=true | K29: 门后命运/三选一/工作台共用卡池 | L29: [已实装] | M29: [部分实装] 塔罗名称、正/逆位效果快照与通用执行已接入；复杂逆位专属行为继续逐卡QA | N29: src/weapons/FateCard.gd；src/weapons/FateCardPresets.gd；src/weapons/FateCardEngine.gd；src/game/FateCardGameBridge.gd；docs/v0.1/14_技术施工_命运塔罗牌组.md；src/weapons/TarotFateCatalog.gd；tests/verification/verify_tarot_fate_runtime.gd | O29: 迁移前名称：配件寄生；稳定ID不变，旧存档迁移为正位，不重投方位 | P29: WEAPON | Q29: 占目标枪械下一个永久命运槽；按序追加、不可拆卸/替换/回退 | R29: [已实装] 塔罗名称、50/50方位、正逆位同ID、代码翻牌、整卡倒置、逆位描述替换与方位持久化已接入 | S29: ★ 星星命运｜权杖·三｜翻牌后显示正位/逆位、目标、槽位与对应功能 | T29: 卡背绕Y轴翻面；逆位整张正面卡牌（含边框、图案、文字与布局）收束180°，并显示逆位效果描述；寄生部位有有机脉冲；命中触发时局部亮起并在目标处播放专属反馈 | U29: [部分实装] 通用卡背/翻牌/逆位倒置已验收；逐卡逆位专属VFX与音效继续QA | V29: 配件寄生 | W29: 3 | X29: MINOR | Y29: WANDS | Z29: 0.5 | AA29: 0.5 | AB29: 选择一个配件使其寄生到子弹上，命中时触发配件效果 | AC29: action=ATTACH_TO_MOUNT；target_slot=MUZZLE；trigger_on_hit=true | AD29: 配件效果改在换弹完成时触发，3秒冷却 | AE29: action=ATTACH_TO_MOUNT; trigger=RELOAD_COMPLETE; cooldown=3 | AF29: 0.00s卡背→0.24s薄边换面→0.42s收束；逆位图案/框体180°，卡名、天体、方位标签和说明文字0°；0.62s后可点 | AG29: [设计完成/数据已入表/运行时待施工]
A30: fate_turret_on_land | B30: 权杖·四 | C30: 变种 | D30: 史诗 | E30: 子弹落地后自动炮击 | F30: 选择一个子弹，子弹落地后生成一座自动炮台，持续射击附近的敌人 | G30: 未命中的子弹拒绝浪费自己，它在落地点扎根并继续履行射击职责。 | H30: [Codex补充] | I30: select=BULLET | J30: action=MUTATE_TO_TURRET_ON_LAND；turret_damage=0.3；turret_duration=8；turret_fire_rate=2 | K30: 门后命运/三选一/工作台共用卡池 | L30: [已实装] | M30: [部分实装] 塔罗名称、正/逆位效果快照与通用执行已接入；复杂逆位专属行为继续逐卡QA | N30: src/weapons/FateCard.gd；src/weapons/FateCardPresets.gd；src/weapons/FateCardEngine.gd；src/game/FateCardGameBridge.gd；docs/v0.1/14_技术施工_命运塔罗牌组.md；src/weapons/TarotFateCatalog.gd；tests/verification/verify_tarot_fate_runtime.gd | O30: 迁移前名称：落地炮台；稳定ID不变，旧存档迁移为正位，不重投方位 | P30: WEAPON | Q30: 占目标枪械下一个永久命运槽；按序追加、不可拆卸/替换/回退 | R30: [已实装] 塔罗名称、50/50方位、正逆位同ID、代码翻牌、整卡倒置、逆位描述替换与方位持久化已接入 | S30: ★ 星星命运｜权杖·四｜翻牌后显示正位/逆位、目标、槽位与对应功能 | T30: 卡背绕Y轴翻面；逆位整张正面卡牌（含边框、图案、文字与布局）收束180°，并显示逆位效果描述；弹体落地变为可辨炮塔，生成、攻击、结束三阶段均有反馈 | U30: [部分实装] 通用卡背/翻牌/逆位倒置已验收；逐卡逆位专属VFX与音效继续QA | V30: 落地炮台 | W30: 4 | X30: MINOR | Y30: WANDS | Z30: 0.5 | AA30: 0.5 | AB30: 选择一个子弹，子弹落地后生成一座自动炮台，持续射击附近的敌人 | AC30: action=MUTATE_TO_TURRET_ON_LAND；turret_damage=0.3；turret_duration=8；turret_fire_rate=2 | AD30: 落地生成4秒追随玩家的移动炮台 | AE30: action=MUTATE_TO_FOLLOW_TURRET; duration=4; turret_damage=0.3; follow_player=true | AF30: 0.00s卡背→0.24s薄边换面→0.42s收束；逆位图案/框体180°，卡名、天体、方位标签和说明文字0°；0.62s后可点 | AG30: [设计完成/数据已入表/运行时待施工]
A31: fate_home_on_land | B31: 权杖·五 | C31: 变种 | D31: 稀有 | E31: 子弹飞出去后返回玩家 | F31: 选择一个子弹，子弹飞出后返回玩家方向，返回途中继续造成 60% 伤害，持续 5 秒 | G31: 被塔拒绝的弹体沿旧轨迹回返，在归途上仍然记得谁是敌人。 | H31: [Codex补充] | I31: select=BULLET | J31: action=MUTATE_TO_HOME_ON_LAND；home_lifetime=5；return_damage_multiplier=0.6 | K31: 门后命运/三选一/工作台共用卡池 | L31: [已实装] | M31: [部分实装] 塔罗名称、正/逆位效果快照与通用执行已接入；复杂逆位专属行为继续逐卡QA | N31: src/weapons/FateCard.gd；src/weapons/FateCardPresets.gd；src/weapons/FateCardEngine.gd；src/game/FateCardGameBridge.gd；docs/v0.1/14_技术施工_命运塔罗牌组.md；src/weapons/TarotFateCatalog.gd；tests/verification/verify_tarot_fate_runtime.gd | O31: 迁移前名称：回家看看；稳定ID不变，旧存档迁移为正位，不重投方位 | P31: WEAPON | Q31: 占目标枪械下一个永久命运槽；按序追加、不可拆卸/替换/回退 | R31: [已实装] 塔罗名称、50/50方位、正逆位同ID、代码翻牌、整卡倒置、逆位描述替换与方位持久化已接入 | S31: ★ 星星命运｜权杖·五｜翻牌后显示正位/逆位、目标、槽位与对应功能 | T31: 卡背绕Y轴翻面；逆位整张正面卡牌（含边框、图案、文字与布局）收束180°，并显示逆位效果描述；落地时生成返航弧线与目标标记，回收/消失时给出明确收束 | U31: [部分实装] 通用卡背/翻牌/逆位倒置已验收；逐卡逆位专属VFX与音效继续QA | V31: 回家看看 | W31: 5 | X31: MINOR | Y31: WANDS | Z31: 0.5 | AA31: 0.5 | AB31: 选择一个子弹，子弹飞出后返回玩家方向，返回途中继续造成 60% 伤害，持续 5 秒 | AC31: action=MUTATE_TO_HOME_ON_LAND；home_lifetime=5；return_damage_multiplier=0.6 | AD31: 去程伤害-30%，回程伤害+120% | AE31: action=MUTATE_TO_HOME_ON_LAND; outbound_damage_scale=0.7; return_damage_multiplier=2.2; lifetime=4 | AF31: 0.00s卡背→0.24s薄边换面→0.42s收束；逆位图案/框体180°，卡名、天体、方位标签和说明文字0°；0.62s后可点 | AG31: [设计完成/数据已入表/运行时待施工]
A32: fate_bullet_return | B32: 权杖·六 | C32: 变种 | D32: 稀有 | E32: 子弹命中后折返并再命中一次 | F32: 选择一个子弹，命中目标后折返回玩家方向，再次尝试命中敌人 | G32: 命中不是终点；弹体借撞击改写方向，寻找第二次穿越战场的机会。 | H32: [Codex补充] | I32: select=BULLET | J32: action=MUTATE_TO_BOUNCE；bounce_count=1；damage_scale_on_bounce=0.7 | K32: 门后命运/三选一/工作台共用卡池 | L32: [已实装] | M32: [部分实装] 塔罗名称、正/逆位效果快照与通用执行已接入；复杂逆位专属行为继续逐卡QA | N32: src/weapons/FateCard.gd；src/weapons/FateCardPresets.gd；src/weapons/FateCardEngine.gd；src/game/FateCardGameBridge.gd；docs/v0.1/14_技术施工_命运塔罗牌组.md；src/weapons/TarotFateCatalog.gd；tests/verification/verify_tarot_fate_runtime.gd | O32: 迁移前名称：子弹折返；稳定ID不变，旧存档迁移为正位，不重投方位 | P32: WEAPON | Q32: 占目标枪械下一个永久命运槽；按序追加、不可拆卸/替换/回退 | R32: [已实装] 塔罗名称、50/50方位、正逆位同ID、代码翻牌、整卡倒置、逆位描述替换与方位持久化已接入 | S32: ★ 星星命运｜权杖·六｜翻牌后显示正位/逆位、目标、槽位与对应功能 | T32: 卡背绕Y轴翻面；逆位整张正面卡牌（含边框、图案、文字与布局）收束180°，并显示逆位效果描述；命中后尾迹反色并沿清晰弧线返回，回到枪/玩家时有回收音 | U32: [部分实装] 通用卡背/翻牌/逆位倒置已验收；逐卡逆位专属VFX与音效继续QA | V32: 子弹折返 | W32: 6 | X32: MINOR | Y32: WANDS | Z32: 0.5 | AA32: 0.5 | AB32: 选择一个子弹，命中目标后折返回玩家方向，再次尝试命中敌人 | AC32: action=MUTATE_TO_BOUNCE；bounce_count=1；damage_scale_on_bounce=0.7 | AD32: 命中后返回枪械并回填1发弹药，不造回程伤害 | AE32: action=RETURN_AND_REFUND; ammo_refund=1; return_damage_scale=0 | AF32: 0.00s卡背→0.24s薄边换面→0.42s收束；逆位图案/框体180°，卡名、天体、方位标签和说明文字0°；0.62s后可点 | AG32: [设计完成/数据已入表/运行时待施工]
A33: fate_chain_lightning | B33: 权杖·七 | C33: 变种 | D33: 史诗 | E33: 命中后在敌人间跳跃，最多3次 | F33: 选择一个子弹，命中后在敌人间跳跃，每次跳跃伤害递减 30% | G33: 导电孢子把一次命中扩散成短暂电网，越远的跳跃越难保持力量。 | H33: [Codex补充] | I33: select=BULLET | J33: action=MUTATE_TO_CHAIN；chain_count=3；chain_damage_scale=0.7；chain_range=150 | K33: 门后命运/三选一/工作台共用卡池 | L33: [已实装] | M33: [部分实装] 塔罗名称、正/逆位效果快照与通用执行已接入；复杂逆位专属行为继续逐卡QA | N33: src/weapons/FateCard.gd；src/weapons/FateCardPresets.gd；src/weapons/FateCardEngine.gd；src/game/FateCardGameBridge.gd；docs/v0.1/14_技术施工_命运塔罗牌组.md；src/weapons/TarotFateCatalog.gd；tests/verification/verify_tarot_fate_runtime.gd | O33: 迁移前名称：连锁闪电；稳定ID不变，旧存档迁移为正位，不重投方位 | P33: WEAPON | Q33: 占目标枪械下一个永久命运槽；按序追加、不可拆卸/替换/回退 | R33: [已实装] 塔罗名称、50/50方位、正逆位同ID、代码翻牌、整卡倒置、逆位描述替换与方位持久化已接入 | S33: ★ 星星命运｜权杖·七｜翻牌后显示正位/逆位、目标、槽位与对应功能 | T33: 卡背绕Y轴翻面；逆位整张正面卡牌（含边框、图案、文字与布局）收束180°，并显示逆位效果描述；敌人间产生按顺序跳转的电弧；每次跳转与实际结算同步 | U33: [部分实装] 通用卡背/翻牌/逆位倒置已验收；逐卡逆位专属VFX与音效继续QA | V33: 连锁闪电 | W33: 7 | X33: MINOR | Y33: WANDS | Z33: 0.5 | AA33: 0.5 | AB33: 选择一个子弹，命中后在敌人间跳跃，每次跳跃伤害递减 30% | AC33: action=MUTATE_TO_CHAIN；chain_count=3；chain_damage_scale=0.7；chain_range=150 | AD33: 最多连锁5次，范围缩小且每跳伤50% | AE33: action=MUTATE_TO_CHAIN; chain_count=5; chain_range=100; chain_damage_scale=0.5 | AF33: 0.00s卡背→0.24s薄边换面→0.42s收束；逆位图案/框体180°，卡名、天体、方位标签和说明文字0°；0.62s后可点 | AG33: [设计完成/数据已入表/运行时待施工]
A34: fate_bounce_bullet | B34: 权杖·八 | C34: 变种 | D34: 普通 | E34: 子弹在边界间弹跳3次 | F34: 选择一个子弹，使其在墙壁和障碍物间弹跳，最多弹跳3次 | G34: 柔性外壳把墙面变成新的枪口，让封闭房间成为弹道的一部分。 | H34: [Codex补充] | I34: select=BULLET | J34: action=MUTATE_TO_BOUNCE；bounce_count=3；bounce_walls=true；damage_scale=0.85 | K34: 门后命运/三选一/工作台共用卡池 | L34: [已实装] | M34: [部分实装] 塔罗名称、正/逆位效果快照与通用执行已接入；复杂逆位专属行为继续逐卡QA | N34: src/weapons/FateCard.gd；src/weapons/FateCardPresets.gd；src/weapons/FateCardEngine.gd；src/game/FateCardGameBridge.gd；docs/v0.1/14_技术施工_命运塔罗牌组.md；src/weapons/TarotFateCatalog.gd；tests/verification/verify_tarot_fate_runtime.gd | O34: 迁移前名称：弹跳弹；稳定ID不变，旧存档迁移为正位，不重投方位 | P34: WEAPON | Q34: 占目标枪械下一个永久命运槽；按序追加、不可拆卸/替换/回退 | R34: [已实装] 塔罗名称、50/50方位、正逆位同ID、代码翻牌、整卡倒置、逆位描述替换与方位持久化已接入 | S34: ★ 星星命运｜权杖·八｜翻牌后显示正位/逆位、目标、槽位与对应功能 | T34: 卡背绕Y轴翻面；逆位整张正面卡牌（含边框、图案、文字与布局）收束180°，并显示逆位效果描述；每次反弹有折线闪光、方向变化和剩余计数，不以普通命中VFX混淆 | U34: [部分实装] 通用卡背/翻牌/逆位倒置已验收；逐卡逆位专属VFX与音效继续QA | V34: 弹跳弹 | W34: 8 | X34: MINOR | Y34: WANDS | Z34: 0.5 | AA34: 0.5 | AB34: 选择一个子弹，使其在墙壁和障碍物间弹跳，最多弹跳3次 | AC34: action=MUTATE_TO_BOUNCE；bounce_count=3；bounce_walls=true；damage_scale=0.85 | AD34: 只弹跳1次，反弹后伤害+35% | AE34: action=MUTATE_TO_BOUNCE; bounce_count=1; damage_scale_on_bounce=1.35 | AF34: 0.00s卡背→0.24s薄边换面→0.42s收束；逆位图案/框体180°，卡名、天体、方位标签和说明文字0°；0.62s后可点 | AG34: [设计完成/数据已入表/运行时待施工]
A35: fate_barrage_copy | B35: 权杖·九 | C35: 复制 | D35: 稀有 | E35: 每次射击分两波发射 | F35: 选择一个枪身，每次射击分两波发射，第二波子弹延迟 0.1 秒 | G35: 复制机构把一次扣扳机拆成两阵回声，第二阵总在敌人以为结束时抵达。 | H35: [Codex补充] | I35: select=GUNBODY | J35: action=COPY_NODE；copy_fire_delay=0.1；second_wave_damage_scale=0.6 | K35: 门后命运/三选一/工作台共用卡池 | L35: [已实装] | M35: [部分实装] 塔罗名称、正/逆位效果快照与通用执行已接入；复杂逆位专属行为继续逐卡QA | N35: src/weapons/FateCard.gd；src/weapons/FateCardPresets.gd；src/weapons/FateCardEngine.gd；src/game/FateCardGameBridge.gd；docs/v0.1/14_技术施工_命运塔罗牌组.md；src/weapons/TarotFateCatalog.gd；tests/verification/verify_tarot_fate_runtime.gd | O35: 迁移前名称：弹幕模式；稳定ID不变，旧存档迁移为正位，不重投方位 | P35: WEAPON | Q35: 占目标枪械下一个永久命运槽；按序追加、不可拆卸/替换/回退 | R35: [已实装] 塔罗名称、50/50方位、正逆位同ID、代码翻牌、整卡倒置、逆位描述替换与方位持久化已接入 | S35: ★ 星星命运｜权杖·九｜翻牌后显示正位/逆位、目标、槽位与对应功能 | T35: 卡背绕Y轴翻面；逆位整张正面卡牌（含边框、图案、文字与布局）收束180°，并显示逆位效果描述；第一波后保留轨迹残影，延迟到点生成第二波并用次级声层区分 | U35: [部分实装] 通用卡背/翻牌/逆位倒置已验收；逐卡逆位专属VFX与音效继续QA | V35: 弹幕模式 | W35: 9 | X35: MINOR | Y35: WANDS | Z35: 0.5 | AA35: 0.5 | AB35: 选择一个枪身，每次射击分两波发射，第二波子弹延迟 0.1 秒 | AC35: action=COPY_NODE；copy_fire_delay=0.1；second_wave_damage_scale=0.6 | AD35: 同时向前/后各发一波，后方波80%伤害 | AE35: action=COPY_NODE; pattern=FRONT_BACK; rear_wave_damage_scale=0.8 | AF35: 0.00s卡背→0.24s薄边换面→0.42s收束；逆位图案/框体180°，卡名、天体、方位标签和说明文字0°；0.62s后可点 | AG35: [设计完成/数据已入表/运行时待施工]
A36: fate_fuse_fire | B36: 权杖·十 | C36: 融合 | D36: 稀有 | E36: 命中附加火焰DOT | F36: 选择一个子弹，融合火焰属性，命中后在目标身上附加火焰持续伤害（每秒8%伤害，持续3秒） | G36: 余烬寄生在弹头内，命中后才真正苏醒，持续啃食目标。 | H36: [Codex补充] | I36: select=BULLET | J36: action=FUSE_DAMAGE；damage_type=fire；dot_damage_per_sec=0.08；dot_duration=3 | K36: 门后命运/三选一/工作台共用卡池 | L36: [已实装] | M36: [部分实装] 塔罗名称、正/逆位效果快照与通用执行已接入；复杂逆位专属行为继续逐卡QA | N36: src/weapons/FateCard.gd；src/weapons/FateCardPresets.gd；src/weapons/FateCardEngine.gd；src/game/FateCardGameBridge.gd；docs/v0.1/14_技术施工_命运塔罗牌组.md；src/weapons/TarotFateCatalog.gd；tests/verification/verify_tarot_fate_runtime.gd | O36: 迁移前名称：火焰子弹；稳定ID不变，旧存档迁移为正位，不重投方位 | P36: WEAPON | Q36: 占目标枪械下一个永久命运槽；按序追加、不可拆卸/替换/回退 | R36: [已实装] 塔罗名称、50/50方位、正逆位同ID、代码翻牌、整卡倒置、逆位描述替换与方位持久化已接入 | S36: ★ 星星命运｜权杖·十｜翻牌后显示正位/逆位、目标、槽位与对应功能 | T36: 卡背绕Y轴翻面；逆位整张正面卡牌（含边框、图案、文字与布局）收束180°，并显示逆位效果描述；弹体火焰尾迹、目标燃烧状态图标和每跳伤害反馈同步 | U36: [部分实装] 通用卡背/翻牌/逆位倒置已验收；逐卡逆位专属VFX与音效继续QA | V36: 火焰子弹 | W36: 10 | X36: MINOR | Y36: WANDS | Z36: 0.5 | AA36: 0.5 | AB36: 选择一个子弹，融合火焰属性，命中后在目标身上附加火焰持续伤害（每秒8%伤害，持续3秒） | AC36: action=FUSE_DAMAGE；damage_type=fire；dot_damage_per_sec=0.08；dot_duration=3 | AD36: 每秒4%火伤，持续6秒，可刷新 | AE36: action=FUSE_DAMAGE; damage_type=fire; dot_damage_per_sec=0.04; dot_duration=6; refresh=true | AF36: 0.00s卡背→0.24s薄边换面→0.42s收束；逆位图案/框体180°，卡名、天体、方位标签和说明文字0°；0.62s后可点 | AG36: [设计完成/数据已入表/运行时待施工]
A37: fate_fuse_frost | B37: 权杖·侍从 | C37: 融合 | D37: 稀有 | E37: 命中后冰冻目标0.5秒 | F37: 选择一个子弹，融合冰霜属性，命中后冰冻目标 0.5 秒（精英怪减半） | G37: 低温胶囊在撞击时碎裂，短暂冻结动作，也让精英更快挣脱。 | H37: [Codex补充] | I37: select=BULLET | J37: action=FUSE_DAMAGE；damage_type=ice；freeze_duration=0.5；freeze_duration_elite=0.25 | K37: 门后命运/三选一/工作台共用卡池 | L37: [已实装] | M37: [部分实装] 塔罗名称、正/逆位效果快照与通用执行已接入；复杂逆位专属行为继续逐卡QA | N37: src/weapons/FateCard.gd；src/weapons/FateCardPresets.gd；src/weapons/FateCardEngine.gd；src/game/FateCardGameBridge.gd；docs/v0.1/14_技术施工_命运塔罗牌组.md；src/weapons/TarotFateCatalog.gd；tests/verification/verify_tarot_fate_runtime.gd | O37: 迁移前名称：冰霜子弹；稳定ID不变，旧存档迁移为正位，不重投方位 | P37: WEAPON | Q37: 占目标枪械下一个永久命运槽；按序追加、不可拆卸/替换/回退 | R37: [已实装] 塔罗名称、50/50方位、正逆位同ID、代码翻牌、整卡倒置、逆位描述替换与方位持久化已接入 | S37: ★ 星星命运｜权杖·侍从｜翻牌后显示正位/逆位、目标、槽位与对应功能 | T37: 卡背绕Y轴翻面；逆位整张正面卡牌（含边框、图案、文字与布局）收束180°，并显示逆位效果描述；冰晶尾迹、目标覆霜与冻结破碎反馈清楚，免疫时显示免疫原因 | U37: [部分实装] 通用卡背/翻牌/逆位倒置已验收；逐卡逆位专属VFX与音效继续QA | V37: 冰霜子弹 | W37: PAGE | X37: MINOR | Y37: WANDS | Z37: 0.5 | AA37: 0.5 | AB37: 选择一个子弹，融合冰霜属性，命中后冰冻目标 0.5 秒（精英怪减半） | AC37: action=FUSE_DAMAGE；damage_type=ice；freeze_duration=0.5；freeze_duration_elite=0.25 | AD37: 不冻结，减速35%持续3秒 | AE37: action=FUSE_DAMAGE; damage_type=ice; slow_multiplier=0.65; duration=3 | AF37: 0.00s卡背→0.24s薄边换面→0.42s收束；逆位图案/框体180°，卡名、天体、方位标签和说明文字0°；0.62s后可点 | AG37: [设计完成/数据已入表/运行时待施工]
A38: fate_fuse_poison | B38: 权杖·骑士 | C38: 融合 | D38: 史诗 | E38: 命中附加毒素，最多叠加5层 | F38: 选择一个子弹，融合毒素属性，命中后附加毒素，每层每秒造成 5% 伤害，最多叠加 5 层 | G38: 孢子毒层层积累，单发并不致命，重复命中才让猎物失去退路。 | H38: [Codex补充] | I38: select=BULLET | J38: action=FUSE_DAMAGE；damage_type=poison；dot_damage_per_stack=0.05；dot_tick_rate=1；max_stacks=5 | K38: 门后命运/三选一/工作台共用卡池 | L38: [已实装] | M38: [部分实装] 塔罗名称、正/逆位效果快照与通用执行已接入；复杂逆位专属行为继续逐卡QA | N38: src/weapons/FateCard.gd；src/weapons/FateCardPresets.gd；src/weapons/FateCardEngine.gd；src/game/FateCardGameBridge.gd；docs/v0.1/14_技术施工_命运塔罗牌组.md；src/weapons/TarotFateCatalog.gd；tests/verification/verify_tarot_fate_runtime.gd | O38: 迁移前名称：剧毒子弹；稳定ID不变，旧存档迁移为正位，不重投方位 | P38: WEAPON | Q38: 占目标枪械下一个永久命运槽；按序追加、不可拆卸/替换/回退 | R38: [已实装] 塔罗名称、50/50方位、正逆位同ID、代码翻牌、整卡倒置、逆位描述替换与方位持久化已接入 | S38: ★ 星星命运｜权杖·骑士｜翻牌后显示正位/逆位、目标、槽位与对应功能 | T38: 卡背绕Y轴翻面；逆位整张正面卡牌（含边框、图案、文字与布局）收束180°，并显示逆位效果描述；毒雾尾迹、目标层数图标和持续伤害节奏同步，达到上限有强调 | U38: [部分实装] 通用卡背/翻牌/逆位倒置已验收；逐卡逆位专属VFX与音效继续QA | V38: 剧毒子弹 | W38: KNIGHT | X38: MINOR | Y38: WANDS | Z38: 0.5 | AA38: 0.5 | AB38: 选择一个子弹，融合毒素属性，命中后附加毒素，每层每秒造成 5% 伤害，最多叠加 5 层 | AC38: action=FUSE_DAMAGE；damage_type=poison；dot_damage_per_stack=0.05；dot_tick_rate=1；max_stacks=5 | AD38: 毒素不叠层，3秒后一次爆发35%武器伤害 | AE38: action=FUSE_DAMAGE; damage_type=poison_burst; delay=3; damage_scale=0.35; max_stacks=1 | AF38: 0.00s卡背→0.24s薄边换面→0.42s收束；逆位图案/框体180°，卡名、天体、方位标签和说明文字0°；0.62s后可点 | AG38: [设计完成/数据已入表/运行时待施工]
A39: fate_crit_kill | B39: 权杖·王后 | C39: 规则 | D39: 稀有 | E39: 击杀后下次射击必定暴击 | F39: 选择一个枪身，击杀敌人后下一次射击必暴击，暴击伤害 × 2.5 | G39: 一次击杀会在枪机里留下短暂确信，使下一发必然寻找最脆弱的位置。 | H39: [Codex补充] | I39: select=GUNBODY | J39: action=CRIT_ON_KILL；crit_damage_multiplier=2.5；stacks=1 | K39: 门后命运/三选一/工作台共用卡池 | L39: [已实装] | M39: [部分实装] 塔罗名称、正/逆位效果快照与通用执行已接入；复杂逆位专属行为继续逐卡QA | N39: src/weapons/FateCard.gd；src/weapons/FateCardPresets.gd；src/weapons/FateCardEngine.gd；src/game/FateCardGameBridge.gd；docs/v0.1/14_技术施工_命运塔罗牌组.md；src/weapons/TarotFateCatalog.gd；tests/verification/verify_tarot_fate_runtime.gd | O39: 迁移前名称：致命一击；稳定ID不变，旧存档迁移为正位，不重投方位 | P39: WEAPON | Q39: 占目标枪械下一个永久命运槽；按序追加、不可拆卸/替换/回退 | R39: [已实装] 塔罗名称、50/50方位、正逆位同ID、代码翻牌、整卡倒置、逆位描述替换与方位持久化已接入 | S39: ★ 星星命运｜权杖·王后｜翻牌后显示正位/逆位、目标、槽位与对应功能 | T39: 卡背绕Y轴翻面；逆位整张正面卡牌（含边框、图案、文字与布局）收束180°，并显示逆位效果描述；暴击击杀出现区别于普通暴击的印记，奖励生效时HUD来源图标亮起 | U39: [部分实装] 通用卡背/翻牌/逆位倒置已验收；逐卡逆位专属VFX与音效继续QA | V39: 致命一击 | W39: QUEEN | X39: MINOR | Y39: WANDS | Z39: 0.5 | AA39: 0.5 | AB39: 选择一个枪身，击杀敌人后下一次射击必暴击，暴击伤害 × 2.5 | AC39: action=CRIT_ON_KILL；crit_damage_multiplier=2.5；stacks=1 | AD39: 暴击击杀后下3发伤害+30%，不保证暴击 | AE39: action=BUFF_ON_CRIT_KILL; shots=3; damage_multiplier=1.3 | AF39: 0.00s卡背→0.24s薄边换面→0.42s收束；逆位图案/框体180°，卡名、天体、方位标签和说明文字0°；0.62s后可点 | AG39: [设计完成/数据已入表/运行时待施工]
A40: fate_huge_scale | B40: 权杖·国王 | C40: 视觉 | D40: 普通 | E40: 节点整体放大 2 倍 | F40: 选择一个节点，该节点及其所有子节点放大 2 倍，伤害提升 50%，速度降低 40% | G40: 命运把整棵装配树一同放大，力量随之增长，惯性也变得无法忽略。 | H40: [Codex补充] | J40: action=SCALE_UP；damage_scale=1.5；scale=2；speed_scale=0.6 | K40: 门后命运/三选一/工作台共用卡池 | L40: [已实装] | M40: [部分实装] 塔罗名称、正/逆位效果快照与通用执行已接入；复杂逆位专属行为继续逐卡QA | N40: src/weapons/FateCard.gd；src/weapons/FateCardPresets.gd；src/weapons/FateCardEngine.gd；src/game/FateCardGameBridge.gd；docs/v0.1/14_技术施工_命运塔罗牌组.md；src/weapons/TarotFateCatalog.gd；tests/verification/verify_tarot_fate_runtime.gd | O40: 迁移前名称：巨大化；稳定ID不变，旧存档迁移为正位，不重投方位 | P40: WEAPON | Q40: 占目标枪械下一个永久命运槽；按序追加、不可拆卸/替换/回退 | R40: [已实装] 塔罗名称、50/50方位、正逆位同ID、代码翻牌、整卡倒置、逆位描述替换与方位持久化已接入 | S40: ★ 星星命运｜权杖·国王｜翻牌后显示正位/逆位、目标、槽位与对应功能 | T40: 卡背绕Y轴翻面；逆位整张正面卡牌（含边框、图案、文字与布局）收束180°，并显示逆位效果描述；目标获得夸张但不遮挡视野的体积变化；碰撞与命中轮廓保持一致 | U40: [部分实装] 通用卡背/翻牌/逆位倒置已验收；逐卡逆位专属VFX与音效继续QA | V40: 巨大化 | W40: KING | X40: MINOR | Y40: WANDS | Z40: 0.5 | AA40: 0.5 | AB40: 选择一个节点，该节点及其所有子节点放大 2 倍，伤害提升 50%，速度降低 40% | AC40: action=SCALE_UP；damage_scale=1.5；scale=2；speed_scale=0.6 | AD40: 节点×0.65、伤害-20%、速度+60% | AE40: action=SCALE_UP; scale=0.65; damage_scale=0.8; speed_scale=1.6 | AF40: 0.00s卡背→0.24s薄边换面→0.42s收束；逆位图案/框体180°，卡名、天体、方位标签和说明文字0°；0.62s后可点 | AG40: [设计完成/数据已入表/运行时待施工]
A41: fate_sword_ace | B41: 宝剑·王牌 | C41: 强化 | D41: 稀有 | E41: 弹速+35%、伤害-10% | F41: 弹速+35%、伤害-10% | G41: 新增塔罗牌“宝剑·王牌”，正位与逆位是同一主题的两种解读。 | H41: [用户设计+Codex规划] | I41: select=GUNBODY_OR_BULLET | J41: action=PROJECTILE_SPEED_TRADE; speed_multiplier=1.35; damage_multiplier=0.9 | K41: 塔罗命运三选一/工作台/局前预选目标卡池 | L41: [用户设计] | M41: [未施工] 名称、正/逆位与效果参数已完成数据设计 | N41: docs/v0.1/14_技术施工_命运塔罗牌组.md；docs/v0.1/data/ShellStorm2_游戏内容数据库_v010.xlsx | O41: 新增塔罗卡；正式卡池和执行器待施工 | P41: WEAPON | Q41: 占目标枪械下一个永久命运槽；正/逆位都占1槽 | R41: [设计完成/待施工] 正逆位、翻牌和塔罗命名未接入运行时 | S41: ★ 星星命运｜宝剑·王牌｜翻牌后显示正位/逆位、目标、槽位与对应功能 | T41: 卡背绕Y轴翻面；逆位整张正面卡牌（含边框、图案、文字与布局）收束180°，并显示逆位效果描述；对应规则必须在HUD/场景中可读 | U41: [设计完成/待施工] 旧正位表现可复用；逆位与翻转待QA | W41: ACE | X41: MINOR | Y41: SWORDS | Z41: 0.5 | AA41: 0.5 | AB41: 弹速+35%、伤害-10% | AC41: action=PROJECTILE_SPEED_TRADE; speed_multiplier=1.35; damage_multiplier=0.9 | AD41: 弹速-25%、伤害+30% | AE41: action=PROJECTILE_SPEED_TRADE; speed_multiplier=0.75; damage_multiplier=1.3 | AF41: 0.00s卡背→0.24s薄边换面→0.42s收束；逆位图案/框体180°，卡名、天体、方位标签和说明文字0°；0.62s后可点 | AG41: [设计完成/数据已入表/运行时待施工]
A42: fate_sword_two | B42: 宝剑·二 | C42: 变种 | D42: 普通 | E42: 连射交替向左/右分叉，各造85%伤害 | F42: 连射交替向左/右分叉，各造85%伤害 | G42: 新增塔罗牌“宝剑·二”，正位与逆位是同一主题的两种解读。 | H42: [用户设计+Codex规划] | I42: select=GUNBODY_OR_BULLET | J42: action=ALTERNATING_FORK; damage_scale=0.85 | K42: 塔罗命运三选一/工作台/局前预选目标卡池 | L42: [用户设计] | M42: [未施工] 名称、正/逆位与效果参数已完成数据设计 | N42: docs/v0.1/14_技术施工_命运塔罗牌组.md；docs/v0.1/data/ShellStorm2_游戏内容数据库_v010.xlsx | O42: 新增塔罗卡；正式卡池和执行器待施工 | P42: WEAPON | Q42: 占目标枪械下一个永久命运槽；正/逆位都占1槽 | R42: [设计完成/待施工] 正逆位、翻牌和塔罗命名未接入运行时 | S42: ★ 星星命运｜宝剑·二｜翻牌后显示正位/逆位、目标、槽位与对应功能 | T42: 卡背绕Y轴翻面；逆位整张正面卡牌（含边框、图案、文字与布局）收束180°，并显示逆位效果描述；对应规则必须在HUD/场景中可读 | U42: [设计完成/待施工] 旧正位表现可复用；逆位与翻转待QA | W42: 2 | X42: MINOR | Y42: SWORDS | Z42: 0.5 | AA42: 0.5 | AB42: 连射交替向左/右分叉，各造85%伤害 | AC42: action=ALTERNATING_FORK; damage_scale=0.85 | AD42: 双弹在6m后汇聚，汇聚命中×1.15 | AE42: action=CONVERGING_PAIR; convergence_distance=6; convergence_damage=1.15 | AF42: 0.00s卡背→0.24s薄边换面→0.42s收束；逆位图案/框体180°，卡名、天体、方位标签和说明文字0°；0.62s后可点 | AG42: [设计完成/数据已入表/运行时待施工]
A43: fate_sword_three | B43: 宝剑·三 | C43: 强化 | D43: 稀有 | E43: 暴击率+12%、暴伤-20% | F43: 暴击率+12%、暴伤-20% | G43: 新增塔罗牌“宝剑·三”，正位与逆位是同一主题的两种解读。 | H43: [用户设计+Codex规划] | I43: select=GUNBODY_OR_BULLET | J43: action=CRIT_TRADE; crit_chance_add=0.12; crit_damage_add=-0.2 | K43: 塔罗命运三选一/工作台/局前预选目标卡池 | L43: [用户设计] | M43: [未施工] 名称、正/逆位与效果参数已完成数据设计 | N43: docs/v0.1/14_技术施工_命运塔罗牌组.md；docs/v0.1/data/ShellStorm2_游戏内容数据库_v010.xlsx | O43: 新增塔罗卡；正式卡池和执行器待施工 | P43: WEAPON | Q43: 占目标枪械下一个永久命运槽；正/逆位都占1槽 | R43: [设计完成/待施工] 正逆位、翻牌和塔罗命名未接入运行时 | S43: ★ 星星命运｜宝剑·三｜翻牌后显示正位/逆位、目标、槽位与对应功能 | T43: 卡背绕Y轴翻面；逆位整张正面卡牌（含边框、图案、文字与布局）收束180°，并显示逆位效果描述；对应规则必须在HUD/场景中可读 | U43: [设计完成/待施工] 旧正位表现可复用；逆位与翻转待QA | W43: 3 | X43: MINOR | Y43: SWORDS | Z43: 0.5 | AA43: 0.5 | AB43: 暴击率+12%、暴伤-20% | AC43: action=CRIT_TRADE; crit_chance_add=0.12; crit_damage_add=-0.2 | AD43: 暴击率-8%、暴伤+70% | AE43: action=CRIT_TRADE; crit_chance_add=-0.08; crit_damage_add=0.7 | AF43: 0.00s卡背→0.24s薄边换面→0.42s收束；逆位图案/框体180°，卡名、天体、方位标签和说明文字0°；0.62s后可点 | AG43: [设计完成/数据已入表/运行时待施工]
A44: fate_sword_four | B44: 宝剑·四 | C44: 规则 | D44: 稀有 | E44: 静止1秒后扩散-40%、伤害+15% | F44: 静止1秒后扩散-40%、伤害+15% | G44: 新增塔罗牌“宝剑·四”，正位与逆位是同一主题的两种解读。 | H44: [用户设计+Codex规划] | I44: select=GUNBODY_OR_BULLET | J44: action=STATIONARY_FOCUS; delay=1; spread_multiplier=0.6; damage_multiplier=1.15 | K44: 塔罗命运三选一/工作台/局前预选目标卡池 | L44: [用户设计] | M44: [未施工] 名称、正/逆位与效果参数已完成数据设计 | N44: docs/v0.1/14_技术施工_命运塔罗牌组.md；docs/v0.1/data/ShellStorm2_游戏内容数据库_v010.xlsx | O44: 新增塔罗卡；正式卡池和执行器待施工 | P44: WEAPON | Q44: 占目标枪械下一个永久命运槽；正/逆位都占1槽 | R44: [设计完成/待施工] 正逆位、翻牌和塔罗命名未接入运行时 | S44: ★ 星星命运｜宝剑·四｜翻牌后显示正位/逆位、目标、槽位与对应功能 | T44: 卡背绕Y轴翻面；逆位整张正面卡牌（含边框、图案、文字与布局）收束180°，并显示逆位效果描述；对应规则必须在HUD/场景中可读 | U44: [设计完成/待施工] 旧正位表现可复用；逆位与翻转待QA | W44: 4 | X44: MINOR | Y44: SWORDS | Z44: 0.5 | AA44: 0.5 | AB44: 静止1秒后扩散-40%、伤害+15% | AC44: action=STATIONARY_FOCUS; delay=1; spread_multiplier=0.6; damage_multiplier=1.15 | AD44: 移动射击扩散-20%、伤害-10% | AE44: action=MOVING_FOCUS; spread_multiplier=0.8; damage_multiplier=0.9 | AF44: 0.00s卡背→0.24s薄边换面→0.42s收束；逆位图案/框体180°，卡名、天体、方位标签和说明文字0°；0.62s后可点 | AG44: [设计完成/数据已入表/运行时待施工]
A45: fate_sword_five | B45: 宝剑·五 | C45: 规则 | D45: 史诗 | E45: 击杀回填弹匣20% | F45: 击杀回填弹匣20% | G45: 新增塔罗牌“宝剑·五”，正位与逆位是同一主题的两种解读。 | H45: [用户设计+Codex规划] | I45: select=GUNBODY_OR_BULLET | J45: action=REFUND_MAG_ON_KILL; ratio=0.2 | K45: 塔罗命运三选一/工作台/局前预选目标卡池 | L45: [用户设计] | M45: [未施工] 名称、正/逆位与效果参数已完成数据设计 | N45: docs/v0.1/14_技术施工_命运塔罗牌组.md；docs/v0.1/data/ShellStorm2_游戏内容数据库_v010.xlsx | O45: 新增塔罗卡；正式卡池和执行器待施工 | P45: WEAPON | Q45: 占目标枪械下一个永久命运槽；正/逆位都占1槽 | R45: [设计完成/待施工] 正逆位、翻牌和塔罗命名未接入运行时 | S45: ★ 星星命运｜宝剑·五｜翻牌后显示正位/逆位、目标、槽位与对应功能 | T45: 卡背绕Y轴翻面；逆位整张正面卡牌（含边框、图案、文字与布局）收束180°，并显示逆位效果描述；对应规则必须在HUD/场景中可读 | U45: [设计完成/待施工] 旧正位表现可复用；逆位与翻转待QA | W45: 5 | X45: MINOR | Y45: SWORDS | Z45: 0.5 | AA45: 0.5 | AB45: 击杀回填弹匣20% | AC45: action=REFUND_MAG_ON_KILL; ratio=0.2 | AD45: 打空弹匣后下次换弹速度+35% | AE45: action=EMPTY_MAG_RELOAD_BUFF; reload_speed_multiplier=1.35 | AF45: 0.00s卡背→0.24s薄边换面→0.42s收束；逆位图案/框体180°，卡名、天体、方位标签和说明文字0°；0.62s后可点 | AG45: [设计完成/数据已入表/运行时待施工]
A46: fate_sword_six | B46: 宝剑·六 | C46: 变种 | D46: 史诗 | E46: 穿透2个敌人，每次穿透伤害-15% | F46: 穿透2个敌人，每次穿透伤害-15% | G46: 新增塔罗牌“宝剑·六”，正位与逆位是同一主题的两种解读。 | H46: [用户设计+Codex规划] | I46: select=GUNBODY_OR_BULLET | J46: action=PIERCE_ENEMIES; count=2; per_target_multiplier=0.85 | K46: 塔罗命运三选一/工作台/局前预选目标卡池 | L46: [用户设计] | M46: [未施工] 名称、正/逆位与效果参数已完成数据设计 | N46: docs/v0.1/14_技术施工_命运塔罗牌组.md；docs/v0.1/data/ShellStorm2_游戏内容数据库_v010.xlsx | O46: 新增塔罗卡；正式卡池和执行器待施工 | P46: WEAPON | Q46: 占目标枪械下一个永久命运槽；正/逆位都占1槽 | R46: [设计完成/待施工] 正逆位、翻牌和塔罗命名未接入运行时 | S46: ★ 星星命运｜宝剑·六｜翻牌后显示正位/逆位、目标、槽位与对应功能 | T46: 卡背绕Y轴翻面；逆位整张正面卡牌（含边框、图案、文字与布局）收束180°，并显示逆位效果描述；对应规则必须在HUD/场景中可读 | U46: [设计完成/待施工] 旧正位表现可复用；逆位与翻转待QA | W46: 6 | X46: MINOR | Y46: SWORDS | Z46: 0.5 | AA46: 0.5 | AB46: 穿透2个敌人，每次穿透伤害-15% | AC46: action=PIERCE_ENEMIES; count=2; per_target_multiplier=0.85 | AD46: 命中第一个目标即停止并爆炸，造60%武器伤害 | AE46: action=STOP_AND_EXPLODE; damage_scale=0.6 | AF46: 0.00s卡背→0.24s薄边换面→0.42s收束；逆位图案/框体180°，卡名、天体、方位标签和说明文字0°；0.62s后可点 | AG46: [设计完成/数据已入表/运行时待施工]
A47: fate_sword_seven | B47: 宝剑·七 | C47: 规则 | D47: 史诗 | E47: 弱点命中标记目标，对其伤害+8%、最多3层 | F47: 弱点命中标记目标，对其伤害+8%、最多3层 | G47: 新增塔罗牌“宝剑·七”，正位与逆位是同一主题的两种解读。 | H47: [用户设计+Codex规划] | I47: select=GUNBODY_OR_BULLET | J47: action=WEAKPOINT_MARK; damage_per_stack=0.08; max_stacks=3 | K47: 塔罗命运三选一/工作台/局前预选目标卡池 | L47: [用户设计] | M47: [未施工] 名称、正/逆位与效果参数已完成数据设计 | N47: docs/v0.1/14_技术施工_命运塔罗牌组.md；docs/v0.1/data/ShellStorm2_游戏内容数据库_v010.xlsx | O47: 新增塔罗卡；正式卡池和执行器待施工 | P47: WEAPON | Q47: 占目标枪械下一个永久命运槽；正/逆位都占1槽 | R47: [设计完成/待施工] 正逆位、翻牌和塔罗命名未接入运行时 | S47: ★ 星星命运｜宝剑·七｜翻牌后显示正位/逆位、目标、槽位与对应功能 | T47: 卡背绕Y轴翻面；逆位整张正面卡牌（含边框、图案、文字与布局）收束180°，并显示逆位效果描述；对应规则必须在HUD/场景中可读 | U47: [设计完成/待施工] 旧正位表现可复用；逆位与翻转待QA | W47: 7 | X47: MINOR | Y47: SWORDS | Z47: 0.5 | AA47: 0.5 | AB47: 弱点命中标记目标，对其伤害+8%、最多3层 | AC47: action=WEAKPOINT_MARK; damage_per_stack=0.08; max_stacks=3 | AD47: 普通命中积累稳定，每第5发转为追踪弹 | AE47: action=BODY_HIT_HOMING; hit_threshold=5 | AF47: 0.00s卡背→0.24s薄边换面→0.42s收束；逆位图案/框体180°，卡名、天体、方位标签和说明文字0°；0.62s后可点 | AG47: [设计完成/数据已入表/运行时待施工]
A48: fate_sword_eight | B48: 宝剑·八 | C48: 变种 | D48: 普通 | E48: 散射角-30%、弹速+15% | F48: 散射角-30%、弹速+15% | G48: 新增塔罗牌“宝剑·八”，正位与逆位是同一主题的两种解读。 | H48: [用户设计+Codex规划] | I48: select=GUNBODY_OR_BULLET | J48: action=SPREAD_TRADE; spread_multiplier=0.7; speed_multiplier=1.15 | K48: 塔罗命运三选一/工作台/局前预选目标卡池 | L48: [用户设计] | M48: [未施工] 名称、正/逆位与效果参数已完成数据设计 | N48: docs/v0.1/14_技术施工_命运塔罗牌组.md；docs/v0.1/data/ShellStorm2_游戏内容数据库_v010.xlsx | O48: 新增塔罗卡；正式卡池和执行器待施工 | P48: WEAPON | Q48: 占目标枪械下一个永久命运槽；正/逆位都占1槽 | R48: [设计完成/待施工] 正逆位、翻牌和塔罗命名未接入运行时 | S48: ★ 星星命运｜宝剑·八｜翻牌后显示正位/逆位、目标、槽位与对应功能 | T48: 卡背绕Y轴翻面；逆位整张正面卡牌（含边框、图案、文字与布局）收束180°，并显示逆位效果描述；对应规则必须在HUD/场景中可读 | U48: [设计完成/待施工] 旧正位表现可复用；逆位与翻转待QA | W48: 8 | X48: MINOR | Y48: SWORDS | Z48: 0.5 | AA48: 0.5 | AB48: 散射角-30%、弹速+15% | AC48: action=SPREAD_TRADE; spread_multiplier=0.7; speed_multiplier=1.15 | AD48: 散射角+45%、投射物+2，每发65%伤害 | AE48: action=SPREAD_TRADE; spread_multiplier=1.45; projectile_add=2; damage_scale=0.65 | AF48: 0.00s卡背→0.24s薄边换面→0.42s收束；逆位图案/框体180°，卡名、天体、方位标签和说明文字0°；0.62s后可点 | AG48: [设计完成/数据已入表/运行时待施工]
A49: fate_sword_nine | B49: 宝剑·九 | C49: 规则 | D49: 史诗 | E49: 换弹最后25%时段不受击，下弹匣射速+20% | F49: 换弹最后25%时段不受击，下弹匣射速+20% | G49: 新增塔罗牌“宝剑·九”，正位与逆位是同一主题的两种解读。 | H49: [用户设计+Codex规划] | I49: select=GUNBODY_OR_BULLET | J49: action=SAFE_RELOAD_REWARD; protected_tail_ratio=0.25; fire_rate_multiplier=1.2 | K49: 塔罗命运三选一/工作台/局前预选目标卡池 | L49: [用户设计] | M49: [未施工] 名称、正/逆位与效果参数已完成数据设计 | N49: docs/v0.1/14_技术施工_命运塔罗牌组.md；docs/v0.1/data/ShellStorm2_游戏内容数据库_v010.xlsx | O49: 新增塔罗卡；正式卡池和执行器待施工 | P49: WEAPON | Q49: 占目标枪械下一个永久命运槽；正/逆位都占1槽 | R49: [设计完成/待施工] 正逆位、翻牌和塔罗命名未接入运行时 | S49: ★ 星星命运｜宝剑·九｜翻牌后显示正位/逆位、目标、槽位与对应功能 | T49: 卡背绕Y轴翻面；逆位整张正面卡牌（含边框、图案、文字与布局）收束180°，并显示逆位效果描述；对应规则必须在HUD/场景中可读 | U49: [设计完成/待施工] 旧正位表现可复用；逆位与翻转待QA | W49: 9 | X49: MINOR | Y49: SWORDS | Z49: 0.5 | AA49: 0.5 | AB49: 换弹最后25%时段不受击，下弹匣射速+20% | AC49: action=SAFE_RELOAD_REWARD; protected_tail_ratio=0.25; fire_rate_multiplier=1.2 | AD49: 取消换弹立即获得1发50%伤害应急弹，5秒冷却 | AE49: action=RELOAD_CANCEL_SHOT; damage_scale=0.5; cooldown=5 | AF49: 0.00s卡背→0.24s薄边换面→0.42s收束；逆位图案/框体180°，卡名、天体、方位标签和说明文字0°；0.62s后可点 | AG49: [设计完成/数据已入表/运行时待施工]
A50: fate_sword_ten | B50: 宝剑·十 | C50: 规则 | D50: 传说 | E50: 溢出伤害化为穿透碎片攻击后方敌人 | F50: 溢出伤害化为穿透碎片攻击后方敌人 | G50: 新增塔罗牌“宝剑·十”，正位与逆位是同一主题的两种解读。 | H50: [用户设计+Codex规划] | I50: select=GUNBODY_OR_BULLET | J50: action=OVERKILL_SHARD; transfer_ratio=1 | K50: 塔罗命运三选一/工作台/局前预选目标卡池 | L50: [用户设计] | M50: [未施工] 名称、正/逆位与效果参数已完成数据设计 | N50: docs/v0.1/14_技术施工_命运塔罗牌组.md；docs/v0.1/data/ShellStorm2_游戏内容数据库_v010.xlsx | O50: 新增塔罗卡；正式卡池和执行器待施工 | P50: WEAPON | Q50: 占目标枪械下一个永久命运槽；正/逆位都占1槽 | R50: [设计完成/待施工] 正逆位、翻牌和塔罗命名未接入运行时 | S50: ★ 星星命运｜宝剑·十｜翻牌后显示正位/逆位、目标、槽位与对应功能 | T50: 卡背绕Y轴翻面；逆位整张正面卡牌（含边框、图案、文字与布局）收束180°，并显示逆位效果描述；对应规则必须在HUD/场景中可读 | U50: [设计完成/待施工] 旧正位表现可复用；逆位与翻转待QA | W50: 10 | X50: MINOR | Y50: SWORDS | Z50: 0.5 | AA50: 0.5 | AB50: 溢出伤害化为穿透碎片攻击后方敌人 | AC50: action=OVERKILL_SHARD; transfer_ratio=1 | AD50: 普通敌人低于8%生命时处决，精英阈值3% | AE50: action=EXECUTE; normal_threshold=0.08; elite_threshold=0.03 | AF50: 0.00s卡背→0.24s薄边换面→0.42s收束；逆位图案/框体180°，卡名、天体、方位标签和说明文字0°；0.62s后可点 | AG50: [设计完成/数据已入表/运行时待施工]
A51: fate_sword_page | B51: 宝剑·侍从 | C51: 规则 | D51: 稀有 | E51: 切换武器时后备枪回填10%弹匣 | F51: 切换武器时后备枪回填10%弹匣 | G51: 新增塔罗牌“宝剑·侍从”，正位与逆位是同一主题的两种解读。 | H51: [用户设计+Codex规划] | I51: select=GUNBODY_OR_BULLET | J51: action=STOWED_MAG_REFILL; ratio=0.1 | K51: 塔罗命运三选一/工作台/局前预选目标卡池 | L51: [用户设计] | M51: [未施工] 名称、正/逆位与效果参数已完成数据设计 | N51: docs/v0.1/14_技术施工_命运塔罗牌组.md；docs/v0.1/data/ShellStorm2_游戏内容数据库_v010.xlsx | O51: 新增塔罗卡；正式卡池和执行器待施工 | P51: WEAPON | Q51: 占目标枪械下一个永久命运槽；正/逆位都占1槽 | R51: [设计完成/待施工] 正逆位、翻牌和塔罗命名未接入运行时 | S51: ★ 星星命运｜宝剑·侍从｜翻牌后显示正位/逆位、目标、槽位与对应功能 | T51: 卡背绕Y轴翻面；逆位整张正面卡牌（含边框、图案、文字与布局）收束180°，并显示逆位效果描述；对应规则必须在HUD/场景中可读 | U51: [设计完成/待施工] 旧正位表现可复用；逆位与翻转待QA | W51: PAGE | X51: MINOR | Y51: SWORDS | Z51: 0.5 | AA51: 0.5 | AB51: 切换武器时后备枪回填10%弹匣 | AC51: action=STOWED_MAG_REFILL; ratio=0.1 | AD51: 后备枪每8秒恢复5%备弹，切出后停止 | AE51: action=STOWED_RESERVE_REGEN; interval=8; ratio=0.05 | AF51: 0.00s卡背→0.24s薄边换面→0.42s收束；逆位图案/框体180°，卡名、天体、方位标签和说明文字0°；0.62s后可点 | AG51: [设计完成/数据已入表/运行时待施工]
A52: fate_sword_knight | B52: 宝剑·骑士 | C52: 规则 | D52: 史诗 | E52: 冲刺后下一发伤害+40%并穿透 | F52: 冲刺后下一发伤害+40%并穿透 | G52: 新增塔罗牌“宝剑·骑士”，正位与逆位是同一主题的两种解读。 | H52: [用户设计+Codex规划] | I52: select=GUNBODY_OR_BULLET | J52: action=DASH_SHOT; damage_multiplier=1.4; pierce=true | K52: 塔罗命运三选一/工作台/局前预选目标卡池 | L52: [用户设计] | M52: [未施工] 名称、正/逆位与效果参数已完成数据设计 | N52: docs/v0.1/14_技术施工_命运塔罗牌组.md；docs/v0.1/data/ShellStorm2_游戏内容数据库_v010.xlsx | O52: 新增塔罗卡；正式卡池和执行器待施工 | P52: WEAPON | Q52: 占目标枪械下一个永久命运槽；正/逆位都占1槽 | R52: [设计完成/待施工] 正逆位、翻牌和塔罗命名未接入运行时 | S52: ★ 星星命运｜宝剑·骑士｜翻牌后显示正位/逆位、目标、槽位与对应功能 | T52: 卡背绕Y轴翻面；逆位整张正面卡牌（含边框、图案、文字与布局）收束180°，并显示逆位效果描述；对应规则必须在HUD/场景中可读 | U52: [设计完成/待施工] 旧正位表现可复用；逆位与翻转待QA | W52: KNIGHT | X52: MINOR | Y52: SWORDS | Z52: 0.5 | AA52: 0.5 | AB52: 冲刺后下一发伤害+40%并穿透 | AC52: action=DASH_SHOT; damage_multiplier=1.4; pierce=true | AD52: 冲刺中击杀使冲刺冷却-0.6秒 | AE52: action=DASH_KILL_COOLDOWN; cooldown_reduction=0.6 | AF52: 0.00s卡背→0.24s薄边换面→0.42s收束；逆位图案/框体180°，卡名、天体、方位标签和说明文字0°；0.62s后可点 | AG52: [设计完成/数据已入表/运行时待施工]
... A54: fate_sword_king | B54: 宝剑·国王 | C54: 规则 | D54: 禁忌 | E54: 每10次命中生成1枚环绕弹，近敌时自动射出 | F54: 每10次命中生成1枚环绕弹，近敌时自动射出 | G54: 新增塔罗牌“宝剑·国王”，正位与逆位是同一主题的两种解读。 | H54: [用户设计+Codex规划] | I54: select=GUNBODY_OR_BULLET | J54: action=ORBITAL_BULLET; hit_threshold=10 | K54: 塔罗命运三选一/工作台/局前预选目标卡池 | L54: [用户设计] | M54: [未施工] 名称、正/逆位与效果参数已完成数据设计 | N54: docs/v0.1/14_技术施工_命运塔罗牌组.md；docs/v0.1/data/ShellStorm2_游戏内容数据库_v010.xlsx | O54: 新增塔罗卡；正式卡池和执行器待施工 | P54: WEAPON | Q54: 占目标枪械下一个永久命运槽；正/逆位都占1槽 | R54: [设计完成/待施工] 正逆位、翻牌和塔罗命名未接入运行时 | S54: ★ 星星命运｜宝剑·国王｜翻牌后显示正位/逆位、目标、槽位与对应功能 | T54: 卡背绕Y轴翻面；逆位整张正面卡牌（含边框、图案、文字与布局）收束180°，并显示逆位效果描述；对应规则必须在HUD/场景中可读 | U54: [设计完成/待施工] 旧正位表现可复用；逆位与翻转待QA | W54: KING | X54: MINOR | Y54: SWORDS | Z54: 0.5 | AA54: 0.5 | AB54: 每10次命中生成1枚环绕弹，近敌时自动射出 | AC54: action=ORBITAL_BULLET; hit_threshold=10 | AD54: 每10次未命中获得1次必暴，命中会重置未命中计数 | AE54: action=MISS_STREAK_CRIT; miss_threshold=10; reset_on_hit=true | AF54: 0.00s卡背→0.24s薄边换面→0.42s收束；逆位图案/框体180°，卡名、天体、方位标签和说明文字0°；0.62s后可点 | AG54: [设计完成/数据已入表/运行时待施工]
A55: fate_moon_dash | B55: 圣杯·王牌 | C55: 规则 | D55: 史诗 | E55: 冲刺冷却-20% | F55: 本局冲刺冷却时间缩短20% | G55: 新月缩短两次位移之间的空白，让脱险节奏更紧凑。 | H55: [用户设计] | J55: action=APPLY_SCOPED_MODIFIER；modifier=dash_cooldown；multiplier=0.8 | K55: 门后命运/三选一/工作台共用正式卡池 | L55: [已实装] | M55: [部分实装] 塔罗名称、正/逆位效果快照与通用执行已接入；复杂逆位专属行为继续逐卡QA | N55: src/weapons/FateCard.gd；src/weapons/FateCardPresets.gd；src/weapons/FateCardEngine.gd；src/game/FateCardGameBridge.gd；src/player3d/Player3D.gd；src/world3d/Dungeon3D.gd；docs/v0.1/14_技术施工_命运塔罗牌组.md；src/weapons/TarotFateCatalog.gd；tests/verification/verify_tarot_fate_runtime.gd | O55: 迁移前名称：新月回转；稳定ID不变，旧存档迁移为正位，不重投方位 | P55: CHARACTER | Q55: 不占武器槽；写入角色局内规则状态 | R55: [已实装] 塔罗名称、50/50方位、正逆位同ID、代码翻牌、整卡倒置、逆位描述替换与方位持久化已接入 | S55: ☾ 月亮命运｜圣杯·王牌｜翻牌后显示正位/逆位、目标、槽位与对应功能 | T55: 卡背绕Y轴翻面；逆位整张正面卡牌（含边框、图案、文字与布局）收束180°，并显示逆位效果描述；冲刺冷却实际缩短，HUD冷却进度按新时长结算 | U55: [部分实装] 通用卡背/翻牌/逆位倒置已验收；逐卡逆位专属VFX与音效继续QA | V55: 新月回转 | W55: ACE | X55: MINOR | Y55: CUPS | Z55: 0.5 | AA55: 0.5 | AB55: 本局冲刺冷却时间缩短20% | AC55: action=APPLY_SCOPED_MODIFIER；modifier=dash_cooldown；multiplier=0.8 | AD55: 冲刺冷却+20%，距离与无敌时长+40% | AE55: action=APPLY_SCOPED_MODIFIER; modifier=dash_power_trade; cooldown_multiplier=1.2; distance_multiplier=1.4; invulnerability_multiplier=1.4 | AF55: 0.00s卡背→0.24s薄边换面→0.42s收束；逆位图案/框体180°，卡名、天体、方位标签和说明文字0°；0.62s后可点 | AG55: [设计完成/数据已入表/运行时待施工]
A56: fate_moon_room_heal | B56: 圣杯·二 | C56: 规则 | D56: 稀有 | E56: 进新房回血6 | F56: 首次进入房间时恢复6生命 | G56: 每个未踏足房间都会带来一次微弱潮汐，修补角色伤势。 | H56: [用户设计] | J56: action=APPLY_SCOPED_MODIFIER；modifier=room_heal；amount=6 | K56: 门后命运/三选一/工作台共用正式卡池 | L56: [已实装] | M56: [部分实装] 塔罗名称、正/逆位效果快照与通用执行已接入；复杂逆位专属行为继续逐卡QA | N56: src/weapons/FateCard.gd；src/weapons/FateCardPresets.gd；src/weapons/FateCardEngine.gd；src/game/FateCardGameBridge.gd；src/player3d/Player3D.gd；src/world3d/Dungeon3D.gd；docs/v0.1/14_技术施工_命运塔罗牌组.md；src/weapons/TarotFateCatalog.gd；tests/verification/verify_tarot_fate_runtime.gd | O56: 迁移前名称：潮汐疗愈；稳定ID不变，旧存档迁移为正位，不重投方位 | P56: CHARACTER | Q56: 不占武器槽；写入角色局内规则状态 | R56: [已实装] 塔罗名称、50/50方位、正逆位同ID、代码翻牌、整卡倒置、逆位描述替换与方位持久化已接入 | S56: ☾ 月亮命运｜圣杯·二｜翻牌后显示正位/逆位、目标、槽位与对应功能 | T56: 卡背绕Y轴翻面；逆位整张正面卡牌（含边框、图案、文字与布局）收束180°，并显示逆位效果描述；首次进房调用角色疗愈，红色生命条即时反馈 | U56: [部分实装] 通用卡背/翻牌/逆位倒置已验收；逐卡逆位专属VFX与音效继续QA | V56: 潮汐疗愈 | W56: 2 | X56: MINOR | Y56: CUPS | Z56: 0.5 | AA56: 0.5 | AB56: 首次进入房间时恢复6生命 | AC56: action=APPLY_SCOPED_MODIFIER；modifier=room_heal；amount=6 | AD56: 进入新房失去3生命，清房后恢复12 | AE56: action=APPLY_SCOPED_MODIFIER; modifier=room_heal_delayed; entry_damage=3; clear_heal=12 | AF56: 0.00s卡背→0.24s薄边换面→0.42s收束；逆位图案/框体180°，卡名、天体、方位标签和说明文字0°；0.62s后可点 | AG56: [设计完成/数据已入表/运行时待施工]
A57: fate_moon_elite_heal | B57: 圣杯·三 | C57: 规则 | D57: 史诗 | E57: 杀精英回血20 | F57: 击杀精英或首领时恢复20生命 | G57: 强敌倒下时留下的回响被月光收回，转成猎人的生命。 | H57: [用户设计] | J57: action=APPLY_SCOPED_MODIFIER；modifier=elite_heal；amount=20 | K57: 门后命运/三选一/工作台共用正式卡池 | L57: [已实装] | M57: [部分实装] 塔罗名称、正/逆位效果快照与通用执行已接入；复杂逆位专属行为继续逐卡QA | N57: src/weapons/FateCard.gd；src/weapons/FateCardPresets.gd；src/weapons/FateCardEngine.gd；src/game/FateCardGameBridge.gd；src/player3d/Player3D.gd；src/world3d/Dungeon3D.gd；docs/v0.1/14_技术施工_命运塔罗牌组.md；src/weapons/TarotFateCatalog.gd；tests/verification/verify_tarot_fate_runtime.gd | O57: 迁移前名称：猎月回响；稳定ID不变，旧存档迁移为正位，不重投方位 | P57: CHARACTER | Q57: 不占武器槽；写入角色局内规则状态 | R57: [已实装] 塔罗名称、50/50方位、正逆位同ID、代码翻牌、整卡倒置、逆位描述替换与方位持久化已接入 | S57: ☾ 月亮命运｜圣杯·三｜翻牌后显示正位/逆位、目标、槽位与对应功能 | T57: 卡背绕Y轴翻面；逆位整张正面卡牌（含边框、图案、文字与布局）收束180°，并显示逆位效果描述；精英或首领击杀事件触发恢复20生命 | U57: [部分实装] 通用卡背/翻牌/逆位倒置已验收；逐卡逆位专属VFX与音效继续QA | V57: 猎月回响 | W57: 3 | X57: MINOR | Y57: CUPS | Z57: 0.5 | AA57: 0.5 | AB57: 击杀精英或首领时恢复20生命 | AC57: action=APPLY_SCOPED_MODIFIER；modifier=elite_heal；amount=20 | AD57: 精英/首领进战时获得20护盾，击杀不回血 | AE57: action=APPLY_SCOPED_MODIFIER; modifier=elite_entry_shield; amount=20 | AF57: 0.00s卡背→0.24s薄边换面→0.42s收束；逆位图案/框体180°，卡名、天体、方位标签和说明文字0°；0.62s后可点 | AG57: [设计完成/数据已入表/运行时待施工]
A58: fate_moon_ammo | B58: 圣杯·四 | C58: 规则 | D58: 稀有 | E58: 进新房补弹20% | F58: 首次进入房间时补充弹匣容量的20% | G58: 月华在房门后凝成弹药，只补充当前手中枪械的弹匣。 | H58: [用户设计] | J58: action=APPLY_SCOPED_MODIFIER；modifier=room_ammo；ratio=0.2 | K58: 门后命运/三选一/工作台共用正式卡池 | L58: [已实装] | M58: [部分实装] 塔罗名称、正/逆位效果快照与通用执行已接入；复杂逆位专属行为继续逐卡QA | N58: src/weapons/FateCard.gd；src/weapons/FateCardPresets.gd；src/weapons/FateCardEngine.gd；src/game/FateCardGameBridge.gd；src/player3d/Player3D.gd；src/world3d/Dungeon3D.gd；docs/v0.1/14_技术施工_命运塔罗牌组.md；src/weapons/TarotFateCatalog.gd；tests/verification/verify_tarot_fate_runtime.gd | O58: 迁移前名称：月华装填；稳定ID不变，旧存档迁移为正位，不重投方位 | P58: CHARACTER | Q58: 不占武器槽；写入角色局内规则状态 | R58: [已实装] 塔罗名称、50/50方位、正逆位同ID、代码翻牌、整卡倒置、逆位描述替换与方位持久化已接入 | S58: ☾ 月亮命运｜圣杯·四｜翻牌后显示正位/逆位、目标、槽位与对应功能 | T58: 卡背绕Y轴翻面；逆位整张正面卡牌（含边框、图案、文字与布局）收束180°，并显示逆位效果描述；首次进房按当前弹匣容量补弹，弹药HUD同步更新 | U58: [部分实装] 通用卡背/翻牌/逆位倒置已验收；逐卡逆位专属VFX与音效继续QA | V58: 月华装填 | W58: 4 | X58: MINOR | Y58: CUPS | Z58: 0.5 | AA58: 0.5 | AB58: 首次进入房间时补充弹匣容量的20% | AC58: action=APPLY_SCOPED_MODIFIER；modifier=room_ammo；ratio=0.2 | AD58: 进新房后首次换弹速度+25% | AE58: action=APPLY_SCOPED_MODIFIER; modifier=room_first_reload; speed_multiplier=1.25 | AF58: 0.00s卡背→0.24s薄边换面→0.42s收束；逆位图案/框体180°，卡名、天体、方位标签和说明文字0°；0.62s后可点 | AG58: [设计完成/数据已入表/运行时待施工]
A59: fate_bless_dead | B59: 圣杯·五 | C59: 规则 | D59: 史诗 | E59: HP<30%存活30秒→伤害+10% | F59: 当 HP 低于 30% 时存活 30 秒，获得伤害 +10% 的祝福（可叠加） | G59: 濒死却坚持存活的人会得到迟来的回报，伤痕被转化为可叠加的力量。 | H59: [Codex补充] | J59: action=BLESS_DEAD；damage_bonus=0.1；hp_threshold=0.3；max_stacks=3；survive_duration=30 | K59: 玩家卡池；也可由地图阈值事件触发 | L59: [已实装] | M59: [部分实装] 塔罗名称、正/逆位效果快照与通用执行已接入；复杂逆位专属行为继续逐卡QA | N59: src/weapons/FateCard.gd；src/weapons/FateCardPresets.gd；src/weapons/FateCardEngine.gd；src/game/FateCardGameBridge.gd；docs/v0.1/14_技术施工_命运塔罗牌组.md；src/weapons/TarotFateCatalog.gd；tests/verification/verify_tarot_fate_runtime.gd | O59: 迁移前名称：亡者祝福；稳定ID不变，旧存档迁移为正位，不重投方位 | P59: CHARACTER | Q59: 不占武器槽；写入角色局内规则状态 | R59: [已实装] 塔罗名称、50/50方位、正逆位同ID、代码翻牌、整卡倒置、逆位描述替换与方位持久化已接入 | S59: ☾ 月亮命运｜圣杯·五｜翻牌后显示正位/逆位、目标、槽位与对应功能 | T59: 卡背绕Y轴翻面；逆位整张正面卡牌（含边框、图案、文字与布局）收束180°，并显示逆位效果描述；低血量时角色HUD与轮廓触发祝福，结束/冷却明确，枪械轨道不改变 | U59: [部分实装] 通用卡背/翻牌/逆位倒置已验收；逐卡逆位专属VFX与音效继续QA | V59: 亡者祝福 | W59: 5 | X59: MINOR | Y59: CUPS | Z59: 0.5 | AA59: 0.5 | AB59: 当 HP 低于 30% 时存活 30 秒，获得伤害 +10% 的祝福（可叠加） | AC59: action=BLESS_DEAD；damage_bonus=0.1；hp_threshold=0.3；max_stacks=3；survive_duration=30 | AD59: 高于70%生命存活30秒，伤害+8% | AE59: action=APPLY_SCOPED_MODIFIER; modifier=high_hp_survival; hp_threshold=0.7; survive_duration=30; damage_bonus=0.08; max_stacks=3 | AF59: 0.00s卡背→0.24s薄边换面→0.42s收束；逆位图案/框体180°，卡名、天体、方位标签和说明文字0°；0.62s后可点 | AG59: [设计完成/数据已入表/运行时待施工]
A60: fate_cup_six | B60: 圣杯·六 | C60: 规则 | D60: 稀有 | E60: 进入已清理房间恢复4生命，每房一次 | F60: 进入已清理房间恢复4生命，每房一次 | G60: 新增塔罗牌“圣杯·六”，正位与逆位是同一主题的两种解读。 | H60: [用户设计+Codex规划] | J60: action=APPLY_SCOPED_MODIFIER; modifier=cleared_room_heal; amount=4; once_per_room=true | K60: 塔罗命运三选一/工作台/局前预选目标卡池 | L60: [用户设计] | M60: [未施工] 名称、正/逆位与效果参数已完成数据设计 | N60: docs/v0.1/14_技术施工_命运塔罗牌组.md；docs/v0.1/data/ShellStorm2_游戏内容数据库_v010.xlsx | O60: 新增塔罗卡；正式卡池和执行器待施工 | P60: CHARACTER | Q60: 不占武器槽；写入角色局内规则状态 | R60: [设计完成/待施工] 正逆位、翻牌和塔罗命名未接入运行时 | S60: ☾ 月亮命运｜圣杯·六｜翻牌后显示正位/逆位、目标、槽位与对应功能 | T60: 卡背绕Y轴翻面；逆位整张正面卡牌（含边框、图案、文字与布局）收束180°，并显示逆位效果描述；对应规则必须在HUD/场景中可读 | U60: [设计完成/待施工] 旧正位表现可复用；逆位与翻转待QA | W60: 6 | X60: MINOR | Y60: CUPS | Z60: 0.5 | AA60: 0.5 | AB60: 进入已清理房间恢复4生命，每房一次 | AC60: action=APPLY_SCOPED_MODIFIER; modifier=cleared_room_heal; amount=4; once_per_room=true | AD60: 进入未清理房间获得8护盾，每房一次 | AE60: action=APPLY_SCOPED_MODIFIER; modifier=hostile_room_shield; amount=8; once_per_room=true | AF60: 0.00s卡背→0.24s薄边换面→0.42s收束；逆位图案/框体180°，卡名、天体、方位标签和说明文字0°；0.62s后可点 | AG60: [设计完成/数据已入表/运行时待施工]
A61: fate_cup_seven | B61: 圣杯·七 | C61: 规则 | D61: 史诗 | E61: 受伤后移速+10%持续3秒 | F61: 受伤后移速+10%持续3秒 | G61: 新增塔罗牌“圣杯·七”，正位与逆位是同一主题的两种解读。 | H61: [用户设计+Codex规划] | J61: action=APPLY_SCOPED_MODIFIER; modifier=hurt_speed; multiplier=1.1; duration=3 | K61: 塔罗命运三选一/工作台/局前预选目标卡池 | L61: [用户设计] | M61: [未施工] 名称、正/逆位与效果参数已完成数据设计 | N61: docs/v0.1/14_技术施工_命运塔罗牌组.md；docs/v0.1/data/ShellStorm2_游戏内容数据库_v010.xlsx | O61: 新增塔罗卡；正式卡池和执行器待施工 | P61: CHARACTER | Q61: 不占武器槽；写入角色局内规则状态 | R61: [设计完成/待施工] 正逆位、翻牌和塔罗命名未接入运行时 | S61: ☾ 月亮命运｜圣杯·七｜翻牌后显示正位/逆位、目标、槽位与对应功能 | T61: 卡背绕Y轴翻面；逆位整张正面卡牌（含边框、图案、文字与布局）收束180°，并显示逆位效果描述；对应规则必须在HUD/场景中可读 | U61: [设计完成/待施工] 旧正位表现可复用；逆位与翻转待QA | W61: 7 | X61: MINOR | Y61: CUPS | Z61: 0.5 | AA61: 0.5 | AB61: 受伤后移速+10%持续3秒 | AC61: action=APPLY_SCOPED_MODIFIER; modifier=hurt_speed; multiplier=1.1; duration=3 | AD61: 8秒未受伤后受伤-12%，直到下次受伤 | AE61: action=APPLY_SCOPED_MODIFIER; modifier=calm_guard; delay=8; damage_multiplier=0.88; consume_on_hit=true | AF61: 0.00s卡背→0.24s薄边换面→0.42s收束；逆位图案/框体180°，卡名、天体、方位标签和说明文字0°；0.62s后可点 | AG61: [设计完成/数据已入表/运行时待施工]
A62: fate_cup_eight | B62: 圣杯·八 | C62: 强化 | D62: 稀有 | E62: 生命>80%时伤害+10% | F62: 生命>80%时伤害+10% | G62: 新增塔罗牌“圣杯·八”，正位与逆位是同一主题的两种解读。 | H62: [用户设计+Codex规划] | J62: action=APPLY_SCOPED_MODIFIER; modifier=high_hp_damage; threshold=0.8; multiplier=1.1 | K62: 塔罗命运三选一/工作台/局前预选目标卡池 | L62: [用户设计] | M62: [未施工] 名称、正/逆位与效果参数已完成数据设计 | N62: docs/v0.1/14_技术施工_命运塔罗牌组.md；docs/v0.1/data/ShellStorm2_游戏内容数据库_v010.xlsx | O62: 新增塔罗卡；正式卡池和执行器待施工 | P62: CHARACTER | Q62: 不占武器槽；写入角色局内规则状态 | R62: [设计完成/待施工] 正逆位、翻牌和塔罗命名未接入运行时 | S62: ☾ 月亮命运｜圣杯·八｜翻牌后显示正位/逆位、目标、槽位与对应功能 | T62: 卡背绕Y轴翻面；逆位整张正面卡牌（含边框、图案、文字与布局）收束180°，并显示逆位效果描述；对应规则必须在HUD/场景中可读 | U62: [设计完成/待施工] 旧正位表现可复用；逆位与翻转待QA | W62: 8 | X62: MINOR | Y62: CUPS | Z62: 0.5 | AA62: 0.5 | AB62: 生命>80%时伤害+10% | AC62: action=APPLY_SCOPED_MODIFIER; modifier=high_hp_damage; threshold=0.8; multiplier=1.1 | AD62: 生命<35%时移速+15% | AE62: action=APPLY_SCOPED_MODIFIER; modifier=low_hp_speed; threshold=0.35; multiplier=1.15 | AF62: 0.00s卡背→0.24s薄边换面→0.42s收束；逆位图案/框体180°，卡名、天体、方位标签和说明文字0°；0.62s后可点 | AG62: [设计完成/数据已入表/运行时待施工]
A63: fate_cup_nine | B63: 圣杯·九 | C63: 规则 | D63: 史诗 | E63: 使用快捷物品后5秒内换弹+25% | F63: 使用快捷物品后5秒内换弹+25% | G63: 新增塔罗牌“圣杯·九”，正位与逆位是同一主题的两种解读。 | H63: [用户设计+Codex规划] | J63: action=APPLY_SCOPED_MODIFIER; modifier=item_reload_buff; duration=5; reload_speed_multiplier=1.25 | K63: 塔罗命运三选一/工作台/局前预选目标卡池 | L63: [用户设计] | M63: [未施工] 名称、正/逆位与效果参数已完成数据设计 | N63: docs/v0.1/14_技术施工_命运塔罗牌组.md；docs/v0.1/data/ShellStorm2_游戏内容数据库_v010.xlsx | O63: 新增塔罗卡；正式卡池和执行器待施工 | P63: CHARACTER | Q63: 不占武器槽；写入角色局内规则状态 | R63: [设计完成/待施工] 正逆位、翻牌和塔罗命名未接入运行时 | S63: ☾ 月亮命运｜圣杯·九｜翻牌后显示正位/逆位、目标、槽位与对应功能 | T63: 卡背绕Y轴翻面；逆位整张正面卡牌（含边框、图案、文字与布局）收束180°，并显示逆位效果描述；对应规则必须在HUD/场景中可读 | U63: [设计完成/待施工] 旧正位表现可复用；逆位与翻转待QA | W63: 9 | X63: MINOR | Y63: CUPS | Z63: 0.5 | AA63: 0.5 | AB63: 使用快捷物品后5秒内换弹+25% | AC63: action=APPLY_SCOPED_MODIFIER; modifier=item_reload_buff; duration=5; reload_speed_multiplier=1.25 | AD63: 拾取可用物时恢复5生命，10秒冷却 | AE63: action=APPLY_SCOPED_MODIFIER; modifier=usable_pickup_heal; amount=5; cooldown=10 | AF63: 0.00s卡背→0.24s薄边换面→0.42s收束；逆位图案/框体180°，卡名、天体、方位标签和说明文字0°；0.62s后可点 | AG63: [设计完成/数据已入表/运行时待施工]
A64: fate_cup_ten | B64: 圣杯·十 | C64: 规则 | D64: 传说 | E64: 每种不同月亮卡使生命上限+3 | F64: 每种不同月亮卡使生命上限+3 | G64: 新增塔罗牌“圣杯·十”，正位与逆位是同一主题的两种解读。 | H64: [用户设计+Codex规划] | J64: action=APPLY_SCOPED_MODIFIER; modifier=moon_variety_hp; amount_per_unique=3 | K64: 塔罗命运三选一/工作台/局前预选目标卡池 | L64: [用户设计] | M64: [未施工] 名称、正/逆位与效果参数已完成数据设计 | N64: docs/v0.1/14_技术施工_命运塔罗牌组.md；docs/v0.1/data/ShellStorm2_游戏内容数据库_v010.xlsx | O64: 新增塔罗卡；正式卡池和执行器待施工 | P64: CHARACTER | Q64: 不占武器槽；写入角色局内规则状态 | R64: [设计完成/待施工] 正逆位、翻牌和塔罗命名未接入运行时 | S64: ☾ 月亮命运｜圣杯·十｜翻牌后显示正位/逆位、目标、槽位与对应功能 | T64: 卡背绕Y轴翻面；逆位整张正面卡牌（含边框、图案、文字与布局）收束180°，并显示逆位效果描述；对应规则必须在HUD/场景中可读 | U64: [设计完成/待施工] 旧正位表现可复用；逆位与翻转待QA | W64: 10 | X64: MINOR | Y64: CUPS | Z64: 0.5 | AA64: 0.5 | AB64: 每种不同月亮卡使生命上限+3 | AC64: action=APPLY_SCOPED_MODIFIER; modifier=moon_variety_hp; amount_per_unique=3 | AD64: 每张重复月亮卡使该卡数值效果+4% | AE64: action=APPLY_SCOPED_MODIFIER; modifier=moon_duplicate_power; multiplier_per_duplicate=1.04 | AF64: 0.00s卡背→0.24s薄边换面→0.42s收束；逆位图案/框体180°，卡名、天体、方位标签和说明文字0°；0.62s后可点 | AG64: [设计完成/数据已入表/运行时待施工]
A65: fate_cup_page | B65: 圣杯·侍从 | C65: 强化 | D65: 稀有 | E65: 主动物品治疗/护盾效果+20% | F65: 主动物品治疗/护盾效果+20% | G65: 新增塔罗牌“圣杯·侍从”，正位与逆位是同一主题的两种解读。 | H65: [用户设计+Codex规划] | J65: action=APPLY_SCOPED_MODIFIER; modifier=usable_effect; multiplier=1.2 | K65: 塔罗命运三选一/工作台/局前预选目标卡池 | L65: [用户设计] | M65: [未施工] 名称、正/逆位与效果参数已完成数据设计 | N65: docs/v0.1/14_技术施工_命运塔罗牌组.md；docs/v0.1/data/ShellStorm2_游戏内容数据库_v010.xlsx | O65: 新增塔罗卡；正式卡池和执行器待施工 | P65: CHARACTER | Q65: 不占武器槽；写入角色局内规则状态 | R65: [设计完成/待施工] 正逆位、翻牌和塔罗命名未接入运行时 | S65: ☾ 月亮命运｜圣杯·侍从｜翻牌后显示正位/逆位、目标、槽位与对应功能 | T65: 卡背绕Y轴翻面；逆位整张正面卡牌（含边框、图案、文字与布局）收束180°，并显示逆位效果描述；对应规则必须在HUD/场景中可读 | U65: [设计完成/待施工] 旧正位表现可复用；逆位与翻转待QA | W65: PAGE | X65: MINOR | Y65: CUPS | Z65: 0.5 | AA65: 0.5 | AB65: 主动物品治疗/护盾效果+20% | AC65: action=APPLY_SCOPED_MODIFIER; modifier=usable_effect; multiplier=1.2 | AD65: 使用主动物品时20%概率不消耗，但效果-10% | AE65: action=APPLY_SCOPED_MODIFIER; modifier=usable_preserve_trade; preserve_probability=0.2; effect_multiplier=0.9 | AF65: 0.00s卡背→0.24s薄边换面→0.42s收束；逆位图案/框体180°，卡名、天体、方位标签和说明文字0°；0.62s后可点 | AG65: [设计完成/数据已入表/运行时待施工]
A66: fate_cup_knight | B66: 圣杯·骑士 | C66: 规则 | D66: 史诗 | E66: 冲刺穿过敌人使其受伤+15%持5秒 | F66: 冲刺穿过敌人使其受伤+15%持5秒 | G66: 新增塔罗牌“圣杯·骑士”，正位与逆位是同一主题的两种解读。 | H66: [用户设计+Codex规划] | J66: action=APPLY_SCOPED_MODIFIER; modifier=dash_mark; damage_taken_multiplier=1.15; duration=5 | K66: 塔罗命运三选一/工作台/局前预选目标卡池 | L66: [用户设计] | M66: [未施工] 名称、正/逆位与效果参数已完成数据设计 | N66: docs/v0.1/14_技术施工_命运塔罗牌组.md；docs/v0.1/data/ShellStorm2_游戏内容数据库_v010.xlsx | O66: 新增塔罗卡；正式卡池和执行器待施工 | P66: CHARACTER | Q66: 不占武器槽；写入角色局内规则状态 | R66: [设计完成/待施工] 正逆位、翻牌和塔罗命名未接入运行时 | S66: ☾ 月亮命运｜圣杯·骑士｜翻牌后显示正位/逆位、目标、槽位与对应功能 | T66: 卡背绕Y轴翻面；逆位整张正面卡牌（含边框、图案、文字与布局）收束180°，并显示逆位效果描述；对应规则必须在HUD/场景中可读 | U66: [设计完成/待施工] 旧正位表现可复用；逆位与翻转待QA | W66: KNIGHT | X66: MINOR | Y66: CUPS | Z66: 0.5 | AA66: 0.5 | AB66: 冲刺穿过敌人使其受伤+15%持5秒 | AC66: action=APPLY_SCOPED_MODIFIER; modifier=dash_mark; damage_taken_multiplier=1.15; duration=5 | AD66: 向远离最近敌人方向冲刺获得10护盾 | AE66: action=APPLY_SCOPED_MODIFIER; modifier=escape_dash_shield; amount=10 | AF66: 0.00s卡背→0.24s薄边换面→0.42s收束；逆位图案/框体180°，卡名、天体、方位标签和说明文字0°；0.62s后可点 | AG66: [设计完成/数据已入表/运行时待施工]
A67: fate_cup_queen | B67: 圣杯·王后 | C67: 规则 | D67: 传说 | E67: 溢出治疗转为护盾，上限15 | F67: 溢出治疗转为护盾，上限15 | G67: 新增塔罗牌“圣杯·王后”，正位与逆位是同一主题的两种解读。 | H67: [用户设计+Codex规划] | J67: action=APPLY_SCOPED_MODIFIER; modifier=overheal_shield; shield_cap=15 | K67: 塔罗命运三选一/工作台/局前预选目标卡池 | L67: [用户设计] | M67: [未施工] 名称、正/逆位与效果参数已完成数据设计 | N67: docs/v0.1/14_技术施工_命运塔罗牌组.md；docs/v0.1/data/ShellStorm2_游戏内容数据库_v010.xlsx | O67: 新增塔罗卡；正式卡池和执行器待施工 | P67: CHARACTER | Q67: 不占武器槽；写入角色局内规则状态 | R67: [设计完成/待施工] 正逆位、翻牌和塔罗命名未接入运行时 | S67: ☾ 月亮命运｜圣杯·王后｜翻牌后显示正位/逆位、目标、槽位与对应功能 | T67: 卡背绕Y轴翻面；逆位整张正面卡牌（含边框、图案、文字与布局）收束180°，并显示逆位效果描述；对应规则必须在HUD/场景中可读 | U67: [设计完成/待施工] 旧正位表现可复用；逆位与翻转待QA | W67: QUEEN | X67: MINOR | Y67: CUPS | Z67: 0.5 | AA67: 0.5 | AB67: 溢出治疗转为护盾，上限15 | AC67: action=APPLY_SCOPED_MODIFIER; modifier=overheal_shield; shield_cap=15 | AD67: 护盾破碎时恢复8生命，12秒冷却 | AE67: action=APPLY_SCOPED_MODIFIER; modifier=shield_break_heal; amount=8; cooldown=12 | AF67: 0.00s卡背→0.24s薄边换面→0.42s收束；逆位图案/框体180°，卡名、天体、方位标签和说明文字0°；0.62s后可点 | AG67: [设计完成/数据已入表/运行时待施工]
A68: fate_cup_king | B68: 圣杯·国王 | C68: 规则 | D68: 禁忌 | E68: Boss房内每10秒恢复3生命 | F68: Boss房内每10秒恢复3生命 | G68: 新增塔罗牌“圣杯·国王”，正位与逆位是同一主题的两种解读。 | H68: [用户设计+Codex规划] | J68: action=APPLY_SCOPED_MODIFIER; modifier=boss_room_regen; interval=10; amount=3 | K68: 塔罗命运三选一/工作台/局前预选目标卡池 | L68: [用户设计] | M68: [未施工] 名称、正/逆位与效果参数已完成数据设计 | N68: docs/v0.1/14_技术施工_命运塔罗牌组.md；docs/v0.1/data/ShellStorm2_游戏内容数据库_v010.xlsx | O68: 新增塔罗卡；正式卡池和执行器待施工 | P68: CHARACTER | Q68: 不占武器槽；写入角色局内规则状态 | R68: [设计完成/待施工] 正逆位、翻牌和塔罗命名未接入运行时 | S68: ☾ 月亮命运｜圣杯·国王｜翻牌后显示正位/逆位、目标、槽位与对应功能 | T68: 卡背绕Y轴翻面；逆位整张正面卡牌（含边框、图案、文字与布局）收束180°，并显示逆位效果描述；对应规则必须在HUD/场景中可读 | U68: [设计完成/待施工] 旧正位表现可复用；逆位与翻转待QA | W68: KING | X68: MINOR | Y68: CUPS | Z68: 0.5 | AA68: 0.5 | AB68: Boss房内每10秒恢复3生命 | AC68: action=APPLY_SCOPED_MODIFIER; modifier=boss_room_regen; interval=10; amount=3 | AD68: Boss房不自动恢复，但伤害+8% | AE68: action=APPLY_SCOPED_MODIFIER; modifier=boss_room_damage; multiplier=1.08 | AF68: 0.00s卡背→0.24s薄边换面→0.42s收束；逆位图案/框体180°，卡名、天体、方位标签和说明文字0°；0.62s后可点 | AG68: [设计完成/数据已入表/运行时待施工]
A69: fate_reinforce | B69: 星币·王牌 | C69: 规则 | D69: 史诗 | E69: 连续击杀后额外刷新一波怪物 | F69: 连续击杀 5 个敌人后，在房间随机位置额外刷新一波怪物 | G69: 连续死亡会惊醒附近房间的警戒网，把原本不属于本波的敌人召来。 | H69: [Codex补充] | J69: action=REINFORCE_WAVE；kill_threshold=5；spawn_count=3 | K69: 玩家卡池；也可由地图阈值事件触发 | L69: [已实装] | M69: [部分实装] 塔罗名称、正/逆位效果快照与通用执行已接入；复杂逆位专属行为继续逐卡QA | N69: src/weapons/FateCard.gd；src/weapons/FateCardPresets.gd；src/weapons/FateCardEngine.gd；src/game/FateCardGameBridge.gd；docs/v0.1/14_技术施工_命运塔罗牌组.md；src/weapons/TarotFateCatalog.gd；tests/verification/verify_tarot_fate_runtime.gd | O69: 迁移前名称：敌增援；稳定ID不变，旧存档迁移为正位，不重投方位 | P69: WORLD | Q69: 不占武器槽；写入行动/房间/掉落规则状态 | R69: [已实装] 塔罗名称、50/50方位、正逆位同ID、代码翻牌、整卡倒置、逆位描述替换与方位持久化已接入 | S69: ☀ 太阳命运｜星币·王牌｜翻牌后显示正位/逆位、目标、槽位与对应功能 | T69: 卡背绕Y轴翻面；逆位整张正面卡牌（含边框、图案、文字与布局）收束180°，并显示逆位效果描述；地图/房间出现增援警报、入口方向和敌人波次反馈，枪身不刻印 | U69: [部分实装] 通用卡背/翻牌/逆位倒置已验收；逐卡逆位专属VFX与音效继续QA | V69: 敌增援 | W69: ACE | X69: MINOR | Y69: PENTACLES | Z69: 0.5 | AA69: 0.5 | AB69: 连续击杀 5 个敌人后，在房间随机位置额外刷新一波怪物 | AC69: action=REINFORCE_WAVE；kill_threshold=5；spawn_count=3 | AD69: 5连杀后增援1精英，击杀额外+50魂 | AE69: action=REINFORCE_ELITE; kill_threshold=5; elite_count=1; currency_reward=50 | AF69: 0.00s卡背→0.24s薄边换面→0.42s收束；逆位图案/框体180°，卡名、天体、方位标签和说明文字0°；0.62s后可点 | AG69: [设计完成/数据已入表/运行时待施工]
A70: fate_lucky_chest | B70: 星币·二 | C70: 规则 | D70: 稀有 | E70: 下一箱物品品质+1 | F70: 下一个开启的箱子物品品质提升 1 级（白色→蓝色→紫色→金色） | G70: 被标记的下一个容器会被命运重新估价，里面的东西更接近玩家需要的层级。 | H70: [Codex补充] | J70: action=LUCKY_CHEST；upgrade_tiers=1 | K70: 玩家卡池；也可由地图阈值事件触发 | L70: [已实装] | M70: [部分实装] 塔罗名称、正/逆位效果快照与通用执行已接入；复杂逆位专属行为继续逐卡QA | N70: src/weapons/FateCard.gd；src/weapons/FateCardPresets.gd；src/weapons/FateCardEngine.gd；src/game/FateCardGameBridge.gd；docs/v0.1/14_技术施工_命运塔罗牌组.md；src/weapons/TarotFateCatalog.gd；tests/verification/verify_tarot_fate_runtime.gd | O70: 迁移前名称：幸运发现；稳定ID不变，旧存档迁移为正位，不重投方位 | P70: WORLD | Q70: 不占武器槽；写入行动/房间/掉落规则状态 | R70: [已实装] 塔罗名称、50/50方位、正逆位同ID、代码翻牌、整卡倒置、逆位描述替换与方位持久化已接入 | S70: ☀ 太阳命运｜星币·二｜翻牌后显示正位/逆位、目标、槽位与对应功能 | T70: 卡背绕Y轴翻面；逆位整张正面卡牌（含边框、图案、文字与布局）收束180°，并显示逆位效果描述；地图/宝箱图标带幸运标记，实际开箱时品质升级动画后再消耗状态 | U70: [部分实装] 通用卡背/翻牌/逆位倒置已验收；逐卡逆位专属VFX与音效继续QA | V70: 幸运发现 | W70: 2 | X70: MINOR | Y70: PENTACLES | Z70: 0.5 | AA70: 0.5 | AB70: 下一个开启的箱子物品品质提升 1 级（白色→蓝色→紫色→金色） | AC70: action=LUCKY_CHEST；upgrade_tiers=1 | AD70: 下一容器品质-1，但额外+2件 | AE70: action=LUCKY_CHEST_TRADE; rarity_tiers=-1; extra_count=2 | AF70: 0.00s卡背→0.24s薄边换面→0.42s收束；逆位图案/框体180°，卡名、天体、方位标签和说明文字0°；0.62s后可点 | AG70: [设计完成/数据已入表/运行时待施工]
A71: fate_extra_loot | B71: 星币·三 | C71: 规则 | D71: 稀有 | E71: 下一箱追加抽取，仍落一件 | F71: 下一个开启的箱子增加一次候选抽取并保留更优结果，地面仍只掉落一件物品 | G71: 命运在下一个箱子的清单末尾多写一行，再从两份结果里只留下更好的一件。 | H71: [Codex补充] | J71: action=EXTRA_LOOT；extra_count=1 | K71: 玩家卡池；也可由地图阈值事件触发 | L71: [已实装] | M71: [部分实装] 塔罗名称、正/逆位效果快照与通用执行已接入；复杂逆位专属行为继续逐卡QA | N71: src/weapons/FateCard.gd；src/weapons/FateCardPresets.gd；src/weapons/FateCardEngine.gd；src/game/FateCardGameBridge.gd；docs/v0.1/14_技术施工_命运塔罗牌组.md；src/weapons/TarotFateCatalog.gd；tests/verification/verify_tarot_fate_runtime.gd | O71: 迁移前名称：额外掉落；稳定ID不变，旧存档迁移为正位，不重投方位 | P71: WORLD | Q71: 不占武器槽；写入行动/房间/掉落规则状态 | R71: [已实装] 塔罗名称、50/50方位、正逆位同ID、代码翻牌、整卡倒置、逆位描述替换与方位持久化已接入 | S71: ☀ 太阳命运｜星币·三｜翻牌后显示正位/逆位、目标、槽位与对应功能 | T71: 开箱时出现一次额外候选扫描和来源提示，触发后只生成1个地面实体并清空计数 | U71: [部分实装] 通用卡背/翻牌/逆位倒置已验收；逐卡逆位专属VFX与音效继续QA | V71: 额外掉落 | W71: 3 | X71: MINOR | Y71: PENTACLES | Z71: 0.5 | AA71: 0.5 | AB71: 下一个开启的箱子增加一次候选抽取并保留更优结果，地面仍只掉落一件物品 | AC71: action=EXTRA_LOOT；extra_count=1 | AD71: 下一容器追加一次候选抽取，保留结果品质提高1级，地面仍只掉落1件 | AE71: action=EXTRA_LOOT_TRADE; count_delta=-1; rarity_tiers=1 | AF71: 0.00s卡背→0.24s薄边换面→0.42s收束；逆位图案/框体180°，卡名、天体、方位标签和说明文字0°；0.62s后可点 | AG71: [设计完成/数据已入表/运行时待施工]
A72: fate_curse_map | B72: 星币·四 | C72: 诅咒 | D72: 禁忌 | E72: 本房间敌人伤害+15% | F72: 当前房间内所有敌人伤害提升 15%，击杀后诅咒消失 | G72: 房间用更危险的敌人交换更强的叙事压力，清理完成后诅咒随之消散。 | H72: [Codex补充] | J72: action=CURSE_ROOM_ENEMIES；clear_on_kill=true；damage_bonus=0.15 | K72: 玩家卡池；也可由地图阈值事件触发 | L72: [已实装] | M72: [部分实装] 塔罗名称、正/逆位效果快照与通用执行已接入；复杂逆位专属行为继续逐卡QA | N72: src/weapons/FateCard.gd；src/weapons/FateCardPresets.gd；src/weapons/FateCardEngine.gd；src/game/FateCardGameBridge.gd；docs/v0.1/14_技术施工_命运塔罗牌组.md；src/weapons/TarotFateCatalog.gd；tests/verification/verify_tarot_fate_runtime.gd | O72: 迁移前名称：诅咒降临；稳定ID不变，旧存档迁移为正位，不重投方位 | P72: WORLD | Q72: 不占武器槽；写入行动/房间/掉落规则状态 | R72: [已实装] 塔罗名称、50/50方位、正逆位同ID、代码翻牌、整卡倒置、逆位描述替换与方位持久化已接入 | S72: ☀ 太阳命运｜星币·四｜翻牌后显示正位/逆位、目标、槽位与对应功能 | T72: 卡背绕Y轴翻面；逆位整张正面卡牌（含边框、图案、文字与布局）收束180°，并显示逆位效果描述；小地图边框、环境异常和受影响单位图标统一使用诅咒语言，枪械不占槽 | U72: [部分实装] 通用卡背/翻牌/逆位倒置已验收；逐卡逆位专属VFX与音效继续QA | V72: 诅咒降临 | W72: 4 | X72: MINOR | Y72: PENTACLES | Z72: 0.5 | AA72: 0.5 | AB72: 当前房间内所有敌人伤害提升 15%，击杀后诅咒消失 | AC72: action=CURSE_ROOM_ENEMIES；clear_on_kill=true；damage_bonus=0.15 | AD72: 当前房敌伤-10%，但魂掉落-30% | AE72: action=CURSE_ROOM_ENEMIES; damage_multiplier=0.9; currency_multiplier=0.7 | AF72: 0.00s卡背→0.24s薄边换面→0.42s收束；逆位图案/框体180°，卡名、天体、方位标签和说明文字0°；0.62s后可点 | AG72: [设计完成/数据已入表/运行时待施工]
A73: fate_sun_quality | B73: 星币·五 | C73: 规则 | D73: 稀有 | E73: 下箱品质+1 | F73: 下一个开启容器的物品品质提升1级 | G73: 晨光先一步照进下个容器，把其中一件物资推向更高层级。 | H73: [用户设计] | J73: action=APPLY_SCOPED_MODIFIER；modifier=next_chest_quality；tiers=1 | K73: 门后命运/三选一/工作台共用正式卡池 | L73: [已实装] | M73: [部分实装] 塔罗名称、正/逆位效果快照与通用执行已接入；复杂逆位专属行为继续逐卡QA | N73: src/weapons/FateCard.gd；src/weapons/FateCardPresets.gd；src/weapons/FateCardEngine.gd；src/game/FateCardGameBridge.gd；src/player3d/Player3D.gd；src/world3d/Dungeon3D.gd；docs/v0.1/14_技术施工_命运塔罗牌组.md；src/weapons/TarotFateCatalog.gd；tests/verification/verify_tarot_fate_runtime.gd | O73: 迁移前名称：晨曦宝库；稳定ID不变，旧存档迁移为正位，不重投方位 | P73: WORLD | Q73: 不占武器槽；写入行动/房间/掉落/撤离规则状态 | R73: [已实装] 塔罗名称、50/50方位、正逆位同ID、代码翻牌、整卡倒置、逆位描述替换与方位持久化已接入 | S73: ☀ 太阳命运｜星币·五｜翻牌后显示正位/逆位、目标、槽位与对应功能 | T73: 卡背绕Y轴翻面；逆位整张正面卡牌（含边框、图案、文字与布局）收束180°，并显示逆位效果描述；世界状态记录下一箱品质；开箱后消费并生成升级物资 | U73: [部分实装] 通用卡背/翻牌/逆位倒置已验收；逐卡逆位专属VFX与音效继续QA | V73: 晨曦宝库 | W73: 5 | X73: MINOR | Y73: PENTACLES | Z73: 0.5 | AA73: 0.5 | AB73: 下一个开启容器的物品品质提升1级 | AC73: action=APPLY_SCOPED_MODIFIER；modifier=next_chest_quality；tiers=1 | AD73: 下一容器品质+2，但数量-1 | AE73: action=APPLY_SCOPED_MODIFIER; modifier=next_chest_quality_trade; tiers=2; count_delta=-1 | AF73: 0.00s卡背→0.24s薄边换面→0.42s收束；逆位图案/框体180°，卡名、天体、方位标签和说明文字0°；0.62s后可点 | AG73: [设计完成/数据已入表/运行时待施工]
A74: fate_sun_reveal | B74: 星币·六 | C74: 规则 | D74: 稀有 | E74: 揭示周围2层 | F74: 立即揭示当前房间周围2层相邻房间 | G74: 曙光沿走廊扩散，把附近两层连接关系投到地图上。 | H74: [用户设计] | J74: action=APPLY_SCOPED_MODIFIER；modifier=reveal_rooms；radius=2 | K74: 门后命运/三选一/工作台共用正式卡池 | L74: [已实装] | M74: [部分实装] 塔罗名称、正/逆位效果快照与通用执行已接入；复杂逆位专属行为继续逐卡QA | N74: src/weapons/FateCard.gd；src/weapons/FateCardPresets.gd；src/weapons/FateCardEngine.gd；src/game/FateCardGameBridge.gd；src/player3d/Player3D.gd；src/world3d/Dungeon3D.gd；docs/v0.1/14_技术施工_命运塔罗牌组.md；src/weapons/TarotFateCatalog.gd；tests/verification/verify_tarot_fate_runtime.gd | O74: 迁移前名称：曙光测绘；稳定ID不变，旧存档迁移为正位，不重投方位 | P74: WORLD | Q74: 不占武器槽；写入行动/房间/掉落/撤离规则状态 | R74: [已实装] 塔罗名称、50/50方位、正逆位同ID、代码翻牌、整卡倒置、逆位描述替换与方位持久化已接入 | S74: ☀ 太阳命运｜星币·六｜翻牌后显示正位/逆位、目标、槽位与对应功能 | T74: 卡背绕Y轴翻面；逆位整张正面卡牌（含边框、图案、文字与布局）收束180°，并显示逆位效果描述；小地图立即揭示两层邻接房，不生成或修改枪械数据 | U74: [部分实装] 通用卡背/翻牌/逆位倒置已验收；逐卡逆位专属VFX与音效继续QA | V74: 曙光测绘 | W74: 6 | X74: MINOR | Y74: PENTACLES | Z74: 0.5 | AA74: 0.5 | AB74: 立即揭示当前房间周围2层相邻房间 | AC74: action=APPLY_SCOPED_MODIFIER；modifier=reveal_rooms；radius=2 | AD74: 揭示周围4层拓扑，但隐藏房间类型 | AE74: action=APPLY_SCOPED_MODIFIER; modifier=reveal_topology_only; radius=4; reveal_room_type=false | AF74: 0.00s卡背→0.24s薄边换面→0.42s收束；逆位图案/框体180°，卡名、天体、方位标签和说明文字0°；0.62s后可点 | AG74: [设计完成/数据已入表/运行时待施工]
A75: fate_sun_bounty | B75: 星币·七 | C75: 规则 | D75: 史诗 | E75: 三房各奖35魂 | F75: 接下来3个敌对房间肃清时各获得35魂 | G75: 长昼把三次肃清写进赏金契约，每完成一间就结算一次。 | H75: [用户设计] | J75: action=APPLY_SCOPED_MODIFIER；modifier=room_clear_bounty；rooms=3；amount=35 | K75: 门后命运/三选一/工作台共用正式卡池 | L75: [已实装] | M75: [部分实装] 塔罗名称、正/逆位效果快照与通用执行已接入；复杂逆位专属行为继续逐卡QA | N75: src/weapons/FateCard.gd；src/weapons/FateCardPresets.gd；src/weapons/FateCardEngine.gd；src/game/FateCardGameBridge.gd；src/player3d/Player3D.gd；src/world3d/Dungeon3D.gd；docs/v0.1/14_技术施工_命运塔罗牌组.md；src/weapons/TarotFateCatalog.gd；tests/verification/verify_tarot_fate_runtime.gd | O75: 迁移前名称：长昼赏金；稳定ID不变，旧存档迁移为正位，不重投方位 | P75: WORLD | Q75: 不占武器槽；写入行动/房间/掉落/撤离规则状态 | R75: [已实装] 塔罗名称、50/50方位、正逆位同ID、代码翻牌、整卡倒置、逆位描述替换与方位持久化已接入 | S75: ☀ 太阳命运｜星币·七｜翻牌后显示正位/逆位、目标、槽位与对应功能 | T75: 卡背绕Y轴翻面；逆位整张正面卡牌（含边框、图案、文字与布局）收束180°，并显示逆位效果描述；敌对房首次肃清结算35魂并扣除1次，HUD货币同步 | U75: [部分实装] 通用卡背/翻牌/逆位倒置已验收；逐卡逆位专属VFX与音效继续QA | V75: 长昼赏金 | W75: 7 | X75: MINOR | Y75: PENTACLES | Z75: 0.5 | AA75: 0.5 | AB75: 接下来3个敌对房间肃清时各获得35魂 | AC75: action=APPLY_SCOPED_MODIFIER；modifier=room_clear_bounty；rooms=3；amount=35 | AD75: 下1房奖120魂，再后2房不掉魂 | AE75: action=APPLY_SCOPED_MODIFIER; modifier=frontloaded_bounty; first_amount=120; blocked_rooms=2 | AF75: 0.00s卡背→0.24s薄边换面→0.42s收束；逆位图案/框体180°，卡名、天体、方位标签和说明文字0°；0.62s后可点 | AG75: [设计完成/数据已入表/运行时待施工]
A76: fate_pentacle_eight | B76: 星币·八 | C76: 规则 | D76: 史诗 | E76: 下2个容器各重投最低品质物1次 | F76: 下2个容器各重投最低品质物1次 | G76: 新增塔罗牌“星币·八”，正位与逆位是同一主题的两种解读。 | H76: [用户设计+Codex规划] | J76: action=APPLY_SCOPED_MODIFIER; modifier=reroll_lowest_item; containers=2; rerolls=1 | K76: 塔罗命运三选一/工作台/局前预选目标卡池 | L76: [用户设计] | M76: [未施工] 名称、正/逆位与效果参数已完成数据设计 | N76: docs/v0.1/14_技术施工_命运塔罗牌组.md；docs/v0.1/data/ShellStorm2_游戏内容数据库_v010.xlsx | O76: 新增塔罗卡；正式卡池和执行器待施工 | P76: WORLD | Q76: 不占武器槽；写入行动/房间/掉落规则状态 | R76: [设计完成/待施工] 正逆位、翻牌和塔罗命名未接入运行时 | S76: ☀ 太阳命运｜星币·八｜翻牌后显示正位/逆位、目标、槽位与对应功能 | T76: 卡背绕Y轴翻面；逆位整张正面卡牌（含边框、图案、文字与布局）收束180°，并显示逆位效果描述；对应规则必须在HUD/场景中可读 | U76: [设计完成/待施工] 旧正位表现可复用；逆位与翻转待QA | W76: 8 | X76: MINOR | Y76: PENTACLES | Z76: 0.5 | AA76: 0.5 | AB76: 下2个容器各重投最低品质物1次 | AC76: action=APPLY_SCOPED_MODIFIER; modifier=reroll_lowest_item; containers=2; rerolls=1 | AD76: 预览下一容器全部内容，但开启时减少1件 | AE76: action=APPLY_SCOPED_MODIFIER; modifier=preview_container_trade; containers=1; count_delta=-1 | AF76: 0.00s卡背→0.24s薄边换面→0.42s收束；逆位图案/框体180°，卡名、天体、方位标签和说明文字0°；0.62s后可点 | AG76: [设计完成/数据已入表/运行时待施工]
A77: fate_pentacle_nine | B77: 星币·九 | C77: 规则 | D77: 稀有 | E77: 下3个敌对房医疗品掉率+25% | F77: 下3个敌对房医疗品掉率+25% | G77: 新增塔罗牌“星币·九”，正位与逆位是同一主题的两种解读。 | H77: [用户设计+Codex规划] | J77: action=APPLY_SCOPED_MODIFIER; modifier=medical_drop_rate; rooms=3; probability_add=0.25 | K77: 塔罗命运三选一/工作台/局前预选目标卡池 | L77: [用户设计] | M77: [未施工] 名称、正/逆位与效果参数已完成数据设计 | N77: docs/v0.1/14_技术施工_命运塔罗牌组.md；docs/v0.1/data/ShellStorm2_游戏内容数据库_v010.xlsx | O77: 新增塔罗卡；正式卡池和执行器待施工 | P77: WORLD | Q77: 不占武器槽；写入行动/房间/掉落规则状态 | R77: [设计完成/待施工] 正逆位、翻牌和塔罗命名未接入运行时 | S77: ☀ 太阳命运｜星币·九｜翻牌后显示正位/逆位、目标、槽位与对应功能 | T77: 卡背绕Y轴翻面；逆位整张正面卡牌（含边框、图案、文字与布局）收束180°，并显示逆位效果描述；对应规则必须在HUD/场景中可读 | U77: [设计完成/待施工] 旧正位表现可复用；逆位与翻转待QA | W77: 9 | X77: MINOR | Y77: PENTACLES | Z77: 0.5 | AA77: 0.5 | AB77: 下3个敌对房医疗品掉率+25% | AC77: action=APPLY_SCOPED_MODIFIER; modifier=medical_drop_rate; rooms=3; probability_add=0.25 | AD77: 下3个敌对房弹药掉率+25% | AE77: action=APPLY_SCOPED_MODIFIER; modifier=ammo_drop_rate; rooms=3; probability_add=0.25 | AF77: 0.00s卡背→0.24s薄边换面→0.42s收束；逆位图案/框体180°，卡名、天体、方位标签和说明文字0°；0.62s后可点 | AG77: [设计完成/数据已入表/运行时待施工]
A78: fate_pentacle_ten | B78: 星币·十 | C78: 规则 | D78: 传说 | E78: 支路房奖励+1，并额外生成1精英 | F78: 支路房奖励+1，并额外生成1精英 | G78: 新增塔罗牌“星币·十”，正位与逆位是同一主题的两种解读。 | H78: [用户设计+Codex规划] | J78: action=APPLY_SCOPED_MODIFIER; modifier=branch_risk_reward; reward_add=1; elite_add=1 | K78: 塔罗命运三选一/工作台/局前预选目标卡池 | L78: [用户设计] | M78: [未施工] 名称、正/逆位与效果参数已完成数据设计 | N78: docs/v0.1/14_技术施工_命运塔罗牌组.md；docs/v0.1/data/ShellStorm2_游戏内容数据库_v010.xlsx | O78: 新增塔罗卡；正式卡池和执行器待施工 | P78: WORLD | Q78: 不占武器槽；写入行动/房间/掉落规则状态 | R78: [设计完成/待施工] 正逆位、翻牌和塔罗命名未接入运行时 | S78: ☀ 太阳命运｜星币·十｜翻牌后显示正位/逆位、目标、槽位与对应功能 | T78: 卡背绕Y轴翻面；逆位整张正面卡牌（含边框、图案、文字与布局）收束180°，并显示逆位效果描述；对应规则必须在HUD/场景中可读 | U78: [设计完成/待施工] 旧正位表现可复用；逆位与翻转待QA | W78: 10 | X78: MINOR | Y78: PENTACLES | Z78: 0.5 | AA78: 0.5 | AB78: 支路房奖励+1，并额外生成1精英 | AC78: action=APPLY_SCOPED_MODIFIER; modifier=branch_risk_reward; reward_add=1; elite_add=1 | AD78: 主路普通敌人-1，但支路奖励-1 | AE78: action=APPLY_SCOPED_MODIFIER; modifier=safe_main_path; main_enemy_delta=-1; branch_reward_delta=-1 | AF78: 0.00s卡背→0.24s薄边换面→0.42s收束；逆位图案/框体180°，卡名、天体、方位标签和说明文字0°；0.62s后可点 | AG78: [设计完成/数据已入表/运行时待施工]
A79: fate_pentacle_page | B79: 星币·侍从 | C79: 规则 | D79: 稀有 | E79: 揭示最近未开容器与最短路线 | F79: 揭示最近未开容器与最短路线 | G79: 新增塔罗牌“星币·侍从”，正位与逆位是同一主题的两种解读。 | H79: [用户设计+Codex规划] | J79: action=APPLY_SCOPED_MODIFIER; modifier=reveal_nearest_container; show_route=true | K79: 塔罗命运三选一/工作台/局前预选目标卡池 | L79: [用户设计] | M79: [未施工] 名称、正/逆位与效果参数已完成数据设计 | N79: docs/v0.1/14_技术施工_命运塔罗牌组.md；docs/v0.1/data/ShellStorm2_游戏内容数据库_v010.xlsx | O79: 新增塔罗卡；正式卡池和执行器待施工 | P79: WORLD | Q79: 不占武器槽；写入行动/房间/掉落规则状态 | R79: [设计完成/待施工] 正逆位、翻牌和塔罗命名未接入运行时 | S79: ☀ 太阳命运｜星币·侍从｜翻牌后显示正位/逆位、目标、槽位与对应功能 | T79: 卡背绕Y轴翻面；逆位整张正面卡牌（含边框、图案、文字与布局）收束180°，并显示逆位效果描述；对应规则必须在HUD/场景中可读 | U79: [设计完成/待施工] 旧正位表现可复用；逆位与翻转待QA | W79: PAGE | X79: MINOR | Y79: PENTACLES | Z79: 0.5 | AA79: 0.5 | AB79: 揭示最近未开容器与最短路线 | AC79: action=APPLY_SCOPED_MODIFIER; modifier=reveal_nearest_container; show_route=true | AD79: 揭示最近高危房，该房首波敌人-1 | AE79: action=APPLY_SCOPED_MODIFIER; modifier=reveal_danger_room; first_wave_enemy_delta=-1 | AF79: 0.00s卡背→0.24s薄边换面→0.42s收束；逆位图案/框体180°，卡名、天体、方位标签和说明文字0°；0.62s后可点 | AG79: [设计完成/数据已入表/运行时待施工]
A80: fate_pentacle_knight | B80: 星币·骑士 | C80: 诅咒 | D80: 史诗 | E80: 敌人移速+10%，魂获取+35% | F80: 敌人移速+10%，魂获取+35% | G80: 新增塔罗牌“星币·骑士”，正位与逆位是同一主题的两种解读。 | H80: [用户设计+Codex规划] | J80: action=APPLY_SCOPED_MODIFIER; modifier=fast_enemies_rich; enemy_speed_multiplier=1.1; currency_multiplier=1.35 | K80: 塔罗命运三选一/工作台/局前预选目标卡池 | L80: [用户设计] | M80: [未施工] 名称、正/逆位与效果参数已完成数据设计 | N80: docs/v0.1/14_技术施工_命运塔罗牌组.md；docs/v0.1/data/ShellStorm2_游戏内容数据库_v010.xlsx | O80: 新增塔罗卡；正式卡池和执行器待施工 | P80: WORLD | Q80: 不占武器槽；写入行动/房间/掉落规则状态 | R80: [设计完成/待施工] 正逆位、翻牌和塔罗命名未接入运行时 | S80: ☀ 太阳命运｜星币·骑士｜翻牌后显示正位/逆位、目标、槽位与对应功能 | T80: 卡背绕Y轴翻面；逆位整张正面卡牌（含边框、图案、文字与布局）收束180°，并显示逆位效果描述；对应规则必须在HUD/场景中可读 | U80: [设计完成/待施工] 旧正位表现可复用；逆位与翻转待QA | W80: KNIGHT | X80: MINOR | Y80: PENTACLES | Z80: 0.5 | AA80: 0.5 | AB80: 敌人移速+10%，魂获取+35% | AC80: action=APPLY_SCOPED_MODIFIER; modifier=fast_enemies_rich; enemy_speed_multiplier=1.1; currency_multiplier=1.35 | AD80: 敌人移速-10%，魂获取-15% | AE80: action=APPLY_SCOPED_MODIFIER; modifier=slow_enemies_poor; enemy_speed_multiplier=0.9; currency_multiplier=0.85 | AF80: 0.00s卡背→0.24s薄边换面→0.42s收束；逆位图案/框体180°，卡名、天体、方位标签和说明文字0°；0.62s后可点 | AG80: [设计完成/数据已入表/运行时待施工]
A81: fate_pentacle_queen | B81: 星币·王后 | C81: 诅咒 | D81: 传说 | E81: Boss生命+20%，Boss奖励品质+1 | F81: Boss生命+20%，Boss奖励品质+1 | G81: 新增塔罗牌“星币·王后”，正位与逆位是同一主题的两种解读。 | H81: [用户设计+Codex规划] | J81: action=APPLY_SCOPED_MODIFIER; modifier=boss_reward_trial; hp_multiplier=1.2; reward_rarity_add=1 | K81: 塔罗命运三选一/工作台/局前预选目标卡池 | L81: [用户设计] | M81: [未施工] 名称、正/逆位与效果参数已完成数据设计 | N81: docs/v0.1/14_技术施工_命运塔罗牌组.md；docs/v0.1/data/ShellStorm2_游戏内容数据库_v010.xlsx | O81: 新增塔罗卡；正式卡池和执行器待施工 | P81: WORLD | Q81: 不占武器槽；写入行动/房间/掉落规则状态 | R81: [设计完成/待施工] 正逆位、翻牌和塔罗命名未接入运行时 | S81: ☀ 太阳命运｜星币·王后｜翻牌后显示正位/逆位、目标、槽位与对应功能 | T81: 卡背绕Y轴翻面；逆位整张正面卡牌（含边框、图案、文字与布局）收束180°，并显示逆位效果描述；对应规则必须在HUD/场景中可读 | U81: [设计完成/待施工] 旧正位表现可复用；逆位与翻转待QA | W81: QUEEN | X81: MINOR | Y81: PENTACLES | Z81: 0.5 | AA81: 0.5 | AB81: Boss生命+20%，Boss奖励品质+1 | AC81: action=APPLY_SCOPED_MODIFIER; modifier=boss_reward_trial; hp_multiplier=1.2; reward_rarity_add=1 | AD81: Boss生命-15%，Boss奖励数量-1 | AE81: action=APPLY_SCOPED_MODIFIER; modifier=boss_safe_trade; hp_multiplier=0.85; reward_count_delta=-1 | AF81: 0.00s卡背→0.24s薄边换面→0.42s收束；逆位图案/框体180°，卡名、天体、方位标签和说明文字0°；0.62s后可点 | AG81: [设计完成/数据已入表/运行时待施工]
A82: fate_pentacle_king | B82: 星币·国王 | C82: 规则 | D82: 禁忌 | E82: 每清理5个敌对房获得1把房间钥匙 | F82: 每清理5个敌对房获得1把房间钥匙 | G82: 新增塔罗牌“星币·国王”，正位与逆位是同一主题的两种解读。 | H82: [用户设计+Codex规划] | J82: action=APPLY_SCOPED_MODIFIER; modifier=room_key_cycle; rooms=5; key_count=1 | K82: 塔罗命运三选一/工作台/局前预选目标卡池 | L82: [用户设计] | M82: [未施工] 名称、正/逆位与效果参数已完成数据设计 | N82: docs/v0.1/14_技术施工_命运塔罗牌组.md；docs/v0.1/data/ShellStorm2_游戏内容数据库_v010.xlsx | O82: 新增塔罗卡；正式卡池和执行器待施工 | P82: WORLD | Q82: 不占武器槽；写入行动/房间/掉落规则状态 | R82: [设计完成/待施工] 正逆位、翻牌和塔罗命名未接入运行时 | S82: ☀ 太阳命运｜星币·国王｜翻牌后显示正位/逆位、目标、槽位与对应功能 | T82: 卡背绕Y轴翻面；逆位整张正面卡牌（含边框、图案、文字与布局）收束180°，并显示逆位效果描述；对应规则必须在HUD/场景中可读 | U82: [设计完成/待施工] 旧正位表现可复用；逆位与翻转待QA | W82: KING | X82: MINOR | Y82: PENTACLES | Z82: 0.5 | AA82: 0.5 | AB82: 每清理5个敌对房获得1把房间钥匙 | AC82: action=APPLY_SCOPED_MODIFIER; modifier=room_key_cycle; rooms=5; key_count=1 | AD82: 立即获得1钥匙，下2个敌对房不掉魂 | AE82: action=APPLY_SCOPED_MODIFIER; modifier=key_debt; key_count=1; blocked_currency_rooms=2 | AF82: 0.00s卡背→0.24s薄边换面→0.42s收束；逆位图案/框体180°，卡名、天体、方位标签和说明文字0°；0.62s后可点 | AG82: [设计完成/数据已入表/运行时待施工]

Sheet 怪物与Boss
A1: ShellStorm2 游戏内容数据库｜怪物与 Boss
A2: 数值采用Enemy3D.PROFILES正式3D基线；MonsterInjector旧2D基线仅换算楼层/主题倍率，不再作为玩家可见生命值。
A3: 字体颜色：绿色=已实装；蓝色=用户设计；橙色=Codex补充。实现状态需结合事实源判断。
A4: 内容ID | B4: 名称 | C4: 原型 | D4: HP | E4: 速度m/s | F4: 伤害 | G4: 攻击范围m | H4: 冷却s | I4: 技能/战术 | J4: 刷新位置 | K4: 掉落/进度 | L4: 状态来源 | M4: 实现状态 | N4: 事实源 | O4: 备注
A5: monster_ambusher | B5: 地刺虫 | C5: ambusher | D5: 50 | E5: 4.65 | F5: 18 | G5: 2.15 | H5: 1.9 | I5: 未触发时潜伏；揭示后高速突进；低矮轮廓 | J5: 深度2+及主题池；COMBAT/ELITE | K5: 由房间/楼层掉落表决定 | L5: [已实装] | M5: 正式3D基础模板 | N5: src/enemy3d/Enemy3D.gd；src/map/MonsterInjector.gd | O5: 正式数值以Enemy3D.PROFILES为基线；旧2D基线仅用于倍率换算
A6: monster_boss_generic | B6: Boss（通用回退模板） | C6: boss | D6: 520 | E6: 1.72 | F6: 24 | G6: 9.5 | H6: 1.45 | I6: 无独立内容ID时使用的确定性弹幕/召唤回退 | J6: 测试/未来未配置Boss楼层 | K6: boss_floor_* | L6: [已实装] | M6: 正式3D低模回退；不作为95/90/85正式内容 | N6: src/enemy3d/Enemy3D.gd；src/map/MonsterInjector.gd | O6: 正式Boss由BossContentCatalog替换模型和阶段技能袋
A7: monster_exploder | B7: 炸弹果 | C7: exploder | D7: 42 | E7: 3.1 | F7: 30 | G7: 2.85 | H7: 3 | I7: 接近目标后3m范围自爆；攻击后死亡 | J7: 浅层及全部战斗层；COMBAT/陷阱倾向/增援 | K7: 由房间/楼层掉落表决定 | L7: [已实装] | M7: 正式3D基础模板 | N7: src/enemy3d/Enemy3D.gd；src/map/MonsterInjector.gd | O7: 正式数值以Enemy3D.PROFILES为基线；旧2D基线仅用于倍率换算
A8: monster_melee_chaser | B8: 小菌猪 | C8: melee_chaser | D8: 58 | E8: 3.7 | F8: 12 | G8: 1.9 | H8: 1.05 | I8: 高速追击；近身突进；接触伤害 | J8: 浅层及全部战斗层；COMBAT/ELITE/撤离增援 | K8: 由房间/楼层掉落表决定 | L8: [已实装] | M8: 正式3D基础模板 | N8: src/enemy3d/Enemy3D.gd；src/map/MonsterInjector.gd | O8: 正式数值以Enemy3D.PROFILES为基线；旧2D基线仅用于倍率换算
A9: monster_ranged_caster | B9: 孢子射手 | C9: ranged_caster | D9: 46 | E9: 2.25 | F9: 10 | G9: 8.8 | H9: 1.8 | I9: 保持中距；三连散射弹幕；侧向走位 | J9: 浅层及全部战斗层；COMBAT/ELITE/撤离增援 | K9: 由房间/楼层掉落表决定 | L9: [已实装] | M9: 正式3D基础模板 | N9: src/enemy3d/Enemy3D.gd；src/map/MonsterInjector.gd | O9: 正式数值以Enemy3D.PROFILES为基线；旧2D基线仅用于倍率换算
A10: monster_shielded | B10: 壳甲卫兵 | C10: shielded | D10: 112 | E10: 2 | F10: 17 | G10: 2.05 | H10: 1.55 | I10: 正面减伤；15%正面完全格挡；穿甲可绕过护盾 | J10: 停止现行刷新，原点位/池由fat_zombie03接替 | K10: 由房间/楼层掉落表决定 | L10: [已退役] | M10: 弃用；旧档兼容保留 | N10: src/enemy3d/Enemy3D.gd；src/map/MonsterInjector.gd | O10: 2026-10-03用户裁定退役；普通怪身份由胖子僵尸03替换。原数值留作历史，未实装壳甲精英设计保留。
A11: monster_summoner | B11: 蜂巢怪 | C11: summoner | D11: 72 | E11: 1.65 | F11: 8 | G11: 7.2 | H11: 4.8 | I11: 周期召唤1–2只；6.5m范围治疗友军；远距游走 | J11: 深度2+及主题池；COMBAT/ELITE | K11: 由房间/楼层掉落表决定 | L11: [已实装] | M11: 正式3D基础模板 | N11: src/enemy3d/Enemy3D.gd；src/map/MonsterInjector.gd | O11: 正式数值以Enemy3D.PROFILES为基线；旧2D基线仅用于倍率换算
A12: boss_abyss_archivist_95 | B12: 深渊档案官 | C12: boss | D12: 520 | E12: 1.72 | F12: 24 | G12: 9.5 | H12: 1.45 | I12: archive_fan / index_beam / archive_storm；召唤档案侍从 | J12: 95F不可绕过Boss竞技场 | K12: boss_floor_5；专用下行权限 | L12: [已实装] | M12: 独立Boss内容/模型/竞技场 | N12: src/enemy3d/BossContentCatalog.gd；assets/art/enemies/bosses_v01/enm_boss_archivist_95_top3d_v001.glb | O12: 独立三阶段技能袋；档案竞技场8组掩体
A13: boss_furnace_warden_90 | B13: 熔炉狱监 | C13: boss | D13: 520 | E13: 1.72 | F13: 24 | G13: 9.5 | H13: 1.45 | I13: molten_volley / hammer_drive / furnace_burst；召唤余烬 | J13: 90F不可绕过Boss竞技场 | K13: boss_floor_10；专用下行权限 | L13: [已实装] | M13: 独立Boss内容/模型/竞技场 | N13: src/enemy3d/BossContentCatalog.gd；assets/art/enemies/bosses_v01/enm_boss_furnace_warden_90_top3d_v001.glb | O13: 独立三阶段技能袋；熔炉竞技场6组掩体
A14: boss_hollow_choir_85 | B14: 空洞合唱团 | C14: boss | D14: 520 | E14: 1.72 | F14: 24 | G14: 9.5 | H14: 1.45 | I14: choir_wave / silence_chord / echo_burst；召唤回声 | J14: 85F不可绕过Boss竞技场 | K14: boss_floor_15；专用下行权限 | L14: [已实装] | M14: 独立Boss内容/模型/竞技场 | N14: src/enemy3d/BossContentCatalog.gd；assets/art/enemies/bosses_v01/enm_boss_hollow_choir_85_top3d_v001.glb | O14: 独立三阶段技能袋；合唱竞技场5组掩体
A15: monster_spike_shell | B15: 暗影兽 | C15: spike_shell | D15: 待定 | E15: 待定 | F15: 待定 | G15: 待定 | H15: 待定 | I15: 待设计（未定形态；造型为低伏四足、背脊尖刺） | J15: 待定（未接入关卡/主题池） | K15: 待定 | L15: [用户设计] | M15: 未实现（仅登记，未接入玩法；无正式3D数值） | N15: assets/registry/ledgers/ShellStorm2_敌人账本_v001.xlsx（《资产主表》r18 = ENM-BEAST-SPIKESHELL01） | O15: 2026-09-23 由业主指示登记为新怪，先不考虑调用。HP/速度/伤害/攻击范围/冷却全部待定：按《字段字典》「怪物与Boss·正式3D数值」要求，这些列必须是 Enemy3D.PROFILES 的正式 3D 基线、不得混用旧 2D 基线，而本怪尚未进入 PROFILES ⇒ 刻意留「待定」而不编造数值。补数时机：接入玩法并写入 Enemy3D.PROFILES 时一并回填。
A16: monster_fat_zombie03 | B16: 胖子僵尸 | C16: fat_zombie03 | D16: 232 | E16: 0.85714286 | F16: 19 | G16: 1.55 | H16: 1.3 | I16: 厚血慢速；张臂抱扑拍合；1.2秒前摇/1.3秒收势；轻击上半身反应 | J16: 远征01纵列/桥心盒；原壳甲默认随机池和锈炉/深渊主题池 | K16: 通用楼层掉落表；killed一次结算 | L16: [已实装] | M16: 正式独立怪物，12态/13动画绑定 | N16: src/enemy3d/Enemy3D.gd；src/map/MonsterInjector.gd；docs/v0.1/design/胖子僵尸03运行配置.md | O16: D/E为PROFILES源基线；实际第一层生命696、追击0.60m/s、巡逻0.30m/s；内容调用ID=fat_zombie03；资产编号03；已接替壳甲卫兵投放
A17: boss_monitor002 | B17: MONITOR.EXE 显示器 | C17: boss | D17: 5200 | E17: 1.204 | F17: 24 | G17: 6 | H17: 0.65 | I17: 键盘24 / 数据线20 / 旋转砸地36 / 接地电流每0.8s12；HP66%/33%三阶段 | J17: 远征01 f00_boss；显式内容ID调用 | K17: Enemy3D Boss结算与既有房间奖励 | L17: 用户激活出场要求；技能设计r3 | M17: active | N17: BossContentCatalog / MonitorBossCombat；Boss002技能设计分页 | O17: 17 Blender剪辑；首次activate6.4s（非伤害技能），四技能/十二态；伤害8%韧性击晕4.8s；通电暴击可打断；独立资产ENM-BOSS-MONITOR002-3D

Sheet 精英怪
A1: ShellStorm2 游戏内容数据库｜12只唯一精英
A2: 名册固定12只并保持稳定ID。2026-08-27：首只背枪的裂口爬虫已完成独立资产、唯一投放和跨局成长闭环；其余11只保留设计与行为雏形但未投放。
A3: 字体颜色：绿色=已实装；蓝色=用户设计；橙色=Codex补充。实现状态需结合事实源判断。
A4: 稳定精英ID | B4: 独立名字 | C4: 基础原型 | D4: 核心特殊玩法 | E4: 成长方向 | F4: 夺械转译 | G4: 刷新位置 | H4: 唯一约束 | I4: 档案重点 | J4: 奖励概念 | K4: 名册来源 | L4: 名称/玩法来源 | M4: 实现状态 | N4: 事实源 | O4: 备注
A5: elite_rift_boar_armed | B5: 背枪的裂口爬虫 | C5: 小菌猪 | D5: 携带被夺取枪身，突进间隙自动射击 | E5: 20%血量进入4.2秒可击杀撤离窗；逃脱或击杀玩家后升级，上限12级。每级生命+8%、伤害+4.5%，5/9级提高副枪追射频率 | F5: 枪身→副枪追射；仅保存稳定内容ID、1—3发弹数预算和受控弹丸特征，最多3件，不保存玩家实例ID | G5: 每次行动按run_seed在98F/97F/96F三选一目标层；目标层ELITE房位置随地图种子随机；同局唯一 | H5: 同ID全局单例；预约后才可实例化 | I5: 跨局等级、逃脱/击杀玩家记录、夺械转译、悬赏等级、唯一预约与陈旧预约恢复 | J5: 精英专属掉落；悬赏1—5级额外兑现45/75/115/165/230魂 | K5: [用户设计] | L5: [已实装] | M5: [已实装｜正式投放与成长闭环完成] | N5: src/enemy3d/EliteContentCatalog.gd；src/enemy3d/EliteRosterService.gd；src/enemy3d/Enemy3D.gd；src/player3d/Player3D.gd；src/world3d/Dungeon3D.gd；tests/verification/verify_first_elite_deployment_flow.gd；tests/verification/verify_first_elite_growth_flow.gd | O5: 98/97/96F每局按run_seed三选一且同局唯一；精英房首个出生点。残血撤离期间血条显示“撤离中”且仍可击杀；成功逃脱或击杀玩家后跨局成长并夺取当前枪械，下次遭遇应用成长、转译能力与悬赏。
A6: elite_spore_devourer | B6: 吞弹者·孢子射手 | C6: 孢子射手 | D6: 吸收特定投射物并转为反击弹幕 | E6: 每次逃脱提高吸收容量和反击弹数 | F6: 子弹模块→敌方弹道/状态技能 | G6: 未投放；设计与行为雏形保留；完成独立内容和专项后再开放楼层 | H6: 同ID全局单例；预约后才可实例化 | I6: 吞弹种类、反击记录、成长等级 | J6: 子弹模块/悬赏资源 | K6: [用户设计] | L6: [已实装] | M6: [行为雏形已实装/未投放] | N6: src/enemy3d/EliteContentCatalog.gd；src/enemy3d/EliteRosterService.gd；src/enemy3d/Enemy3D.gd | O6: 稳定ID、档案字段和行为分支保留；当前deployment_status=design_only，无独立正式资产/血条/合法楼层，不进入随机池
A7: elite_iron_carapace | B7: 铁壁·壳甲统领 | C7: 壳甲卫兵 | D7: 旋转护甲面控制可攻击窗口，受击后反冲 | E7: 成长后增加护甲面并缩短转向间隔 | F7: 枪托/弹匣→格挡反击与耐久技能 | G7: 未投放；设计与行为雏形保留；完成独立内容和专项后再开放楼层 | H7: 同ID全局单例；预约后才可实例化 | I7: 破盾次数、反击命中、当前护甲 | J7: 护甲配件/高价壳片 | K7: [用户设计] | L7: [Codex补充] | M7: [行为雏形已实装/未投放] | N7: src/enemy3d/EliteContentCatalog.gd；src/enemy3d/EliteRosterService.gd；src/enemy3d/Enemy3D.gd | O7: 稳定ID、档案字段和行为分支保留；当前deployment_status=design_only，无独立正式资产/血条/合法楼层，不进入随机池
A8: elite_ninth_hive_queen | B8: 蜂后“第九巢” | C8: 蜂巢怪 | D8: 建立蜂巢网络，存活节点为本体转移伤害 | E8: 成长后增加巢数并强化节点协同 | F8: 配件→召唤物共享修饰 | G8: 未投放；设计与行为雏形保留；完成独立内容和专项后再开放楼层 | H8: 同ID全局单例；预约后才可实例化 | I8: 存活巢数、召唤谱系、逃脱路线 | J8: 蜂巢核心/召唤系模块 | K8: [用户设计] | L8: [Codex补充] | M8: [行为雏形已实装/未投放] | N8: src/enemy3d/EliteContentCatalog.gd；src/enemy3d/EliteRosterService.gd；src/enemy3d/Enemy3D.gd | O8: 稳定ID、档案字段和行为分支保留；当前deployment_status=design_only，无独立正式资产/血条/合法楼层，不进入随机池
A9: elite_emberfruit | B9: 焦雷果·余烬 | C9: 炸弹果 | D9: 投放可再生爆雷种子，本体不会首次爆炸即死亡 | E9: 成长后种子可连锁并留下燃烧区 | F9: 爆炸子弹→地雷/燃烧区技能 | G9: 未投放；设计与行为雏形保留；完成独立内容和专项后再开放楼层 | H9: 同ID全局单例；预约后才可实例化 | I9: 种子批次、连锁次数、重生次数 | J9: 爆炸模块/余烬核 | K9: [用户设计] | L9: [Codex补充] | M9: [行为雏形已实装/未投放] | N9: src/enemy3d/EliteContentCatalog.gd；src/enemy3d/EliteRosterService.gd；src/enemy3d/Enemy3D.gd | O9: 稳定ID、档案字段和行为分支保留；当前deployment_status=design_only，无独立正式资产/血条/合法楼层，不进入随机池
A10: elite_blackneedle | B10: 缝行者“黑针” | C10: 地刺虫 | D10: 沿地面标记潜行线路，从玩家盲区连续穿刺 | E10: 成长后假路线增多并获得第二次突袭 | F10: 穿甲子弹/瞄具→直线穿刺与锁定 | G10: 未投放；设计与行为雏形保留；完成独立内容和专项后再开放楼层 | H10: 同ID全局单例；预约后才可实例化 | I10: 潜行路线、揭示次数、命中角度 | J10: 穿甲模块/黑针 | K10: [用户设计] | L10: [Codex补充] | M10: [行为雏形已实装/未投放] | N10: src/enemy3d/EliteContentCatalog.gd；src/enemy3d/EliteRosterService.gd；src/enemy3d/Enemy3D.gd | O10: 稳定ID、档案字段和行为分支保留；当前deployment_status=design_only，无独立正式资产/血条/合法楼层，不进入随机池
A11: elite_mirror_shell | B11: 反射者·镜壳 | C11: 壳甲卫兵 | D11: 周期展开镜面扇区，反射正面投射物 | E11: 成长后扇区扩大但保留可读空隙 | F11: 弹跳子弹/瞄具→定向反射与弱点窗口 | G11: 未投放；设计与行为雏形保留；完成独立内容和专项后再开放楼层 | H11: 同ID全局单例；预约后才可实例化 | I11: 反射弹种、弱点击破、镜面阶段 | J11: 反射配件/镜壳碎片 | K11: [用户设计] | L11: [Codex补充] | M11: [行为雏形已实装/未投放] | N11: src/enemy3d/EliteContentCatalog.gd；src/enemy3d/EliteRosterService.gd；src/enemy3d/Enemy3D.gd | O11: 稳定ID、档案字段和行为分支保留；当前deployment_status=design_only，无独立正式资产/血条/合法楼层，不进入随机池
A12: elite_arms_taker | B12: 夺械者“收租人” | C12: 小菌猪/孢子射手混合 | D12: 遭遇中扫描玩家主枪并切换近战/远程阶段 | E12: 逃脱后永久保留一次完整枪身转译 | F12: 枪身→阶段主技能；配件→副技能 | G12: 未投放；设计与行为雏形保留；完成独立内容和专项后再开放楼层 | H12: 同ID全局单例；预约后才可实例化 | I12: 夺械清单、阶段偏好、玩家克制记录 | J12: 被夺枪械蓝图/高额悬赏 | K12: [用户设计] | L12: [Codex补充] | M12: [行为雏形已实装/未投放] | N12: src/enemy3d/EliteContentCatalog.gd；src/enemy3d/EliteRosterService.gd；src/enemy3d/Enemy3D.gd | O12: 稳定ID、档案字段和行为分支保留；当前deployment_status=design_only，无独立正式资产/血条/合法楼层，不进入随机池
A13: elite_seven_signs | B13: 命运残响“七签” | C13: 孢子射手 | D13: 每七次攻击切换一条公开命运规则 | E13: 成长后规则组合从一条增至两条 | F13: 命运卡→受预算约束的敌方规则 | G13: 未投放；设计与行为雏形保留；完成独立内容和专项后再开放楼层 | H13: 同ID全局单例；预约后才可实例化 | I13: 已见规则、卡片残响、七签序列 | J13: 命运残片/稀有卡机会 | K13: [用户设计] | L13: [Codex补充] | M13: [行为雏形已实装/未投放] | N13: src/enemy3d/EliteContentCatalog.gd；src/enemy3d/EliteRosterService.gd；src/enemy3d/Enemy3D.gd | O13: 稳定ID、档案字段和行为分支保留；当前deployment_status=design_only，无独立正式资产/血条/合法楼层，不进入随机池
A14: elite_echo_brood | B14: 寄生母体“回声” | C14: 蜂巢怪 | D14: 召唤物复制玩家最近使用的一个配件行为 | E14: 成长后可维持两种回声但降低单体强度 | F14: 配件→召唤物修饰模板 | G14: 未投放；设计与行为雏形保留；完成独立内容和专项后再开放楼层 | H14: 同ID全局单例；预约后才可实例化 | I14: 复制配件、召唤代次、母体伤势 | J14: 寄生样本/配件 | K14: [用户设计] | L14: [Codex补充] | M14: [行为雏形已实装/未投放] | N14: src/enemy3d/EliteContentCatalog.gd；src/enemy3d/EliteRosterService.gd；src/enemy3d/Enemy3D.gd | O14: 稳定ID、档案字段和行为分支保留；当前deployment_status=design_only，无独立正式资产/血条/合法楼层，不进入随机池
A15: elite_returning_king | B15: 逃亡王“折返者” | C15: 地刺虫 | D15: 低生命触发一次公开撤退路线，阻止其离开可获额外奖励 | E15: 每次成功逃脱增加新折返段和伏击次数 | F15: 回旋/返航子弹→折返突袭技能 | G15: 未投放；设计与行为雏形保留；完成独立内容和专项后再开放楼层 | H15: 同ID全局单例；预约后才可实例化 | I15: 逃脱次数、追击失败、路线记忆 | J15: 逃亡悬赏/返航模块 | K15: [用户设计] | L15: [Codex补充] | M15: [行为雏形已实装/未投放] | N15: src/enemy3d/EliteContentCatalog.gd；src/enemy3d/EliteRosterService.gd；src/enemy3d/Enemy3D.gd | O15: 稳定ID、档案字段和行为分支保留；当前deployment_status=design_only，无独立正式资产/血条/合法楼层，不进入随机池
A16: elite_nameless_crown | B16: 准首领“无名王冠” | C16: Boss轻量模板 | D16: 根据玩家已遭遇精英数量轮换三种战术冠位 | E16: 成长受整个精英档案推进，接近区域Boss | F16: 完整装配快照→三阶段技能组 | G16: 未投放；设计与行为雏形保留；完成独立内容和专项后再开放楼层 | H16: 同ID全局单例；预约后才可实例化 | I16: 冠位阶段、遭遇名册、夺取装配 | J16: 王冠核心/阶段级奖励 | K16: [用户设计] | L16: [Codex补充] | M16: [行为雏形已实装/未投放] | N16: src/enemy3d/EliteContentCatalog.gd；src/enemy3d/EliteRosterService.gd；src/enemy3d/Enemy3D.gd | O16: 稳定ID、档案字段和行为分支保留；当前deployment_status=design_only，无独立正式资产/血条/合法楼层，不进入随机池

Sheet 掉落物品
A1: ShellStorm2 游戏内容数据库｜掉落物品
A2: 导入ItemRegistry当前44条正式记录与1条设计契约条目（Boss下行专用钥匙），共45条；大型电池、电芯包和三档手电模块均使用正式运行ID。价格0不自动代表免费，进度物不进入普通商店。
A3: 字体颜色：绿色=已实装；蓝色=用户设计；橙色=Codex补充。实现状态需结合事实源判断。
A4: 物品ID | B4: 名称 | C4: 种类 | D4: 子类 | E4: 稀有度 | F4: 价格 | G4: 堆叠 | H4: 使用动作 | I4: 功能描述 | J4: 产出位置/权重 | K4: 商人Tier | L4: 状态来源 | M4: 实现状态 | N4: 事实源 | O4: 备注 | P4: 基地购买价 | Q4: 基地出售价 | R4: 基地商店上架 | S4: 基地库存规则 | T4: 基地货架顺序
A5: attach_big_mag | B5: 肉质弹匣 | C5: attachment | D5: magazine | E5: uncommon | F5: 80 | G5: 5 | J5: combat_floor_1×2.5；combat_floor_2×3；loot_abyss×2；loot_floor_3_4×2；loot_floor_5×2.5；scavenge_floor_3×2；scavenge_floor_4×2.5；scavenge_floor_5×2 | K5: 1 | L5: [已实装] | M5: 已注册；具体掉落概率按同池权重计算 | N5: src/base/ItemRegistry.gd | O5: tags=attachment、magazine、heal | P5: =IF(F5>0,F5,0) | Q5: =IF(F5>0,ROUND(F5*0.5,0),0) | R5: FALSE | S5: not_listed | T5: 0
A6: attach_copy_sticker | B6: 复制贴纸 | C6: attachment | D6: mutator | E6: epic | F6: 200 | G6: 3 | J6: boss_floor_1×3；boss_floor_2×4；combat_floor_3×1；combat_floor_4×1.5；combat_floor_5×2；loot_abyss×2；scavenge_floor_4×2；scavenge_floor_5×3 | K6: 3 | L6: [已实装] | M6: 已注册；具体掉落概率按同池权重计算 | N6: src/base/ItemRegistry.gd | O6: tags=attachment、mutator、copy | P6: =IF(F6>0,F6,0) | Q6: =IF(F6>0,ROUND(F6*0.5,0),0) | R6: FALSE | S6: not_listed | T6: 0
A7: attach_fan | B7: 小风扇 | C7: attachment | D7: external | E7: epic | F7: 150 | G7: 3 | J7: boss_floor_1×3；combat_floor_3×1.5；combat_floor_4×2；combat_floor_5×2.5；loot_abyss×2.5；loot_floor_5×2；scavenge_floor_4×2；scavenge_floor_5×2.5 | K7: 3 | L7: [已实装] | M7: 已注册；具体掉落概率按同池权重计算 | N7: src/base/ItemRegistry.gd | O7: tags=attachment、external、pull | P7: =IF(F7>0,F7,0) | Q7: =IF(F7>0,ROUND(F7*0.5,0),0) | R7: FALSE | S7: not_listed | T7: 0
A8: attach_rubber_stock | B8: 橡皮枪托 | C8: attachment | D8: stock | E8: common | F8: 45 | G8: 5 | J8: combat_floor_1×2.5；combat_floor_2×2；loot_abyss×1.5；loot_floor_1_2×3；loot_floor_3_4×2.5；loot_floor_5×2；scavenge_floor_1×3；scavenge_floor_2×2.5；scavenge_floor_3×2；scavenge_floor_4×1.5；spawn_starter×3 | K8: 0 | L8: [已实装] | M8: 已注册；具体掉落概率按同池权重计算 | N8: src/base/ItemRegistry.gd | O8: tags=attachment、stock、bounce | P8: =IF(F8>0,F8,0) | Q8: =IF(F8>0,ROUND(F8*0.5,0),0) | R8: FALSE | S8: not_listed | T8: 0
A9: attach_scope | B9: 放大镜瞄具 | C9: attachment | D9: scope | E9: rare | F9: 100 | G9: 5 | J9: combat_floor_2×1.5；combat_floor_3×2.5；loot_abyss×3；loot_floor_3_4×2；loot_floor_5×2.5；scavenge_floor_3×2；scavenge_floor_4×2.5；scavenge_floor_5×3 | K9: 2 | L9: [已实装] | M9: 已注册；具体掉落概率按同池权重计算 | N9: src/base/ItemRegistry.gd | O9: tags=attachment、scope、crit | P9: =IF(F9>0,F9,0) | Q9: =IF(F9>0,ROUND(F9*0.5,0),0) | R9: FALSE | S9: not_listed | T9: 0
A10: attach_triple_muzzle | B10: 三叉枪口 | C10: attachment | D10: muzzle | E10: uncommon | F10: 70 | G10: 5 | J10: combat_floor_1×2；combat_floor_2×1.5；loot_abyss×1；loot_floor_1_2×2.5；loot_floor_3_4×2；loot_floor_5×1.5；scavenge_floor_1×2.5；scavenge_floor_2×2；scavenge_floor_3×1.5；scavenge_floor_4×1；spawn_starter×2.5 | K10: 1 | L10: [已实装] | M10: 已注册；具体掉落概率按同池权重计算 | N10: src/base/ItemRegistry.gd | O10: tags=attachment、muzzle、multi_shot | P10: =IF(F10>0,F10,0) | Q10: =IF(F10>0,ROUND(F10*0.5,0),0) | R10: FALSE | S10: not_listed | T10: 0
A11: bp_charge | B11: 蓄力萝卜炮蓝图碎片 | C11: blueprint | D11: gun_body | E11: epic | F11: 200 | G11: 99 | H11: unlock_blueprint | I11: 使用后解锁蓄力萝卜炮蓝图，并获得 80 资源点 | J11: boss_floor_2×4；combat_floor_4×0.5；combat_floor_5×1；loot_abyss×2；scavenge_floor_5×0.5 | K11: 3 | L11: [已实装] | M11: 已注册；具体掉落概率按同池权重计算 | N11: src/base/ItemRegistry.gd | O11: tags=blueprint、gun_body、charge | P11: =IF(F11>0,F11,0) | Q11: =IF(F11>0,ROUND(F11*0.5,0),0) | R11: FALSE | S11: not_listed | T11: 0
A12: bp_launcher | B12: 反胃榴弹筒蓝图碎片 | C12: blueprint | D12: gun_body | E12: rare | F12: 130 | G12: 99 | H12: unlock_blueprint | I12: 使用后解锁反胃榴弹筒蓝图，并获得 55 资源点 | J12: boss_floor_1×3；boss_floor_2×4；combat_floor_3×0.5；combat_floor_4×0.3；loot_abyss×2.5；scavenge_floor_5×1 | K12: 2 | L12: [已实装] | M12: 已注册；具体掉落概率按同池权重计算 | N12: src/base/ItemRegistry.gd | O12: tags=blueprint、gun_body、launcher | P12: =IF(F12>0,F12,0) | Q12: =IF(F12>0,ROUND(F12*0.5,0),0) | R12: FALSE | S12: not_listed | T12: 0
A13: bp_machinegun | B13: 蜂窝机枪蓝图碎片 | C13: blueprint | D13: gun_body | E13: uncommon | F13: 90 | G13: 99 | H13: unlock_blueprint | I13: 使用后解锁蜂窝机枪蓝图，并获得 40 资源点 | J13: combat_floor_1×0.8；combat_floor_2×0.5；loot_abyss×2.5；loot_floor_3_4×1.5；loot_floor_5×2；scavenge_floor_3×1.5；scavenge_floor_4×2；scavenge_floor_5×2.5 | K13: 1 | L13: [已实装] | M13: 已注册；具体掉落概率按同池权重计算 | N13: src/base/ItemRegistry.gd | O13: tags=blueprint、gun_body、auto | P13: =IF(F13>0,F13,0) | Q13: =IF(F13>0,ROUND(F13*0.5,0),0) | R13: FALSE | S13: not_listed | T13: 0
A14: bp_pistol | B14: 豌豆手枪蓝图碎片 | C14: blueprint | D14: gun_body | E14: common | F14: 50 | G14: 99 | H14: unlock_blueprint | I14: 使用后解锁豌豆手枪蓝图，并获得 20 资源点 | J14: combat_floor_1×1.5；combat_floor_2×1；loot_abyss×1.5；loot_common×1；loot_floor_1_2×3；loot_floor_3_4×2.5；loot_floor_5×2；scavenge_floor_1×2.5；scavenge_floor_2×1.8；spawn_starter×4 | K14: 0 | L14: [已实装] | M14: 已注册；具体掉落概率按同池权重计算 | N14: src/base/ItemRegistry.gd | O14: tags=blueprint、gun_body | P14: =IF(F14>0,F14,0) | Q14: =IF(F14>0,ROUND(F14*0.5,0),0) | R14: FALSE | S14: not_listed | T14: 0
A15: bp_rifle | B15: 步枪蓝图碎片 | C15: blueprint | D15: gun_body | E15: uncommon | F15: 80 | G15: 99 | H15: unlock_blueprint | I15: 使用后解锁步枪蓝图，并获得 35 资源点 | J15: boss_floor_1×3；combat_floor_1×1.5；combat_floor_2×1；combat_floor_3×0.8；loot_abyss×3；loot_common×1；loot_floor_3_4×2；loot_floor_5×2.5；scavenge_floor_3×1.5；scavenge_floor_4×2；spawn_starter×2 | K15: 1 | L15: [已实装] | M15: 已注册；具体掉落概率按同池权重计算 | N15: src/base/ItemRegistry.gd | O15: tags=blueprint、gun_body、rifle | P15: =IF(F15>0,F15,0) | Q15: =IF(F15>0,ROUND(F15*0.5,0),0) | R15: FALSE | S15: not_listed | T15: 0
A16: bp_shotgun | B16: 散射喷壶蓝图碎片 | C16: blueprint | D16: gun_body | E16: common | F16: 60 | G16: 99 | H16: unlock_blueprint | I16: 使用后解锁散射喷壶蓝图，并获得 25 资源点 | J16: combat_floor_1×1；combat_floor_2×0.5；loot_abyss×1；loot_common×1；loot_floor_1_2×2.5；loot_floor_3_4×2；loot_floor_5×1.5；scavenge_floor_1×2；scavenge_floor_2×1.5；spawn_starter×3.5 | K16: 0 | L16: [已实装] | M16: 已注册；具体掉落概率按同池权重计算 | N16: src/base/ItemRegistry.gd | O16: tags=blueprint、gun_body、shotgun | P16: =IF(F16>0,F16,0) | Q16: =IF(F16>0,ROUND(F16*0.5,0),0) | R16: FALSE | S16: not_listed | T16: 0
A17: bp_sniper | B17: 弹弓狙击蓝图碎片 | C17: blueprint | D17: gun_body | E17: rare | F17: 120 | G17: 99 | H17: unlock_blueprint | I17: 使用后解锁弹弓狙击蓝图，并获得 50 资源点 | J17: boss_floor_1×4；boss_floor_2×5；combat_floor_3×1.5；combat_floor_4×2；combat_floor_5×2.5；loot_abyss×3；loot_common×0.5；loot_floor_5×2；scavenge_floor_5×1.5；spawn_starter×1 | K17: 2 | L17: [已实装] | M17: 已注册；具体掉落概率按同池权重计算 | N17: src/base/ItemRegistry.gd | O17: tags=blueprint、gun_body、sniper | P17: =IF(F17>0,F17,0) | Q17: =IF(F17>0,ROUND(F17*0.5,0),0) | R17: FALSE | S17: not_listed | T17: 0
A18: item_ammo_pack | B18: 通用弹药 | C18: consumable | E18: common | F18: 30 | G18: 999 | H18: refill_ammo | I18: 额外弹药补给 | J18: combat_floor_1×2；combat_floor_2×2.5；combat_floor_3×2；combat_floor_4×2.5；combat_floor_5×2；loot_common×1.5；loot_floor_1_2×2.5；spawn_starter×2 | L18: [已实装] | M18: 已注册；具体掉落概率按同池权重计算 | N18: src/base/ItemRegistry.gd | O18: tags=consumable、ammo | P18: =IF(F18>0,F18,0) | Q18: =IF(F18>0,ROUND(F18*0.5,0),0) | R18: FALSE | S18: not_listed | T18: 0
A19: item_beacon | B19: 撤离信标 | C19: consumable | E19: rare | F19: 150 | G19: 3 | H19: summon_beacon_extraction | I19: 消耗此道具召唤紧急撤离点。读条期间会刷出追击怪物。 | J19: boss_floor_1×3；boss_floor_2×4；combat_floor_4×0.8；combat_floor_5×1.2；elite_floor_1×1.5；elite_floor_2×1.5；loot_abyss×2.5；loot_floor_1_2×1；loot_floor_3_4×1.5；loot_floor_5×2；scavenge_floor_1×0.8；scavenge_floor_2×1；scavenge_floor_3×1.2；scavenge_floor_4×1.5；scavenge_floor_5×1.8 | K19: 2 | L19: [已实装] | M19: 已注册；具体掉落概率按同池权重计算 | N19: src/base/ItemRegistry.gd | O19: tags=extraction、consumable、beacon | P19: =IF(F19>0,F19,0) | Q19: =IF(F19>0,ROUND(F19*0.5,0),0) | R19: FALSE | S19: not_listed | T19: 0
A20: item_health_potion | B20: 治疗药水 | C20: consumable | E20: common | F20: 40 | G20: 5 | H20: heal | I20: 恢复 30 点生命值 | J20: combat_floor_1×1.5；combat_floor_2×2；combat_floor_3×1；loot_common×2；loot_floor_1_2×2；loot_floor_3_4×1.5；spawn_starter×2 | L20: [已实装] | M20: 已注册；具体掉落概率按同池权重计算 | N20: src/base/ItemRegistry.gd | O20: tags=consumable、healing | P20: 40 | Q20: 20 | R20: 1 | S20: unlimited | T20: 6
A21: item_room_key | B21: 房间钥匙 | C21: key | E21: common | F21: 40 | G21: 9 | I21: 普通房间钥匙；不进入基地购买货架，可按单把20魂出售。Boss与任务钥匙不使用此价格。 | J21: combat_floor_1×1.2；elite_floor_1×1；elite_floor_2×1；loot_common×1；loot_floor_1_2×1.8；scavenge_floor_1×2.4；scavenge_floor_2×2 | L21: [已实装] | M21: 已注册；具体掉落概率按同池权重计算 | N21: src/base/ItemRegistry.gd | O21: tags=key、progression | P21: 40 | Q21: 20 | R21: FALSE | S21: not_listed | T21: 0
A22: mod_bullet_balloon | B22: 气球弹模块 | C22: module | D22: bullet | E22: rare | F22: 90 | G22: 10 | J22: combat_floor_3×1；combat_floor_4×1.5；loot_abyss×2；loot_floor_3_4×1.5；loot_floor_5×2；scavenge_floor_3×1.5；scavenge_floor_4×2；scavenge_floor_5×2 | K22: 2 | L22: [已实装] | M22: 已注册；具体掉落概率按同池权重计算 | N22: src/base/ItemRegistry.gd | O22: tags=module、bullet、balloon、slow | P22: =IF(F22>0,F22,0) | Q22: =IF(F22>0,ROUND(F22*0.5,0),0) | R22: FALSE | S22: not_listed | T22: 0
A23: mod_bullet_blackhole | B23: 黑洞弹模块 | C23: module | D23: bullet | E23: epic | F23: 180 | G23: 10 | J23: boss_floor_1×3；boss_floor_2×4；combat_floor_4×2；combat_floor_5×3；loot_abyss×2.5；scavenge_floor_4×2.5；scavenge_floor_5×4 | K23: 3 | L23: [已实装] | M23: 已注册；具体掉落概率按同池权重计算 | N23: src/base/ItemRegistry.gd | O23: tags=module、bullet、blackhole、pull | P23: =IF(F23>0,F23,0) | Q23: =IF(F23>0,ROUND(F23*0.5,0),0) | R23: FALSE | S23: not_listed | T23: 0
A24: mod_bullet_bounce | B24: 回旋镖弹模块 | C24: module | D24: bullet | E24: uncommon | F24: 60 | G24: 10 | J24: combat_floor_1×1.5；combat_floor_2×2；loot_abyss×2；loot_floor_1_2×1.5；loot_floor_3_4×2；loot_floor_5×2.5；scavenge_floor_1×1.5；scavenge_floor_2×2；spawn_starter×1.5 | K24: 1 | L24: [已实装] | M24: 已注册；具体掉落概率按同池权重计算 | N24: src/base/ItemRegistry.gd | O24: tags=module、bullet、bounce | P24: =IF(F24>0,F24,0) | Q24: =IF(F24>0,ROUND(F24*0.5,0),0) | R24: FALSE | S24: not_listed | T24: 0
A25: mod_bullet_explosive | B25: 爆炸弹模块 | C25: module | D25: bullet | E25: rare | F25: 100 | G25: 10 | J25: combat_floor_3×1；loot_abyss×2.5；loot_floor_3_4×1.5；loot_floor_5×2；scavenge_floor_3×1.5；scavenge_floor_4×2；scavenge_floor_5×2.5 | K25: 2 | L25: [已实装] | M25: 已注册；具体掉落概率按同池权重计算 | N25: src/base/ItemRegistry.gd | O25: tags=module、bullet、explosive | P25: =IF(F25>0,F25,0) | Q25: =IF(F25>0,ROUND(F25*0.5,0),0) | R25: FALSE | S25: not_listed | T25: 0
A26: mod_bullet_homing | B26: 蜂卵弹模块 | C26: module | D26: bullet | E26: epic | F26: 150 | G26: 10 | J26: boss_floor_1×4；combat_floor_4×1.5；combat_floor_5×2.5；loot_abyss×3；loot_floor_5×2；scavenge_floor_4×2；scavenge_floor_5×3 | K26: 3 | L26: [已实装] | M26: 已注册；具体掉落概率按同池权重计算 | N26: src/base/ItemRegistry.gd | O26: tags=module、bullet、homing、summon | P26: =IF(F26>0,F26,0) | Q26: =IF(F26>0,ROUND(F26*0.5,0),0) | R26: FALSE | S26: not_listed | T26: 0
A27: mod_bullet_piercing | B27: 穿甲弹模块 | C27: module | D27: bullet | E27: rare | F27: 80 | G27: 10 | J27: combat_floor_3×1.5；loot_abyss×3；loot_floor_3_4×2；loot_floor_5×2.5；scavenge_floor_3×2；scavenge_floor_4×2.5；scavenge_floor_5×3 | K27: 2 | L27: [已实装] | M27: 已注册；具体掉落概率按同池权重计算 | N27: src/base/ItemRegistry.gd | O27: tags=module、bullet、piercing | P27: =IF(F27>0,F27,0) | Q27: =IF(F27>0,ROUND(F27*0.5,0),0) | R27: FALSE | S27: not_listed | T27: 0
A28: mod_bullet_standard | B28: 标准子弹模块 | C28: module | D28: bullet | E28: common | F28: 30 | G28: 10 | J28: combat_floor_1×3；combat_floor_2×2.5；loot_abyss×1.5；loot_floor_1_2×3；loot_floor_3_4×2.5；loot_floor_5×2；scavenge_floor_1×3；scavenge_floor_2×2.5；spawn_starter×3 | K28: 0 | L28: [已实装] | M28: 已注册；具体掉落概率按同池权重计算 | N28: src/base/ItemRegistry.gd | O28: tags=module、bullet | P28: =IF(F28>0,F28,0) | Q28: =IF(F28>0,ROUND(F28*0.5,0),0) | R28: FALSE | S28: not_listed | T28: 0
A29: mod_bullet_sticky | B29: 黏黏弹模块 | C29: module | D29: bullet | E29: uncommon | F29: 50 | G29: 10 | J29: combat_floor_1×2；combat_floor_2×2.5；loot_abyss×1.5；loot_floor_1_2×2；loot_floor_3_4×2.5；loot_floor_5×2；scavenge_floor_1×2；scavenge_floor_2×2.5；spawn_starter×2 | K29: 1 | L29: [已实装] | M29: 已注册；具体掉落概率按同池权重计算 | N29: src/base/ItemRegistry.gd | O29: tags=module、bullet、sticky | P29: =IF(F29>0,F29,0) | Q29: =IF(F29>0,ROUND(F29*0.5,0),0) | R29: FALSE | S29: not_listed | T29: 0
A30: weapon_charge | B30: 蓄力萝卜炮 | C30: weapon | D30: gun_body | E30: epic | F30: 350 | G30: 1 | I30: 蓄力时间越长伤害越高，超蓄力后弹体变大并附带穿透。左键装备为当前主武器。 | J30: boss_floor_2×4；combat_floor_4×0.5；combat_floor_5×1；elite_floor_2×3；loot_abyss×2；loot_floor_5×0.8；scavenge_floor_4×0.4；scavenge_floor_5×1 | L30: [已实装] | M30: 基础成品已注册；独立WeaponInstance与随枪构筑未实装 | N30: src/base/ItemRegistry.gd | O30: 新设计：stack_max=1；生成永久weapon_instance_id，并保存命运槽、子弹模块与配件快照 | P30: =IF(F30>0,F30,0) | Q30: =IF(F30>0,ROUND(F30*0.5,0),0) | R30: FALSE | S30: not_listed | T30: 0
A31: weapon_launcher | B31: 反胃榴弹筒 | C31: weapon | D31: gun_body | E31: rare | F31: 250 | G31: 1 | I31: 发射爆炸弹，抛物线弹道，大范围AOE。左键装备为当前主武器。 | J31: boss_floor_1×2.5；boss_floor_2×4；combat_floor_3×0.8；combat_floor_4×0.5；combat_floor_5×1；elite_floor_2×3；loot_abyss×2.5；loot_floor_3_4×1；loot_floor_5×1.5；scavenge_floor_3×0.5；scavenge_floor_4×1；scavenge_floor_5×2 | L31: [已实装] | M31: 基础成品已注册；独立WeaponInstance与随枪构筑未实装 | N31: src/base/ItemRegistry.gd | O31: 新设计：stack_max=1；生成永久weapon_instance_id，并保存命运槽、子弹模块与配件快照 | P31: =IF(F31>0,F31,0) | Q31: =IF(F31>0,ROUND(F31*0.5,0),0) | R31: FALSE | S31: not_listed | T31: 0
A32: weapon_machinegun | B32: 蜂窝机枪 | C32: weapon | D32: gun_body | E32: uncommon | F32: 180 | G32: 1 | I32: 高射速压制武器，适合清群怪。左键装备为当前主武器。 | J32: combat_floor_1×0.8；combat_floor_2×1.2；combat_floor_3×1.5；elite_floor_1×1.5；elite_floor_2×2.5；loot_abyss×2.5；loot_floor_1_2×1；loot_floor_3_4×1.5；loot_floor_5×2；scavenge_floor_1×0.5；scavenge_floor_2×1；scavenge_floor_3×1.2；scavenge_floor_4×1.5；scavenge_floor_5×2.5 | L32: [已实装] | M32: 基础成品已注册；独立WeaponInstance与随枪构筑未实装 | N32: src/base/ItemRegistry.gd | O32: 新设计：stack_max=1；生成永久weapon_instance_id，并保存命运槽、子弹模块与配件快照 | P32: =IF(F32>0,F32,0) | Q32: =IF(F32>0,ROUND(F32*0.5,0),0) | R32: FALSE | S32: not_listed | T32: 0
A33: weapon_pistol | B33: 豌豆手枪 | C33: weapon | D33: gun_body | E33: common | F33: 70 | G33: 1 | I33: 可靠的基础半自动武器。左键装备为当前主武器。 | J33: combat_floor_1×0.5；combat_floor_2×0.8；loot_floor_1_2×0.8；scavenge_floor_1×0.8；scavenge_floor_2×1.4 | L33: [已实装] | M33: 基础成品已注册；独立WeaponInstance与随枪构筑未实装 | N33: src/base/ItemRegistry.gd | O33: 新设计：stack_max=1；生成永久weapon_instance_id，并保存命运槽、子弹模块与配件快照 | P33: 70 | Q33: 35 | R33: 1 | S33: unlimited | T33: 2
A34: weapon_rifle | B34: 步枪 | C34: weapon | D34: gun_body | E34: rare | F34: 150 | G34: 1 | I34: 稳定连发的中距离武器。左键装备为当前主武器。 | J34: boss_floor_1×2；boss_floor_2×3；combat_floor_1×0.5；combat_floor_2×1；combat_floor_3×1.5；elite_floor_1×1.5；elite_floor_2×2；loot_abyss×2.5；loot_floor_1_2×0.3；loot_floor_3_4×1.5；loot_floor_5×2；scavenge_floor_3×1；scavenge_floor_4×1.5；scavenge_floor_5×2 | L34: [已实装] | M34: 基础成品已注册；独立WeaponInstance与随枪构筑未实装 | N34: src/base/ItemRegistry.gd | O34: 新设计：stack_max=1；生成永久weapon_instance_id，并保存命运槽、子弹模块与配件快照 | P34: 150 | Q34: 75 | R34: 1 | S34: unlimited | T34: 4
A35: weapon_shotgun | B35: 散射喷壶 | C35: weapon | D35: gun_body | E35: uncommon | F35: 110 | G35: 1 | I35: 近距离多弹丸散射武器。左键装备为当前主武器。 | J35: combat_floor_1×0.8；combat_floor_2×1.2；loot_floor_1_2×1；scavenge_floor_1×1.4；scavenge_floor_2×2；spawn_starter×3 | L35: [已实装] | M35: 基础成品已注册；独立WeaponInstance与随枪构筑未实装 | N35: src/base/ItemRegistry.gd | O35: 新设计：stack_max=1；生成永久weapon_instance_id，并保存命运槽、子弹模块与配件快照 | P35: 110 | Q35: 55 | R35: 1 | S35: unlimited | T35: 3
A36: weapon_sniper | B36: 弹弓狙击 | C36: weapon | D36: gun_body | E36: rare | F36: 220 | G36: 1 | I36: 低射速高伤害，穿透力强，适合精准打击。左键装备为当前主武器。 | J36: boss_floor_1×2；boss_floor_2×4；combat_floor_2×0.3；combat_floor_3×0.8；elite_floor_1×1.5；elite_floor_2×2；loot_abyss×2.5；loot_floor_3_4×0.5；loot_floor_5×1.5；scavenge_floor_3×0.5；scavenge_floor_4×1；scavenge_floor_5×2 | L36: [已实装] | M36: 基础成品已注册；独立WeaponInstance与随枪构筑未实装 | N36: src/base/ItemRegistry.gd | O36: 新设计：stack_max=1；生成永久weapon_instance_id，并保存命运槽、子弹模块与配件快照 | P36: =IF(F36>0,F36,0) | Q36: =IF(F36>0,ROUND(F36*0.5,0),0) | R36: FALSE | S36: not_listed | T36: 0
A37: item_boss_descent_key | B37: Boss下行专用钥匙 | C37: key | D37: boss_progression | E37: special | F37: 0 | G37: 1 | H37: open_boss_descent_gate | I37: 击败Boss后获得，只能开启本阶段唯一Boss下行门；不进入普通商店、普通掉落或撤离带出。 | J37: Boss击败结算（唯一签发） | K37: 不可出售 | L37: [用户设计] | M37: 设计冻结；未实装 | N37: 游戏设计文档 §8；技术施工_关卡生成与爬楼 | O37: 必须记录来源阶段ID；不能与item_room_key互换 | P37: =IF(F37>0,F37,0) | Q37: =IF(F37>0,ROUND(F37*0.5,0),0) | R37: FALSE | S37: not_listed | T37: 0
A38: equipment_backpack_2 | B38: 轻型腰包 | C38: equipment | D38: backpack | E38: common | F38: 55 | G38: 1 | H38: equip_backpack（左键/拖拽） | I38: 装备后增加2个物品格；卸下或换包时容量不足部分落到当前房间 | J38: combat_floor_1×0.28；combat_floor_2×0.2；loot_common×0.22；loot_floor_1_2×0.5；scavenge_floor_1×1.2；scavenge_floor_2×0.9 | K38: 1 | L38: [已实装] | M38: 正式3D已验证：物品/装备槽/动态容量/背部Mesh/溢出落地 | N38: src/base/ItemRegistry.gd；src/game/InventoryModule.gd；src/world3d/Dungeon3D.gd；src/player3d/Player3D.gd | O38: tags=equipment, backpack, capacity；基础12+2；浅层搜索/普通怪偏重 | P38: 55 | Q38: 28 | R38: 1 | S38: unlimited | T38: 5
A39: equipment_backpack_4 | B39: 战术背包 | C39: equipment | D39: backpack | E39: uncommon | F39: 120 | G39: 1 | H39: equip_backpack（左键/拖拽） | I39: 装备后增加4个物品格；卸下或换包时容量不足部分落到当前房间 | J39: combat_floor_3×0.22；elite_floor_1×0.85；elite_floor_2×0.55；loot_floor_1_2×0.16；loot_floor_3_4×0.65；scavenge_floor_2×0.35；scavenge_floor_3×1；scavenge_floor_4×0.8 | K39: 2 | L39: [已实装] | M39: 正式3D已验证：物品/装备槽/动态容量/背部Mesh/溢出落地 | N39: src/base/ItemRegistry.gd；src/game/InventoryModule.gd；src/world3d/Dungeon3D.gd；src/player3d/Player3D.gd | O39: tags=equipment, backpack, capacity；基础12+4；中层搜索/精英偏重 | P39: =IF(F39>0,F39,0) | Q39: =IF(F39>0,ROUND(F39*0.5,0),0) | R39: FALSE | S39: not_listed | T39: 0
A40: equipment_backpack_8 | B40: 远征背包 | C40: equipment | D40: backpack | E40: rare | F40: 260 | G40: 1 | H40: equip_backpack（左键/拖拽） | I40: 装备后增加8个物品格；卸下或换包时容量不足部分落到当前房间 | J40: boss_floor_1×1.25；boss_floor_2×1.8；elite_floor_2×0.75；loot_abyss×0.85；loot_floor_5×0.55；scavenge_floor_4×0.25；scavenge_floor_5×0.9 | K40: 3 | L40: [已实装] | M40: 正式3D已验证：物品/装备槽/动态容量/背部Mesh/溢出落地 | N40: src/base/ItemRegistry.gd；src/game/InventoryModule.gd；src/world3d/Dungeon3D.gd；src/player3d/Player3D.gd | O40: tags=equipment, backpack, capacity；基础12+8；深层搜索/精英/Boss偏重 | P40: =IF(F40>0,F40,0) | Q40: =IF(F40>0,ROUND(F40*0.5,0),0) | R40: FALSE | S40: not_listed | T40: 0
A41: item_battery_s | B41: 小型电池 | C41: consumable | D41: battery | E41: common | F41: 25 | G41: 5 | H41: restore_flashlight_charge | I41: 恢复手电筒25%电量；满电时不消耗 | J41: loot_common×2；loot_floor_1_2×2.5；spawn_starter×2；combat_floor_1-5×1.5；base_vending unlimited | K41: 1 | L41: [已实装] | M41: 电量恢复、满电不消耗、基地外开关不重置及贩卖机接入已验收 | N41: src/base/ItemRegistry.gd；src/player3d/PlayerFlashlight3D.gd；tests/verification/verify_3d_flashlight_charge_flow.gd | O41: tags=consumable、flashlight、battery | P41: 25 | Q41: 12 | R41: 1 | S41: unlimited | T41: 7
A42: item_battery_l | B42: 大型电池 | C42: consumable | D42: battery | E42: uncommon | F42: 60 | G42: 5 | H42: restore_flashlight_charge | I42: 恢复手电筒75%电量。中深层掉落或精英包。 | J42: loot_floor_3_4×1.2；scavenge_floor_3×1；scavenge_floor_4×1；scavenge_floor_5×1；elite_floor_1×0.8；elite_floor_2×0.8；boss_floor_1×1.5 | K42: 0 | L42: [已实装] | M42: 已注册；75%恢复、堆叠与运行掉落已接入 | N42: src/base/ItemRegistry.gd；src/game/ItemUseHandler.gd；tests/verification/verify_3d_flashlight_charge_flow.gd | O42: tags=consumable、flashlight、battery；正式ID=item_battery_l | P42: =IF(F42>0,F42,0) | Q42: =IF(F42>0,ROUND(F42*0.5,0),0) | R42: FALSE | S42: not_listed | T42: 0
A43: item_cell_pack | B43: 电芯包 | C43: consumable | D43: battery | E43: rare | F43: 120 | G43: 3 | H43: restore_flashlight_charge | I43: 完全充满手电筒。稀有掉落。 | J43: loot_floor_5×0.6；loot_abyss×1；boss_floor_2×1.5 | K43: 0 | L43: [已实装] | M43: 已注册；100%恢复、堆叠与运行掉落已接入 | N43: src/base/ItemRegistry.gd；src/game/ItemUseHandler.gd；tests/verification/verify_3d_flashlight_charge_flow.gd | O43: tags=consumable、flashlight、battery；正式ID=item_cell_pack | P43: =IF(F43>0,F43,0) | Q43: =IF(F43>0,ROUND(F43*0.5,0),0) | R43: FALSE | S43: not_listed | T43: 0
A44: item_flashlight_basic | B44: 基础模块 | C44: module | D44: flashlight_module | E44: common | F44: 0 | G44: 1 | H44: equip_flashlight_module | I44: 默认手电筒模块。耗电1.00×，揭示1.00×。 | J44: 默认装备，未列入普通掉落 | L44: [已实装] | M44: 已注册；默认模块已接入运行与存档 | N44: src/base/ItemRegistry.gd；src/player3d/PlayerFlashlight3D.gd；src/base/BaseManager.gd | O44: module_id=basic；tags=module、flashlight_module、basic | P44: =IF(F44>0,F44,0) | Q44: =IF(F44>0,ROUND(F44*0.5,0),0) | R44: FALSE | S44: not_listed | T44: 0
A45: item_flashlight_advanced | B45: 加强模块 | C45: module | D45: flashlight_module | E45: uncommon | F45: 0 | G45: 1 | H45: equip_flashlight_module | I45: 耗电0.7143×，揭示1.20×。蓝图解锁后工坊可选。 | J45: blueprint_attachment_unlock×1 | L45: [已实装] | M45: 已注册；Tier 1解锁、工坊切换与存档恢复已接入 | N45: src/base/ItemRegistry.gd；src/player3d/PlayerFlashlight3D.gd；src/base/BaseManager.gd；tests/verification/verify_3d_flashlight_charge_flow.gd | O45: module_id=advanced；blueprint_unlock_tier=1 | P45: =IF(F45>0,F45,0) | Q45: =IF(F45>0,ROUND(F45*0.5,0),0) | R45: TRUE | S45: limited | T45: 7
A46: item_flashlight_efficient | B46: 节能模块 | C46: module | D46: flashlight_module | E46: rare | F46: 0 | G46: 1 | H46: equip_flashlight_module | I46: 耗电0.50×，范围/揭示0.85×。带回99F安装后永久解锁。 | J46: elite_floor_1×0.6；elite_floor_2×0.8；boss_floor_2×1 | L46: [已实装] | M46: 已注册；掉落、带回解锁、工坊切换与存档已接入 | N46: src/base/ItemRegistry.gd；src/player3d/PlayerFlashlight3D.gd；src/base/BaseManager.gd；tests/verification/verify_3d_flashlight_charge_flow.gd | O46: module_id=efficient；tags=module、flashlight_module、efficient | P46: =IF(F46>0,F46,0) | Q46: =IF(F46>0,ROUND(F46*0.5,0),0) | R46: FALSE | S46: not_listed | T46: 0
A47: weapon_greatblade | B47: 巨型工业断刃 | C47: weapon | D47: melee_weapon | E47: uncommon | F47: 165 | G47: 1 | I47: 宽扇区三段重型挥砍；第三段过顶重劈强化伤害与击退；无弹药/换弹。 | J47: spawn_starter×1.2；loot_floor_1_2×0.75；loot_floor_3_4×1.2；scavenge_floor_1×0.65；scavenge_floor_2×1.1；combat_floor_1×0.5；combat_floor_2×0.9 | K47: 0 | L47: [已实装] | M47: 正式注册；完整WeaponInstance与近战专项已验收 | N47: src/base/ItemRegistry.gd；src/base/BlueprintRegistry.gd | O47: tags=weapon, melee, heavy_melee, greatblade；stack_max=1；assembly_id=bp_greatblade | P47: 165 | Q47: 83 | R47: 0 | S47: not_listed | T47: 0
A48: weapon_waraxe | B48: 攻城裂甲斧 | C48: weapon | D48: melee_weapon | E48: rare | F48: 240 | G48: 1 | I48: 高伤高击退三段攻城斧；第三段砸地前后摇较长；无弹药/换弹。 | J48: loot_floor_1_2×0.18；loot_floor_3_4×0.95；loot_floor_5×1.45；loot_abyss×1.8；scavenge_floor_3×0.8；combat_floor_3×0.72；elite_floor_1×1.2；elite_floor_2×1.8 | K48: 1 | L48: [已实装] | M48: 正式注册；完整WeaponInstance与近战专项已验收 | N48: src/base/ItemRegistry.gd；src/base/BlueprintRegistry.gd | O48: tags=weapon, melee, heavy_melee, waraxe；stack_max=1；assembly_id=bp_waraxe | P48: 240 | Q48: 120 | R48: 0 | S48: not_listed | T48: 0
A49: weapon_baseball_bat | B49: 废土棒球棍 | C49: weapon | D49: melee_weapon | E49: common | F49: 45 | G49: 1 | I49: 基地贩卖机初级近战；三段快速挥击，第三段强化伤害与击退 | J49: spawn_starter×2.2；loot_floor_1_2×1.6；scavenge_floor_1×1.8；scavenge_floor_2×1.2；combat_floor_1×1.0；base_vending unlimited | K49: 0 | L49: [已实装] | M49: 正式注册；基地贩卖/WeaponInstance/三段状态机/模型/反馈已验收 | N49: src/base/ItemRegistry.gd；src/base/BlueprintRegistry.gd；tests/verification/verify_weapon_attachment_inventory_flow.gd | O49: tags=weapon、melee、light_melee、baseball_bat；无枪械公共配件槽 | P49: 45 | Q49: 23 | R49: 1 | S49: unlimited | T49: 1

Sheet 字段字典
A1: ShellStorm2 游戏内容数据库｜字段字典
A2: 字段字典内容调整至人的共同契约。新增命运塔罗的阿尔卡那、花色、正/逆位概率、参数快照与翻牌字段。
A3: 字体颜色：绿色=已实装；蓝色=用户设计；橙色=Codex补充。实现状态需结合事实源判断。
A4: 工作表 | B4: 字段 | C4: 定义 | D4: 数据类型 | E4: 必填 | F4: 所有者 | G4: 验证规则 | H4: 来源
A5: 全表 | B5: 稳定ID | C5: 跨版本稳定的内容定义主键 | D5: string | E5: 是 | F5: 内容系统 | G5: 小写蛇形；全局/表内唯一 | H5: [Codex补充]
A6: 全表 | B6: 状态来源 | C6: 区分已实装、用户设计、Codex补充 | D6: enum | E6: 是 | F6: 文档治理 | G6: 三种固定值 | H6: [用户设计]
A7: 全表 | B7: 实现状态 | C7: 说明正式3D、兼容原型、未实现或待QA | D7: string | E7: 是 | F7: 对应系统 | G7: 不得只写完成/未完成 | H7: [Codex补充]
A8: 全表 | B8: 事实源 | C8: 代码、场景、设计或数据库来源 | D8: string | E8: 是 | F8: 对应系统 | G8: 至少一个可定位来源 | H8: [Codex补充]
A9: 武器 | B9: 蓝图Tier | C9: 基地蓝图许可层级 | D9: integer | E9: 是 | F9: 战斗/基地 | G9: 0–99；当前0–3 | H9: [已实装]
A10: 武器 | B10: 核心数值 | C10: 枪身/子弹/配件自身提供的基础参数 | D10: key=value | E10: 是 | F10: 战斗 | G10: 不写最终合成结果 | H10: [已实装]
A11: 武器 | B11: 产出与掉落 | C11: ItemRegistry掉落池键和相对权重 | D11: list | E11: 是 | F11: 掉落 | G11: 权重不是百分比 | H11: [已实装]
A12: 命运卡 | B12: 背景来源 | C12: 区分功能来源与新增背景文案来源 | D12: enum | E12: 是 | F12: 叙事内容 | G12: 使用三色固定值 | H12: [Codex补充]
A13: 命运卡 | B13: 目标规则 | C13: 卡片可以选择的装配节点 | D13: list/dict | E13: 是 | F13: 战斗 | G13: 空值表示执行器自动选择/环境规则 | H13: [已实装]
A14: 命运卡 | B14: 效果参数 | C14: EffectAction和全部执行参数 | D14: key=value | E14: 是 | F14: 战斗 | G14: 动作名必须可读 | H14: [已实装]
A15: 怪物与Boss | B15: 正式3D数值 | C15: Enemy3D Profile基线 | D15: number | E15: 是 | F15: 怪物 | G15: 不得混用旧2D基线 | H15: [已实装]
... A62: 武器 | B62: attachment_ownership_contract | C62: 配件单拆与整枪所有权事务 | D62: runtime contract | E62: 枪械必填 | F62: 背包/主副武器/存档 | G62: 单配件可装拆/替换并回滚；整枪移动、切换、掉落、保险和存档时assembly_snapshot整体随枪 | H62: [已实装并验收]

Sheet 基地商店
A1: 基地自动贩卖机｜固定货物清单 v0.1
A2: 价格、上架与库存公式回查《掉落物品》；ItemRegistry运行时定义必须与本表验收一致。正式99F购买进入当前I键背包并生成独立实例；独立主基地使用待装载集合，不写成保险柜。
A4: 货架ID | B4: facility_id | C4: 物品ID | D4: 来源表 | E4: 名称 | F4: 类型 | G4: 货币 | H4: 购买价 | I4: 出售价 | J4: 库存规则 | K4: 顺序 | L4: 购买去向 | M4: 实例规则 | N4: 上架 | O4: 状态来源 | P4: 实现状态 | Q4: 事实源 | R4: 备注
A5: base_stock_baseball_bat | B5: base_vending | C5: weapon_baseball_bat | D5: 掉落物品 | E5: 废土棒球棍 | F5: weapon | G5: extraction_points | H5: 45 | I5: 23 | J5: unlimited | K5: 1 | L5: 当前I键背包 | M5: 生成 item_instance_id + weapon_instance_id；初级近战；无枪械配件槽 | N5: =XLOOKUP(C5,'掉落物品'!$A$5:$A$46,'掉落物品'!$R$5:$R$46,FALSE) | O5: 用户设计+Codex补充 | P5: 已接入 | Q5: ItemRegistry/BaseShopService | R5: 基础手枪
A6: base_stock_pistol | B6: base_vending | C6: weapon_pistol | D6: 掉落物品 | E6: 豌豆手枪 | F6: weapon | G6: extraction_points | H6: 70 | I6: 35 | J6: unlimited | K6: 2 | L6: 当前I键背包 | M6: 生成 item_instance_id + weapon_instance_id；六公共配件槽随枪 | N6: =XLOOKUP(C6,'掉落物品'!$A$5:$A$46,'掉落物品'!$R$5:$R$46,FALSE) | O6: 用户设计+Codex补充 | P6: 已接入 | Q6: ItemRegistry/BaseShopService | R6: 基础霰弹枪
A7: base_stock_shotgun | B7: base_vending | C7: weapon_shotgun | D7: 掉落物品 | E7: 散射喷壶 | F7: weapon | G7: extraction_points | H7: 110 | I7: 55 | J7: unlimited | K7: 3 | L7: 当前I键背包 | M7: 生成 item_instance_id + weapon_instance_id；六公共配件槽随枪 | N7: =XLOOKUP(C7,'掉落物品'!$A$5:$A$46,'掉落物品'!$R$5:$R$46,FALSE) | O7: 用户设计+Codex补充 | P7: 已接入 | Q7: ItemRegistry/BaseShopService | R7: 基础步枪
A8: base_stock_rifle | B8: base_vending | C8: weapon_rifle | D8: 掉落物品 | E8: 步枪 | F8: weapon | G8: extraction_points | H8: 150 | I8: 75 | J8: unlimited | K8: 4 | L8: 当前I键背包 | M8: 生成 item_instance_id + weapon_instance_id；六公共配件槽随枪 | N8: =XLOOKUP(C8,'掉落物品'!$A$5:$A$46,'掉落物品'!$R$5:$R$46,FALSE) | O8: 用户设计+Codex补充 | P8: 已接入 | Q8: ItemRegistry/BaseShopService | R8: +2格初级背包
A9: base_stock_backpack_2 | B9: base_vending | C9: equipment_backpack_2 | D9: 掉落物品 | E9: 轻型腰包 | F9: equipment | G9: extraction_points | H9: 55 | I9: 28 | J9: unlimited | K9: 5 | L9: 当前I键背包 | M9: 生成 item_instance_id | N9: =XLOOKUP(C9,'掉落物品'!$A$5:$A$46,'掉落物品'!$R$5:$R$46,FALSE) | O9: 用户设计+Codex补充 | P9: 已接入 | Q9: ItemRegistry/BaseShopService | R9: 基础治疗药水
A10: base_stock_health_potion | B10: base_vending | C10: item_health_potion | D10: 掉落物品 | E10: 治疗药水 | F10: consumable | G10: extraction_points | H10: 40 | I10: 20 | J10: unlimited | K10: 6 | L10: 当前I键背包 | M10: 按stack_max=5堆叠 | N10: =XLOOKUP(C10,'掉落物品'!$A$5:$A$46,'掉落物品'!$R$5:$R$46,FALSE) | O10: 用户设计+Codex补充 | P10: 设计完成；未实装 | Q10: ItemRegistry/BaseShopService | R10: 基础小型电池（手电筒电量 25%）
A11: base_stock_battery_s | B11: base_vending | C11: item_battery_s | D11: 掉落物品 | E11: 小型电池 | F11: consumable | G11: extraction_points | H11: 25 | I11: 12 | J11: unlimited | K11: 7 | L11: 当前I键背包 | M11: 按stack_max=5堆叠；恢复25%电量

Sheet Boss002技能设计
A2: Boss002 显示器技能设计
A4: 内容ID | B4: boss_monitor002 | F4: 生命 | G4: 5200
A5: AssetID | B5: ENM-BOSS-MONITOR002-3D | F5: 移动m/s | G5: 1.204
A8: 技能ID | B8: 名称 | C8: 动作 | D8: 前摇秒 | E8: 生效秒 | F8: 总时长秒 | G8: 范围与伤害 | H8: 打断与特效
A9: monitor_keyboard | B9: 键盘拍地 | C9: melee_keyboard | D9: 1.066667 | E9: 1.066667 | F9: 1.8 | G9: 前方3.2m，半径1.65m；24 | H9: 单次命中；蓝/玫红；黄闪1帧
A10: monitor_cable | B10: 数据线甩击 | C10: melee_cable | D10: 0.8 | E10: 0.8–0.967 | F10: 2 | G10: 160°弧，半径6m；20 | H10: 螺旋前摇；平滑弧带；每目标1次
A11: monitor_spin_slam | B11: 旋转砸地 | C11: heavy_spin_slam | D11: 2.133333 | E11: 2.133333 | F11: 3.2 | G11: 前方1.4m，半径5.2m；36 | H11: 3圈屏幕旋转；后仰停顿；黄闪1帧
A12: monitor_ground_current | B12: 接地电流 | C12: special四段 | D12: 1.8 | E12: 每0.8秒脉冲 | F12: 5.1 / 5.9 / 6.7 | G12: 线尖接地点半径7m；每次12 | H12: 通电2.4/3.2/4s；暴击可打断；冷却10s
A15: 阶段 | B15: HP阈值 | C15: 技能序列
A16: 1 | B16: >66% | C16: 键盘、数据线、键盘、重击
A17: 2 | B17: ≤66% | C17: 数据线、插线、键盘、重击
A18: 3 | B18: ≤33% | C18: 重击、插线、数据线、重击、插线
A20: 状态ID | B20: 表现动作 | G20: 规则
A21: dormant | B21: 未激活：activate第0帧；已出场：idle | G21: Enemy3D状态与真实进度单向采样
A22: idle | B22: idle | G22: Enemy3D状态与真实进度单向采样
A23: patrol | B23: move | G23: Enemy3D状态与真实进度单向采样
A24: alert | B24: 首次activate6.4s；之后idle | G24: Enemy3D状态与真实进度单向采样
A25: chase | B25: move / turn_left/right | G25: Enemy3D状态与真实进度单向采样
A26: search | B26: move | G26: Enemy3D状态与真实进度单向采样
A27: return | B27: move | G27: Enemy3D状态与真实进度单向采样
A28: telegraph | B28: 技能剪辑前摇 | G28: Enemy3D状态与真实进度单向采样
A29: attack | B29: 技能剪辑生效段 / special_channel | G29: Enemy3D状态与真实进度单向采样
A30: recovery | B30: 技能剪辑恢复段 / special_recover | G30: Enemy3D状态与真实进度单向采样
A31: stagger | B31: hurt / stun_enter→stun_loop→stun_exit | G31: 韧性8%：坐下1.4s、坐地2.4s、起身1s
A32: dead | B32: dead | G32: 死亡2s后回收；根不压扁
A34: 规则 | B34: 首轮出场进度/完成标记随实例保存；休眠暂停，重进续播；旧档默认已出场。危险技能仍取消。
A36: 设计主源 | B36: docs/v0.1/design/Boss002显示器技能设计.md（r3）；动画设计r28
A37: 实现源 | B37: src/enemy3d/MonitorBossCombat.gd
