Workbook

Sheet 总览
A1: SHELLSTORM 2 · 关卡场景美术账本 v0.1
A3: 归属域=关卡场景｜覆盖大类=场景 / 场景道具 / 基地资产包｜AssetID 前缀=ART / ENV / BPK / PRP｜主账本（总目录）=assets/registry/ShellStorm2_美术资产台账_v001.xlsx；本账本可独立并行编辑，跨域契约见主账本
A5: 资产总数 | C5: 已完成/已接入 | E5: 待制作/程序占位 | G5: 重复警报 | I5: 域内专表 / 3D Prefab 分页
A6: =COUNTA(资产主表!$A$6:$A$928) | C6: =COUNTIF(资产主表!$K$6:$K$928,"已完成")+COUNTIF(资产主表!$K$6:$K$928,"原型已接入")+COUNTIF(资产主表!$K$6:$K$928,"正式美术已接入")+COUNTIF(资产主表!$K$6:$K$928,"已优化并正式接入")+COUNTIF(资产主表!$K$6:$K$928,"Blender源已完成")+COUNTIF(资产主表!$K$6:$K$928,"已导入；优化完成")+COUNTIF(资产主表!$K$6:$K$928,"白模源已完成；QA PASS") | E6: =COUNTIF(资产主表!$K$6:$K$928,"待制作")+COUNTIF(资产主表!$K$6:$K$928,"程序占位") | G6: =COUNTIF(资产主表!$S$6:$S$928,"重复") | I6: 域内专表：3D-场景通用 / 3D-设施 / 3D-其他 | 3D Prefab 分页：3D-场景通用 / 3D-设施 / 3D-其他
A9: 大类 | B9: 资产数 | C9: 完成/接入 | E9: 本账本只登记上列大类；跨域搬运资产须同步主账本《分类与编码》并重跑门禁
A10: 场景 | B10: =COUNTIF(资产主表!$C$6:$C$928,A10) | C10: =SUMPRODUCT((资产主表!$C$6:$C$928=A10)*((资产主表!$K$6:$K$928="已完成")+(资产主表!$K$6:$K$928="原型已接入")+(资产主表!$K$6:$K$928="正式美术已接入")+(资产主表!$K$6:$K$928="已优化并正式接入")+(资产主表!$K$6:$K$928="Blender源已完成")+(资产主表!$K$6:$K$928="已导入；优化完成")+(资产主表!$K$6:$K$928="白模源已完成；QA PASS")))
A11: 场景道具 | B11: =COUNTIF(资产主表!$C$6:$C$928,A11) | C11: =SUMPRODUCT((资产主表!$C$6:$C$928=A11)*((资产主表!$K$6:$K$928="已完成")+(资产主表!$K$6:$K$928="原型已接入")+(资产主表!$K$6:$K$928="正式美术已接入")+(资产主表!$K$6:$K$928="已优化并正式接入")+(资产主表!$K$6:$K$928="Blender源已完成")+(资产主表!$K$6:$K$928="已导入；优化完成")+(资产主表!$K$6:$K$928="白模源已完成；QA PASS")))
A12: 基地资产包 | B12: =COUNTIF(资产主表!$C$6:$C$928,A12) | C12: =SUMPRODUCT((资产主表!$C$6:$C$928=A12)*((资产主表!$K$6:$K$928="已完成")+(资产主表!$K$6:$K$928="原型已接入")+(资产主表!$K$6:$K$928="正式美术已接入")+(资产主表!$K$6:$K$928="已优化并正式接入")+(资产主表!$K$6:$K$928="Blender源已完成")+(资产主表!$K$6:$K$928="已导入；优化完成")+(资产主表!$K$6:$K$928="白模源已完成；QA PASS")))
A13: 合计 | B13: ==COUNTIF(资产主表!$C$6:$C$928,A13) | C13: ==SUMPRODUCT((资产主表!$C$6:$C$928=A13)*((资产主表!$K$6:$K$928="已完成")+(资产主表!$K$6:$K$928="原型已接入")+(资产主表!$K$6:$K$928="正式美术已接入")+(资产主表!$K$6:$K$928="已优化并正式接入")+(资产主表!$K$6:$K$928="Blender源已完成")+(资产主表!$K$6:$K$928="已导入；优化完成")+(资产主表!$K$6:$K$928="白模源已完成；QA PASS")))
A15: 域内 3D Prefab 分页统计（快照口径与本账本分页一致；权威清单在各分页表）
A16: 分页 | B16: Prefab 数 | C16: 直接引用 GLB | D16: 有功能脚本 | E16: 碰撞开启 | F16: 说明
A17: 3D-场景通用 | B17: =COUNTA('3D-场景通用'!$A$5:$A$726) | C17: =COUNTIF('3D-场景通用'!$D$5:$D$726,"<>") | D17: =COUNTIF('3D-场景通用'!$G$5:$G$726,"<>") | E17: =COUNTIF('3D-场景通用'!$H$5:$H$726,"开") | F17: 一行 = 一个实际存在的 Godot PackedScene
A18: 3D-设施 | B18: ==COUNTA('3D-设施'!$A$5:$A$204) | C18: ==COUNTIF('3D-设施'!$D$5:$D$204,"<>") | D18: ==COUNTIF('3D-设施'!$G$5:$G$204,"<>") | E18: ==COUNTIF('3D-设施'!$H$5:$H$204,"开") | F18: 一行 = 一个实际存在的 Godot PackedScene
A19: 3D-其他 | B19: ==COUNTA('3D-其他'!$A$5:$A$204) | C19: ==COUNTIF('3D-其他'!$D$5:$D$204,"<>") | D19: ==COUNTIF('3D-其他'!$G$5:$G$204,"<>") | E19: ==COUNTIF('3D-其他'!$H$5:$H$204,"开") | F19: 一行 = 一个实际存在的 Godot PackedScene
A20: 合计 | B20: ==SUM(B17:B19) | C20: ==SUM(C17:C19) | D20: ==SUM(D17:D19) | E20: ==SUM(E17:E19)

Sheet 账本说明
A1: 本账本说明 · 关卡场景
A3: 本表是分账本自描述；机器可读真源为 assets/registry/ledger_index.json，二者不一致时以 JSON 为准
A5: 项 | B5: 值
A6: 账本归属域 | B6: 关卡场景
A7: 分账本文件 | B7: assets/registry/ledgers/ShellStorm2_场景账本_v001.xlsx
A8: 覆盖大类 | B8: 场景 / 场景道具 / 基地资产包
A9: AssetID 前缀 | B9: ART / ENV / BPK / PRP
A10: 域内专表 | B10: 3D-场景通用 / 3D-设施 / 3D-其他
A11: 3D Prefab 分页 | B11: 3D-场景通用 / 3D-设施 / 3D-其他
A12: 动画登记表 | B12: 无
A13: 主账本（总目录） | B13: assets/registry/ShellStorm2_美术资产台账_v001.xlsx
A14: 跨域契约 | B14: 分类与编码 / 命名与查重 / 版本记录 / Skill 清单 / 3D Prefab 总控 —— 全部只在主账本维护
A15: 首选制作 Skill | B15: scene-full-pipeline
A16: 协作 Skill | B16: godot-model-asset-import-standard / blender-game-prop-standard / scene-art-merge-into-shared-component
... A23: 快照日期 | B23: 2026-09-18

Sheet 资产主表
A1: 资产主表 · 唯一登记源
A3: 查重键由公式生成；S 列出现“重复”时禁止制作，先合并或建立变体父子关系
A5: AssetID | B5: 中文名 | C5: 大类 | D5: 子类 | E5: 逻辑ID/源键 | F5: 组件槽 | G5: 变体父ID | H5: 视角 | I5: 状态/动画 | J5: 复用范围 | K5: 制作状态 | L5: 优先级 | M5: 版本 | N5: 规格(px) | O5: 文件路径 | P5: 源码/策划依据 | Q5: 关键词/别名 | R5: 查重键 | S5: 查重结果 | T5: SHA-256 | U5: 负责人 | V5: 更新时间 | W5: 来源/许可 | X5: 源编号（Blender collection） | Y5: 备注
A6: ENV-BASE-WORLD-KIT | B6: 末日基地与荒野 | C6: 场景 | D6: biome_kit | E6: base_world | F6: root | H6: 顶视 | I6: default | J6: 同主题房间共享 | K6: 程序占位 | L6: P0 | M6: v001 | N6: 64 px 网格；模块化 Tile/Prop | P6: scenes/BaseWorld.tscn | R6: =LOWER(TRIM(C6)&"|"&TRIM(D6)&"|"&TRIM(E6)&"|"&TRIM(F6)&"|"&TRIM(H6)&"|"&TRIM(I6)) | S6: =IF(COUNTIF($R$6:$R$928,R6)>1,"重复","唯一") | U6: 待分配 | V6: 46224 | W6: 原创/待确认 | X6: — | Y6: 先拆地面/墙/门/大中小道具，禁止整张场景烘焙
A7: ENV-IRON-FRONTIER-KIT | B7: 冷钢边境 | C7: 场景 | D7: biome_kit | E7: iron_frontier | F7: root | H7: 顶视 | I7: default | J7: 同主题房间共享 | K7: 程序占位 | L7: P0 | M7: v001 | N7: 64 px 网格；模块化 Tile/Prop | P7: scenes/levels/IronFrontier.tscn | R7: =LOWER(TRIM(C7)&"|"&TRIM(D7)&"|"&TRIM(E7)&"|"&TRIM(F7)&"|"&TRIM(H7)&"|"&TRIM(I7)) | S7: =IF(COUNTIF($R$6:$R$928,R7)>1,"重复","唯一") | U7: 待分配 | V7: 46224 | W7: 原创/待确认 | X7: — | Y7: 先拆地面/墙/门/大中小道具，禁止整张场景烘焙
A8: ENV-RUST-FOUNDRY-KIT | B8: 锈蚀铸造厂 | C8: 场景 | D8: biome_kit | E8: rust_foundry | F8: root | H8: 顶视 | I8: default | J8: 同主题房间共享 | K8: 程序占位 | L8: P1 | M8: v001 | N8: 64 px 网格；模块化 Tile/Prop | P8: scenes/levels/RustFoundry.tscn | R8: =LOWER(TRIM(C8)&"|"&TRIM(D8)&"|"&TRIM(E8)&"|"&TRIM(F8)&"|"&TRIM(H8)&"|"&TRIM(I8)) | S8: =IF(COUNTIF($R$6:$R$928,R8)>1,"重复","唯一") | U8: 待分配 | V8: 46224 | W8: 原创/待确认 | X8: — | Y8: 先拆地面/墙/门/大中小道具，禁止整张场景烘焙
A9: ENV-SPORE-DEPTHS-KIT | B9: 孢子深层 | C9: 场景 | D9: biome_kit | E9: spore_depths | F9: root | H9: 顶视 | I9: default | J9: 同主题房间共享 | K9: 程序占位 | L9: P1 | M9: v001 | N9: 64 px 网格；模块化 Tile/Prop | P9: scenes/levels/SporeDepths.tscn | R9: =LOWER(TRIM(C9)&"|"&TRIM(D9)&"|"&TRIM(E9)&"|"&TRIM(F9)&"|"&TRIM(H9)&"|"&TRIM(I9)) | S9: =IF(COUNTIF($R$6:$R$928,R9)>1,"重复","唯一") | U9: 待分配 | V9: 46224 | W9: 原创/待确认 | X9: — | Y9: 先拆地面/墙/门/大中小道具，禁止整张场景烘焙
A10: ENV-ABYSS-ARCHIVE-KIT | B10: 深渊档案库 | C10: 场景 | D10: biome_kit | E10: abyss_archive | F10: root | H10: 顶视 | I10: default | J10: 同主题房间共享 | K10: 程序占位 | L10: P1 | M10: v001 | N10: 64 px 网格；模块化 Tile/Prop | P10: scenes/levels/AbyssArchive.tscn | R10: =LOWER(TRIM(C10)&"|"&TRIM(D10)&"|"&TRIM(E10)&"|"&TRIM(F10)&"|"&TRIM(H10)&"|"&TRIM(I10)) | S10: =IF(COUNTIF($R$6:$R$928,R10)>1,"重复","唯一") | U10: 待分配 | V10: 46224 | W10: 原创/待确认 | X10: — | Y10: 先拆地面/墙/门/大中小道具，禁止整张场景烘焙
A11: ENV-TRAINING-RANGE-KIT | B11: 地下训练靶场 | C11: 场景 | D11: biome_kit | E11: training_range | F11: root | H11: 顶视 | I11: default | J11: 同主题房间共享 | K11: 程序占位 | L11: P0 | M11: v001 | N11: 64 px 网格；模块化 Tile/Prop | P11: scenes/TrainingRange.tscn | R11: =LOWER(TRIM(C11)&"|"&TRIM(D11)&"|"&TRIM(E11)&"|"&TRIM(F11)&"|"&TRIM(H11)&"|"&TRIM(I11)) | S11: =IF(COUNTIF($R$6:$R$928,R11)>1,"重复","唯一") | U11: 待分配 | V11: 46224 | W11: 原创/待确认 | X11: — | Y11: 先拆地面/墙/门/大中小道具，禁止整张场景烘焙
A12: ENV-ROOM-COMBAT-DRESSING | B12: combat 房间陈设包 | C12: 场景 | D12: room_dressing | E12: room_combat | F12: root | H12: 顶视 | I12: default | J12: 跨楼层配色变体 | K12: 程序占位 | L12: P1 | M12: v001 | N12: 64 px 网格 | P12: scenes/RoomCombat.tscn | R12: =LOWER(TRIM(C12)&"|"&TRIM(D12)&"|"&TRIM(E12)&"|"&TRIM(F12)&"|"&TRIM(H12)&"|"&TRIM(I12)) | S12: =IF(COUNTIF($R$6:$R$928,R12)>1,"重复","唯一") | U12: 待分配 | V12: 46224 | W12: 原创/待确认 | X12: — | Y12: 只登记房间独有件；地板墙体引用 biome kit
A13: ENV-ROOM-ELITE-DRESSING | B13: elite 房间陈设包 | C13: 场景 | D13: room_dressing | E13: room_elite | F13: root | H13: 顶视 | I13: default | J13: 跨楼层配色变体 | K13: 程序占位 | L13: P2 | M13: v001 | N13: 64 px 网格 | P13: scenes/RoomElite.tscn | R13: =LOWER(TRIM(C13)&"|"&TRIM(D13)&"|"&TRIM(E13)&"|"&TRIM(F13)&"|"&TRIM(H13)&"|"&TRIM(I13)) | S13: =IF(COUNTIF($R$6:$R$928,R13)>1,"重复","唯一") | U13: 待分配 | V13: 46224 | W13: 原创/待确认 | X13: — | Y13: 只登记房间独有件；地板墙体引用 biome kit
A14: ENV-ROOM-BOSS-DRESSING | B14: boss 房间陈设包 | C14: 场景 | D14: room_dressing | E14: room_boss | F14: root | H14: 顶视 | I14: default | J14: 跨楼层配色变体 | K14: 程序占位 | L14: P1 | M14: v001 | N14: 64 px 网格 | P14: scenes/RoomBoss.tscn | R14: =LOWER(TRIM(C14)&"|"&TRIM(D14)&"|"&TRIM(E14)&"|"&TRIM(F14)&"|"&TRIM(H14)&"|"&TRIM(I14)) | S14: =IF(COUNTIF($R$6:$R$928,R14)>1,"重复","唯一") | U14: 待分配 | V14: 46224 | W14: 原创/待确认 | X14: — | Y14: 只登记房间独有件；地板墙体引用 biome kit
A15: ENV-ROOM-EVENT-DRESSING | B15: event 房间陈设包 | C15: 场景 | D15: room_dressing | E15: room_event | F15: root | H15: 顶视 | I15: default | J15: 跨楼层配色变体 | K15: 程序占位 | L15: P2 | M15: v001 | N15: 64 px 网格 | P15: scenes/RoomEvent.tscn | R15: =LOWER(TRIM(C15)&"|"&TRIM(D15)&"|"&TRIM(E15)&"|"&TRIM(F15)&"|"&TRIM(H15)&"|"&TRIM(I15)) | S15: =IF(COUNTIF($R$6:$R$928,R15)>1,"重复","唯一") | U15: 待分配 | V15: 46224 | W15: 原创/待确认 | X15: — | Y15: 只登记房间独有件；地板墙体引用 biome kit
A16: ENV-ROOM-EXTRACTION-DRESSING | B16: extraction 房间陈设包 | C16: 场景 | D16: room_dressing | E16: room_extraction | F16: root | H16: 顶视 | I16: default | J16: 跨楼层配色变体 | K16: 程序占位 | L16: P1 | M16: v001 | N16: 64 px 网格 | P16: scenes/RoomExtraction.tscn | R16: =LOWER(TRIM(C16)&"|"&TRIM(D16)&"|"&TRIM(E16)&"|"&TRIM(F16)&"|"&TRIM(H16)&"|"&TRIM(I16)) | S16: =IF(COUNTIF($R$6:$R$928,R16)>1,"重复","唯一") | U16: 待分配 | V16: 46224 | W16: 原创/待确认 | X16: — | Y16: 只登记房间独有件；地板墙体引用 biome kit
A17: ENV-ROOM-MERCHANT-DRESSING | B17: merchant 房间陈设包 | C17: 场景 | D17: room_dressing | E17: room_merchant | F17: root | H17: 顶视 | I17: default | J17: 跨楼层配色变体 | K17: 程序占位 | L17: P2 | M17: v001 | N17: 64 px 网格 | P17: scenes/RoomMerchant.tscn | R17: =LOWER(TRIM(C17)&"|"&TRIM(D17)&"|"&TRIM(E17)&"|"&TRIM(F17)&"|"&TRIM(H17)&"|"&TRIM(I17)) | S17: =IF(COUNTIF($R$6:$R$928,R17)>1,"重复","唯一") | U17: 待分配 | V17: 46224 | W17: 原创/待确认 | X17: — | Y17: 只登记房间独有件；地板墙体引用 biome kit
... A31: PRP-DOOR | B31: 房门 | C31: 场景道具 | D31: facility | E31: door | F31: root | H31: 顶视 | I31: default | J31: 基地/房间 | K31: 程序占位 | L31: P1 | M31: v001 | N31: 64 px 网格对齐 | P31: scenes/BaseWorld.tscn | R31: =LOWER(TRIM(C31)&"|"&TRIM(D31)&"|"&TRIM(E31)&"|"&TRIM(F31)&"|"&TRIM(H31)&"|"&TRIM(I31)) | S31: =IF(COUNTIF($R$6:$R$928,R31)>1,"重复","唯一") | U31: 待分配 | V31: 46224 | W31: 原创/待确认 | X31: — | Y31: 状态变体使用同一 AssetID + state，不复制新命名根
A32: ENV-BASE99-FLOOR-DETAILS-V017 | B32: 基地99层完整地板替换 V021 | C32: 场景 | D32: environment_module_3d | E32: base99_floor_full_replacement_v021 | F32: full_floor_visual_replacement | G32: ENV-BASE99-ART-LAYOUT-3D | H32: Top3D / local -Z 正面 | I32: default / visual_only | J32: 99层基地地面表现 | K32: 已完成 | L32: P0 | M32: v003 | N32: 30×30m；6×6×5m；2网格；4材质表面；498,920三角面；无内置碰撞 | O32: assets/art/environments/base_facility_3d/runtime/env_base99_floor_full_replacement/env_base99_floor_full_replacement_root_top3d.tscn | P32: art_source/design/blender/base_facility_layout/base_facility_runtime_layout_hq_v020.blend（Blender v020）；assets/art/environments/base_facility_3d/components/env_base99_floor_full_replacement_v021/env_base99_floor_full_replacement_v021_visual_top3d_v003.glb；assets/art/environments/base_facility_3d/components/env_base99_floor_full_replacement_v021/env_base99_floor_full_replacement_v021_runtime_manifest_v003.json；scripts/blender/export_base_facility_v021_floor_replacement.py；tests/verification/verify_base99_floor_visuals_v021.tscn | Q32: 基地99层;完整地板替换;V021;PaletteUV;visual_only;旧MultiMesh已移除;无重叠 | R32: =LOWER(TRIM(C32)&"|"&TRIM(D32)&"|"&TRIM(E32)&"|"&TRIM(F32)&"|"&TRIM(H32)&"|"&TRIM(I32)) | S32: =IF(COUNTIF($R$6:$R$928,R32)>1,"重复","唯一") | T32: e0c6ff0eae3b248affa941ed793ac8cfe7c681995e3eb514ebd686f5a91d6944 | U32: Codex | V32: 46269 | W32: 用户自制Blender资产 | X32: — | Y32: GLB SHA256=6655e4322cd654e533e53670fb1e6611ce65818068de016faaea1b59ffb6835a；基础18普通板+18铆钉板保持复用；V017独占细节聚合为2网格，承重碰撞不变。
A33: ENV-BASE99-LOFT-FLOOR-FINISH-V017 | B33: 基地99层二层地板面层 V020 | C33: 场景 | D33: environment_module_3d | E33: base99_loft_floor_finish_v020 | F33: loft_floor_finish_overlay | G33: ENV-BASE99-ART-LAYOUT-3D | H33: Top3D / local -Z 正面 | I33: default / visual_only | J33: 99层基地楼中楼地面表现 | K33: 已完成 | L33: P0 | M33: v002 | N33: 19.6×9.6×0.108m；1网格；2材质表面；206三角面；无内置碰撞 | O33: assets/art/environments/base_facility_3d/runtime/env_base99_loft_floor_finish/env_base99_loft_floor_finish_root_top3d.tscn | P33: art_source/design/blender/base_facility_layout/base_facility_runtime_layout_hq_v020.blend（Blender v020）；assets/art/environments/base_facility_3d/components/env_base99_loft_floor_finish_v020/env_base99_loft_floor_finish_v020_visual_top3d_v002.glb；scripts/blender/export_base_facility_v020_floor_visuals.py；tests/verification/verify_base99_floor_visuals_v020.tscn | Q33: 基地99层;二层地板;V020;PaletteUV;visual_only;无重叠 | R33: =LOWER(TRIM(C33)&"|"&TRIM(D33)&"|"&TRIM(E33)&"|"&TRIM(F33)&"|"&TRIM(H33)&"|"&TRIM(I33)) | S33: =IF(COUNTIF($R$6:$R$928,R33)>1,"重复","唯一") | T33: 6fa73686f671683d08dfdbaadc315b996874404341318cbab806bbcfa7631a65 | U33: Codex | V33: 46269 | W33: 用户自制Blender资产 | X33: — | Y33: GLB SHA256=bf66319f75f5cac1c301dbfc09e4e7fe4ec0f518b7ee7dadb8e7068b94a2939c；运行时Y=-1m偏移；V020新增二楼地板面层保留，并作为V004阁楼结构唯一可见甲板。
A34: ENV-BASE99-FLOOR-VISUAL-LAYOUT-V017 | B34: 基地99层完整地板表现装配 V021 | C34: 场景 | D34: environment_module_3d | E34: base99_floor_visual_layout_v021 | F34: floor_visual_assembly | G34: ENV-BASE99-ART-LAYOUT-3D | H34: Top3D / local -Z 正面 | I34: default / visual_only | J34: 99层基地美术布局 | K34: 已完成 | L34: P0 | M34: v003 | N34: 一层30×30m + 二层20×10m；无内置碰撞 | O34: assets/art/environments/base_facility_3d/runtime/env_base99_floor_visuals/env_base99_floor_visuals_root_top3d.tscn | P34: art_source/design/blender/base_facility_layout/base_facility_runtime_layout_hq_v020.blend（Blender v020）；assets/art/environments/base_facility_3d/runtime/env_base99_floor_visuals_v021/env_base99_floor_visuals_root_top3d_v003.tscn；assets/art/environments/base_facility_3d/runtime/env_base99_loft_floor_finish_v020/env_base99_loft_floor_finish_v020_root_top3d_v002.tscn；assets/art/environments/base_facility_3d/runtime/env_base99_mezzanine_20x10_z5/env_base99_mezzanine_20x10_z5_root_top3d_v004.tscn；assets/art/environments/base_facility_3d/runtime/env_base99_wall_contents_v021/env_base99_wall_contents_root_top3d_v001.tscn；tests/verification/verify_base99_structural_asset_integration.tscn；tests/verification/verify_base99_wall_content_v021.tscn | Q34: 基地99层;完整地板表现装配;V021;visual_only;旧MultiMesh已移除 | R34: =LOWER(TRIM(C34)&"|"&TRIM(D34)&"|"&TRIM(E34)&"|"&TRIM(F34)&"|"&TRIM(H34)&"|"&TRIM(I34)) | S34: =IF(COUNTIF($R$6:$R$928,R34)>1,"重复","唯一") | T34: 0627bed9c921913e241bedcbd0265cffa173f32f3bd1e9a716045fb7441a9719 | U34: Codex | V34: 46269 | W34: 项目现有Godot资产 | X34: — | Y34: 运行时布局接入点；一层保持Blender V021完整地板替换与既有FloorSupport碰撞；二层保留Blender V020新增地板面层。2026-09-05：阁楼结构V004与L型楼梯V004恢复正式实例化；阁楼移除9个重复地板网格，二层甲板继续复用V020。下方工业铁门保持未实例化。新增V021非门墙面内容仅表现导入。
A35: ENV-BASE-WORLD-KIT-3D | B35: 入口基地3D环境套件 | C35: 场景 | D35: base | E35: base_world | F35: root_3d | G35: ENV-BASE-WORLD-KIT | H35: 俯视3D | I35: default | J35: 入口基地地图 | K35: 原型已接入 | L35: P0 | M35: v001 | N35: 约1:100迁移/程序几何 | O35: assets/art/environments/base_world_3d/env_base_world_kit_top3d.tscn | P35: scenes/BaseWorld3D.tscn | Q35: 基地;道路;废墟;3D;入口地图 | R35: =LOWER(TRIM(C35)&"|"&TRIM(D35)&"|"&TRIM(E35)&"|"&TRIM(F35)&"|"&TRIM(H35)&"|"&TRIM(I35)) | S35: =IF(COUNTIF($R$6:$R$928,R35)>1,"重复","唯一") | T35: 63c840d59bcecefab946690136474c9ca7b70408fb7b6bcc264819f9b66f14a5 | U35: Codex | V35: 46224 | W35: 原创程序几何 | X35: — | Y35: 保留原2D布局语义；首张3D迁移地图
A36: PRP-BASE-FACILITY-3D | B36: 基地设施3D通用模块 | C36: 场景道具 | D36: facility | E36: base_facility_module | F36: root_3d | G36: ENV-BASE-WORLD-KIT-3D | H36: 俯视3D | I36: default | J36: 8类基地设施/统一状态牌 | K36: 原型已接入 | L36: P0 | M36: v001 | N36: PackedScene/材质变体/名称与实时摘要共用Label3D | O36: assets/art/props/base_world_3d/prp_base_facility_root_top3d.tscn | P36: src/base3d/BaseFacility3D.gd; src/base/BaseFacilityCatalog.gd; src/base/BaseFacilityService.gd; src/world3d/TowerDescent3D.gd; tests/verification/verify_base_facility_framework.tscn; tests/verification/verify_base_world_3d_visual.tscn | Q36: 设施;交互;信标;3D;facility_id;实时摘要;状态牌;共享目录 | R36: =LOWER(TRIM(C36)&"|"&TRIM(D36)&"|"&TRIM(E36)&"|"&TRIM(F36)&"|"&TRIM(H36)&"|"&TRIM(I36)) | S36: =IF(COUNTIF($R$6:$R$928,R36)>1,"重复","唯一") | T36: 391cad1c83f33586ba70d208dca713c52c05e62c6c8100801a615c84d2d7c719 | U36: Codex | V36: 46264 | W36: 原创程序几何 | X36: — | Y36: 2026-08-06：确认该根资产服务正式基地8项设施；颜色材质、名称、交互提示与实时摘要均由稳定facility_id驱动，基地大世界与塔内99层同类设施共用。复用原NameLabel显示名称+状态，不增加节点和碰撞；注意态为金色、正常态为青绿色、不可用态为红色。管理终端与3D设施读取同一快照；Metal/OpenGL 1280×720基地和终端画面验收通过。塔楼电梯只复用外壳，保持独立交通身份。 2026-08-30 AST-02：合法内容更新；文件为Git已跟踪且修改时间不早于原台账日期；验收：verify_base_facility_framework；verify_base_facility_interaction_zones；SHA 18921dbda4e5→391cad1c83f3。
A37: PRP-DUNGEON-GATE-3D | B37: 地下城入口3D模块 | C37: 场景道具 | D37: door | E37: dungeon_gate | F37: root_3d | G37: PRP-DUNGEON-GATE | H37: 俯视3D | I37: default | J37: 4个地下城入口 | K37: 原型已接入 | L37: P0 | M37: v001 | N37: PackedScene/材质变体 | O37: assets/art/props/base_world_3d/prp_dungeon_gate_root_top3d.tscn | P37: src/base3d/DungeonEntrance3D.gd | Q37: 地下城;门;交互;3D | R37: =LOWER(TRIM(C37)&"|"&TRIM(D37)&"|"&TRIM(E37)&"|"&TRIM(F37)&"|"&TRIM(H37)&"|"&TRIM(I37)) | S37: =IF(COUNTIF($R$6:$R$928,R37)>1,"重复","唯一") | T37: 1fc802ceb8caef1ce77a54958a8b5e82a0fcae37459106fee970c8941146ba8f | U37: Codex | V37: 46224 | W37: 原创程序几何 | X37: — | Y37: 保持旧入口ID与目标场景；地下城内部暂保留2D
A38: ENV-BASE-WORLD-3D-PREVIEW | B38: 入口基地3D验收预览 | C38: 场景 | D38: review_board | E38: base_world | F38: preview_3d | G38: ENV-BASE-WORLD-KIT-3D | H38: 俯视3D | I38: default | J38: 评审与资产QA | K38: 已完成 | L38: P1 | M38: v001 | N38: 1280×720 PNG | O38: assets/art/environments/base_world_3d/env_base_world_preview_top3d_v001.png | P38: tests/verification/verify_base_world_3d_visual.tscn | Q38: 3D预览;评审;入口地图 | R38: =LOWER(TRIM(C38)&"|"&TRIM(D38)&"|"&TRIM(E38)&"|"&TRIM(F38)&"|"&TRIM(H38)&"|"&TRIM(I38)) | S38: =IF(COUNTIF($R$6:$R$928,R38)>1,"重复","唯一") | T38: 6ad569cd014b50df23e17e694063da49f49740413da4351eb4ff9de22ed230b9 | U38: Codex | V38: 46224 | W38: 项目运行截图 | X38: — | Y38: 用于检查3D布局、镜头、组件比例与交互可读性
A39: ENV-DUNGEON-RUNTIME-3D | B39: 3D随机关卡通用房间套件 | C39: 场景 | D39: room | E39: dungeon_runtime | F39: root_3d | H39: 俯视3D | I39: default | J39: 四主题副本/随机房间 | K39: 原型已接入 | L39: P0 | M39: v001 | N39: PackedScene/三档程序几何 | O39: assets/art/environments/dungeon_3d/env_dungeon_runtime_kit_top3d.tscn | P39: src/world3d/DungeonRoom3D.gd | Q39: 房间;门洞;走廊;随机地图;3D | R39: =LOWER(TRIM(C39)&"|"&TRIM(D39)&"|"&TRIM(E39)&"|"&TRIM(F39)&"|"&TRIM(H39)&"|"&TRIM(I39)) | S39: =IF(COUNTIF($R$6:$R$928,R39)>1,"重复","唯一") | T39: fc33ac084150c3e3cbba89505b3e04f35712abbceaa5cec297c94fe4d7dcc2f3 | U39: Codex | V39: 46233 | W39: 原创程序几何 | X39: — | Y39: v0.1：塔楼98—95层形成可闭环的搜打撤流程；普通层每层同时含战斗房和搜刮房，容器按种子掉落。Boss房清理后现在按房间类型正确解锁撤离，不再依赖固定room_id。生成快照增加门连通与全息小地图实时状态，测试覆盖100→99→98实机楼梯路径、95层Boss和撤离完成。
A40: ENV-DUNGEON-IRON-FRONTIER-3D | B40: 冷钢边境3D主题资源 | C40: 场景 | D40: biome | E40: iron_frontier | F40: theme_3d | G40: ENV-DUNGEON-RUNTIME-3D | H40: 俯视3D | I40: default | J40: 冷钢边境 | K40: 原型已接入 | L40: P0 | M40: v001 | N40: DungeonTheme3D Resource | O40: assets/art/environments/dungeon_3d/env_iron_frontier_kit_top3d_v001.tres | P40: scenes/levels3d/IronFrontier3D.tscn | Q40: 冷钢;冷蓝;边境;雾;灯光 | R40: =LOWER(TRIM(C40)&"|"&TRIM(D40)&"|"&TRIM(E40)&"|"&TRIM(F40)&"|"&TRIM(H40)&"|"&TRIM(I40)) | S40: =IF(COUNTIF($R$6:$R$928,R40)>1,"重复","唯一") | T40: a3c6e7e5433928b790e1fa0fe5124beaeb5ab579f2d376aa35a1be25b6736b58 | U40: Codex | V40: 46224 | W40: 原创程序配置 | X40: — | Y40: 只保存3D色彩/雾/灯光/家具倾向；玩法读取MapThemeProfile
A41: ENV-DUNGEON-RUST-FOUNDRY-3D | B41: 锈蚀铸造厂3D主题资源 | C41: 场景 | D41: biome | E41: rust_foundry | F41: theme_3d | G41: ENV-DUNGEON-RUNTIME-3D | H41: 俯视3D | I41: default | J41: 锈蚀铸造厂 | K41: 原型已接入 | L41: P0 | M41: v001 | N41: DungeonTheme3D Resource | O41: assets/art/environments/dungeon_3d/env_rust_foundry_kit_top3d_v001.tres | P41: scenes/levels3d/RustFoundry3D.tscn | Q41: 锈蚀;铸造;橙光;工业 | R41: =LOWER(TRIM(C41)&"|"&TRIM(D41)&"|"&TRIM(E41)&"|"&TRIM(F41)&"|"&TRIM(H41)&"|"&TRIM(I41)) | S41: =IF(COUNTIF($R$6:$R$928,R41)>1,"重复","唯一") | T41: 0c14c1dd5a5b8edcb51fa5bb024666d845611bfd87c3c4ee0ded56c4614010a8 | U41: Codex | V41: 46224 | W41: 原创程序配置 | X41: — | Y41: 复用通用房间根；主题资源不复制玩法规则
A42: ENV-DUNGEON-SPORE-DEPTHS-3D | B42: 孢子深层3D主题资源 | C42: 场景 | D42: biome | E42: spore_depths | F42: theme_3d | G42: ENV-DUNGEON-RUNTIME-3D | H42: 俯视3D | I42: default | J42: 孢子深层 | K42: 原型已接入 | L42: P0 | M42: v001 | N42: DungeonTheme3D Resource | O42: assets/art/environments/dungeon_3d/env_spore_depths_kit_top3d_v001.tres | P42: scenes/levels3d/SporeDepths3D.tscn | Q42: 孢子;病绿;地下;异化 | R42: =LOWER(TRIM(C42)&"|"&TRIM(D42)&"|"&TRIM(E42)&"|"&TRIM(F42)&"|"&TRIM(H42)&"|"&TRIM(I42)) | S42: =IF(COUNTIF($R$6:$R$928,R42)>1,"重复","唯一") | T42: bbd5cc04028e3962ce9eb8ea04c1c06157d128b5dbad1cea64bed7b4a02e7689 | U42: Codex | V42: 46224 | W42: 原创程序配置 | X42: — | Y42: 复用通用房间根；主题资源不复制玩法规则
A43: ENV-DUNGEON-ABYSS-ARCHIVE-3D | B43: 深渊档案库3D主题资源 | C43: 场景 | D43: biome | E43: abyss_archive | F43: theme_3d | G43: ENV-DUNGEON-RUNTIME-3D | H43: 俯视3D | I43: default | J43: 深渊档案库 | K43: 原型已接入 | L43: P0 | M43: v001 | N43: DungeonTheme3D Resource | O43: assets/art/environments/dungeon_3d/env_abyss_archive_kit_top3d_v001.tres | P43: scenes/levels3d/AbyssArchive3D.tscn | Q43: 深渊;档案;紫光;禁区 | R43: =LOWER(TRIM(C43)&"|"&TRIM(D43)&"|"&TRIM(E43)&"|"&TRIM(F43)&"|"&TRIM(H43)&"|"&TRIM(I43)) | S43: =IF(COUNTIF($R$6:$R$928,R43)>1,"重复","唯一") | T43: fb276fb1586de1b69d306ff894800f51da600b8dfb2780cf8bc8d22695ad3a52 | U43: Codex | V43: 46224 | W43: 原创程序配置 | X43: — | Y43: 复用通用房间根；主题资源不复制玩法规则
A44: PRP-WASTELAND-LIGHT-3D | B44: 废土灯具3D通用模块（街灯/顶灯） | C44: 场景道具 | D44: light | E44: wasteland_light | F44: root_3d | G44: ENV-DUNGEON-RUNTIME-3D | H44: 俯视3D | I44: default | J44: 关卡/靶场/房间中央照明 | K44: 原型已接入 | L44: P0 | M44: v001 | N44: PackedScene/OmniLight3D | O44: assets/art/props/dungeon_3d/prp_wasteland_light_root_top3d.tscn | P44: src/world3d/WastelandLight3D.gd | Q44: 灯具;街灯;中央顶灯;故障灯;废土 | R44: =LOWER(TRIM(C44)&"|"&TRIM(D44)&"|"&TRIM(E44)&"|"&TRIM(F44)&"|"&TRIM(H44)&"|"&TRIM(I44)) | S44: =IF(COUNTIF($R$6:$R$928,R44)>1,"重复","唯一") | T44: 0a6ec0add8b6e01b83f4dbaae421ff0dc69ed08648d304bac061f540af27d99b | U44: Codex | V44: 46237 | W44: 原创程序几何 | X44: — | Y44: v0.1：房间灯统一覆盖环境layer1与角色layer2；普通房中央灯与基地四灯组各只保留一盏投影主灯，其余灯无阴影以控制预算。流送状态改为递归同步嵌套灯具，玩家与怪物均可在开灯房间产生投影。 2026-08-03：failing=false 稳定灯不进入慢波/微波亮度调制；房灯开关仅切换 0/配置能量并保留 Compatibility 渲染实例，固定机位初始开灯与复明后的地面采样一致。
A45: PRP-ROOM-FURNITURE-3D | B45: 房间家具3D通用模块 | C45: 场景道具 | D45: furniture | E45: room_furniture | F45: root_3d | G45: ENV-DUNGEON-RUNTIME-3D | H45: 俯视3D | I45: default | J45: 全部3D房间 | K45: 原型已接入 | L45: P0 | M45: v001 | N45: PackedScene/类型与尺寸配置 | O45: assets/art/props/dungeon_3d/prp_room_furniture_root_top3d.tscn | P45: src/world3d/RoomFurniture3D.gd | Q45: 家具;小中大;箱柜;工作台 | R45: =LOWER(TRIM(C45)&"|"&TRIM(D45)&"|"&TRIM(E45)&"|"&TRIM(F45)&"|"&TRIM(H45)&"|"&TRIM(I45)) | S45: =IF(COUNTIF($R$6:$R$928,R45)>1,"重复","唯一") | T45: a78a7eaac02ce39add97d8a57754cc86ea34e740e24e0e901f4e037198a086e9 | U45: Codex | V45: 46224 | W45: 原创程序几何 | X45: — | Y45: 11类轮廓；small/medium/large影响占地与碰撞
A46: PRP-SEARCH-CONTAINER-3D | B46: 可搜索容器3D通用模块 | C46: 场景道具 | D46: container | E46: search_container | F46: root_3d | G46: PRP-ROOM-FURNITURE-3D | H46: 俯视3D | I46: closed_opened | J46: 搜索房/仓储/事件 | K46: 原型已接入 | L46: P0 | M46: v001 | N46: PackedScene/搜索状态 | O46: assets/art/props/dungeon_3d/prp_search_container_root_top3d.tscn | P46: src/world3d/RoomFurniture3D.gd | Q46: 搜索;容器;战利品;小中大 | R46: =LOWER(TRIM(C46)&"|"&TRIM(D46)&"|"&TRIM(E46)&"|"&TRIM(F46)&"|"&TRIM(H46)&"|"&TRIM(I46)) | S46: =IF(COUNTIF($R$6:$R$928,R46)>1,"重复","唯一") | T46: 2c0852d86e7c0e635e76197ff8d2f6a030daa186f760dfb339d3fdeddf3c192d | U46: Codex | V46: 46224 | W46: 原创程序几何 | X46: — | Y46: 搜索为家具状态与配置，不建立关卡局部重复模型
A47: PRP-SERVICE-STATION-3D | B47: 废土服务终端3D模块 | C47: 场景道具 | D47: facility | E47: service_station | F47: root_3d | G47: ENV-DUNGEON-RUNTIME-3D | H47: 俯视3D | I47: default | J47: 商店/升级/事件/重置 | K47: 原型已接入 | L47: P0 | M47: v001 | N47: PackedScene/程序组件 | O47: assets/art/props/dungeon_3d/prp_service_station_root_top3d.tscn | P47: src/world3d/ServiceStation3D.gd | Q47: 终端;商店;升级;事件;重置 | R47: =LOWER(TRIM(C47)&"|"&TRIM(D47)&"|"&TRIM(E47)&"|"&TRIM(F47)&"|"&TRIM(H47)&"|"&TRIM(I47)) | S47: =IF(COUNTIF($R$6:$R$928,R47)>1,"重复","唯一") | T47: da288e4a8ffc005053741d2eda3bbcbf2f6ad34c32c6657e35d0ddf62b837be4 | U47: Codex | V47: 46224 | W47: 原创程序几何 | X47: — | Y47: 四种服务行为复用同一视觉与交互组件
A48: PRP-EXTRACTION-BEACON-3D | B48: 撤离信标3D模块 | C48: 场景道具 | D48: facility | E48: extraction_beacon | F48: root_3d | G48: ENV-DUNGEON-RUNTIME-3D | H48: 俯视3D | I48: locked_active_done | J48: 四主题撤离房 | K48: 原型已接入 | L48: P0 | M48: v001 | N48: PackedScene/程序组件 | O48: assets/art/props/dungeon_3d/prp_extraction_beacon_root_top3d.tscn | P48: src/world3d/ExtractionBeacon3D.gd | Q48: 撤离;信标;倒计时;Boss解锁 | R48: =LOWER(TRIM(C48)&"|"&TRIM(D48)&"|"&TRIM(E48)&"|"&TRIM(F48)&"|"&TRIM(H48)&"|"&TRIM(I48)) | S48: =IF(COUNTIF($R$6:$R$928,R48)>1,"重复","唯一") | T48: f2638fdaca3f9542e918a56750bda04a5828b18a763569eb16a36619e9e336b4 | U48: Codex | V48: 46237 | W48: 原创程序几何 | X48: — | Y48: 锁定/同步/取消/完成四段生命周期 2026-08-03：待机/锁定 STANDARD 信标局部光固定为 2.2；仅正式撤离倒计时允许能量脉冲，避免干扰基地房灯的地面反馈。
A49: ENV-TRAINING-RANGE-KIT-3D | B49: 独立3D训练靶场套件 | C49: 场景 | D49: training_range | E49: training_range | F49: root_3d | H49: 俯视3D | I49: default | J49: 独立训练地图 | K49: 原型已接入 | L49: P0 | M49: v001 | N49: PackedScene/程序环境 | O49: assets/art/environments/training_range_3d/env_training_range_kit_top3d.tscn | P49: scenes/TrainingRange3D.tscn | Q49: 靶场;射击道;货架;59组合;三类靶 | R49: =LOWER(TRIM(C49)&"|"&TRIM(D49)&"|"&TRIM(E49)&"|"&TRIM(F49)&"|"&TRIM(H49)&"|"&TRIM(I49)) | S49: =IF(COUNTIF($R$6:$R$928,R49)>1,"重复","唯一") | T49: 4d1153bc736fab0790300f171beef8435002670f3789d6434e966bca0a79d28e | U49: Codex | V49: 46224 | W49: 原创程序几何 | X49: — | Y49: 18货架（7远程+3近战+8子弹）、三射击道、三靶标、重置与返回；BaseData隔离
A50: ENV-DUNGEON-RUNTIME-3D-PREVIEW | B50: 3D关卡运行时验收预览 | C50: 场景 | D50: review_board | E50: dungeon_runtime | F50: preview_3d | G50: ENV-DUNGEON-RUNTIME-3D | H50: 俯视3D | I50: default | J50: 评审与资产QA | K50: 已完成 | L50: P1 | M50: v001 | N50: 1280×720 PNG | O50: ../ShellStorm2-backup/2026-10-11_art_source_split/original_tree/assets/art/environments/dungeon_3d/previews/env_dungeon_runtime_preview_top3d_v001.png | P50: tests/verification/verify_full_3d_visual.tscn | Q50: 3D关卡;预览;灯光;战斗;QA | R50: =LOWER(TRIM(C50)&"|"&TRIM(D50)&"|"&TRIM(E50)&"|"&TRIM(F50)&"|"&TRIM(H50)&"|"&TRIM(I50)) | S50: =IF(COUNTIF($R$6:$R$928,R50)>1,"重复","唯一") | T50: 3b2c2212f1283ed366a31dc3a101b3555c78768c3906600eb0b18c74423fb247 | U50: Codex | V50: 46264 | W50: 项目运行截图 | X50: — | Y50: 实际GPU窗口确认360°遮挡逻辑与96°定向表现；v0.1三层玩家灯去除头顶溢光，角色正面柔光、增强中央灯与战斗轮廓通过验收 2026-08-30 AST-04：验证预览图从生产运行目录迁移到 previews/ 隔离目录；稳定 AssetID 与版本不变；路径 assets/art/environments/dungeon_3d/env_dungeon_runtime_preview_top3d_v001.png → ../ShellStorm2-backup/2026-10-11_art_source_split/original_tree/assets/art/environments/dungeon_3d/previews/env_dungeon_runtime_preview_top3d_v001.png；SHA-256 已重算。该图仅用于美术/关卡验证，不作为 Godot 运行时资源。
A51: ENV-TRAINING-RANGE-3D-PREVIEW | B51: 3D训练靶场验收预览 | C51: 场景 | D51: review_board | E51: training_range | F51: preview_3d | G51: ENV-TRAINING-RANGE-KIT-3D | H51: 俯视3D | I51: default | J51: 评审与资产QA | K51: 已完成 | L51: P1 | M51: v001 | N51: 1280×720 PNG | O51: assets/art/environments/training_range_3d/env_training_range_preview_top3d_v001.png | P51: tests/verification/verify_training_range_3d_visual.tscn | Q51: 3D靶场;预览;射击道;目标;QA | R51: =LOWER(TRIM(C51)&"|"&TRIM(D51)&"|"&TRIM(E51)&"|"&TRIM(F51)&"|"&TRIM(H51)&"|"&TRIM(I51)) | S51: =IF(COUNTIF($R$6:$R$928,R51)>1,"重复","唯一") | T51: 2597d0d8bc0cdb95e04a38f444bdde37316c373b230fe3024621a4d1dbcf52d8 | U51: Codex | V51: 46224 | W51: 项目运行截图 | X51: — | Y51: 真实GPU窗口检查三条射击道、三类靶、枪弹组合区与灯光
A52: PRP-ROOM-LIGHT-SWITCH-3D | B52: 房间中央灯墙面开关3D | C52: 场景道具 | D52: facility | E52: room_light_switch | F52: root_3d | G52: ENV-DUNGEON-RUNTIME-3D | H52: 俯视3D | I52: default | J52: 随机关卡房间/四主题复用 | K52: 原型已接入 | L52: P0 | M52: v001 | N52: PackedScene/Area3D | O52: assets/art/props/dungeon_3d/prp_room_light_switch_root_top3d.tscn | P52: src/world3d/RoomLightSwitch3D.gd | Q52: 房灯开关;墙面交互;中央顶灯;E键 | R52: =LOWER(TRIM(C52)&"|"&TRIM(D52)&"|"&TRIM(E52)&"|"&TRIM(F52)&"|"&TRIM(H52)&"|"&TRIM(I52)) | S52: =IF(COUNTIF($R$6:$R$928,R52)>1,"重复","唯一") | T52: 7802bc3a71d892072e43962875e26b60443d19de35bcc77fe0cbedcfa6dd5d94 | U52: Codex | V52: 46237 | W52: 原创程序几何 | X52: — | Y52: v0.1：开关新增灯组控制，同一开关可统一切换多盏房间灯；基地四灯共用一个墙边开关并在快照中报告控制灯数量。单灯房继续兼容原接口。 2026-08-03：基地四灯总开关不再移除 OmniLight3D 渲染实例；关灯能量归零，复明恢复配置能量、范围与阴影，真实 GPU 双区域像素差验收通过。
A53: ENV-TOWER-DESCENT-KIT-3D | B53: 局内关卡01-顶部数据库 | C53: 场景 | D53: room_kit | E53: tower_descent | F53: root_3d | G53: ENV-DUNGEON-RUNTIME-3D | H53: 俯视3D | I53: godot_runtime | J53: 程序占位 | K53: 程序占位 | L53: P0 | M53: v002 | N53: 98–95F白盒区块；稳定编号=局内关卡01；可变设定名=顶部数据库 | O53: scenes/TowerDescent3D.tscn | P53: art_source/design/whitebox/tower_zones/battle_level01/v002/QA_REPORT.md; art_source/design/whitebox/tower_zones/battle_level01/v002/data/unit_plan.json; art_source/design/whitebox/tower_zones/battle_level01/v002/blender/; docs/v0.1/05.1_关卡区块设计.md | Q53: 局内关卡01;顶部数据库;98到95;Battle;首个Boss区段;白盒 | R53: =LOWER(TRIM(C53)&"|"&TRIM(D53)&"|"&TRIM(E53)&"|"&TRIM(F53)&"|"&TRIM(H53)&"|"&TRIM(I53)) | S53: =IF(COUNTIF($R$6:$R$928,R53)>1,"重复","唯一") | T53: e9bf6b5353fe1caa548053d6e7e8aa18ae1eefa40c64307f3cbe13204b6c9097 | U53: Codex | V53: 46295 | W53: 程序生成 Blender 源集合 | X53: 命名合同：level_number=1，level_code=局内关卡01，setting_name=顶部数据库，display_name=局内关卡01-顶部数据库。设定名可改，编号、block_id、AssetID与路径保持稳定。当前白盒为battle_level01/v002的19个可维护Blender源；楼梯白盒另归stairs。 | Y53: 命名合同：level_number=1，level_code=局内关卡01，setting_name=顶部数据库，display_name=局内关卡01-顶部数据库。设定名可改，编号、block_id、AssetID与路径保持稳定。
A54: ENV-TOWER-FLOOR-TILE-5M | B54: 塔楼5米地砖模块 | C54: 场景 | D54: room_kit | E54: tower_descent | F54: floor_tile_5m | G54: ENV-TOWER-DESCENT-KIT-3D | H54: 俯视3D | I54: godot_runtime | J54: 100F天台与98F楼板；旧v001保留其他楼层与交通模块 | K54: 已完成 | L54: P0 | M54: v003 | N54: 5×5×0.304m；740三角面；2材质；共享MultiMesh；行走面锚点+0.1500不变；装饰件反共面阶梯+0.1520/+0.1540（XY重叠可见面高度差≥2mm） | O54: assets/art/environments/tower_descent_3d/runtime/floor_tile_5m/env_tower_floor_tile_5m_root_top3d.tscn | P54: art_source/environments/tower_descent_3d/source/floor_tile_5m/env_tower_floor_tile_5m_source_v003.blend; assets/art/environments/tower_descent_3d/components/floor_tile_5m/env_tower_floor_tile_5m_top3d.glb; scripts/blender/build_tower_floor_tile_5m_v003.py; assets/art/props/dungeon_3d/prp_tower_floor_tile_5m.tscn; tests/verification/verify_tower_journey_polish.tscn | Q54: 塔楼;地砖;楼板;5米;模块化;平铺;四向接口 | R54: =LOWER(TRIM(C54)&"|"&TRIM(D54)&"|"&TRIM(E54)&"|"&TRIM(F54)&"|"&TRIM(H54)&"|"&TRIM(I54)) | S54: =IF(COUNTIF($R$6:$R$928,R54)>1,"重复","唯一") | T54: 97e44015f71bd2c180aa5b51a937f57a543e14d40138ac8c44e0d9b34c025cea | U54: Codex | V54: 2026-09-22 00:00:00 | W54: 程序生成Blender源集合 | X54: — | Y54: 2026-08-02：复用于99层楼梯间—基地房间的15m/20m接驳走廊地面，继续遵守5m网格与不透明材质规范。 2026-08-03：水平通道按每5m一块动态生成地砖实例；使用MultiMesh批量提交但保留逐格坐标，禁止拉伸单块Mesh代替模块拼接。 2026-08-18：保留通用塔楼地板稳定ID；基地地板另登记ENV-BASE99-FLOOR-PLAIN-5M / RIVET-5M。本轮地板运行时不切换，允许临时复用。 2026-09-06：纠正旧台账GLB与实际BoxMesh引用差异。v002工业面板、金属压边、紧固槽与检修盖正式接入100F/98F；单包410面逐面PaletteUV验收通过。 2026-09-22：修复细节级闪面（z-fighting）升 v003。v002 顶面四家族（哑光面板/角部紧固座/紧固槽/检修盖板）同落 +0.1500 且 XY 互叠（跨零件共面 13 对、0.3745㎡，最严重一处为检修盖板整片 0.324㎡），相机贴地观察时逐像素闪烁；另一并存缺陷是检修盖框顶面 +0.1480，比面板低 2mm 被永久埋没不可见。v003 采用反共面阶梯：行走面锚点 +0.1500 不动（TowerFloorStage3D 固定 -FLOOR_THICKNESS*0.5=-0.15 偏移契约不受影响），盖框/紧固座/警示短标抬到 +0.1520，紧固槽/盖板格栅条抬到 +0.1540，并将检修盖缝改为 2mm 真实凹槽（通透负空间）。本件与 prp_tower_floor_tile_5m.tscn 共用同一个已去版本化的 GLB，故 98F 标准砖与远征/98F 抛光砖同时受益；99F 自持地砖不受影响。
A55: ENV-TOWER-WALL-SOLID-5M | B55: 塔楼5米满高实墙模块 | C55: 场景 | D55: room_kit | E55: tower_descent | F55: wall_solid_5m | G55: ENV-TOWER-DESCENT-KIT-3D | H55: 俯视3D | I55: godot_runtime | J55: 整层外墙/65m核心/探索房内墙/5m正交走廊 | K55: 原型已接入 | L55: P0 | M55: v004 | N55: GLB / 可视包络 5×11.9×0.4675m（结构阻挡 0.30m）/ 12m逻辑碰撞 / 共享Mesh / 可旋转 | O55: assets/art/environments/tower_descent_3d/components/env_tower_wall_solid_5m_top3d.glb | P55: art_source/environments/tower_descent_3d/source/wall_height12/env_tower_wall_solid_5m_source_v004.blend; art_source/environments/tower_descent_3d/source/wall_height12/export_env_tower_wall_solid_5m_v004.py; art_source/environments/tower_zones/battle/source/common_components/v007/env_battle_common_components_source_v007.blend; assets/art/props/dungeon_3d/prp_tower_wall_solid_5m.tscn; src/world3d/TowerGeometry3D.gd | Q55: 塔楼;实墙;满高墙;5米;12米逻辑墙;11.9米可见墙;模块化 | R55: =LOWER(TRIM(C55)&"|"&TRIM(D55)&"|"&TRIM(E55)&"|"&TRIM(F55)&"|"&TRIM(H55)&"|"&TRIM(I55)) | S55: =IF(COUNTIF($R$6:$R$928,R55)>1,"重复","唯一") | T55: 0bca134eef74148f0df444d72afff769974863cab6fec4ca885b773186649fb9 | U55: Codex | V55: 46284 | W55: Blender 派生（自 v007 通用实墙组件） | X55: — | Y55: 2026-08-02：南北向水平共享墙统一注册相机抬升判定，楼梯南侧墙纳入同一规则；墙体始终不透明，取消运行时墙体透明度改写。 2026-08-03：东西向5m房间连接通道的无门南侧实墙增加独立camera_lower_wall碰撞标记；南北向通道的东/西墙保持不触发。真实98层侧门通道相机回归通过。 2026-08-03：水平通道按每5m左右各一块动态生成9m实墙实例；墙体可视覆盖与连续碰撞严格等长，东西向通道南墙继续承担相机抬升判定。 2026-08-03：动态水平通道按实墙Mesh包围盒底面自动贴合楼面；GLB几何保持Y=0..9m，可视原点不再误用碰撞盒4.5m中心。新增墙底高度与9m墙高自动回归。 2026-09-19：可视网格换为 v004（自 battle/common_components v007「wall_standard_5m_通用包」派生，派生脚本 art_source/environments/tower_descent_3d/source/wall_height12/export_env_tower_wall_solid_5m_v004.py）。Blender 内对根节点烘焙 180° 偏航后 transform_apply，使装饰面落在 Godot +Z（与 prp_tower_* A 套 forward_axis="+Z" 对齐）；先三角化再删朝下面（去 1095 面）、join 成单 Mesh，丢掉无几何的 03_清漆反光_紫粉点缀 槽，只留 01/02/04 三个共享色盘角色。稳定路径 GLB 原地覆盖（文件名去版本号），节点名统一 ENV_TOWER_WALL_SOLID_5M，根变换为单位矩阵（该 GLB 被 TowerDescent3D 直接 preload，根变换会直接决定走廊墙位置）。阻挡不动：结构碰撞仍 0.30m 代理，可视包络 5×11.9×0.4675m（正面装甲凸到 +Z 0.3175）。 2026-10-12：可视本体被复用 —— 远征关卡01 的通用实墙组件 ENV-BATTLE-COMMON-WALL-STANDARD-5M（wall_standard_5m_root_top3d.tscn）把可视 GLB 换成本件，使该关 7 个房间（room_02/05/06/07/10/extraction/start）的实墙统一为本件重装甲外观；结构阻挡仍由该战局组件自持的 BoxShape3D 提供，本件在此纯作视觉来源。
A56: ENV-TOWER-WALL-PARAPET-5M | B56: 塔楼5米楼顶女儿墙模块 | C56: 场景 | D56: room_kit | E56: tower_descent | F56: wall_parapet_5m | G56: ENV-TOWER-DESCENT-KIT-3D | H56: 俯视3D | I56: godot_runtime | J56: 335m楼顶四周边界/268段MultiMesh围栏 | K56: 原型已接入 | L56: P1 | M56: v001 | N56: GLB / 5×0.30×1.50m / 共享Mesh | O56: assets/art/environments/tower_descent_3d/components/env_tower_wall_parapet_5m_top3d.glb | P56: Blender集合=10C_MOD_WALL_PARAPET_5M_U01; export_env_tower_5m_modules_v001.py; TowerFloorStage3D.gd; tests/verification/verify_tower_descent_visual.tscn | Q56: 塔楼;女儿墙;护栏;5米;模块化;楼顶边界 | R56: =LOWER(TRIM(C56)&"|"&TRIM(D56)&"|"&TRIM(E56)&"|"&TRIM(F56)&"|"&TRIM(H56)&"|"&TRIM(I56)) | S56: =IF(COUNTIF($R$6:$R$928,R56)>1,"重复","唯一") | T56: 44fdb663487a9bf010d8fa249a2f9811843409c35d9f7ce8d09c48f7de7bf808 | U56: Codex | V56: 46233 | W56: 程序生成Blender源集合 | X56: — | Y56: v0.1：继续复用同一5m围栏模块，按50×50网格环绕250×250m楼顶与整层边界，不新增大块整体网格；普通楼顶由统一太阳照明，楼梯口局部阴影不再靠提高全局环境亮度解决。
A57: ENV-TOWER-WALL-DOOR-5M | B57: 塔楼5米带门墙模块 | C57: 场景 | D57: room_kit | E57: tower_descent | F57: wall_door_5m | G57: ENV-TOWER-DESCENT-KIT-3D | H57: 俯视3D | I57: godot_runtime | J57: 5m墙位/2.2m净宽/2.5m净高/独立门扇 | K57: 原型已接入 | L57: P0 | M57: v005 | N57: GLB / 可视包络 5×11.9×0.683m（双面装饰，两侧各前凸 0.3415；结构阻挡 0.30m）/ 门洞净空 2.2×2.5m / 12m逻辑碰撞 / 共享Mesh / 可旋转 | O57: assets/art/environments/tower_descent_3d/components/env_tower_wall_door_5m_top3d.glb | P57: art_source/environments/tower_descent_3d/source/wall_height12/env_tower_wall_door_5m_source_v005.blend; art_source/environments/tower_descent_3d/source/wall_height12/export_env_tower_wall_door_5m_v005.py; art_source/environments/tower_zones/battle/source/common_components/v007/env_battle_common_components_source_v007.blend; assets/art/props/dungeon_3d/prp_tower_wall_door_5m.tscn; src/world3d/DungeonRoom3D.gd | Q57: 塔楼;门;门洞;5米;模块化;肉鸽触发;独立门扇 | R57: =LOWER(TRIM(C57)&"|"&TRIM(D57)&"|"&TRIM(E57)&"|"&TRIM(F57)&"|"&TRIM(H57)&"|"&TRIM(I57)) | S57: =IF(COUNTIF($R$6:$R$928,R57)>1,"重复","唯一") | T57: 473a2d18971202580e37823da026f53528774b527a307b05517a45aaf73cb8e0 | U57: Codex | V57: 46277 | W57: Blender 派生（自 v007 通用门墙组件，v005 双面） | X57: — | Y57: 2026-08-02：南北门墙统一使用仅限相机层的门洞代理，开门不再全局绕过后墙检测；代理不阻挡玩家、怪物或子弹。 2026-09-19：可视本体由「塔楼旧套件程序生成源」换成战局通用组件派生美术（grep 关键词：DOOR_V004_DERIVE_REPORT / DOOR_V004_APERTURE_FAILED / PREFAB_DOOR_WALL_OK / DOOR_WALL_VISUAL_OK）。旧 GLB 出自 env_tower_descent_kit_top3d_v007.blend 的集合 10D_MOD_WALL_DOOR_5M_U01（本行 W 列原值即「程序生成 Blender 源集合」）：41,760 B、方块门垛+门楣、没有 PaletteUV、.import 里 import_script/path 为空且 embedded_image_handling=1，游离在共享色盘体系之外——同批其它塔楼构件（实墙/门扇/L 墙角）都已绑定。新资产自 tower_zones/battle/source/common_components/v007 的 wall_door_5m_通用包（ROOT_wall_door_5m_通用组件 + 主体_输出 4410 面 + UI灯光_柔和自发光 182 面）派生：绕竖轴 180°（美术自述正面在 Blender +Y，经 YUP 会落到 Godot -Z，而塔楼 A 套硬要求 forward_axis=+Z）后把偏移烘焙进顶点、ROOT 空物体丢弃、两网格合并为单 Mesh、12 个审阅场景塌缩为 1 个。朝下面剔除刻意只剔「贴地」那一层：门墙有门楣，其底面朝下且位于净高 2.5m 处，照实墙那样全剔会让玩家仰头看穿墙体；实测删掉 116 个地面封口面、保留 1376 个高于地面的朝下面，派生脚本内置断言（lintel underside was culled）挡住回退。门洞净空不采信源文件自报包络，改用射线从门洞内部实测复核：净宽 2.2（±1.1）、净高 2.5（门楣底），与 TowerGeometry3D.DOOR_CLEAR_WIDTH_M / DOOR_CLEAR_HEIGHT_M 及 DungeonRoom3D._add_tower_wall_collision() 的脚本碰撞代理逐值一致，故碰撞代理与门洞口径无需改动。实测：GLB 581,392 B / sha256 d5fd5a75…；4 个材质角色（01/02/03/04）全部有面、无空槽；.import 已绑 tools/asset_pipeline/scene_facility_shared_palette_post_import.gd 且 embedded_image_handling=0，探针实测四个表面 albedo_texture=true（色盘真的生效）；可视包络 5×11.9×0.4915（装饰面朝房内 Godot +Z 凸到 0.3415、结构背 -0.15）；PREFAB_CONTRACT_OK count=6；TOWER_GRID_COMPONENT_ALIGNMENT_OK；TOWER_PALETTE_VISIBLE_OK（各房间 Imported_DoorWall5M_* 全部 override=null 且无残留门扇）；运行时递归探针实测 118 个塔楼门墙模块全部 4 表面 / AABB=(5,11.9,0.4915) / 装饰面朝 +Z；DOOR_WALL_VISUAL_OK captured=4（房内侧/外侧细节能量比 4.247，外侧为纯平板无装饰）；PREFAB_DOOR_WALL_OK（无静态门扇、无内嵌碰撞）。程序生成旧资产自带的那片静态门扇 DoorLeaf_OPEN 随重导出消失（通用包本来就不含门扇），qa/probe_tower_palette_visible.gd 的对应断言已由「必须隐藏」反转为「必须不存在」。注：节点名前缀 Imported_DoorWall5M_* 被两条路径共用——基地99层设施房走 ENV-BASE99-WALL-DOOR-5X12（自身包络 1.051m 深），核对时须按 asset_id 区分，否则会拿 A 套契约量出假失败。 2026-09-19（v005）：门墙改为**双面装饰**。用户原话「我发现这个墙会连着走廊，做成两面都有效果的，直接复制一个镜像一下，在blender里头制作，完成后重新导入」。v004 只有房内侧（Godot +Z）有装饰，走廊侧（−Z）是一块平整结构背，玩家站在走廊里看过去是素板。v005 在派生脚本里新增 mirror_decoration 阶段：在 yaw 烘焙与三角化之后、朝下剔面之前，把「位于结构面前侧（Blender y ≤ −0.152，结构面 −0.15 加 2mm 切割容差）」的装饰面复制一份，用 Mirror 修改器绕 y=0 基准面（网格中心线）翻转后与原网格 join。（grep 关键词：DOOR_V005_DERIVE_REPORT / DOOR_V005_DERIVE_CONTRACT_FAILED / DOOR_V005_GLB_VERIFY_FAILED / DOOR_V005_EXPORT_CONTRACT_FAILED / DERIVE_OK / EXPORT_OK / PREFAB_DOOR_WALL_OK / DOOR_WALL_RUNTIME_OK / DOOR_WALL_VISUAL_OK。）Mirror 必须 use_mirror_merge=false、use_clip=false——门洞隧道与背壳横跨 y=0，开启合并会把它们粘在基准面上、开启裁剪会把它们钉死；关掉这两项后修改器自动翻转绕向，镜像面法线朝外，无需手工 flip。**整物体镜像不可行**：会与保留的背板共面闪烁，并把门洞复制成两条，所以切割后只复制装饰面。实测：装饰面/侧 7883 面（剔贴地面后 7799），镜像新增 7883（1:1）；跨侧共面孪生 0（源本身有 132 组薄片双面写法，镜像后恰好 264 组，未新增）；包络 Blender y∈[−0.3415, +0.3415]（Godot z 同值），关于 z=0 对称；门洞射线三向复测：±X 净宽 2.2、+Z 净高 2.5、±Y 贯穿厚度无阻挡（clear_through_thickness=true）——镜像面没有把门洞堵死；门楣底面仍在（朝下面只剔贴地一层 GROUND_BAND_M=0.05，保留 2734 个、删 200 个，断言「lintel underside was culled」挡住回退）。⚠️ float32 陷阱：镜像后顶点以 float32 存盘，面色心/法线会差约 1e-5，任何基于色心的逐项比对（排序后 zip、容差桶贪心匹配）都会误报「不对称」（本次曾误报 911 条、再误报 29 条）。改用两个对 float32 逐位稳定的不变量：① 顶点位置键多重集（镜像只翻 abs(y)，逐位精确）② 向量面积相对偏差（抓绕向反转）——实测 position_key_mismatches=0、area_delta=0.0，两侧顶点位置多重集差异为 0。⚠️ 退化面陷阱：源含 24 个零面积面（area<1e-9），其法线是数值垃圾，会让「朝下面」的阈值计数在存盘/重载之间翻转（实测 1367/1368）。已在统计中排除并单独报告 degenerate_zero_area_faces=24，门楣保留断言加 DOWN_FACE_COUNT_TOLERANCE=4 容差（门楣是否存在由门洞射线精确证明，不靠计数）。实测：GLB 1,147,372 B（v004 为 581,392 B）/ sha256 473a2d18…；4 个材质角色（01_精工金属_紫色骨架 / 02_细腻哑光_青绿大面 / 03_清漆反光_紫粉点缀 / 04_柔和自发光_UI灯光）全部保留；prefab 声明 asset_version=v005、visual_bounds_size_m=(5,11.9,0.683)、新增 metadata/double_sided=true；bounds_size_m 仍为 (5,11.9,0.3)（结构阻挡量，刻意与可视包络分离）。门禁：PREFAB_CONTRACT_OK count=6；TOWER_GRID_COMPONENT_ALIGNMENT_OK；TOWER_PALETTE_VISIBLE_OK；PREFAB_DOOR_WALL_OK；DOOR_WALL_RUNTIME_OK（递归探针实测 120 个模块中塔楼 A 套 118 个全部包络 ±0.3415 双面对称、4 表面）；DOOR_WALL_VISUAL_OK captured=4。画面取证（probe_door_wall_visual，v004 → v005）：房内侧保持 7 层亮度分层 / 细节能量 0.0015 不变（v004 与 v005 房内侧图做像素比对，平均通道差 0.04/255，判定「几乎同一画面」）；走廊侧 2 层 / 0.0004 → 6 层 / 0.0018（×4.5）；两侧能量比 4.247 → 0.829，即真正「两面都有效果」。走廊侧图与房内侧图互为左右镜像（B1 标牌、警示三角、门楣黄黑警示条全部左右翻转），水平翻转后平均通道差 1.59 → 0.96/255（v004 基线翻转前后 2.75→2.73，毫无变化——素背板翻转等于没翻）；门洞近景仍通透、仰视门楣底面仍在。接线：**未改任何运行时代码**——门洞净空 2.2×2.5 与 TowerGeometry3D.DOOR_CLEAR_WIDTH_M / DOOR_CLEAR_HEIGHT_M 及 DungeonRoom3D._add_tower_wall_collision() 的脚本碰撞代理逐值一致，碰撞代理与门洞口径无需改动；节点名前缀 Imported_DoorWall5M_* 仍被基地99层设施门墙（ENV-BASE99-WALL-DOOR-5X12，自身包络 1.051m 深）共用，核对须按 asset_id 过滤。 2026-10-12：可视本体被复用 —— 远征关卡01 的门墙组件 ENV-BATTLE-COMMON-WALL-DOOR-5M（wall_door_5m_root_top3d.tscn）把可视 GLB 换成本件，使该关 13 个房间场景（含入口安全房）共 14 个门位统一为本件重装甲外观；结构阻挡仍由该战局组件自持的 3×BoxShape3D 提供，本件在此纯作视觉来源。
A58: ENV-TOWER-STAIRWELL-GENERIC-12M | B58: 楼梯B（99→98通用） | C58: 场景 | D58: room_kit | E58: stairwell_generic_12m | F58: stairwell_generic_12m | G58: ENV-TOWER-DESCENT-KIT-3D | H58: 俯视3D | I58: godot_runtime | J58: 正式美术已接入 | K58: 正式美术已接入 | L58: P0 | M58: v002 | N58: Blender v021；GLB/PackedScene v002；15×30m占地；12m层差；共享色盘；3网格运行优化；1个Walkable与1个EnclosureWall碰撞源 | O58: assets/art/environments/tower_descent_3d/components/env_tower_stairwell_generic_12m_top3d.glb | P58: art_source/environments/tower_descent_3d/source/stairs_12m/stairwell_art_v021/env_tower_stairwell_dual_art_source_v021.blend；运行包装：assets/art/environments/tower_descent_3d/runtime/env_tower_stairwell_generic_12m/env_tower_stairwell_generic_12m_root_top3d_v002.tscn；导出脚本：art_source/environments/tower_descent_3d/source/stairs_12m/stairwell_art_v021/qa/export_godot_v002.py | Q58: 楼梯B;Stair_B;通用楼梯;99到98;12米层高;Blender直出 | R58: =LOWER(TRIM(C58)&"|"&TRIM(D58)&"|"&TRIM(E58)&"|"&TRIM(F58)&"|"&TRIM(H58)&"|"&TRIM(I58)) | S58: =IF(COUNTIF($R$6:$R$928,R58)>1,"重复","唯一") | T58: 1865f6e89650640f12e1234b547f726d983c94fce215e74027f7489b43fd33dd | U58: Codex | V58: 46279 | W58: 用户手工Blender模型 | X58: — | Y58: 2026-09-15：楼梯B（99→98）正式美术由v021源导出为GLB v002，经共享色盘后处理导入PackedScene v002并替换TowerDescent3D临时资产。运行时3个MeshInstance3D，碰撞为1个Walkable与1个EnclosureWall；组件、流程及Forward+真实渲染验收通过。v001保留回滚。
A59: ENV-TOWER-STAIRWELL-ROOFTOP-12M | B59: 楼梯A（100→99天台） | C59: 场景 | D59: room_kit | E59: stairwell_rooftop_12m | F59: stairwell_rooftop_12m | G59: ENV-TOWER-DESCENT-KIT-3D | H59: 俯视3D | I59: godot_runtime | J59: 正式美术已接入 | K59: 正式美术已接入 | L59: P0 | M59: v002 | N59: Blender v021；GLB/PackedScene v002；15×30m占地；12m层差；共享色盘；3网格运行优化；1个Walkable与1个EnclosureWall碰撞源 | O59: assets/art/environments/tower_descent_3d/components/env_tower_stairwell_rooftop_12m_top3d.glb | P59: art_source/environments/tower_descent_3d/source/stairs_12m/stairwell_art_v021/env_tower_stairwell_dual_art_source_v021.blend；运行包装：assets/art/environments/tower_descent_3d/runtime/env_tower_stairwell_rooftop_12m/env_tower_stairwell_rooftop_12m_root_top3d_v002.tscn；导出脚本：art_source/environments/tower_descent_3d/source/stairs_12m/stairwell_art_v021/qa/export_godot_v002.py | Q59: 楼梯A;Stair_A;天台楼梯;100到99;12米层高;Blender直出 | R59: =LOWER(TRIM(C59)&"|"&TRIM(D59)&"|"&TRIM(E59)&"|"&TRIM(F59)&"|"&TRIM(H59)&"|"&TRIM(I59)) | S59: =IF(COUNTIF($R$6:$R$928,R59)>1,"重复","唯一") | T59: ab0d7e543ab36d5798d0cfa35c9eb824ae9a53edda3cd8b1a4ab090708ecffdf | U59: Codex | V59: 46279 | W59: 用户手工Blender模型 | X59: — | Y59: 2026-09-15：楼梯A（100→99）正式美术由v021源导出为GLB v002，经共享色盘后处理导入PackedScene v002并替换TowerDescent3D临时资产。运行时3个MeshInstance3D，碰撞为1个Walkable与1个EnclosureWall；组件、流程及Forward+真实渲染验收通过。v001保留回滚。
A60: ENV-BOSS-ARENA-ARCHIVE-95 | B60: 档案回廊竞技场组件 | C60: 场景 | D60: boss_arena | E60: arena_archive_95 | F60: dressing | H60: Top3D | I60: default / 高模流式 | J60: 95层Boss场地 | K60: 已完成 | L60: P0 | M60: v001 | N60: GLB；8组柱体与掩体 | O60: assets/art/environments/boss_arenas_v01/env_boss_arena_archive_95_top3d_v001.glb | P60: art_source/design/blender/bosses_v01/env_boss_arena_archive_95_top3d_v001.blend; src/world3d/DungeonRoom3D.gd | Q60: 档案竞技场; 95F; arena; cover | R60: =LOWER(TRIM(C60)&"|"&TRIM(D60)&"|"&TRIM(E60)&"|"&TRIM(F60)&"|"&TRIM(H60)&"|"&TRIM(I60)) | S60: =IF(COUNTIF($R$6:$R$928,R60)>1,"重复","唯一") | T60: ff10424d3c6898385aad9eaf0de32b644eb282a567b36aa422c4dd9decff7d69 | U60: Codex | V60: 46247 | W60: 原创程序建模 | X60: — | Y60: 高模装饰可流式；对应8组碰撞掩体。永久楼板/关卡墙/外墙不隐藏。 2026-08-30 AST-01规范化（原制作状态：正式美术已接入）
A61: ENV-BOSS-ARENA-FURNACE-90 | B61: 熔炉竞技场组件 | C61: 场景 | D61: boss_arena | E61: arena_furnace_90 | F61: dressing | H61: Top3D | I61: default / 高模流式 | J61: 90层Boss场地 | K61: 已完成 | L61: P0 | M61: v001 | N61: GLB；熔炉核心与6组掩体 | O61: assets/art/environments/boss_arenas_v01/env_boss_arena_furnace_90_top3d_v001.glb | P61: art_source/design/blender/bosses_v01/env_boss_arena_furnace_90_top3d_v001.blend; src/world3d/DungeonRoom3D.gd | Q61: 熔炉竞技场; 90F; arena; cover | R61: =LOWER(TRIM(C61)&"|"&TRIM(D61)&"|"&TRIM(E61)&"|"&TRIM(F61)&"|"&TRIM(H61)&"|"&TRIM(I61)) | S61: =IF(COUNTIF($R$6:$R$928,R61)>1,"重复","唯一") | T61: d376fba6190728dc8bf50664f4082b954a077fa96799d68f118ead53cb7aa63c | U61: Codex | V61: 46247 | W61: 原创程序建模 | X61: — | Y61: 高模装饰可流式；对应6组碰撞掩体。永久楼板/关卡墙/外墙不隐藏。 2026-08-30 AST-01规范化（原制作状态：正式美术已接入）
A62: ENV-BOSS-ARENA-CHOIR-85 | B62: 共鸣合唱竞技场组件 | C62: 场景 | D62: boss_arena | E62: arena_choir_85 | F62: dressing | H62: Top3D | I62: default / 高模流式 | J62: 85层Boss场地 | K62: 已完成 | L62: P0 | M62: v001 | N62: GLB；共鸣环与5组掩体 | O62: assets/art/environments/boss_arenas_v01/env_boss_arena_choir_85_top3d_v001.glb | P62: art_source/design/blender/bosses_v01/env_boss_arena_choir_85_top3d_v001.blend; src/world3d/DungeonRoom3D.gd | Q62: 合唱竞技场; 85F; arena; cover | R62: =LOWER(TRIM(C62)&"|"&TRIM(D62)&"|"&TRIM(E62)&"|"&TRIM(F62)&"|"&TRIM(H62)&"|"&TRIM(I62)) | S62: =IF(COUNTIF($R$6:$R$928,R62)>1,"重复","唯一") | T62: d2aae2a6fd2f091d5cb9c05d103a4512179bdc6ef0e9d77ba5834efc723eba3a | U62: Codex | V62: 46247 | W62: 原创程序建模 | X62: — | Y62: 高模装饰可流式；对应5组碰撞掩体。永久楼板/关卡墙/外墙不隐藏。 2026-08-30 AST-01规范化（原制作状态：正式美术已接入）
A63: ENV-BASE99-MODULAR-KIT-3D | B63: 基地99层模块化房间3D套件 | C63: 场景 | D63: environment_kit_3d | E63: base99_modular_room | F63: root_3d | G63: ENV-TOWER-DESCENT-KIT-3D | H63: Top3D / local -Z 正面 | I63: default / modular | J63: 99层基地专属环境模块 | K63: 弃用 | L63: P0 | M63: v001 | N63: 5m网格；30×30m房间；9m层高；9个稳定Prefab | P63: 聚合目录条目，不属于独立 PackedScene；由布局与 BPK 子项登记 | Q63: 基地99层;模块化房间;5米网格;9个Prefab;GLB;PackedScene | R63: =LOWER(TRIM(C63)&"|"&TRIM(D63)&"|"&TRIM(E63)&"|"&TRIM(F63)&"|"&TRIM(H63)&"|"&TRIM(I63)) | S63: =IF(COUNTIF($R$6:$R$928,R63)>1,"重复","唯一") | U63: Codex | V63: 46252 | W63: 用户自制Blender资产 | X63: — | Y63: 九件模块已接入；99层外圈14段普通墙+2段门墙，窗墙仅供100层；楼板/楼梯改由可编辑布局Prefab持有碰撞。 2026-08-30 AST-01规范化（原制作状态：正式美术已接入）
A64: ENV-BASE99-WALL-PLAIN-5X12 | B64: 基地99层普通墙体5×12米 | C64: 场景 | D64: environment_module_3d | E64: base99_wall_plain_5x12 | F64: wall_plain | G64: ENV-BASE99-MODULAR-KIT-3D | H64: Top3D / local -Z 正面 | I64: default / visual_only | J64: 99层基地模块化结构 | K64: 已完成 | L64: P0 | M64: v002 | N64: 5×12×0.36m逻辑外廓；11.9m可见墙；底边中心原点；无内置碰撞 | O64: assets/art/environments/base_facility_3d/runtime/env_base99_wall_plain_5x12/env_base99_wall_plain_5x12_root_top3d.tscn | P64: art_source/environments/base_facility_3d/source/wall_height12/env_base99_wall_plain_5x12_source_v002.blend; scripts/blender/extend_wall_glb_to_11p9_v001.py; src/world3d/DungeonRoom3D.gd | Q64: 基地99层普通墙体5×12米;base99;11.9米可见墙;PaletteUV | R64: =LOWER(TRIM(C64)&"|"&TRIM(D64)&"|"&TRIM(E64)&"|"&TRIM(F64)&"|"&TRIM(H64)&"|"&TRIM(I64)) | S64: =IF(COUNTIF($R$6:$R$928,R64)>1,"重复","唯一") | T64: 6394e2a471b5bd0feac0a3390c5fbeb4a6cbd1c9d2576a4ad67c4a1dd487a817 | U64: Codex | V64: 46277 | W64: 用户自制Blender资产 | X64: — | Y64: 99层运行时14段普通墙；不放窗墙；0.30m结构碰撞归DungeonRoom3D；模型参与挡光与投影。 2026-08-30 AST-01规范化（原制作状态：正式美术已接入） 2026-08-30 AST-02：合法内容更新；文件为Git已跟踪且修改时间不早于原台账日期；验收：verify_base99_floor_player_collision_flow；verify_base_facility_interaction_zones；SHA 2e7d0d9e6d4f→223079d316dd。
A65: ENV-BASE99-WALL-DOOR-5X12 | B65: 基地99层带门墙体5×12米 | C65: 场景 | D65: environment_module_3d | E65: base99_wall_door_5x12 | F65: wall_door | G65: ENV-BASE99-MODULAR-KIT-3D | H65: Top3D / local -Z 正面 | I65: default / visual_only | J65: 99层基地模块化结构 | K65: 已完成 | L65: P0 | M65: v004 | N65: 5×12×1.1712m逻辑外廓；11.9m可见墙；2.2×2.5m门洞 | O65: assets/art/environments/base_facility_3d/runtime/env_base99_wall_door_5x12/env_base99_wall_door_5x12_root_top3d.tscn | P65: art_source/environments/base_facility_3d/source/wall_height12/env_base99_wall_door_5x12_source_v004.blend; scripts/blender/extend_wall_glb_to_11p9_v001.py; src/world3d/DungeonRoom3D.gd | Q65: 基地99层带门墙体5×12米;base99;11.9米可见墙;2.2×2.5米门洞 | R65: =LOWER(TRIM(C65)&"|"&TRIM(D65)&"|"&TRIM(E65)&"|"&TRIM(F65)&"|"&TRIM(H65)&"|"&TRIM(I65)) | S65: =IF(COUNTIF($R$6:$R$928,R65)>1,"重复","唯一") | T65: f64d8aa2f7e39a5250aba1344ffe3ca3a3f4b0bbfd53d5e17a8e44dbb4caa4ab | U65: Codex | V65: 46277 | W65: 用户自制Blender资产 | X65: — | Y65: 运行时2段独立门墙；墙体模型投影；门扇、门状态机、提示、碰撞和寻路仍由Godot原系统拥有。 2026-08-30 AST-01规范化（原制作状态：正式美术已接入） 2026-08-30 AST-02：合法内容更新；文件为Git已跟踪且修改时间不早于原台账日期；验收：verify_base99_floor_player_collision_flow；verify_base_facility_interaction_zones；SHA 156222718efe→4135557211e0。
A66: ENV-BASE99-FLOOR-PLAIN-5M | B66: 基地99层普通地板5×5米 | C66: 场景 | D66: environment_module_3d | E66: base99_floor_plain_5m | F66: floor_plain | G66: ENV-BASE99-MODULAR-KIT-3D | H66: Top3D / local -Z 正面 | I66: default / visual_only | J66: 99层基地模块化结构 | K66: 已完成 | L66: P0 | M66: v001 | N66: 5×5×0.30m；平面中心/结构底面原点 | O66: assets/art/environments/base_facility_3d/runtime/env_base99_floor_plain_5m/env_base99_floor_plain_5m_root_top3d.tscn | P66: ../ShellStorm2-backup/2026-10-11_slimming/original_tree/art_source/environments/base_facility_3d/source/env_base99_modular_room/env_base99_modular_room_assets_clean_v001.blend; scripts/blender/export_base99_runtime_modules.py; src/world3d/DungeonRoom3D.gd | Q66: 基地99层普通地板5×5米;base99;PaletteUV;cast_and_receive | R66: =LOWER(TRIM(C66)&"|"&TRIM(D66)&"|"&TRIM(E66)&"|"&TRIM(F66)&"|"&TRIM(H66)&"|"&TRIM(I66)) | S66: =IF(COUNTIF($R$6:$R$928,R66)>1,"重复","唯一") | T66: 79fb968ac36150a07be25dabb1b9a01cf0fb687e641d1c97c54dd97f9c63ee06 | U66: Codex | V66: 46264 | W66: 用户自制Blender资产 | X66: — | Y66: 运行时18块；承重仍由TowerFloorStage地面碰撞负责；模型参与挡光与投影。 2026-08-30 AST-01规范化（原制作状态：正式美术已接入） 2026-08-30 AST-02：合法内容更新；文件为Git已跟踪且修改时间不早于原台账日期；验收：verify_base99_floor_player_collision_flow；verify_base_facility_interaction_zones；SHA 22085ad0a0af→7d3c4a543b46。
A67: ENV-BASE99-FLOOR-RIVET-5M | B67: 基地99层铆钉铁皮带地板5×5米 | C67: 场景 | D67: environment_module_3d | E67: base99_floor_rivet_5m | F67: floor_rivet | G67: ENV-BASE99-MODULAR-KIT-3D | H67: Top3D / local -Z 正面 | I67: default / visual_only | J67: 99层基地模块化结构 | K67: 已完成 | L67: P0 | M67: v001 | N67: 5×5×0.395m视觉外廓；0.30m结构板+0.095m装饰凸起 | O67: assets/art/environments/base_facility_3d/runtime/env_base99_floor_rivet_5m/env_base99_floor_rivet_5m_root_top3d.tscn | P67: ../ShellStorm2-backup/2026-10-11_slimming/original_tree/art_source/environments/base_facility_3d/source/env_base99_modular_room/env_base99_modular_room_assets_clean_v001.blend; scripts/blender/export_base99_runtime_modules.py; src/world3d/DungeonRoom3D.gd | Q67: 基地99层铆钉铁皮带地板5×5米;base99;PaletteUV;cast_and_receive | R67: =LOWER(TRIM(C67)&"|"&TRIM(D67)&"|"&TRIM(E67)&"|"&TRIM(F67)&"|"&TRIM(H67)&"|"&TRIM(I67)) | S67: =IF(COUNTIF($R$6:$R$928,R67)>1,"重复","唯一") | T67: 85845249e764b1062d9f884b5e388dea99f5edeb46015c65d5b3da68cfbf19e3 | U67: Codex | V67: 46264 | W67: 用户自制Blender资产 | X67: — | Y67: 运行时18块，与普通基地地板棋盘式互用；承重碰撞不变；模型参与挡光与投影。 2026-08-30 AST-01规范化（原制作状态：正式美术已接入） 2026-08-30 AST-02：合法内容更新；文件为Git已跟踪且修改时间不早于原台账日期；验收：verify_base99_floor_player_collision_flow；verify_base_facility_interaction_zones；SHA 14fd4be6488e→bc849c71619f。
A68: ENV-BASE99-ART-LAYOUT-3D | B68: 基地区美术 | C68: 场景 | D68: environment_module_3d | E68: base_facility_art_layout | F68: root_3d | G68: ENV-BASE99-MODULAR-KIT-3D | H68: Top3D / local -Z 正面 | I68: default / prefab | J68: Blocks/Base/Art；99F基地区 | K68: 原型已接入 | L68: P1 | M68: v002 | N68: Godot PackedScene；根=Node3D；碰撞节点=0 | O68: assets/art/environments/tower_zones/base/runtime/zone_base.tscn | P68: art_source/design/blender/base_facility_layout/source/base_facility_runtime_layout_hq_v026.blend; art_source/design/blender/base_facility_layout/source/base_facility_runtime_layout_hq_v026.godot.json; assets/art/environments/tower_zones/base/runtime/zone_base_v002.tscn; docs/v0.1/05.1_关卡区块设计.md | Q68: 基地区;Base;Art;99F;基地美术;Prefab;场景区块 | R68: =LOWER(TRIM(C68)&"|"&TRIM(D68)&"|"&TRIM(E68)&"|"&TRIM(F68)&"|"&TRIM(H68)&"|"&TRIM(I68)) | S68: =IF(COUNTIF($R$6:$R$928,R68)>1,"重复","唯一") | T68: 4ef886885f5f9cd3e8d3e586d4112e27ddea4001acf18162cc58236f9be94ceb | U68: Codex | V68: 46278 | W68: 项目现有Godot资产 | X68: — | Y68: 主场景可编辑布局；现含8个设施及楼板、L梯、外门小梯三个结构Prefab，位置旋转可在tscn直接调整。 2026-08-30 AST-02：合法内容更新；文件为Git已跟踪且修改时间不早于原台账日期；验收：verify_base99_floor_player_collision_flow；verify_base_facility_interaction_zones；SHA 2ecff00457fc→9d7f7b7d6699。 2026-09-02 HQ-v003：新增30×30m高品质Blender微缩基地母版；20×10m北侧6m阁楼、15×30m东西主通道地面净空、南侧仓储/能源/供水区和240帧循环动效。复用现有墙/地板身份，设施作为独立组件重制；4个共享材质，275002/275002面PaletteUV严格验收通过。Blend SHA256=614039f9aae4。当前仅为Blender美术母版，未替换Godot运行时TSCN、GLB、碰撞或交互。 2026-09-04：已挂载 assets/art/environments/base_facility_3d/runtime/env_base99_floor_visuals_v017/env_base99_floor_visuals_root_top3d_v001.tscn。基础地砖维持18块 ENV-BASE99-FLOOR-PLAIN-5M 与18块 ENV-BASE99-FLOOR-RIVET-5M 的棋盘格复用；V017新增一层深化覆层与二层面层，均无玩法碰撞。 2026-09-04 V020：地板表现装配已切换至 env_base99_floor_visuals_v020/env_base99_floor_visuals_root_top3d_v002.tscn；源文件 base_facility_runtime_layout_hq_v020.blend（Blender v020）；V017输出保留回滚。 2026-09-04 V021：完整新地板装配已切换至 assets/art/environments/base_facility_3d/runtime/env_base99_floor_visuals_v021/env_base99_floor_visuals_root_top3d_v003.tscn；旧DungeonRoom3D普通/铆钉MultiMesh视觉不再生成，FloorSupport碰撞规格保持不变。 2026-09-06：19个既有GLB补齐共享色盘导入脚本及禁止内嵌图参数；基地中央主灯改为中性冷白，保留1盏投影灯及原开关。122模型353材质共享色盘专项通过。 2026-09-06 灯具表现：BaseFixtureGlow3D 为9组霓虹/灯具提供分级HDR自发光，并为BASE CAMP、GOOD VIBES、STAY CURIOUS、床头灯、梯下壁灯、东侧吊灯和仓库吊灯增加7盏环境层局部灯；其余设备发光面保留轻微微光。共53个运行时发光材质，继续复用共享色盘与原UV；冷色适度去饱和，暖灯保留橙色温度，无阴影且距离淡出。验证 verify_base_fixture_glow，源Blend与GLB未改动。 2026-09-13 WORLD-BLOCKS r1：运行入口迁入 tower_zones/base/runtime/zone_base_v002.tscn，场景树为 Blocks/Base/Art。v026 Blend保持原字节，Godot映射记录在同目录sidecar；未重新导入GLB。
A69: ENV-TOWER-CORNER-L-5M | B69: 塔楼L型转角5米 | C69: 场景 | D69: room_kit | E69: tower_descent | F69: corner_l_5m | G69: ENV-TOWER-DESCENT-KIT-3D | H69: 俯视3D | I69: godot_runtime | J69: 场景通用组件 | K69: 原型已接入 | L69: P0 | M69: v001 | N69: GLB / 可视包络 5.15×11.9×5.15m（原点=转角，两臂向 +X/-Z 伸出；两臂装饰面都朝房内：长臂 Godot -Z、短臂 Godot +X）/ 结构占地 5×11.9×5m / 单 Mesh 三材质角色 / 自带两臂碰撞 | O69: assets/art/environments/tower_descent_3d/components/env_tower_corner_l_5m_top3d.glb | P69: art_source/environments/tower_descent_3d/source/corner_l_5m/export_env_tower_corner_l_5m_v001.py; assets/art/props/dungeon_3d/prp_corner_l_5m.tscn; src/world3d/DungeonRoom3D.gd; ../ShellStorm2-backup/2026-10-11_art_source_split/original_tree/assets/art/props/dungeon_3d/qa/verify_tower_module_prefabs.gd | Q69: 塔楼L型转角5米;12米逻辑墙;11.9米可见墙;PaletteUV;L墙角;corner_l;bottom_corner | R69: =LOWER(TRIM(C69)&"|"&TRIM(D69)&"|"&TRIM(E69)&"|"&TRIM(F69)&"|"&TRIM(H69)&"|"&TRIM(I69)) | S69: =IF(COUNTIF($R$6:$R$928,R69)>1,"重复","唯一") | T69: 451ba73e82aa38fa4bf91e8421496b09488cd202c453aee2c749619146031c71 | U69: Codex | V69: 46284 | W69: Blender 派生（由两份通用墙刚性拼成） | X69: — | Y69: 2026-08-18项目扫描补登记；按Prefab独立身份管理；根节点=PrpCornerL5m(Node3D)；2026-08-18扫描补登记资产主表 2026-08-30 AST-03：asset_guard PASS；生产路径 assets/art/props/dungeon_3d/prp_corner_L_5m.tscn → assets/art/props/dungeon_3d/prp_corner_l_5m_v001.tscn；稳定 AssetID 不变；代码引用已迁移；验收 verify_rooftop_railing / verify_rooftop_32x32_contract / verify_door_passability / verify_full_3d_game_flow。 2026-09-19：可视本体换成塔楼 A 套正式美术（grep 关键词：bottom_corner / CORNER_L_V001）。稳定 AssetID 不变，仍 ENV-TOWER-CORNER-L-5M；prefab 仍是 assets/art/props/dungeon_3d/prp_corner_l_5m.tscn（DungeonRoom3D.TOWER_CORNER_L_PREFAB，非 FACILITY 房间的四个转角）。本次把原来的程序化 BoxMesh 占位换成 A 套正式 GLB，做法是**由两份同一通用墙刚性拼成**而非单独建模：取自与实心墙同源的包 battle/source/common_components/v007（包 wall_standard_5m_通用包 / 根件 ROOT_wall_standard_5m_通用组件）。摆位：长臂 T(+2.5,0,0) 沿 +X 覆盖 0..5m，短臂 T(0,+2.5,0)@Rz(90°) 沿 -Z 覆盖 -5..0m；两臂先在烘焙坐标系内各自完成 triangulate→删朝下面，再刚性复制两次，逐臂断言 5319 三角面 == 通用墙、L 合计 10638 == 2×墙，因此与直墙逐面一致。装饰面朝外（长臂 Godot +Z、短臂 Godot +X）。原点契约由 bottom_center 变为 bottom_corner（原点=转角，两臂向 +X/-Z 伸出）：DungeonRoom3D._spawn_room_corner() 直接摆到房间角点再按 NW/NE/SW/SE 旋转，把几何重新居中会让所有房间角错位；统一契约门禁 verify_tower_module_prefabs.gd 为此新增 bottom_corner 识别。本件是六件通用物体里唯一自带碰撞的件（visual_only=false / collision_owner=self）：prefab 内两个 StaticBody3D（WallCollisionLong / WallCollisionShort，12m 高 0.30m 厚）的节点名是 _configure_corner_camera_collisions() 的镜头下压契约，改名即回归。保留美术自带共享色盘（01 精工金属_紫色骨架 / 02 细腻哑光_青绿大面 / 04 柔和自发光_UI灯光；空槽 03 已丢）。版本提法：本行 M 由 v004 改为 v001 —— 旧值 v004 属于 base_facility(99F) 那条派生线，本件的稳定 GLB 改走 tower_descent_3d/source/corner_l_5m/ 的 v001 线，与实心墙 v004 / 门扇 v001 同口径。原登记的 O/P 指向 base_facility_3d 的 env_base99_corner_l_5m（99F 那条线，运行时由 BASE99_CORNER_L_PREFAB 承担 FACILITY 房间），与塔楼 prefab 无关，本次一并纠正。注意：新生成 GLB 的 .import 不会自动绑定 scene_facility_shared_palette_post_import.gd，缺绑定会渲染成白板且不触发任何 *_OK 门禁，需手工绑定。 2026-09-19 同日朝向修正（grep 关键词：ARM_FACING_GODOT / CORNER_ARM_FACING_WRONG）：首版长臂是纯平移 T(+2.5,0,0)、无偏航，于是保留了烘焙后朝 Godot +Z 的装饰面——那是 L 的外侧，玩家在房间里面对长臂时看到的是平整的结构背；短臂当时是对的（+X）。根因是「哪一侧算房间内」被写错：两臂沿 +X 与 -Z 伸出，房间内侧是两臂之间的凹象限（+X/-Z），而 prefab 注释与探针当时标成 -X/-Z，朝向断言也照错标号写成「长臂装饰面在 +Z」，于是自洽放行。正确口径只认运行时：_spawn_room_corner()（两臂从角点沿房间两条边指向房内）与 _build_corner_aware_wall_run()（南墙 rotation_y=PI、西墙 +PI/2，装饰面永远朝房内）。修正：长臂补 Rz(+180°)（与南墙同款；短臂不变）；派生脚本新增 ARM_FACING_GODOT 逐臂断言——拿「装饰面凸 0.3175 / 结构背 0.15」这条美术不对称当朝向指纹，逐臂比对自身 AABB，任一条反了即 CORNER_ARM_FACING_WRONG（既有包络/面数/材质/原点四类断言都抓不到朝向）；prefab origin_note 与 probe_corner_l_visual 机位改成「房内侧 = 两臂之间的凹象限（+X/-Z）」。重导出实测：两臂仍各 5319 面、L 合计 10638（「与直墙逐面一致」未被破坏）；可视包络 5.15×11.9×5.15、最小角 (-0.15, 0, -5.0)（z_max 由 0.3175 收成 0.15：装饰面朝内、外侧只剩结构背）；PREFAB_CONTRACT_OK count=6（0 ERROR）；CORNER_L_VISUAL_OK captured=4；逐面细节能量：长臂房内面 4.99 vs 外面 1.54，pair 图对照直墙 3.72 / L 长臂 3.97。本行 T 列 GLB 哈希随之二次改写（297ffb52… -> 451ba73e…）：路径与版本串仍是 v001（同一份资产的当日修正，不是新版本），但哈希变了，凡引用哈希处须同批更新。判据固化（2026-09-19 同日，第二轮）：上述逐面细节能量已从临时对照脚本搬进画面探针 probe_corner_l_visual.gd —— 新增 FACE_GAUGES + _measure_faces()：把长臂装饰面（房内侧 z=-0.3175）与结构背（外侧 z=+0.15）的世界四角用 Camera3D.unproject_position() 投影到屏幕取外接矩形裁出来，量高通能量（积分图盒式模糊半径 6，平均 |灰度-邻域均值|，与离线脚本同口径）；判据 room/outer >= FACE_ENERGY_RATIO_MIN = 1.6，机内实测 3.220（0.02099 / 0.00652，多轮重跑数值一致）。反向对照（把两个取样面互换机位）得 0.149 -> exit 1 并报「长臂装饰面疑似朝外」，判别力约 21x —— 即该判据不是「怎么都绿」的摆设。这是本件唯一能抓住「面朝反」的自动判据：包络 / 面数 / 材质角色 / 原点约定四类断言对朝向缺陷全部全绿。
A70: ENV-TOWER-CORNER-L-PARAPET-5M | B70: 塔楼L型女儿墙转角5米 | C70: 场景 | D70: environment_module_3d | E70: corner_L_parapet_5m | F70: root_3d | G70: ENV-TOWER-DESCENT-KIT-3D | H70: Top3D / local -Z 正面 | I70: default / prefab | J70: 场景通用组件 | K70: 程序占位 | L70: P1 | M70: v001 | N70: Godot PackedScene；根=Node3D；碰撞节点=2 | O70: assets/art/props/dungeon_3d/prp_corner_l_parapet_5m.tscn | P70: assets/art/3D模型资产目录与命名规范.md | Q70: 塔楼L型女儿墙转角5米;3D;Prefab;场景通用组件;corner_L_parapet_5m | R70: =LOWER(TRIM(C70)&"|"&TRIM(D70)&"|"&TRIM(E70)&"|"&TRIM(F70)&"|"&TRIM(H70)&"|"&TRIM(I70)) | S70: =IF(COUNTIF($R$6:$R$928,R70)>1,"重复","唯一") | T70: e08fcac94b8fac78352e62b5566215fa0a01baa19fcd76a910d82b4d462ff884 | U70: Codex | V70: 46264 | W70: 项目现有Godot资产 | X70: — | Y70: 2026-08-18项目扫描补登记；按Prefab独立身份管理；根节点=PrpCornerLParapet5m(Node3D)；2026-08-18扫描补登记资产主表 2026-08-30 AST-03：asset_guard PASS；生产路径 assets/art/props/dungeon_3d/prp_corner_L_parapet_5m.tscn → assets/art/props/dungeon_3d/prp_corner_l_parapet_5m_v001.tscn；稳定 AssetID 不变；代码引用已迁移；验收 verify_rooftop_railing / verify_rooftop_32x32_contract / verify_door_passability / verify_full_3d_game_flow。
A71: ENV-TOWER-CORNER-T-5M | B71: 塔楼T型转角5米 | C71: 场景 | D71: environment_module_3d | E71: corner_T_5m | F71: root_3d | G71: ENV-TOWER-DESCENT-KIT-3D | H71: Top3D / local -Z 正面 | I71: default / prefab | J71: 场景通用组件 | K71: 程序占位 | L71: P1 | M71: v001 | N71: Godot PackedScene；根=Node3D；碰撞节点=3 | O71: assets/art/props/dungeon_3d/prp_corner_t_5m.tscn | P71: assets/art/3D模型资产目录与命名规范.md | Q71: 塔楼T型转角5米;3D;Prefab;场景通用组件;corner_T_5m | R71: =LOWER(TRIM(C71)&"|"&TRIM(D71)&"|"&TRIM(E71)&"|"&TRIM(F71)&"|"&TRIM(H71)&"|"&TRIM(I71)) | S71: =IF(COUNTIF($R$6:$R$928,R71)>1,"重复","唯一") | T71: 38be070ae70cf35c83d3e817b62e21428f7dc97548a10b4907e30064df3276e7 | U71: Codex | V71: 46264 | W71: 项目现有Godot资产 | X71: — | Y71: 2026-08-18项目扫描补登记；按Prefab独立身份管理；根节点=PrpCornerT5m(Node3D)；2026-08-18扫描补登记资产主表 2026-08-30 AST-03：asset_guard PASS；生产路径 assets/art/props/dungeon_3d/prp_corner_T_5m.tscn → assets/art/props/dungeon_3d/prp_corner_t_5m_v001.tscn；稳定 AssetID 不变；代码引用已迁移；验收 verify_rooftop_railing / verify_rooftop_32x32_contract / verify_door_passability / verify_full_3d_game_flow。
A72: ENV-TOWER-CORNER-X-5M | B72: 塔楼十字转角5米 | C72: 场景 | D72: environment_module_3d | E72: corner_X_5m | F72: root_3d | G72: ENV-TOWER-DESCENT-KIT-3D | H72: Top3D / local -Z 正面 | I72: default / prefab | J72: 场景通用组件 | K72: 程序占位 | L72: P1 | M72: v001 | N72: Godot PackedScene；根=Node3D；碰撞节点=4 | O72: assets/art/props/dungeon_3d/prp_corner_x_5m.tscn | P72: assets/art/3D模型资产目录与命名规范.md | Q72: 塔楼十字转角5米;3D;Prefab;场景通用组件;corner_X_5m | R72: =LOWER(TRIM(C72)&"|"&TRIM(D72)&"|"&TRIM(E72)&"|"&TRIM(F72)&"|"&TRIM(H72)&"|"&TRIM(I72)) | S72: =IF(COUNTIF($R$6:$R$928,R72)>1,"重复","唯一") | T72: 8f83e7591e65997f404f7137b11f9b7cf02dc962af97384831061a2a3242ff9c | U72: Codex | V72: 46264 | W72: 项目现有Godot资产 | X72: — | Y72: 2026-08-18项目扫描补登记；按Prefab独立身份管理；根节点=PrpCornerX5m(Node3D)；2026-08-18扫描补登记资产主表 2026-08-30 AST-03：asset_guard PASS；生产路径 assets/art/props/dungeon_3d/prp_corner_X_5m.tscn → assets/art/props/dungeon_3d/prp_corner_x_5m_v001.tscn；稳定 AssetID 不变；代码引用已迁移；验收 verify_rooftop_railing / verify_rooftop_32x32_contract / verify_door_passability / verify_full_3d_game_flow。
A73: ENV-DUNGEON-CORRIDOR-CEILING-SEGMENT | B73: 地牢走廊天花段 | C73: 场景 | D73: environment_module_3d | E73: corridor_ceiling_segment | F73: root_3d | G73: ENV-DUNGEON-RUNTIME-3D | H73: Top3D / local -Z 正面 | I73: default / prefab | J73: 场景通用组件 | K73: 程序占位 | L73: P1 | M73: v001 | N73: Godot PackedScene；根=Node3D；碰撞节点=1 | O73: assets/art/props/dungeon_3d/prp_corridor_ceiling_segment.tscn | P73: assets/art/3D模型资产目录与命名规范.md | Q73: 地牢走廊天花段;3D;Prefab;场景通用组件;corridor_ceiling_segment | R73: =LOWER(TRIM(C73)&"|"&TRIM(D73)&"|"&TRIM(E73)&"|"&TRIM(F73)&"|"&TRIM(H73)&"|"&TRIM(I73)) | S73: =IF(COUNTIF($R$6:$R$928,R73)>1,"重复","唯一") | T73: de6c149315d394d21427445145cbac33ef5652db02b18b2d0080748dd0f82ff3 | U73: Codex | V73: 46264 | W73: 项目现有Godot资产 | X73: — | Y73: 2026-08-18项目扫描补登记；按Prefab独立身份管理；根节点=PrpCorridorCeilingSegment(Node3D)；2026-08-18扫描补登记资产主表 2026-08-30 AST-03：asset_guard PASS；生产路径 assets/art/props/dungeon_3d/prp_corridor_ceiling_segment.tscn → assets/art/props/dungeon_3d/prp_corridor_ceiling_segment_v001.tscn；稳定 AssetID 不变；代码引用已迁移；验收 verify_rooftop_railing / verify_rooftop_32x32_contract / verify_door_passability / verify_full_3d_game_flow。
A74: ENV-DUNGEON-CORRIDOR-FLOOR-SEGMENT | B74: 地牢走廊地板段 | C74: 场景 | D74: environment_module_3d | E74: corridor_floor_segment | F74: root_3d | G74: ENV-DUNGEON-RUNTIME-3D | H74: Top3D / local -Z 正面 | I74: default / prefab | J74: 场景通用组件 | K74: 程序占位 | L74: P1 | M74: v001 | N74: Godot PackedScene；根=Node3D；碰撞节点=1 | O74: assets/art/props/dungeon_3d/prp_corridor_floor_segment.tscn | P74: assets/art/3D模型资产目录与命名规范.md | Q74: 地牢走廊地板段;3D;Prefab;场景通用组件;corridor_floor_segment | R74: =LOWER(TRIM(C74)&"|"&TRIM(D74)&"|"&TRIM(E74)&"|"&TRIM(F74)&"|"&TRIM(H74)&"|"&TRIM(I74)) | S74: =IF(COUNTIF($R$6:$R$928,R74)>1,"重复","唯一") | T74: 89457606145ca7caa6db48cdf9362a670ce296fd191d8dc67ca8a704c7a3ad31 | U74: Codex | V74: 46264 | W74: 项目现有Godot资产 | X74: — | Y74: 2026-08-18项目扫描补登记；按Prefab独立身份管理；根节点=PrpCorridorFloorSegment(Node3D)；2026-08-18扫描补登记资产主表 2026-08-30 AST-03：asset_guard PASS；生产路径 assets/art/props/dungeon_3d/prp_corridor_floor_segment.tscn → assets/art/props/dungeon_3d/prp_corridor_floor_segment_v001.tscn；稳定 AssetID 不变；代码引用已迁移；验收 verify_rooftop_railing / verify_rooftop_32x32_contract / verify_door_passability / verify_full_3d_game_flow。
A75: ENV-DUNGEON-CORRIDOR-STAIR-TREAD | B75: 地牢走廊楼梯踏步 | C75: 场景 | D75: environment_module_3d | E75: corridor_stair_tread | F75: root_3d | G75: ENV-DUNGEON-RUNTIME-3D | H75: Top3D / local -Z 正面 | I75: default / prefab | J75: 场景通用组件 | K75: 程序占位 | L75: P1 | M75: v001 | N75: Godot PackedScene；根=Node3D；碰撞节点=0 | O75: assets/art/props/dungeon_3d/prp_corridor_stair_tread.tscn | P75: assets/art/3D模型资产目录与命名规范.md | Q75: 地牢走廊楼梯踏步;3D;Prefab;场景通用组件;corridor_stair_tread | R75: =LOWER(TRIM(C75)&"|"&TRIM(D75)&"|"&TRIM(E75)&"|"&TRIM(F75)&"|"&TRIM(H75)&"|"&TRIM(I75)) | S75: =IF(COUNTIF($R$6:$R$928,R75)>1,"重复","唯一") | T75: 9cb096178ff640d1a46dc773d86af69873c5f92f054ead84ee6fdeaac15e608d | U75: Codex | V75: 46264 | W75: 项目现有Godot资产 | X75: — | Y75: 2026-08-18项目扫描补登记；按Prefab独立身份管理；根节点=PrpCorridorStairTread(Node3D)；2026-08-18扫描补登记资产主表 2026-08-30 AST-03：asset_guard PASS；生产路径 assets/art/props/dungeon_3d/prp_corridor_stair_tread.tscn → assets/art/props/dungeon_3d/prp_corridor_stair_tread_v001.tscn；稳定 AssetID 不变；代码引用已迁移；验收 verify_rooftop_railing / verify_rooftop_32x32_contract / verify_door_passability / verify_full_3d_game_flow。
... A112: ENV-BASE99-MEZZANINE-UNDERDECK-BLOCKER | B112: 基地99层楼中楼下方工业仓库挡板 | C112: 场景 | D112: environment_module | E112: base99_mezzanine_underdeck_blocker | F112: underdeck_blocker | G112: ENV-BASE99-MODULAR-ROOM | H112: 俯视3D / local -Z 正面 | I112: default / permanent solid enclosure | J112: 基地99F楼中楼下方 | K112: 旧资产已从正式基地移除 | L112: P0 | M112: v003 | N112: 19.31×9.11×4.65m视觉；0.55m内收；三面横向冷灰门板；碰撞顶4.95m | O112: assets/art/environments/base_facility_3d/runtime/env_base99_mezzanine_underdeck_blocker/env_base99_mezzanine_underdeck_blocker_root_top3d.tscn | P112: art_source/environments/base_facility_3d/source/env_base99_mezzanine_underdeck_blocker/env_base99_mezzanine_underdeck_blocker_source_v003.blend; scripts/blender/build_base99_mezzanine_underdeck_blocker_v003.py; src/world3d/Base99MezzanineUnderdeckBlocker3D.gd | Q112: 基地99层; 楼中楼; 横向门板; Blender母版; PaletteUV; 三面永久阻挡; 0.55米内收; 物理射线验收 | R112: =LOWER(TRIM(C112)&"|"&TRIM(D112)&"|"&TRIM(E112)&"|"&TRIM(F112)&"|"&TRIM(H112)&"|"&TRIM(I112)) | S112: =IF(COUNTIF($R$6:$R$928,R112)>1,"重复","唯一") | T112: 1f3f5c3b0d6c41955e36c7e1ad37c7a0ce313dce58b073f4dd907f0eb4c7a8c5 | U112: Codex | V112: 46264 | W112: 用户自制Blender资产 | X112: — | Y112: 2026-08-28：v003由Blender源文件重导；Godot包装显式保存南/西/东三块与横向门板对齐的永久Box阻挡，六条高低位物理射线通过；v002保留回滚。 2026-08-30 AST-01规范化（原制作状态：正式美术已接入） 2026-08-30 AST-02：合法内容更新；文件为Git已跟踪且修改时间不早于原台账日期；验收：verify_base99_mezzanine_underdeck_blocker；SHA 387af92bd387→7e2172604715。 2026-09-05：按13号恢复到基地正式美术布局；复用优化Blender源文件 env_base99_mezzanine_underdeck_blocker_source_v003.blend；永久包络阻挡验收通过：verify_base99_structural_asset_integration。 2026-09-05：旧v003阁楼下铁皮包裹区实例与永久阻挡已从基地正式布局移除；资产与Blender源文件保留，仅供回滚，等待V017→V021替换资产。
A113: PRP-BASE-AVATAR-WARDROBE-001 | B113: 基地角色衣柜 | C113: 场景道具 | D113: base_facility | E113: avatar_wardrobe | F113: root | H113: 俯视3D | I113: default | J113: 主基地/99F | K113: 原型已接入 | L113: P0 | M113: v001 | N113: 根缩放1 | O113: assets/art/props/base_world_3d/runtime/avatar_wardrobe/prp_base_avatar_wardrobe_root_top3d.tscn | P113: src/ui/wardrobe/WardrobeMenu3D.gd | Q113: 衣柜; avatar; 换装; 6分类 | R113: =LOWER(TRIM(C113)&"|"&TRIM(D113)&"|"&TRIM(E113)&"|"&TRIM(F113)&"|"&TRIM(H113)&"|"&TRIM(I113)) | S113: =IF(COUNTIF($R$6:$R$928,R113)>1,"重复","唯一") | T113: a5bfa9b1c406a16ef02f3b6bd5f645f501c92c774ea2b64257dd69a2f2320bd8 | U113: Codex | V113: 46264 | W113: 用户自制/项目内资产 | X113: — | Y113: 2026-08-20：本轮基地系统、角色母版与资产流程登记。 2026-08-30 AST-01规范化（原制作状态：功能已接入/复用模型；原大类：设施） 2026-08-30 AST-02：补齐单一生产路径SHA；验收：verify_wardrobe_preview_fill_flow；SHA 237ab00d041b。
A114: ART-PALETTE-FACILITY-LOWLIGHT-DOPAMINE | B114: 设施低亮多巴胺共享色盘 | C114: 场景 | D114: shared_palette | E114: palette_facility_lowlight_dopamine | F114: root | H114: 不适用 | I114: default | J114: 场景/设施/固定装饰共享 | K114: 已完成 | L114: P0 | M114: v001 | N114: 512×512 PNG；10×10 色格；VRAM 压缩 | O114: assets/art/shared/palette/设施低亮多巴胺色盘_10x10_512.png | P114: art_source/shared/palette/palette_dopamine_10x10_512_v001.psd；tools/asset_pipeline/scene_facility_shared_palette_post_import.gd；tests/verification/verify_scene_facility_shared_palette.tscn | Q114: facility palette dopamine lowlight shared | R114: =LOWER(TRIM(C114)&"|"&TRIM(D114)&"|"&TRIM(E114)&"|"&TRIM(F114)&"|"&TRIM(H114)&"|"&TRIM(I114)) | S114: =IF(COUNTIF($R$6:$R$928,R114)>1,"重复","唯一") | T114: a6b1838fb80ad3ce7764e998bb1dfb70edf2b9315a4282da0fb2ae35ed266ce3 | U114: 美术 | V114: 46264 | W114: 项目自制/内部使用 | X114: — | Y114: 2026-08-30 AST-04：asset_guard PASS；中文无版本生产路径迁移到小写 snake_case v001；导入契约、DCC脚本、清单、文档和专项测试引用全部迁移；验收 verify_scene_facility_shared_palette。 2026-08-30 AST-04契约纠正：设施资产专用规范要求公共色盘保持唯一固定中文路径；已撤销通用英文重命名。该路径是唯一命名门禁例外，稳定 AssetID 与SHA不变；专项验证通过。
A115: PRP-BASE-RECOVERY-STATION-3D | B115: 基地恢复站 | C115: 场景道具 | D115: 基地设施 | E115: recovery_station | F115: root | H115: 3D | I115: default | J115: 基地复用 | K115: 原型已接入 | L115: P1 | M115: v001 | N115: PackedScene；固定设施；独立碰撞 | O115: assets/art/props/base_world_3d/runtime/recovery_station/prp_base_recovery_station_root_top3d.tscn | P115: scenes/BaseWorld3D.tscn；assets/art/environments/base_facility_3d/runtime/env_base_facility_art_layout_top3d_v001.tscn；3D-设施!A20 | Q115: base recovery station | R115: =LOWER(TRIM(C115)&"|"&TRIM(D115)&"|"&TRIM(E115)&"|"&TRIM(F115)&"|"&TRIM(H115)&"|"&TRIM(I115)) | S115: =IF(COUNTIF($R$6:$R$928,R115)>1,"重复","唯一") | T115: ce54a12451f6cd98eb09165c94a301c28393d4250c7c574c664604710795f292 | U115: 美术 | V115: 46264 | W115: 项目现有/内部制作 | X115: — | Y115: 2026-08-30 AST-04：从3D-设施分表提升为主表权威根资产；asset_guard PASS；运行时由BaseWorld3D与基地美术布局直接消费。
A116: PRP-TOWER-ROOM-DOOR-3D | B116: 塔楼房间交互门 | C116: 场景道具 | D116: 门 | E116: room_door | F116: root | H116: 3D | I116: closed/open/locked | J116: 塔楼房间复用 | K116: 原型已接入 | L116: P0 | M116: v001 | N116: StaticBody3D；脚本驱动开关与碰撞 | O116: assets/art/props/dungeon_3d/prp_room_door_3d.tscn | P116: src/world3d/RoomDoor3D.gd；src/world3d/DungeonRoom3D.gd；src/world3d/TowerDescent3D.gd；tests/verification/verify_door_passability.tscn | Q116: tower room interactive door | R116: =LOWER(TRIM(C116)&"|"&TRIM(D116)&"|"&TRIM(E116)&"|"&TRIM(F116)&"|"&TRIM(H116)&"|"&TRIM(I116)) | S116: =IF(COUNTIF($R$6:$R$928,R116)>1,"重复","唯一") | T116: b0071bee31068f2d3995005cac41a93567ddfc68f662b4c8d9428d59b8083fc3 | U116: 程序/美术 | V116: 46264 | W116: 项目现有/内部制作 | X116: — | Y116: 2026-08-30 AST-04：运行时正式房门包装场景补登记；路径规范化为小写 snake_case v001；asset_guard PASS；不改变门行为、碰撞或塔楼围护；验收 verify_door_passability / verify_full_3d_game_flow。
A117: BPK-BASE99-EAST-MEZZANINE-STRUCTURE | B117: 基地99层 · 东墙阁楼主体结构 | C117: 基地资产包 | D117: 建筑结构包 | E117: base99_package_east_mezzanine_structure | F117: package_root | G117: ENV-BASE99-ART-LAYOUT-3D | H117: Top3D / Blender +Y北 | I117: static / default | J117: 3D-设施 / 基地99层独立资产包 | K117: 已优化并正式接入 | L117: P0 | M117: v017 | N117: 优化输出包络 20.069×9.993×7.315m；3440 三角面 | O117: ../ShellStorm2-backup/2026-10-11_art_source_split/original_tree/source/art/blender/base_facility_layout/component_packages/architecture/east_mezzanine_structure/asset_manifest.json | P117: art_source/design/blender/base_facility_layout/source/base_facility_runtime_layout_hq_v026.blend; ../ShellStorm2-backup/2026-10-11_art_source_split/original_tree/source/art/blender/base_facility_layout/component_packages/architecture/east_mezzanine_structure/asset_manifest.json | Q117: 基地99层;基地资产包;3D设施;建筑结构包;east_mezzanine_structure;PaletteUV | R117: =LOWER(TRIM(C117)&"|"&TRIM(D117)&"|"&TRIM(E117)&"|"&TRIM(F117)&"|"&TRIM(H117)&"|"&TRIM(I117)) | S117: =IF(COUNTIF($R$6:$R$928,R117)>1,"重复","唯一") | T117: 85c5a1e4e65168ecb8bad3439181965e5c8dac006af56fcd76b131d9a9de5701 | U117: Codex | V117: 46269 | W117: 用户自制Blender资产 | X117: 12 | Y117: package_id=ENV-BASE99-ART-LAYOUT-3D::east_mezzanine_structure；对象 87；中心 (5.000, 10.000, 3.663)m；朝向 Blender +Y north；预期导出 east_mezzanine_structure_visual_top3d_v001.glb；当前 not_exported；碰撞 not_authored_in_this_collection_only_pass；母版SHA-256=65ea9b7e5a75。 2026-09-05：V017→V021优化后正式接入；向下朝向面已剔除，阻挡随V021 Prefab维护。 2026-09-05：V021 GLB v002重新导入，自发光与主体分离。 GLB v002。公共色盘自发光改为MULTIPLY，修复白色叠加。T列为当前GLB SHA256。真实Player3D完成基地阁楼楼梯双向通行验证。 2026-09-05：阁楼南侧与西侧栏杆阻挡改为从Y=6楼板起算的1.2m连续盒；西北L梯入口保留开口。
A118: BPK-BASE99-EAST-UPPER-TRANSITION-STAIR | B118: 基地99层 · 东侧5米至12米上行楼梯 | C118: 基地资产包 | D118: 建筑结构包 | E118: base99_package_east_upper_transition_stair | F118: package_root | G118: ENV-BASE99-ART-LAYOUT-3D | H118: Top3D / Blender +Y北 | I118: static / default | J118: 3D-设施 / 基地99层独立资产包 | K118: 弃用 | L118: P0 | M118: v002 | N118: 5→12m连续坡面；20级；0.35m级高；2.2m净宽；平面门位不变 | O118: assets/art/environments/base_facility_3d/runtime/env_base99_structural/east_upper_transition_stair/east_upper_transition_stair_root_top3d.tscn | P118: art_source/environments/base_facility_3d/source/wall_height12/env_base99_east_upper_transition_stair_12m_source_v001.blend; scripts/blender/build_base99_upper_transition_stair_12m_v001.py | Q118: 基地99层;建筑结构包;上行楼梯;5米平台;12米门槛;20级 | R118: =LOWER(TRIM(C118)&"|"&TRIM(D118)&"|"&TRIM(E118)&"|"&TRIM(F118)&"|"&TRIM(H118)&"|"&TRIM(I118)) | S118: =IF(COUNTIF($R$6:$R$928,R118)>1,"重复","唯一") | T118: dde79d4673028d3930a3887c3633d9bd85a53b215d9c732b96e2837ac1cada86 | U118: Codex | V118: 46294 | W118: 用户自制Blender资产 | X118: 51 | Y118: 2026-09-13：随标准层高升级，保留5米平台起点与东门平面坐标，重制为20级、0.35米级高并以连续坡面碰撞接至12米门槛。T列为v002运行包装SHA-256。 2026-09-29：99F东侧旧斜梯从运行时布局移除；历史源与Prefab保留；由PRP-BASE99-TELESCOPIC-LADDER-3D替换。
A119: BPK-BASE99-NORTHWEST-L-STAIR | B119: 基地99层 · 西北贴墙L型楼梯 | C119: 基地资产包 | D119: 建筑结构包 | E119: base99_package_northwest_l_stair | F119: package_root | G119: ENV-BASE99-ART-LAYOUT-3D | H119: Top3D / Blender +Y北 | I119: static / default | J119: 3D-设施 / 基地99层独立资产包 | K119: 已优化并正式接入 | L119: P0 | M119: v022 | N119: 优化输出包络 10.082×7.908×7.124m；20310 三角面 | O119: ../ShellStorm2-backup/2026-10-11_art_source_split/original_tree/source/art/blender/base_facility_layout/component_packages/architecture/northwest_l_stair/asset_manifest.json | P119: art_source/design/blender/base_facility_layout/source/base_facility_runtime_layout_hq_v026.blend; ../ShellStorm2-backup/2026-10-11_art_source_split/original_tree/source/art/blender/base_facility_layout/component_packages/architecture/northwest_l_stair/asset_manifest.json | Q119: 基地99层;基地资产包;3D设施;建筑结构包;northwest_l_stair;PaletteUV | R119: =LOWER(TRIM(C119)&"|"&TRIM(D119)&"|"&TRIM(E119)&"|"&TRIM(F119)&"|"&TRIM(H119)&"|"&TRIM(I119)) | S119: =IF(COUNTIF($R$6:$R$928,R119)>1,"重复","唯一") | T119: 09f601c1c417c226db5ac1f275101a65ab389934be742844bd090a7e750f54e2 | U119: Codex | V119: 46269 | W119: 用户自制Blender资产 | X119: 14 | Y119: package_id=ENV-BASE99-ART-LAYOUT-3D::northwest_l_stair；对象 178；中心 (-9.735, 11.402, 3.564)m；朝向 Blender +Y north；预期导出 northwest_l_stair_visual_top3d_v001.glb；当前 not_exported；碰撞 source collider attached；母版SHA-256=65ea9b7e5a75。 2026-09-05：V017→V021优化后正式接入；向下朝向面已剔除，阻挡随V021 Prefab维护。 2026-09-05：V017改为27.7°两跑缓坡，每跑16级，级高0.1903m；连续凸体斜坡、平台及独立护栏。 GLB v002。公共色盘自发光改为MULTIPLY，修复白色叠加。T列为当前GLB SHA256。真实Player3D完成基地阁楼楼梯双向通行验证。
A120: BPK-BASE99-RETAINED-WALL-SYSTEM | B120: 基地99层 · 四向保留墙体系统 | C120: 基地资产包 | D120: 建筑结构包 | E120: base99_package_retained_wall_system | F120: package_root | G120: ENV-BASE99-ART-LAYOUT-3D | H120: Top3D / Blender +Y北 | I120: static / default | J120: 3D-设施 / 基地99层独立资产包 | K120: Blender源已完成 | L120: P0 | M120: v017 | N120: 包络 31.171×30.360×9.000m；24 网格；0 灯 | O120: ../ShellStorm2-backup/2026-10-11_art_source_split/original_tree/source/art/blender/base_facility_layout/component_packages/architecture/retained_wall_system/asset_manifest.json | P120: art_source/design/blender/base_facility_layout/source/base_facility_runtime_layout_hq_v026.blend; ../ShellStorm2-backup/2026-10-11_art_source_split/original_tree/source/art/blender/base_facility_layout/component_packages/architecture/retained_wall_system/asset_manifest.json | Q120: 基地99层;基地资产包;3D设施;建筑结构包;retained_wall_system;PaletteUV | R120: =LOWER(TRIM(C120)&"|"&TRIM(D120)&"|"&TRIM(E120)&"|"&TRIM(F120)&"|"&TRIM(H120)&"|"&TRIM(I120)) | S120: =IF(COUNTIF($R$6:$R$928,R120)>1,"重复","唯一") | T120: c772d3d1da76ff56c14a297936c0736a85c12acc4be69681dba1f125710b359d | U120: Codex | V120: 46269 | W120: 用户自制Blender资产 | X120: 11 | Y120: package_id=ENV-BASE99-ART-LAYOUT-3D::retained_wall_system；对象 72；中心 (0.000, 0.000, 4.500)m；朝向 Blender +Y north；预期导出 retained_wall_system_visual_top3d_v001.glb；当前 not_exported；碰撞 not_authored_in_this_collection_only_pass；母版SHA-256=65ea9b7e5a75。
A121: BPK-BASE99-UNDERDECK-SHEET-BLOCKER | B121: 基地99层 · 阁楼下方铁皮封闭体 | C121: 基地资产包 | D121: 建筑结构包 | E121: base99_package_underdeck_sheet_blocker | F121: package_root | G121: ENV-BASE99-ART-LAYOUT-3D | H121: Top3D / Blender +Y北 | I121: static / fixture_light | J121: 3D-设施 / 基地99层独立资产包 | K121: 已优化并正式接入 | L121: P0 | M121: v017 | N121: 优化输出包络 19.315×9.500×5.393m；2630 三角面 | O121: ../ShellStorm2-backup/2026-10-11_art_source_split/original_tree/source/art/blender/base_facility_layout/component_packages/architecture/underdeck_sheet_blocker/asset_manifest.json | P121: art_source/design/blender/base_facility_layout/source/base_facility_runtime_layout_hq_v026.blend; ../ShellStorm2-backup/2026-10-11_art_source_split/original_tree/source/art/blender/base_facility_layout/component_packages/architecture/underdeck_sheet_blocker/asset_manifest.json | Q121: 基地99层;基地资产包;3D设施;建筑结构包;underdeck_sheet_blocker;PaletteUV | R121: =LOWER(TRIM(C121)&"|"&TRIM(D121)&"|"&TRIM(E121)&"|"&TRIM(F121)&"|"&TRIM(H121)&"|"&TRIM(I121)) | S121: =IF(COUNTIF($R$6:$R$928,R121)>1,"重复","唯一") | T121: 8b8a3a689384ef1519e86259e762c2f56f2f2c30e04e52e142123f9faa1b0f9b | U121: Codex | V121: 46269 | W121: 用户自制Blender资产 | X121: 13 | Y121: package_id=ENV-BASE99-ART-LAYOUT-3D::underdeck_sheet_blocker；对象 11；中心 (5.000, 9.685, 2.700)m；朝向 Blender +Y north；预期导出 underdeck_sheet_blocker_visual_top3d_v001.glb；当前 not_exported；碰撞 not_authored_in_this_collection_only_pass；母版SHA-256=65ea9b7e5a75。 2026-09-05：V017→V021优化后正式接入；向下朝向面已剔除，阻挡随V021 Prefab维护。 2026-09-05：V021 GLB v002重新导入，自发光与主体分离。 GLB v002。公共色盘自发光改为MULTIPLY，修复白色叠加。T列为当前GLB SHA256。真实Player3D完成基地阁楼楼梯双向通行验证。
A122: BPK-BASE99-EAST-FLAMMABLE-BIN | B122: 基地99层 · FLAMMABLE可燃垃圾设施 | C122: 基地资产包 | D122: 东侧固定设施包 | E122: base99_package_east_flammable_bin | F122: package_root | G122: ENV-BASE99-ART-LAYOUT-3D | H122: Top3D / Blender +Y北 | I122: static / default | J122: 3D-设施 / 基地99层独立资产包 | K122: Blender源已完成 | L122: P1 | M122: v017 | N122: 包络 1.298×1.100×1.460m；12 网格；0 灯 | O122: ../ShellStorm2-backup/2026-10-11_art_source_split/original_tree/source/art/blender/base_facility_layout/component_packages/east_facilities/east_flammable_bin/asset_manifest.json | P122: art_source/design/blender/base_facility_layout/source/base_facility_runtime_layout_hq_v026.blend; ../ShellStorm2-backup/2026-10-11_art_source_split/original_tree/source/art/blender/base_facility_layout/component_packages/east_facilities/east_flammable_bin/asset_manifest.json | Q122: 基地99层;基地资产包;3D设施;东侧固定设施包;east_flammable_bin;PaletteUV | R122: =LOWER(TRIM(C122)&"|"&TRIM(D122)&"|"&TRIM(E122)&"|"&TRIM(F122)&"|"&TRIM(H122)&"|"&TRIM(I122)) | S122: =IF(COUNTIF($R$6:$R$928,R122)>1,"重复","唯一") | T122: b761ec0a6c0fb6ef88a5b3ce229c69e447bc9d0a8ada0dabf3928b28a0136d3e | U122: Codex | V122: 46269 | W122: 用户自制Blender资产 | X122: 76 | Y122: package_id=ENV-BASE99-ART-LAYOUT-3D::east_flammable_bin；对象 12；中心 (10.701, -6.650, 0.730)m；朝向 Blender +Y north；预期导出 east_flammable_bin_visual_top3d_v001.glb；当前 not_exported；碰撞 not_authored_in_this_collection_only_pass；母版SHA-256=65ea9b7e5a75。
A123: BPK-BASE99-EAST-INDUSTRIAL-PIPELINE-SYSTEM | B123: 基地99层 · 东墙工业管线系统 | C123: 基地资产包 | D123: 东侧固定设施包 | E123: base99_package_east_industrial_pipeline_system | F123: package_root | G123: ENV-BASE99-ART-LAYOUT-3D | H123: Top3D / Blender +Y北 | I123: static / default | J123: 3D-设施 / 基地99层独立资产包 | K123: Blender源已完成 | L123: P1 | M123: v022 | N123: 包络 0.578×17.600×5.460m；57 网格；0 灯 | O123: ../ShellStorm2-backup/2026-10-11_art_source_split/original_tree/source/art/blender/base_facility_layout/component_packages/east_facilities/east_industrial_pipeline_system/asset_manifest.json | P123: art_source/design/blender/base_facility_layout/source/base_facility_runtime_layout_hq_v026.blend; ../ShellStorm2-backup/2026-10-11_art_source_split/original_tree/source/art/blender/base_facility_layout/component_packages/east_facilities/east_industrial_pipeline_system/asset_manifest.json | Q123: 基地99层;基地资产包;3D设施;东侧固定设施包;east_industrial_pipeline_system;PaletteUV | R123: =LOWER(TRIM(C123)&"|"&TRIM(D123)&"|"&TRIM(E123)&"|"&TRIM(F123)&"|"&TRIM(H123)&"|"&TRIM(I123)) | S123: =IF(COUNTIF($R$6:$R$928,R123)>1,"重复","唯一") | T123: 30cd758456e0e41dc59246f4ef6bb520f135799624b178e6e987ee463d156150 | U123: Codex | V123: 46269 | W123: 用户自制Blender资产 | X123: 74 | Y123: package_id=ENV-BASE99-ART-LAYOUT-3D::east_industrial_pipeline_system；对象 57；中心 (14.271, -5.000, 4.450)m；朝向 Blender +Y north；预期导出 east_industrial_pipeline_system_visual_top3d_v001.glb；当前 not_exported；碰撞 not_authored_in_this_collection_only_pass；母版SHA-256=65ea9b7e5a75。
A124: BPK-BASE99-EAST-LOW-STORAGE-BENCH | B124: 基地99层 · 低矮储物收纳区 | C124: 基地资产包 | D124: 东侧固定设施包 | E124: base99_package_east_low_storage_bench | F124: package_root | G124: ENV-BASE99-ART-LAYOUT-3D | H124: Top3D / Blender +Y北 | I124: static / default | J124: 3D-设施 / 基地99层独立资产包 | K124: Blender源已完成 | L124: P1 | M124: v017 | N124: 包络 2.900×1.225×1.690m；10 网格；0 灯 | O124: ../ShellStorm2-backup/2026-10-11_art_source_split/original_tree/source/art/blender/base_facility_layout/component_packages/east_facilities/east_low_storage_bench/asset_manifest.json | P124: art_source/design/blender/base_facility_layout/source/base_facility_runtime_layout_hq_v026.blend; ../ShellStorm2-backup/2026-10-11_art_source_split/original_tree/source/art/blender/base_facility_layout/component_packages/east_facilities/east_low_storage_bench/asset_manifest.json | Q124: 基地99层;基地资产包;3D设施;东侧固定设施包;east_low_storage_bench;PaletteUV | R124: =LOWER(TRIM(C124)&"|"&TRIM(D124)&"|"&TRIM(E124)&"|"&TRIM(F124)&"|"&TRIM(H124)&"|"&TRIM(I124)) | S124: =IF(COUNTIF($R$6:$R$928,R124)>1,"重复","唯一") | T124: da684e47481e7979da47f1ffd0ee9bea0a3cd930a1eedf9d5975c3cf5680a10e | U124: Codex | V124: 46269 | W124: 用户自制Blender资产 | X124: 80 | Y124: package_id=ENV-BASE99-ART-LAYOUT-3D::east_low_storage_bench；对象 10；中心 (10.850, -14.037, 0.915)m；朝向 Blender +Y north；预期导出 east_low_storage_bench_visual_top3d_v001.glb；当前 not_exported；碰撞 not_authored_in_this_collection_only_pass；母版SHA-256=65ea9b7e5a75。
A125: BPK-BASE99-EAST-MAINTENANCE-WORKSTATION | B125: 基地99层 · 维修工作台与工具墙 | C125: 基地资产包 | D125: 东侧固定设施包 | E125: base99_package_east_maintenance_workstation | F125: package_root | G125: ENV-BASE99-ART-LAYOUT-3D | H125: Top3D / Blender +Y北 | I125: static / default | J125: 3D-设施 / 基地99层独立资产包 | K125: Blender源已完成 | L125: P1 | M125: v022 | N125: 包络 5.000×2.560×4.220m；115 网格；0 灯 | O125: ../ShellStorm2-backup/2026-10-11_art_source_split/original_tree/source/art/blender/base_facility_layout/component_packages/east_facilities/east_maintenance_workstation/asset_manifest.json | P125: art_source/design/blender/base_facility_layout/source/base_facility_runtime_layout_hq_v026.blend; ../ShellStorm2-backup/2026-10-11_art_source_split/original_tree/source/art/blender/base_facility_layout/component_packages/east_facilities/east_maintenance_workstation/asset_manifest.json | Q125: 基地99层;基地资产包;3D设施;东侧固定设施包;east_maintenance_workstation;PaletteUV | R125: =LOWER(TRIM(C125)&"|"&TRIM(D125)&"|"&TRIM(E125)&"|"&TRIM(F125)&"|"&TRIM(H125)&"|"&TRIM(I125)) | S125: =IF(COUNTIF($R$6:$R$928,R125)>1,"重复","唯一") | T125: 6be24f334d15b77481f4d717c365bda4342d511b50c9da81d2099424d367dff6 | U125: Codex | V125: 46269 | W125: 用户自制Blender资产 | X125: 78 | Y125: package_id=ENV-BASE99-ART-LAYOUT-3D::east_maintenance_workstation；对象 115；中心 (6.200, -13.190, 2.200)m；朝向 Blender +Y north；预期导出 east_maintenance_workstation_visual_top3d_v001.glb；当前 not_exported；碰撞 not_authored_in_this_collection_only_pass；母版SHA-256=65ea9b7e5a75。
A126: BPK-BASE99-EAST-PERSONNEL-SECURITY-DOOR | B126: 基地99层 · 正式人员安全门 | C126: 基地资产包 | D126: 东侧固定设施包 | E126: base99_package_east_personnel_security_door | F126: package_root | G126: ENV-BASE99-ART-LAYOUT-3D | H126: Top3D / Blender +Y北 | I126: static / fixture_light | J126: 3D-设施 / 基地99层独立资产包 | K126: Blender源已完成 | L126: P1 | M126: v021 | N126: 包络 0.898×2.040×2.340m；2 网格；1 灯 | O126: ../ShellStorm2-backup/2026-10-11_art_source_split/original_tree/source/art/blender/base_facility_layout/component_packages/east_facilities/east_personnel_security_door/asset_manifest.json | P126: art_source/design/blender/base_facility_layout/source/base_facility_runtime_layout_hq_v026.blend; ../ShellStorm2-backup/2026-10-11_art_source_split/original_tree/source/art/blender/base_facility_layout/component_packages/east_facilities/east_personnel_security_door/asset_manifest.json | Q126: 基地99层;基地资产包;3D设施;东侧固定设施包;east_personnel_security_door;PaletteUV | R126: =LOWER(TRIM(C126)&"|"&TRIM(D126)&"|"&TRIM(E126)&"|"&TRIM(F126)&"|"&TRIM(H126)&"|"&TRIM(I126)) | S126: =IF(COUNTIF($R$6:$R$928,R126)>1,"重复","唯一") | T126: d13c58d2b093487ecec279f163a1cc93810a7f5683ea2b701d2c645ed2cbe54e | U126: Codex | V126: 46269 | W126: 用户自制Blender资产 | X126: 71 | Y126: package_id=ENV-BASE99-ART-LAYOUT-3D::east_personnel_security_door；中心 (15.000, 2.500, 1.270)m；独立复制 west_door_lift_instance 的620mm双面加厚滑升门；东侧专属门禁包未改动。视觉迭代 v017_east_copies_west_double_sided_003；预期替换 undefined；当前 not_exported。
A127: BPK-BASE99-EAST-PLANT-GROUP | B127: 基地99层 · 东面植物点缀组 | C127: 基地资产包 | D127: 东侧固定设施包 | E127: base99_package_east_plant_group | F127: package_root | G127: ENV-BASE99-ART-LAYOUT-3D | H127: Top3D / Blender +Y北 | I127: static / default | J127: 3D-设施 / 基地99层独立资产包 | K127: Blender源已完成 | L127: P1 | M127: v017 | N127: 包络 1.364×17.030×2.000m；15 网格；0 灯 | O127: ../ShellStorm2-backup/2026-10-11_art_source_split/original_tree/source/art/blender/base_facility_layout/component_packages/east_facilities/east_plant_group/asset_manifest.json | P127: art_source/design/blender/base_facility_layout/source/base_facility_runtime_layout_hq_v026.blend; ../ShellStorm2-backup/2026-10-11_art_source_split/original_tree/source/art/blender/base_facility_layout/component_packages/east_facilities/east_plant_group/asset_manifest.json | Q127: 基地99层;基地资产包;3D设施;东侧固定设施包;east_plant_group;PaletteUV | R127: =LOWER(TRIM(C127)&"|"&TRIM(D127)&"|"&TRIM(E127)&"|"&TRIM(F127)&"|"&TRIM(H127)&"|"&TRIM(I127)) | S127: =IF(COUNTIF($R$6:$R$928,R127)>1,"重复","唯一") | T127: 666e4f4de4e76543f3eea83348d3ba9f4cb2c07dce740b1b4b904b863e38a419 | U127: Codex | V127: 46269 | W127: 用户自制Blender资产 | X127: 83 | Y127: package_id=ENV-BASE99-ART-LAYOUT-3D::east_plant_group；对象 15；中心 (12.250, -5.035, 1.110)m；朝向 Blender +Y north；预期导出 east_plant_group_visual_top3d_v001.glb；当前 not_exported；碰撞 not_authored_in_this_collection_only_pass；母版SHA-256=65ea9b7e5a75。
A128: BPK-BASE99-EAST-POWER-DISTRIBUTION | B128: 基地99层 · POWER工业配电系统 | C128: 基地资产包 | D128: 东侧固定设施包 | E128: base99_package_east_power_distribution | F128: package_root | G128: ENV-BASE99-ART-LAYOUT-3D | H128: Top3D / Blender +Y北 | I128: static / default | J128: 3D-设施 / 基地99层独立资产包 | K128: Blender源已完成 | L128: P1 | M128: v022 | N128: 包络 0.828×1.550×2.690m；25 网格；0 灯 | O128: ../ShellStorm2-backup/2026-10-11_art_source_split/original_tree/source/art/blender/base_facility_layout/component_packages/east_facilities/east_power_distribution/asset_manifest.json | P128: art_source/design/blender/base_facility_layout/source/base_facility_runtime_layout_hq_v026.blend; ../ShellStorm2-backup/2026-10-11_art_source_split/original_tree/source/art/blender/base_facility_layout/component_packages/east_facilities/east_power_distribution/asset_manifest.json | Q128: 基地99层;基地资产包;3D设施;东侧固定设施包;east_power_distribution;PaletteUV | R128: =LOWER(TRIM(C128)&"|"&TRIM(D128)&"|"&TRIM(E128)&"|"&TRIM(F128)&"|"&TRIM(H128)&"|"&TRIM(I128)) | S128: =IF(COUNTIF($R$6:$R$928,R128)>1,"重复","唯一") | T128: 279060f71448bd2de0fdce48209ef571577e8efe06e5a8187ce2dcad86ede7a8 | U128: Codex | V128: 46269 | W128: 用户自制Blender资产 | X128: 73 | Y128: package_id=ENV-BASE99-ART-LAYOUT-3D::east_power_distribution；对象 25；中心 (13.986, -5.550, 2.355)m；朝向 Blender +Y north；预期导出 east_power_distribution_visual_top3d_v001.glb；当前 not_exported；碰撞 not_authored_in_this_collection_only_pass；母版SHA-256=65ea9b7e5a75。
... A231: ENV-BASE99-WALL-CONTENTS-V021 | B231: 基地99层非门墙面内容资产包 | C231: 场景 | D231: environment_module_3d | E231: base99_wall_contents_v021 | F231: wall_content_visual_bundle | G231: ENV-BASE99-ART-LAYOUT-3D | H231: Top3D / Blender烘焙布局 | I231: default / visual_only | J231: 99层基地墙面内容 | K231: 已导入；优化完成 | L231: P0 | M231: v003 | N231: 18包；18网格；86,538三角面；无内置碰撞 | O231: assets/art/environments/base_facility_3d/runtime/env_base99_wall_contents/env_base99_wall_contents_root_top3d.tscn | P231: art_source/design/blender/base_facility_layout/source/base_facility_runtime_layout_hq_v026.blend; art_source/environments/base_facility_3d/source/env_base99_wall_contents_v021_manifest.json | Q231: 基地99层;墙面内容;V021;非门;visual_only;无新增碰撞;Blender坐标复用 | R231: =LOWER(TRIM(C231)&"|"&TRIM(D231)&"|"&TRIM(E231)&"|"&TRIM(F231)&"|"&TRIM(H231)&"|"&TRIM(I231)) | S231: =IF(COUNTIF($R$6:$R$928,R231)>1,"重复","唯一") | T231: 93d762c294174d26fa78544cd0824999521732b85456861fa55ff0c3604e86da | U231: Codex | V231: 46270 | W231: 用户自制Blender资产 | X231: — | Y231: 2026-09-05：导入终端、管线、霓虹标识、工具板、公告/资料板、海报与安全/配电件；所有门、门框、墙体模块、墙板、墙皮和挡板均排除。顶视角优化：移除朝下表面并对运行时副本抽稀；每包合并为一个静态网格。墙体结构碰撞仍为唯一阻挡来源。
A232: ENV-BASE99-REMAINING-FACILITIES-V021 | B232: 基地99层剩余非门非墙独立设施资产包 | C232: 场景 | D232: environment_facility_bundle | E232: base99_remaining_facilities_v021 | F232: facility_bundle | G232: ENV-BASE99-ART-LAYOUT-3D | H232: Top3D / Blender烘焙布局 | I232: default / static + visual_only | J232: 99层基地 | K232: 已导入；优化完成 | L232: P0 | M232: v004 | N232: 45独立包；45运行时网格；84,274三角面；34包逐物件简化阻挡，11包仅视觉 | O232: assets/art/environments/base_facility_3d/runtime/env_base99_remaining_facilities/env_base99_remaining_facilities_root_top3d.tscn | P232: art_source/design/blender/base_facility_layout/source/base_facility_runtime_layout_hq_v026.blend; art_source/environments/base_facility_3d/source/env_base99_remaining_facilities_v021_manifest.json | Q232: 基地99层；仓储；阁楼家具；环境支持；排除门/墙/地板 | R232: =LOWER(TRIM(C232)&"|"&TRIM(D232)&"|"&TRIM(E232)&"|"&TRIM(F232)&"|"&TRIM(H232)&"|"&TRIM(I232)) | S232: =IF(COUNTIF($R$6:$R$928,R232)>1,"重复","唯一") | T232: d153967cd3c333b46dc8fbf2c89b73ffb095a834be12a7daf774fef0418af1a7 | U232: Codex | V232: 2026-09-21 | W232: base_facility_runtime_layout_hq_v017.blend | X232: — | Y232: Godot正式导入完成；45个GLB均公共色盘、无嵌入贴图；基地美术布局已实例化 ｜ 2026-09-21 业主在 Godot 编辑器内手工微调本包运行时布局并定版：该 .tscn 的节点变换即布局真源（15 件实际位移 / 4 件 facility 包装包空操作覆盖 / 9 份有意多份实例），坐标已固化为 source/env_base99_remaining_facilities_v021_placement.{json,md}；不写回 Blender，重生成通道会覆盖它。SHA-256 d153967cd3c333b46dc8fbf2c89b73ffb095a834be12a7daf774fef0418af1a7
A233: ENV-TOWER-STAIR-FLOOR-LOWER | B233: 楼梯间下层楼板 | C233: 场景 | D233: environment_module_3d | E233: tower_stair_floor_lower | F233: floor_lower | H233: Top3D / Blender Z-up | I233: whitebox / default | J233: 楼梯区专用 | K233: 程序占位 | L233: P2 | M233: v001 | N233: 每间下层18块5×5×0.3m固定地砖，完成面+0.1m | O233: art_source/design/whitebox/tower_zones/v015/data/whitebox_tower_stairs_v015.json | P233: art_source/design/whitebox/tower_zones/v015/blender/whitebox_tower_stairs_v015.blend | Q233: 楼梯间;下层楼板;白盒 | R233: =LOWER(TRIM(C233)&"|"&TRIM(D233)&"|"&TRIM(E233)&"|"&TRIM(F233)&"|"&TRIM(H233)&"|"&TRIM(I233)) | S233: =IF(COUNTIF($R$6:$R$928,R233)>1,"重复","唯一") | U233: Codex | V233: 2026-09-14 | W233: 用户设计 | X233: — | Y233: v015原位组件拼装；墙板固定模数+收边件；楼梯高度/坡度参数编辑；Scale=1。 2026-09-23：连续爬塔当前非主要玩法，保留白盒设计与源文件，降为程序占位/P2；未来重新开放时再恢复专项验收。
A234: ENV-TOWER-STAIR-FLOOR-MID | B234: 楼梯间中层楼板 | C234: 场景 | D234: environment_module_3d | E234: tower_stair_floor_mid | F234: floor_mid | H234: Top3D / Blender Z-up | I234: whitebox / default | J234: 楼梯区专用 | K234: 程序占位 | L234: P2 | M234: v001 | N234: 每间中层6块固定拼接件，沿原平台边界收边 | O234: art_source/design/whitebox/tower_zones/v015/data/whitebox_tower_stairs_v015.json | P234: art_source/design/whitebox/tower_zones/v015/blender/whitebox_tower_stairs_v015.blend | Q234: 楼梯间;中层楼板;转角平台;白盒 | R234: =LOWER(TRIM(C234)&"|"&TRIM(D234)&"|"&TRIM(E234)&"|"&TRIM(F234)&"|"&TRIM(H234)&"|"&TRIM(I234)) | S234: =IF(COUNTIF($R$6:$R$928,R234)>1,"重复","唯一") | U234: Codex | V234: 2026-09-14 | W234: 用户设计 | X234: — | Y234: v015原位组件拼装；墙板固定模数+收边件；楼梯高度/坡度参数编辑；Scale=1。 2026-09-23：连续爬塔当前非主要玩法，保留白盒设计与源文件，降为程序占位/P2；未来重新开放时再恢复专项验收。
A235: ENV-TOWER-STAIR-FLOOR-UPPER | B235: 楼梯间上层楼板 | C235: 场景 | D235: environment_module_3d | E235: tower_stair_floor_upper | F235: floor_upper | H235: Top3D / Blender Z-up | I235: whitebox / default | J235: 楼梯区专用 | K235: 程序占位 | L235: P2 | M235: v001 | N235: 每间上层6块固定拼接件，另有2块门口连接板 | O235: art_source/design/whitebox/tower_zones/v015/data/whitebox_tower_stairs_v015.json | P235: art_source/design/whitebox/tower_zones/v015/blender/whitebox_tower_stairs_v015.blend | Q235: 楼梯间;上层楼板;白盒 | R235: =LOWER(TRIM(C235)&"|"&TRIM(D235)&"|"&TRIM(E235)&"|"&TRIM(F235)&"|"&TRIM(H235)&"|"&TRIM(I235)) | S235: =IF(COUNTIF($R$6:$R$928,R235)>1,"重复","唯一") | U235: Codex | V235: 2026-09-14 | W235: 用户设计 | X235: — | Y235: v015原位组件拼装；墙板固定模数+收边件；楼梯高度/坡度参数编辑；Scale=1。 2026-09-23：连续爬塔当前非主要玩法，保留白盒设计与源文件，降为程序占位/P2；未来重新开放时再恢复专项验收。
A236: ENV-TOWER-STAIR-FLIGHT-ADJUSTABLE | B236: 楼梯间可调直梯母组件 | C236: 场景 | D236: environment_module_3d | E236: tower_stair_flight_adjustable | F236: stair_flight | H236: Top3D / Blender Z-up | I236: whitebox / default | J236: 楼梯区专用 | K236: 程序占位 | L236: P2 | M236: v002 | N236: 单母组件；每跑6m高/15m水平长度/21.8014°；20级；另一跑180°；高度/角度可调 | O236: art_source/design/whitebox/tower_zones/v015/data/whitebox_tower_stairs_v015.json | P236: art_source/design/whitebox/tower_zones/v015/blender/whitebox_tower_stairs_v015.blend | Q236: 楼梯间;直梯;可调坡度;可调长度;白盒 | R236: =LOWER(TRIM(C236)&"|"&TRIM(D236)&"|"&TRIM(E236)&"|"&TRIM(F236)&"|"&TRIM(H236)&"|"&TRIM(I236)) | S236: =IF(COUNTIF($R$6:$R$928,R236)>1,"重复","唯一") | U236: Codex | V236: 2026-09-14 | W236: 用户设计 | X236: — | Y236: v015原位组件拼装；墙板固定模数+收边件；楼梯高度/坡度参数编辑；Scale=1。 2026-09-23：连续爬塔当前非主要玩法，保留白盒设计与源文件，降为程序占位/P2；未来重新开放时再恢复专项验收。
A237: ENV-TOWER-CORNER-COLUMN-05M | B237: 塔楼通用拐角柱 | C237: 场景 | D237: environment_module_3d | E237: tower_corner_column_05m | F237: corner_column | H237: Top3D / Blender Z-up | I237: whitebox / default | J237: 全区块通用 | K237: 程序占位 | L237: P2 | M237: v001 | N237: 0.5×0.5×12.9m | O237: art_source/design/whitebox/tower_zones/v013/data/stair_component_library_v001.json | P237: tools/3Dgame-design/src/main.js | Q237: 拐角柱;角柱;通用组件;白盒 | R237: =LOWER(TRIM(C237)&"|"&TRIM(D237)&"|"&TRIM(E237)&"|"&TRIM(F237)&"|"&TRIM(H237)&"|"&TRIM(I237)) | S237: =IF(COUNTIF($R$6:$R$928,R237)>1,"重复","唯一") | U237: Codex | V237: 2026-09-14 | W237: 用户设计 | X237: — | Y237: 3Dgame-design通用组件；未重新导入Godot。 2026-09-23：连续爬塔当前非主要玩法，保留白盒设计与源文件，降为程序占位/P2；未来重新开放时再恢复专项验收。
A238: ENV-ROOFTOP-REFERENCE-COMPONENT-LIBRARY | B238: 天台参考组件库 | C238: 场景 | D238: environment_kit_3d | E238: rooftop_reference | F238: component_library | H238: Blender Z-up / -Y | I238: reference_components | J238: 100F独立组件制作；装饰件已按布局接入运行场景 | K238: Blender源已完成 | L238: P1 | M238: v002 | N238: 47包 / 4共享材质；女儿墙方案A 0.80m；17件已导出（含12件装饰接入） | O238: art_source/environments/tower_zones/rooftop/source/reference_components/v002/天台区块_参考组件库_v002.blend | P238: 用户参考与加厚门口追加要求；v002/qa/验证报告 | Q238: 天台;屋顶;女儿墙;外墙;空调;管道;藤蔓;女儿墙挂藤 | R238: =LOWER(TRIM(C238)&"|"&TRIM(D238)&"|"&TRIM(E238)&"|"&TRIM(F238)&"|"&TRIM(H238)&"|"&TRIM(I238)) | S238: =IF(COUNTIF($R$6:$R$928,R238)>1,"重复","唯一") | T238: d9e96fa13e39e4e11abaef6c59b7d6211e9c616717a5ca59488c959dda31cc0a | U238: Codex | V238: 46286 | W238: 用户提供参考图；Blender几何制作 | X238: 项目内部 | Y238: 2026-09-20 女儿墙 1.80m→0.80m（方案A平整墙板）写回主库，三件破损变种入 02_女儿墙；2026-09-21 组件库升至 47 包；11 类装饰（空调/通风口/水管/藤蔓/花圃盆栽）导出 GLB 并接入 100F 装饰布局。 2026-09-21 二次修正：装饰接入增至 12 类（新增「女儿墙挂藤」，7×01_女儿墙 包），导出件 16 → 17。
A239: ENV-TOWER-DOOR-LEAF-5M | B239: 塔楼5米门扇模块 | C239: 场景 | D239: room_kit | E239: tower_descent | F239: door_leaf_5m | G239: ENV-TOWER-DESCENT-KIT-3D | H239: 俯视3D | I239: godot_runtime | J239: 普通战斗房/BOSS房/入口安全房的房间门门板（99F 基地滑升门与 start→facility 除外） | K239: 原型已接入 | L239: P0 | M239: v001 | N239: GLB / 可视包络 2.2×2.492×0.18m（底边悬原点上方 0.008m）/ 门扇厚 0.18m / 单 Mesh 四材质角色 / 随门垂直升降 0.32m | O239: assets/art/environments/tower_descent_3d/components/env_tower_door_leaf_5m_top3d.glb | P239: art_source/environments/tower_descent_3d/source/door_leaf_5m/export_env_tower_door_leaf_5m_v001.py; assets/art/props/dungeon_3d/prp_tower_door_leaf_5m.tscn; src/world3d/DungeonRoom3D.gd; src/world3d/RoomDoor3D.gd | Q239: 门扇/门板/door_leaf/door_panel/tower_descent/door_5m | R239: =LOWER(TRIM(C239)&"|"&TRIM(D239)&"|"&TRIM(E239)&"|"&TRIM(F239)&"|"&TRIM(H239)&"|"&TRIM(I239)) | S239: =IF(COUNTIF($R$6:$R$928,R239)>1,"重复","唯一") | T239: 067fa07693c766bf8025ee2b47c451b76f3b4f2a04765a7319def325e2702bcc | U239: Codex | V239: 46284 | W239: Blender 派生（自 door_5m_通用包） | X239: — | Y239: 2026-09-19：新建。自 B 套战局通用组件 art_source/design/whitebox/tower_zones/battle/components/common_components/v007 门扇件（包 door_5m_通用包 / 根件 ROOT_door_5m_通用组件）派生：Blender 内绕 Z 烘焙 180° 偏航后 transform_apply，使装饰面落在 Godot +Z（与 A 套 prp_tower_* forward_axis="+Z" 对齐）；先三角化再删朝下面；join 成单 Mesh，四材质角色 01/02/03/04 全保留。底边悬原点上方 8mm 是美术原始几何（关闭的门不该擦地），非几何压平。运行时替换掉战斗房原程序化深色 BoxMesh 门板；碰撞责任归 RoomDoor3D（门扇自声明 visual_only，无内嵌碰撞），升降开合由 DoorPanel.position.y 驱动。
A240: ENV-ROOFTOP-DECOR-LAYOUT-100F | B240: 100F天台装饰布局 | C240: 场景 | D240: environment_layout_3d | E240: rooftop_100f_decorated_layout | F240: root_3d | H240: Blender Z-up / -Y | I240: static / per_instance(visual_only+blocking) | J240: 100F天台专用；只摆共享组件实例，不拥有几何 | K240: 正式美术已接入 | L240: P1 | M240: v001 | N240: 120装饰实例/6组（房屋围护由Base100UpperShell独占）；外围72件（68直段+4外角）；266块5m地砖；20启用碰撞（绿化：8花箱+6大盆栽+6小盆栽，layer=1 包络代理） | O240: art_source/environments/tower_zones/rooftop/source/layouts/100f_decorated_v001/rooftop_100f_decorated_layout_v001.blend | P240: art_source/environments/tower_zones/rooftop/source/layouts/100f_decorated_v001/rooftop_100f_decorated_layout_v001.json; src/world3d/TowerFloorStage3D.gd | Q240: 天台;装饰布局;空调;通风口;水管;藤蔓;女儿墙挂藤;花圃盆栽;100F | R240: =LOWER(TRIM(C240)&"|"&TRIM(D240)&"|"&TRIM(E240)&"|"&TRIM(F240)&"|"&TRIM(H240)&"|"&TRIM(I240)) | S240: =IF(COUNTIF($R$6:$R$928,R240)>1,"重复","唯一") | T240: 788d177634fe6086fd971f20c74ed9638053929c3e7fb00e297291997629d222 | U240: 摩斯拉 | V240: 46287 | W240: 用户要求「用组件库现有件装饰天台」；Blender 组件实例布局；2026-09-21 业主实机报「坐标偏移 / 范围也错 / 没和 99 层基地正上方的墙壁一体」，修正坐标契约、装饰外皮与重复层；2026-09-22 业主口径「所有楼层都和 100 层面积一致」：壳体扩到 100×80（20×16 格），布局源随之重生成 | X240: 100F_decorated_v001 | Y240: 2026-09-21 二次修正（业主实机报「花圃花盆悬空 / 藤蔓要更高更错落 / 挡门 / 加栏杆挂藤」）：①竖向基准 —— 运行时天台承重面 y=0（TowerFloorStage3D 把地砖可视顶面对齐到 Y=0），而布局源把落地装饰写在 h=0.3（= 自持地砖顶面），地砖组又不进重放 ⇒ 实机花草整块砖厚悬空 0.30m、藤蔓 0.35m；现落地件统一 h=0，自持参照地砖改 h=−0.30 使砖顶面落 0。②基地东门净空 —— 门洞净宽 2.2m（世界 gz∈[−3.6,−1.4]），东墙藤蔓 gz −5.0→−8.5、东侧大盆栽 −4.0→−6.2，另把正插在门洞正中的东墙立管 −2.0→+5.5。③藤蔓加高错落 —— 11 基座落地 + 5 件上层叠高（2.0/2.4/2.6/3.2/3.6m；运行时禁非单位缩放，故只能用叠件而非 scale）⇒ 顶高 5.80~7.40m。④新增「女儿墙挂藤」8 件，贴外圈女儿墙中心线（四边各 2，宽度与 5m 直段同宽）。重放实例 99 → 112 / 6 组。运行时重放 99 个装饰实例/5组＝空调与通风口6+绿化20+藤蔓11+水管54+立管支架8；布局源按 Godot 世界平面口径书写、写入 Blender 只做 by=−gz 一步换算，运行时用 (x, h, −by) 还原，并断言换算后必须落在 ROOFTOP_WORLD_RECT 内；装饰贴的是 Base100UpperShell（30×30，中心 (0,5)，东墙门 z=−2.5）的外墙皮；全部实例缩放=1且启用碰撞=0；结构壳体（234地砖/68件女儿墙/楼梯与碰撞）仍由 TowerFloorStage3D 拥有。2026-09-21 修正三处：①缺 by=−gz 换算 ⇒ 整份布局南北镜像、整体偏北 10m；②房屋误做 20×20 且偏北，装饰随之偏；③布局源的 24 墙+36 封顶与 Base100UpperShell 自带件重复，改名 shell_reference（仅 Blender 侧参照、不重放），避免逐面 z-fighting。2026-09-21 三次修正（业主实机报「水管接下来接到地板上面基本看不到 / 空调机在墙上的状态需要 90 度旋转让风扇朝外」）：①立管落地 —— pipe_riser 件高 4.945m、原点在管底、顶端是朝 +X 的鹅颈出水口；旧版放 h=5.8 ⇒ 管底悬空 5.8m。现每处摆两段、两段 h 都是 4.945：下段 rotation_x_deg=180 倒装（包络 0~4.945m，原点即上端）、上段正装（4.945~9.89m），合成一根 0~9.89m 连续落水管，与 10.65m 环管之间残留 0.76m 由环管本体与支架轨遮住；支架补一段低位（1.5m）与原有 7.0m 位，覆盖 1.56~10.64m。②墙挂空调倾倒 —— 新增实例朝向分量 rotation_x_deg（绕自身 X 轴的倾倒）；组件 hvac_small 顶面（Blender 局部 +Z）是出风风扇、前面（局部 −Y）是进风格栅，故 4 台墙挂机统一 rotation_x_deg=90 让风扇朝外（旧版风扇朝天）。⚠️ Blender 默认 XYZ 序、Godot 默认 YXZ 序，只有 rz 分量为 0 时 Rz@Rx 与 Ry@Rx 同序、角度可逐值搬运，本布局遵守该约束（tip 只与 yaw 组合）。③立管/支架按各自墙面给 yaw（旧版立管一律 0 ⇒ 东西墙鹅颈朝墙里）；6 个墙挂件（4 空调 + 2 通风口）后背统一埋进墙外皮内 0.05m。重放实例 112 → 120（pipe_risers 8 → 16）。2026-09-21 四次修正（业主实机报「花盆和花圃没有阻挡」）：绿化 20 件（8 花箱 + 6 大盆栽 + 6 小盆栽）由 visual_only 改 blocking —— 布局源 add() 新增实例级 collision 策略（词表 visual_only / blocking，白名单 flowerbox / plant_large / plant_small），运行时 TowerFloorStage3D 新增 _apply_rooftop_collision_policy()：blocking 件用 TowerGeometry3D.resolve_visual_bounds() 量出**实测可视包络**、挂一个 StaticBody3D(BlockingCollision, layer=1, mask=0, PROCESS_MODE_ALWAYS) + BoxShape3D(BlockingBox) 代理挡玩家（尺寸随美术走、不写死常量），其余 462 件仍 visual_only（组件自带碰撞一律先关）。布局清单 design_intent/validation 记 blocking_collision_count=20 / visual_only_collision_count=462；校验器新增第 5 层断言（策略词表 + 白名单 slug + 计数 + 清单交叉一致）。反向对照：把 20 件翻回 visual_only ⇒ 两份运行时探针 exit 1、QA 报 3 条 FAIL；还原后 .blend 与 .json 逐字节一致。2026-09-21 五次修正（业主实机报「花盆和花圃靠墙太远了，要挨着墙放，不然还有个空虚」）：绿化环由「离墙中心线 2.15m 单一环线」改为**逐件按自身半进深背贴建筑外皮** —— 件心离墙中心线 = SHELL_WALL_T/2 − WALL_MOUNT_EMBED(0.05) + half_depth（背面埋进外皮 0.05m，与墙挂空调同口径）；花箱 0.5925 / 大盆栽 0.8727377 / 小盆栽 0.5473868，南/北/东/西四边各成对，背面齐平、正面自然错落（旧版每件背后空 1.14~1.45m 可见地砖带）。朝向补齐：三件 front_direction 均为 −Y ⇒ yaw 0/π/+π/2/−π/2 分别朝南/北/东/西（旧版西侧花圃 +π/2 正面朝墙里、与同墙藤蔓 −π/2 矛盾，一并修正）。布局 QA 新增「3e 绿化背贴外皮」断言（背面埋入量 = 0.05、沿墙法线跨度 = 2×半进深），可反向对照。重放实例仍 120/6 组、构件计数与 blocking 20 不变。2026-09-22 六次修正（业主口径「所有楼层都和 100 层面积一致」）：塔楼壳体平面由 18×16 格（90×80m）向东再扩 2 格到 20×16 格（100×80m），98F/99F/100F 三层共用同一矩形（TOWER_SHELL_WORLD_RECT = (-50,-35,100,80)，中心 (0,5)，8000㎡）；原先「100F 走 90×80、99F 楼板 250×250 / 外墙 160×160、普通层 250×250」三套口径作废。驱动原因：east 楼梯井（99↔98）外廓是固定世界常量 x∈[35,50]，90m 窗口（东界 x=40）装不下它；100m 下两个在用井（west x[-45,-30]、east x[35,50]）全部落在壳体内。本布局随之重生成：自持地砖 234→266 块、外围女儿墙 68→72 件（64→68 直段 + 4 外角）；重放 6 组仍 120 件不变（装饰贴 30×30 房屋与环管，只有东侧贴 x_east 的 parapet_ivy 1 件由 x=39.75 东移到 49.75）。
A241: ENV-EXPEDITION-L01-BOSS-ARENA | B241: 远征关卡01 Boss竞技场 50×40m 白模 | C241: 场景 | D241: boss_arena | E241: expedition_01_boss_arena | F241: root | H241: Top3D / Blender Z-up | I241: whitebox / default | J241: 远征关卡01 专用 | K241: Blender源已完成 | L241: P1 | M241: v001 | N241: 50×40×11.9m；10×8 个 5m 槽 | O241: art_source/design/whitebox/tower_zones/expedition_01/v001/blender/远征关卡01_白模_Boss竞技场_50x40m_v001.blend | P241: art_source/design/whitebox/tower_zones/battle_level01/v003/blender/局内关卡01_白模_Boss竞技场_190x90m_v003.blend | Q241: 远征关卡01;Boss竞技场;白模;50×40m;竞技场 | R241: =LOWER(TRIM(C241)&"|"&TRIM(D241)&"|"&TRIM(E241)&"|"&TRIM(F241)&"|"&TRIM(H241)&"|"&TRIM(I241)) | S241: =IF(COUNTIF($R$6:$R$928,R241)>1,"重复","唯一") | T241: e243a47df4f2e061c6b298c2c6a6d14465bc083b5d671c0e3c12a59355b8cb75 | U241: 摩斯拉 | V241: 2026-09-22 | W241: 用户设计（由局内关卡01竞技场白模派生） | X241: 远征关卡01 Boss竞技场 50×40m 白模_资产管理 | Y241: 由局内关卡01 Boss竞技场190×90m白模v003按5m网格重建（非缩放；1/3线性缩放落在63.33×30m、X轴非5m整数倍，业主裁决取50×40m）。墙按固定5m槽位拼装，门墙完整占用5m槽并保留左右柱与门楣；两轴均为5m整数倍，无FIXED_TRIM收边。门：南→boss_prep(+2.5)、西→boss_exit(-2.5)。未导GLB、未接Godot。
A242: ENV-EXPEDITION-L01-L-CORRIDOR | B242: 远征关卡01 L型走廊 数据连廊 45×40m 房间种类源 | C242: 场景 | D242: l_corridor | E242: expedition_01_l_corridor | F242: room_type | H242: Top3D / Blender Z-up | I242: scene_art / reference_derived | J242: 远征关卡01 专用；连接房间之间的 L 型通廊房间种类源 | K242: 正式美术已接入 | L242: P1 | M242: v012 | N242: 45×40m；组件库 v012：27 个唯一组件 / 121 个 l_turn 实例；room_01 / room_08 正式重放，42 块通用 C01/C02 地砖、49 个普通组件、30 个结构墙、unresolved=0、2 扇门；u_turn 差异布局待制作 | O242: art_source/environments/tower_zones/expedition/source/room_types/l_corridor/v003/ | P242: art_source/environments/tower_zones/expedition/source/room_types/l_corridor/v003/；art_source/environments/tower_zones/expedition/source/common_components/v012/component_catalog.json；component_instances.json；运行时 PackedScene 注册表 shell_component_catalog.json | Q242: 远征关卡01;L型走廊;数据连廊;房间种类;45×40m;走廊;服务器机柜;运维通道 | R242: =LOWER(TRIM(C242)&"|"&TRIM(D242)&"|"&TRIM(E242)&"|"&TRIM(F242)&"|"&TRIM(H242)&"|"&TRIM(I242)) | S242: =IF(COUNTIF($R$6:$R$928,R242)>1,"重复","唯一") | T242: 1ec561cf6c9668c580e662a41ad947df8e94e017ce451b8e2c70857ae6912b33 | U242: 摩斯拉 | V242: 2026-09-28 | W242: 用户设计（参考图推定尺寸；业主 2026-09-24 裁决归属远征关卡01） | X242: — | Y242: room_04 的 u_turn v001 差异布局已完成并接入，复用 v012 的 27 个组件；正式布局 123 实例（60 floor_tile、46 solid_wall、17 room_type_component），房间专用组件 0。 2026-09-28：远征关卡01完成每房独立静态 TSCN 改造。start、room_01…room_10、boss、extraction 各由显式 static_layout_scene_path 加载 runtime/room_instances/f00_<room_id>/room_static_layout.tscn；场景只拥有顶层 PackedScene prefab 实例根，不递归改 prefab 内部 owner，避免内部网格/碰撞展开。静态 TSCN 接管视觉与固定碰撞，代码继续负责动态门、触发器、刷怪、导航、流送、存档、交互与撤离。专项验收 EXPEDITION_ROOM_STATIC_SCENES_OK checks=209 rooms=13、ROOM_TYPE_COMPONENT_REPLAY_OK checks=4540，退出码 0 且无 RID/ObjectDB/resource 泄漏。完整 verify_expedition_level01_flow 仍因数据库房/撤离房周界碰撞及入口安全房旧快照兼容字段失败；本次不把程序壳体转正为正式美术资产。
A243: ENV-EXPEDITION-L01-OFFICE-ROOM | B243: 远征关卡01 办公室 开放办公 30×40m 房间种类源 | C243: 场景 | D243: office_room | E243: expedition_01_office_room | F243: room_type | H243: Top3D / Blender Z-up | I243: scene_art / reference_derived | J243: 远征关卡01 专用；room_03 与 room_09 两处实例共用同一房型源（同 office_60x70 模板） | K243: 正式美术已接入 | L243: P1 | M243: v001 | N243: 30×40×11.9m（6×8 个 5m 槽 / 28 个墙位）；106 个独立组件包 / 193 输出网格 / 211708 面；无内墙；4 组工位；门洞 2.2×2.5m（净空底 0.30m、门楣 2.80m）；QA PASS（22 项断言）；组件库 v009：25 个唯一组件 / 106 个实例，运行时按 component_instances.json 逐组件重放；filing_run 档案柜带按西/东两端实体几何拆为 2 个独立碰撞盒，中段空腔不阻挡（碰撞盒尺寸 0.765×2.832×4.53m，中心 z=±17.425m） | O243: art_source/environments/tower_zones/expedition/source/room_types/office_room/v001/办公室房间种类_开放办公_30x40m_v001.blend | P243: art_source/environments/tower_zones/expedition/source/room_types/office_room/v001/build_office_room_v001.py；白盒 art_source/design/whitebox/tower_zones/expedition_01/v001/data/room_templates/office_60x70.json | Q243: 远征关卡01;办公室;开放办公;房间种类;30×40m;工位;文件柜;白板;图腾;绿植 | R243: =LOWER(TRIM(C243)&"|"&TRIM(D243)&"|"&TRIM(E243)&"|"&TRIM(F243)&"|"&TRIM(H243)&"|"&TRIM(I243)) | S243: =IF(COUNTIF($R$6:$R$928,R243)>1,"重复","唯一") | T243: 9426753acdec4ebf84176b1fe98951228c851c444035e2bf770678927b9aaedf | U243: 摩斯拉 | V243: 摩斯拉 | W243: 2026-10-12 | X243: — | Y243: 服务远征关卡01 的 room_03（COMBAT，中心 -45/50）与 room_09（EVENT，中心 15/-45）；两房实测同为 office_60x70（30×40m）模板 ⇒ 共用一份房型源。白盒尺寸/门洞/墙高锁定，只做场景美术。2026-09-27：房型组件库 v009 已逐件导出 25 个稳定 GLB/PackedScene 并接入运行时（room_03 / room_09 各 106 实例、unresolved=0、门 2 扇）；主层地砖运行时换通用 C01/C02 棋盘砖。2026-09-27（同轮，业主裁定）：① UV 配色「保色相提亮 3 个挡位」——组件库 v009 的 20 个在用例按图面行 +3 重导向（第 10 列冷调灰阶栏行 +3、彩色族同族列 +3、封顶列 8；浅端溢出与近黑 `0_0` #05050c 原样保留），深色面（HSV 明度 <40%）占比 65.7% → 30.0%（母版 118206 面中移动 75934 面）。② 材质按「主面判据」（按槽面积不按面数）改亚光——本库全部为哑光/反光/自发光，无金属槽 ⇒ 实际改动 0 处，金属面积占比 0.0% 不变。③ 随后按新源重导出 98 个稳定 GLB（本库 25 件）并重建 PackedScene 与 `shell_component_catalog.json`（110 条），Godot 重导后房型重放验收 2051 项断言全通过（room_03 / room_09 各 106 实例、unresolved=0）。房型概念源 blend 未动，SHA-256 不变。④ 2026-09-27（同轮收尾）：按 `04-battle-room-runtime-assembler`「房间输出」要求补齐**逐房间运行时装配清单** —— `room_03` / `room_09` 各产出 `runtime/room_instances/f00_room_0{3,9}/room_runtime_manifest.json` + `acceptance/`，`assembly_route = room_type_layout_replay`（分支 A0，具体房间白模与房型默认尺寸/门槽/必需设施一致、无 instance_overrides）。清单记 106 实例（door_wall 1 / solid_wall 28 / room_type_component 29 / floor_tile 48）、组件库源哈希 83c1e268…、逐组件 PackedScene 与碰撞责任、门洞契约与门位（门位不冻结、按种子现算；RUN_SEED=77001199 实测 `room_03` 北接 room_02 / 南接 room_04，`room_09` 南接 room_08 / 北接 room_10；以 `acceptance/runtime_doors.txt` 为准）。⑤ 2026-09-27（同轮收尾·组件库升版）：按 `02-battle-room-component-decomposer` 第 184 行「生成组件源版本，不覆盖房间种类源，也不覆盖历史组件源」，把**组件库由原地改写改为正式升版 v006 → v009**（目录 `common_components/v006` → `v009`，母版改名 `…_v009.blend`）：v009 = 提亮 + 亚光后的当前源；原 v006 目录内容由 `git checkout HEAD --` 恢复为**提亮前的历史源**（只读留档）。同步改写全部引用：① `component_catalog.json` 的 `version` / `component_library` / 25 个包的 `component_library_blend`；② `component_instances.json` 的 `library`（**改** ＝ 本库自身版本；`source_library` = v004 与 `source_blend_sha256` 指向**整屋／房间种类源** v004 母版，**未动**）；③ 组件库级 `runtime_manifest.json` 与 `room_03` / `room_09` 的 `room_runtime_manifest.json`；④ 98 个 PackedScene 的 `metadata/asset_version` 与 `source_blend`；⑤ `FloorPlanGenerator.ROOM_TYPE_LAYOUT_SOURCES`、两个导出脚本的 `LIBRARIES`、`build_room_runtime_manifests.py` 的 `ROOM_TYPE_BINDING`、重放验收探针 `expected_version`。**运行时路径一律不带版本号**（`04-battle-room-runtime-assembler` 第 155 行：替换即覆盖同路径同名文件），版本只写在 `source/`、`asset_manifest.json`、PackedScene metadata、布局快照与本账本。组件库母版 SHA-256：v006 `f5e666ee…`（提亮前）→ v009 `926a881d…`。升版后重导出 98 个稳定 GLB、重建 98 个 PackedScene 与 `shell_component_catalog.json`（110 条），Godot 重导后房型重放验收 2051 项断言全通过。 2026-09-28：远征关卡01完成每房独立静态 TSCN 改造。start、room_01…room_10、boss、extraction 各由显式 static_layout_scene_path 加载 runtime/room_instances/f00_<room_id>/room_static_layout.tscn；场景只拥有顶层 PackedScene prefab 实例根，不递归改 prefab 内部 owner，避免内部网格/碰撞展开。静态 TSCN 接管视觉与固定碰撞，代码继续负责动态门、触发器、刷怪、导航、流送、存档、交互与撤离。专项验收 EXPEDITION_ROOM_STATIC_SCENES_OK checks=209 rooms=13、ROOM_TYPE_COMPONENT_REPLAY_OK checks=4540，退出码 0 且无 RID/ObjectDB/resource 泄漏。完整 verify_expedition_level01_flow 仍因数据库房/撤离房周界碰撞及入口安全房旧快照兼容字段失败；本次不把程序壳体转正为正式美术资产。 2026-10-12：仅修正 office_room/v009 的 filing_run 组件 PackedScene 碰撞代理。原整条 0.765×3.05×39.38m AABB 会封住中段空腔；现按玩家高度带几何拆为西/东两盒，中段净空恢复。几何双向校验 BOX_SEGMENTS_OK：无穿模、无空阻挡、无重叠、无漏覆盖。
A244: ENV-EXPEDITION-L01-BRIDGE-ROOM | B244: 远征关卡01 通道桥 工字型 30×60m 房间种类源 | C244: 场景 | D244: bridge_room | E244: expedition_01_bridge_room | F244: room_type | H244: Top3D / Blender Z-up | I244: scene_art / reference_derived | J244: 远征关卡01 专用；room_05 通道桥房间（工字型） | K244: 正式美术已接入 | L244: P1 | M244: v002 | N244: 30×60×11.9m（工字型）；上层平台 30×60（Z∈[-0.32,0]）；中央跨桥 10×30m；下沉坑 30×30m、坑底 Z=-12.0；4 个下层服务标高；242 个独立组件包 / 314 输出网格 / 312370 面；门洞 2.2×2.5m；QA PASS（17 项断言）；组件库 v010：35 个唯一组件 / 242 个实例，运行时按 component_instances.json 逐组件重放 | O244: art_source/environments/tower_zones/expedition/source/room_types/bridge_room/v002/通道桥房间种类_工字型_30x60m_v002.blend | P244: art_source/environments/tower_zones/expedition/source/room_types/bridge_room/v002/build_bridge_room_v002.py；白盒 art_source/design/whitebox/tower_zones/expedition_01/v001/data/room_templates/bridge_60x50.json | Q244: 远征关卡01;通道桥;工字型;房间种类;30×60m;跨桥;下沉区;多层几何 | R244: =LOWER(TRIM(C244)&"|"&TRIM(D244)&"|"&TRIM(E244)&"|"&TRIM(F244)&"|"&TRIM(H244)&"|"&TRIM(I244)) | S244: =IF(COUNTIF($R$6:$R$928,R244)>1,"重复","唯一") | T244: 0a20c0cace52d81def123b3b688c53944e18c64d91479d94f3b4f55db58c0251 | U244: 摩斯拉 | V244: 2026-09-28 | W244: 用户设计（参考图见 room_type_manifest.json 的 reference_image） | X244: — | Y244: 服务远征关卡01 的 room_05（通道桥房间 30×60 · 工字型；转置姿态用 template_rotation_deg:90）。本批唯一需多层几何与碰撞的房型。v001 保留在同目录历史版本。2026-09-27：房型组件库 v010 已逐件导出 35 个稳定 GLB/PackedScene 并接入运行时（room_05 242 实例、unresolved=0、门 2 扇）；主层地砖换通用 C01/C02 棋盘砖，坑底 36 块砖保持原样。2026-09-27（同轮，业主裁定）：① 组件库 v010（36 个 blend）UV 配色保色相提亮 3 个挡位，深色面（HSV 明度 <40%）占比 59.2% → 17.2%（母版 135984 面中移动 113068 面）。② 材质主面判据：本库无金属槽 ⇒ 改动 0 处，金属面积占比 0.0% 不变。③ 按新源重导出 98 个稳定 GLB（本库 35 件）并重建 PackedScene / 组件目录（110 条），Godot 重导后房型重放验收全通过（room_05 242 实例、unresolved=0）。房型概念源 blend 未动，SHA-256 不变。④ 2026-09-27（同轮收尾）：补齐**逐房间运行时装配清单** —— `room_05` 产出 `runtime/room_instances/f00_room_05/room_runtime_manifest.json` + `acceptance/`，`assembly_route = room_type_layout_replay`。清单记 242 实例（room_type_component 158 / solid_wall 36 / floor_tile 48，另有 36 块坑底 tile_lower 保留下沉标高不入主层刷怪格）、组件库源哈希 89e46e4e…、门位不冻结、按种子现算（RUN_SEED=77001199 实测东接 room_04 / 西接 room_06；探针日志 `acceptance/runtime_doors.txt`）、下沉坑底砖不计入换砖数。⑤ 2026-09-27（同轮收尾·组件库升版）：按 `02-battle-room-component-decomposer` 第 184 行「生成组件源版本，不覆盖房间种类源，也不覆盖历史组件源」，把**组件库由原地改写改为正式升版 v007 → v010**（目录 `common_components/v007` → `v010`，母版改名 `…_v010.blend`）：v010 = 提亮 + 亚光后的当前源；原 v007 目录由 `git checkout HEAD --` 恢复为**提亮前的历史源**（只读留档）。同步改写全部引用：① `component_catalog.json` 的 `version` / `component_library` / 35 个包的 `component_library_blend`；② `component_instances.json` 的 `library`（`source_library` = v005 与 `source_blend_sha256` 指向**整屋／房间种类源** v005 母版，**未动**）；③ 组件库级 `runtime_manifest.json` 与 `room_05` 的 `room_runtime_manifest.json`；④ 98 个 PackedScene 的 `metadata/asset_version` 与 `source_blend`；⑤ `FloorPlanGenerator.ROOM_TYPE_LAYOUT_SOURCES`、两个导出脚本的 `LIBRARIES`、`build_room_runtime_manifests.py` 的 `ROOM_TYPE_BINDING`、重放验收探针 `expected_version`。运行时路径不带版本号，版本只写在 source / manifest / PackedScene metadata / 布局快照 / 本账本。组件库母版 SHA-256：v007 `9f6a23ab…`（提亮前）→ v010 `f219156e…`。升版后重导出 98 个稳定 GLB 并重建 PackedScene 与组件目录，Godot 重导后房型重放验收 2051 项断言全通过（room_05 242 实例、unresolved=0）。 2026-09-28：远征关卡01完成每房独立静态 TSCN 改造。start、room_01…room_10、boss、extraction 各由显式 static_layout_scene_path 加载 runtime/room_instances/f00_<room_id>/room_static_layout.tscn；场景只拥有顶层 PackedScene prefab 实例根，不递归改 prefab 内部 owner，避免内部网格/碰撞展开。静态 TSCN 接管视觉与固定碰撞，代码继续负责动态门、触发器、刷怪、导航、流送、存档、交互与撤离。专项验收 EXPEDITION_ROOM_STATIC_SCENES_OK checks=209 rooms=13、ROOM_TYPE_COMPONENT_REPLAY_OK checks=4540，退出码 0 且无 RID/ObjectDB/resource 泄漏。完整 verify_expedition_level01_flow 仍因数据库房/撤离房周界碰撞及入口安全房旧快照兼容字段失败；本次不把程序壳体转正为正式美术资产。
A245: ENV-EXPEDITION-L01-ROOM-STD-25X25 | B245: 远征关卡01 标准房间 四墙平房 25×25m 房间种类源 | C245: 场景 | D245: std_25x25 | E245: expedition_01_std_room | F245: room_type | H245: Top3D / Blender Z-up | I245: scene_art / composed_from_linked_components | J245: 远征关卡01 专用；room_07 标准房间（25×25m）。本房型不自持几何：25 地砖 + 18 实墙 + 2 门墙 + 37 陈设共 82 个集合实例，全部 Library Link 自 office_room/v001 与 bridge_room/v002 两批已验收资产包 | K245: Blender源已完成 | L245: P1 | M245: v001 | N245: 25×25×11.9m（5×5 个 5m 槽；四墙各 5 槽，墙槽心 ±10/±5/0）；82 个集合实例 / 引用 81 个已验收资产包 / 本文件自持网格 0；西·东墙 lane 0 对穿门洞 2.2×2.5m（净空底 0.30m、门楣 2.80m）；QA PASS（9 组断言） | O245: art_source/environments/tower_zones/expedition/source/room_types/std_25x25/v001/标准房间种类_四墙平房_25x25m_v001.blend | P245: art_source/environments/tower_zones/expedition/source/room_types/std_25x25/v001/build_std25_room_v001.py；摆位真源 同目录 std_25x25_v001.layout.json（由 _scratch/std25_layout/plan_std25_layout.py 算出）；白盒 art_source/design/whitebox/tower_zones/expedition_01/v001/data/room_templates/std_25x25.json | Q245: 远征关卡01;标准房间;四墙平房;房间种类;25×25m;组件拼装;LibraryLink;西东对穿;office_room;bridge_room | R245: =LOWER(TRIM(C245)&"|"&TRIM(D245)&"|"&TRIM(E245)&"|"&TRIM(F245)&"|"&TRIM(H245)&"|"&TRIM(I245)) | S245: =IF(COUNTIF($R$6:$R$928,R245)>1,"重复","唯一") | T245: acce620bf5f87f6cdac33f884d244dbbb1075b3b88b6354264934bc869da17c7 | U245: 摩斯拉 | V245: 2026-09-28 | W245: 用户设计（组件拼装；组件来源 office_room/v001 与 bridge_room/v002 两批已验收房型源） | X245: — | Y245: 服务远征关卡01 的 room_07（标准房间，中心 −17.5/−87.5）。与 office/bridge 两行的语义差异：那两行是房型**自持几何**的组件源，本行是 skill 03 意义上的**实例布局源** ⇒ 自持几何 0、组件几何/材质/根原点一律不改、不缩放进位、不 Append 复制网格。与本房型摆位真源 std_25x25_v001.layout.json 配套的清单为同目录 component_inventory.json（记**被引用的**81 个外部资产包及本房用法）与 room_type_manifest.json。门位冻结为西/东墙 lane 0 对穿（依据设计页 §4.2.1 与参考图 08-标准房间.svg）。未导 GLB、未接 Godot。 2026-09-28：远征关卡01完成每房独立静态 TSCN 改造。start、room_01…room_10、boss、extraction 各由显式 static_layout_scene_path 加载 runtime/room_instances/f00_<room_id>/room_static_layout.tscn；场景只拥有顶层 PackedScene prefab 实例根，不递归改 prefab 内部 owner，避免内部网格/碰撞展开。静态 TSCN 接管视觉与固定碰撞，代码继续负责动态门、触发器、刷怪、导航、流送、存档、交互与撤离。专项验收 EXPEDITION_ROOM_STATIC_SCENES_OK checks=209 rooms=13、ROOM_TYPE_COMPONENT_REPLAY_OK checks=4540，退出码 0 且无 RID/ObjectDB/resource 泄漏。完整 verify_expedition_level01_flow 仍因数据库房/撤离房周界碰撞及入口安全房旧快照兼容字段失败；本次不把程序壳体转正为正式美术资产。
A246: ENV-EXPEDITION-L01-ROOM-DB-70X50 | B246: 远征关卡01 数据库房间 数据机房 40×30m 房间种类源 | C246: 场景 | D246: db_room | E246: expedition_01_db_room | F246: room_type | H246: Top3D / Blender Z-up | I246: scene_art / reference_derived_with_linked_shell | J246: 远征关卡01 专用；room_02 / room_06 / room_10 三处实例共用同一房型源（同 db_70x50 模板）。本轮按参考图做 db_01 布局（主体 40×25 + 南侧中段外凸 10×5）；墙体与地砖 Library Link 复用 office_room/v001，其余 37 个组件包为数据库机房专属新制 | K246: 正式美术已接入 | L246: P1 | M246: v014 | N246: 40×30m；房型组件库 v014：35 个唯一组件 / 86 个实例；运行时 3 间房均按 component_instances.json 重放，42 块主层地砖换通用 C01/C02，44 个普通房型组件，unresolved=0，门 2 扇；db_02 仍待另行制作 | O246: art_source/environments/tower_zones/expedition/source/room_types/db_room/v002/ | P246: art_source/environments/tower_zones/expedition/source/room_types/db_room/v002/；art_source/environments/tower_zones/expedition/source/common_components/v014/component_catalog.json；component_instances.json；运行时 PackedScene 注册表 shell_component_catalog.json | Q246: 远征关卡01;数据库房间;数据机房;房间种类;40×30m;db_01;db_02;机柜;工作台;壁挂大屏;工具车;电缆盘;警示边带;LibraryLink;office_room | R246: =LOWER(TRIM(C246)&"|"&TRIM(D246)&"|"&TRIM(E246)&"|"&TRIM(F246)&"|"&TRIM(H246)&"|"&TRIM(I246)) | S246: =IF(COUNTIF($R$6:$R$928,R246)>1,"重复","唯一") | T246: ba0d29bcd4e89d901fa3102f66fa449ea6028bcb860c5be170bdc50fd31303c6 | U246: 摩斯拉 | V246: 2026-09-28 | W246: 用户设计（参考图 docs/v0.1/design/refs/expedition01/数据库房间01.jpg；墙件与地砖复用 office_room/v001 已验收组件） | X246: — | Y246: 2026-09-27：数据库房 v014 已完成 35 个独立 GLB/PackedScene 导出并接入 Godot。room_02 / room_06 / room_10 均通过组件重放验收（86 实例、42 通用棋盘砖、44 普通组件、unresolved=0、2 扇门）；room_06 当前暂重放 db_01 默认布局，db_02 变体仍待另行制作。 2026-09-28：远征关卡01完成每房独立静态 TSCN 改造。start、room_01…room_10、boss、extraction 各由显式 static_layout_scene_path 加载 runtime/room_instances/f00_<room_id>/room_static_layout.tscn；场景只拥有顶层 PackedScene prefab 实例根，不递归改 prefab 内部 owner，避免内部网格/碰撞展开。静态 TSCN 接管视觉与固定碰撞，代码继续负责动态门、触发器、刷怪、导航、流送、存档、交互与撤离。专项验收 EXPEDITION_ROOM_STATIC_SCENES_OK checks=209 rooms=13、ROOM_TYPE_COMPONENT_REPLAY_OK checks=4540，退出码 0 且无 RID/ObjectDB/resource 泄漏。完整 verify_expedition_level01_flow 仍因数据库房/撤离房周界碰撞及入口安全房旧快照兼容字段失败；本次不把程序壳体转正为正式美术资产。
A247: ENV-EXPEDITION-L01-BOSS-ROOM | B247: 远征关卡01 Boss竞技场 故障数据库 50×40m 房间种类源 | C247: 场景 | D247: boss_room | E247: expedition_01_boss_room | F247: room_type | H247: Top3D / Blender Z-up | I247: scene_art / reference_derived | J247: 远征关卡01 专用；boss 房（boss_50x40，50×40m）。房型套件为独立一库（common_components/v011，与 office / bridge 两批不混用） | K247: 正式美术已接入 | L247: P1 | M247: v002 | N247: 50×40×11.9m（10×8 个 5m 槽 / 72 个墙位）；组件库 v011：38 个唯一组件 / 210 个实例（17 族）；主层地砖 80 格运行时换通用 C01/C02 棋盘砖；门位 2（西 / 东 lane −2.5）；QA PASS（专项探针 2051 项断言） | O247: art_source/environments/tower_zones/expedition/source/room_types/boss_room/v002/Boss房种类_故障数据库_50x40m_v002.blend | P247: art_source/environments/tower_zones/expedition/source/room_types/boss_room/v002/room_type_manifest.json；art_source/environments/tower_zones/expedition/source/common_components/v011/component_plan.json；component_slug_map.json；归并工具 scripts/blender/regroup_room_type_components.py | Q247: 远征关卡01;Boss竞技场;故障数据库;房间种类;50×40m;服务器机柜;主屏;桥架;组件库;v011 | R247: =LOWER(TRIM(C247)&"|"&TRIM(D247)&"|"&TRIM(E247)&"|"&TRIM(F247)&"|"&TRIM(H247)&"|"&TRIM(I247)) | S247: =IF(COUNTIF($R$6:$R$928,R247)>1,"重复","唯一") | T247: 3c533d323faae3667459b61f49f15608add757fccd6d6b83d6308d35fdbb3ec2 | U247: 摩斯拉 | V247: 2026-09-28 | W247: 用户设计（参考图见 room_type_manifest.json 的 reference_image） | X247: — | Y247: 服务远征关卡01 的 boss 房（BOSS，中心 -20/0/-85）。房型套件独立一库（common_components/v011，38 组件 / 210 实例），运行时按 component_instances.json 重放；主层地砖统一换通用 C01/C02 棋盘砖，墙 / 家具 / 标识 / 碎屑保留自有美术。2026-09-27（同轮，业主裁定）：① 组件库 v011（39 个 blend）UV 配色保色相提亮 3 个挡位，深色面（HSV 明度 <40%）占比 72.6% → 24.5%（母版 39930 面中移动 39444 面）。② 材质主面判据：把面积占多数的 `01_精工金属` 槽改指 `02_细腻哑光`（只改槽指向，不动 PBR 参数 / 几何 / UV / 色盘格），改 60 槽 / 17896 面，金属面积占比 37.4% → 2.9%；按判据保留金属的小件为 `workstation_a/b/c`、`chair`、`archive_shelf`、`debris_*`。③ 按新源重导出 98 个稳定 GLB（本库 38 件）并重建 PackedScene / 组件目录，Godot 重导后房型重放验收全通过（boss 210 实例、unresolved=0）。房型概念源 blend 未动，SHA-256 不变。④ 2026-09-27（同轮收尾）：补齐**逐房间运行时装配清单** —— `boss` 产出 `runtime/room_instances/f00_boss/room_runtime_manifest.json` + `acceptance/`，`assembly_route = room_type_layout_replay`。清单记 210 实例（room_type_component 58 / solid_wall 72 / floor_tile 80）、组件库源哈希 5047d566…、门位不冻结、按种子现算（RUN_SEED=77001199 实测西接 room_10 / 东接撤离屋 —— 与静态兜底样例推导的「南接撤离屋」不一致，落地以探针为准）、运行时门扇节点数 2。⑤ 2026-09-27（同轮收尾·组件库升版）：按 `02-battle-room-component-decomposer` 第 184 行「生成组件源版本，不覆盖房间种类源，也不覆盖历史组件源」，把**独立组件库由原地改写改为正式升版 v008 → v011**（目录 `common_components/v008` → `v011`，母版改名 `…_v011.blend`，`component_slug_map.json` 与 `component_catalog.json` 的 `regroup_analysis` 随迁）：v011 = 提亮 + 亚光校正后的当前源；原 v008 目录由 `git checkout HEAD --` 恢复为**提亮前的历史源**（只读留档）。同步改写全部引用：① `component_catalog.json` 的 `version` / `component_library` / 38 个包的 `component_library_blend`；② `component_instances.json` 的 `library`（`source_library` = v001 与 `source_blend_sha256` 指向**整屋／房间种类源** v001 母版，**未动**）；③ 组件库级 `runtime_manifest.json` 与 `boss` 的 `room_runtime_manifest.json`；④ 98 个 PackedScene 的 `metadata/asset_version` 与 `source_blend`；⑤ `FloorPlanGenerator.ROOM_TYPE_LAYOUT_SOURCES`、两个导出脚本的 `LIBRARIES`、`build_room_runtime_manifests.py` 的 `ROOM_TYPE_BINDING`、重放验收探针 `expected_version`；⑥ 本行 J / N / P / Q 列的版本串。组件库母版 SHA-256：v008 `9ffd58e5…`（提亮前）→ v011 `b05b0151…`。升版后重导出 98 个稳定 GLB 并重建 PackedScene 与组件目录，Godot 重导后房型重放验收 2051 项断言全通过（boss 210 实例、unresolved=0、门位净空 0 覆盖）。 2026-09-28：远征关卡01完成每房独立静态 TSCN 改造。start、room_01…room_10、boss、extraction 各由显式 static_layout_scene_path 加载 runtime/room_instances/f00_<room_id>/room_static_layout.tscn；场景只拥有顶层 PackedScene prefab 实例根，不递归改 prefab 内部 owner，避免内部网格/碰撞展开。静态 TSCN 接管视觉与固定碰撞，代码继续负责动态门、触发器、刷怪、导航、流送、存档、交互与撤离。专项验收 EXPEDITION_ROOM_STATIC_SCENES_OK checks=209 rooms=13、ROOM_TYPE_COMPONENT_REPLAY_OK checks=4540，退出码 0 且无 RID/ObjectDB/resource 泄漏。完整 verify_expedition_level01_flow 仍因数据库房/撤离房周界碰撞及入口安全房旧快照兼容字段失败；本次不把程序壳体转正为正式美术资产。
A248: ENV-OPENWORLD-TOWER02 | B248: 开放世界 塔2 施工高楼 70×50m | C248: 场景 | D248: environment_kit_3d | E248: open_world_tower_02 | F248: building_root | H248: Top3D / Godot Y-up | I248: construction | J248: 开放世界独立建筑，与主塔平级 | K248: 已导入；优化完成 | L248: P1 | M248: v004 | N248: 主体70×50m；施工屋顶 | O248: assets/art/environments/open_world/runtime/tower_02/env_tower_02_root_top3d.tscn | P248: 用户参考图；docs/v0.1/development/2026-09-29_openworld_tower02_source.md | Q248: 塔2;施工高楼;塔吊独立合集;错层屋顶;灰色顶面;v004 | R248: =LOWER(TRIM(C248)&"|"&TRIM(D248)&"|"&TRIM(E248)&"|"&TRIM(F248)&"|"&TRIM(H248)&"|"&TRIM(I248)) | S248: =IF(COUNTIF($R$6:$R$928,R248)>1,"重复","唯一") | T248: d0efc5a27ac1db77e0abfbb79db2dedb8f031eb6852447d69eae3fed81c1e8fb | U248: Codex | V248: 46301 | W248: 用户提供参考图，仅据图建模 | X248: 塔2 | Y248: 仅表现；无碰撞、导航或玩法脚本；原始Blender保留不变。原始Blender v003保留不变；v004优化源：art_source/environments/open_world/source/tower_02/export/v004/tower02_game_output_optimized_v004.blend；运行时总三角面80952。
A249: ENV-OPENWORLD-TOWER03 | B249: 开放世界 塔楼03 设备天台办公楼 70×44m | C249: 场景 | D249: environment_kit_3d | E249: open_world_tower_03 | F249: building_root | H249: Top3D / Godot Y-up | I249: office_rooftop | J249: 开放世界独立塔楼，与主塔、塔2平级 | K249: 已导入；优化完成 | L249: P1 | M249: v001 | N249: 主体70×44m；屋顶40m、机房8m | O249: assets/art/environments/open_world/runtime/tower_03/env_tower_03_root_top3d.tscn | P249: 用户参考图1（天台布局）及图2（整体结构）；art_source/environments/open_world/source/tower_03/v001/catalog.json | Q249: 塔楼03;设备天台;办公楼;风机;风管;通信桅杆;卫星天线;70×44m | R249: =LOWER(TRIM(C249)&"|"&TRIM(D249)&"|"&TRIM(E249)&"|"&TRIM(F249)&"|"&TRIM(H249)&"|"&TRIM(I249)) | S249: =IF(COUNTIF($R$6:$R$928,R249)>1,"重复","唯一") | T249: d3f2eafc1268b6a4feadfd71fa3233f3c3aa0c120ec5e44a6ecbddcfd5a2d078 | U249: Codex | V249: 46295 | W249: 用户提供参考图，仅据图建模 | X249: 塔楼03 | Y249: 仅表现；无碰撞、导航或玩法脚本；原始Blender保留不变。源：art_source/environments/open_world/source/tower_03/v001/塔楼03_设备天台办公楼_v001.blend
A250: ENV-OPENWORLD-TOWER02-FLOOR-00 | B250: 塔2 楼层_00_楼板柱梁 | C250: 场景 | D250: environment_module_3d | E250: open_world_tower_02 | F250: floor_00 | G250: ENV-OPENWORLD-TOWER02 | H250: Top3D / Godot Y-up | I250: default | J250: 开放世界塔楼独立可复用组件 | K250: 已导入；优化完成 | L250: P1 | M250: v004 | N250: 70.130×50.113×4.600m (Blender XYZ) | O250: assets/art/environments/open_world/runtime/tower_02/floor_00/env_tower_02_floor_00_root_top3d.tscn | P250: docs/v0.1/development/2026-09-30_openworld_towers_runtime_import.md | Q250: 塔2 楼层_00_楼板柱梁;v004 | R250: =LOWER(TRIM(C250)&"|"&TRIM(D250)&"|"&TRIM(E250)&"|"&TRIM(F250)&"|"&TRIM(H250)&"|"&TRIM(I250)) | S250: =IF(COUNTIF($R$6:$R$928,R250)>1,"重复","唯一") | T250: c8b22eb571918db728e3da148ba72779006ce41dce8b8df7089f610aa3510401 | U250: Codex | V250: 46301 | W250: 用户参考图；项目自制模型 | X250: floor_00 | Y250: 仅表现；无碰撞、导航或玩法脚本；原始Blender保留不变。原始Blender v003保留不变；v004优化源：art_source/environments/open_world/source/tower_02/export/v004/tower02_game_output_optimized_v004.blend；运行时总三角面80952。
A251: ENV-OPENWORLD-TOWER02-FLOOR-01 | B251: 塔2 楼层_01_楼板柱梁 | C251: 场景 | D251: environment_module_3d | E251: open_world_tower_02 | F251: floor_01 | G251: ENV-OPENWORLD-TOWER02 | H251: Top3D / Godot Y-up | I251: default | J251: 开放世界塔楼独立可复用组件 | K251: 已导入；优化完成 | L251: P1 | M251: v004 | N251: 70.130×50.113×4.600m (Blender XYZ) | O251: assets/art/environments/open_world/runtime/tower_02/floor_01/env_tower_02_floor_01_root_top3d.tscn | P251: docs/v0.1/development/2026-09-30_openworld_towers_runtime_import.md | Q251: 塔2 楼层_01_楼板柱梁;v004 | R251: =LOWER(TRIM(C251)&"|"&TRIM(D251)&"|"&TRIM(E251)&"|"&TRIM(F251)&"|"&TRIM(H251)&"|"&TRIM(I251)) | S251: =IF(COUNTIF($R$6:$R$928,R251)>1,"重复","唯一") | T251: 6d742b32f7cbeb968bd25c2b5334aefb87311800ab227492fc252a43e0c59960 | U251: Codex | V251: 46301 | W251: 用户参考图；项目自制模型 | X251: floor_01 | Y251: 仅表现；无碰撞、导航或玩法脚本；原始Blender保留不变。原始Blender v003保留不变；v004优化源：art_source/environments/open_world/source/tower_02/export/v004/tower02_game_output_optimized_v004.blend；运行时总三角面80952。
A252: ENV-OPENWORLD-TOWER02-FLOOR-02 | B252: 塔2 楼层_02_楼板柱梁 | C252: 场景 | D252: environment_module_3d | E252: open_world_tower_02 | F252: floor_02 | G252: ENV-OPENWORLD-TOWER02 | H252: Top3D / Godot Y-up | I252: default | J252: 开放世界塔楼独立可复用组件 | K252: 已导入；优化完成 | L252: P1 | M252: v004 | N252: 70.130×50.113×4.600m (Blender XYZ) | O252: assets/art/environments/open_world/runtime/tower_02/floor_02/env_tower_02_floor_02_root_top3d.tscn | P252: docs/v0.1/development/2026-09-30_openworld_towers_runtime_import.md | Q252: 塔2 楼层_02_楼板柱梁;v004 | R252: =LOWER(TRIM(C252)&"|"&TRIM(D252)&"|"&TRIM(E252)&"|"&TRIM(F252)&"|"&TRIM(H252)&"|"&TRIM(I252)) | S252: =IF(COUNTIF($R$6:$R$928,R252)>1,"重复","唯一") | T252: cccd7b5d71b58bb75a93cab95dd3dcb0690a1077bea095dbae3b0163df3f2d82 | U252: Codex | V252: 46301 | W252: 用户参考图；项目自制模型 | X252: floor_02 | Y252: 仅表现；无碰撞、导航或玩法脚本；原始Blender保留不变。原始Blender v003保留不变；v004优化源：art_source/environments/open_world/source/tower_02/export/v004/tower02_game_output_optimized_v004.blend；运行时总三角面80952。
A253: ENV-OPENWORLD-TOWER02-FLOOR-03 | B253: 塔2 楼层_03_楼板柱梁 | C253: 场景 | D253: environment_module_3d | E253: open_world_tower_02 | F253: floor_03 | G253: ENV-OPENWORLD-TOWER02 | H253: Top3D / Godot Y-up | I253: default | J253: 开放世界塔楼独立可复用组件 | K253: 已导入；优化完成 | L253: P1 | M253: v004 | N253: 70.130×50.113×4.600m (Blender XYZ) | O253: assets/art/environments/open_world/runtime/tower_02/floor_03/env_tower_02_floor_03_root_top3d.tscn | P253: docs/v0.1/development/2026-09-30_openworld_towers_runtime_import.md | Q253: 塔2 楼层_03_楼板柱梁;v004 | R253: =LOWER(TRIM(C253)&"|"&TRIM(D253)&"|"&TRIM(E253)&"|"&TRIM(F253)&"|"&TRIM(H253)&"|"&TRIM(I253)) | S253: =IF(COUNTIF($R$6:$R$928,R253)>1,"重复","唯一") | T253: b6194aec005742f98c5597e07b96f5f71968605b6b65f6d9f8efefd87c4ba009 | U253: Codex | V253: 46301 | W253: 用户参考图；项目自制模型 | X253: floor_03 | Y253: 仅表现；无碰撞、导航或玩法脚本；原始Blender保留不变。原始Blender v003保留不变；v004优化源：art_source/environments/open_world/source/tower_02/export/v004/tower02_game_output_optimized_v004.blend；运行时总三角面80952。
...

Sheet 3D-场景通用
A1: ShellStorm2 · 场景通用组件 3D Prefab
A2: 关卡结构、地板、墙体、走廊、楼梯与楼板；场景模型统一引用 assets/art/shared/palette/设施低亮多巴胺色盘_10x10_512.png。
A4: AssetID | B4: 中文名 | C4: Prefab路径 | D4: GLB模型路径 | E4: Blender源文件 | F4: 功能说明 | G4: 功能脚本路径 | H4: 碰撞开关 | I4: 碰撞归属 | J4: 碰撞方式 | K4: 标准尺寸 | L4: 原点与朝向 | M4: 使用位置 | N4: 制作状态 | O4: 版本 | P4: 备注
A5: ENV-BASE99-ART-LAYOUT-3D | B5: 基地区美术 | C5: assets/art/environments/tower_zones/base/runtime/zone_base.tscn | E5: art_source/design/blender/base_facility_layout/source/base_facility_runtime_layout_hq_v026.blend; art_source/design/blender/base_facility_layout/source/base_facility_runtime_layout_hq_v026.godot.json | F5: Blocks/Base/Art区块入口；运行时桥接基地设施与美术布局 | G5: src/world3d/DungeonRoom3D.gd | H5: 无 | I5: 无 | J5: 无 | K5: 未声明 | L5: 未声明 | M5: Blocks/Base；99F | N5: 原型已接入 | O5: v002 | P5: 根节点=Art(Node3D)；Godot短名和Blender v026源通过账本映射；未重新导入GLB。
A6: ENV-BASE99-WALL-PLAIN-5X12 | B6: 基地99层普通墙体5×12米 | C6: assets/art/environments/base_facility_3d/runtime/env_base99_wall_plain_5x12/env_base99_wall_plain_5x12_root_top3d.tscn | D6: assets/art/environments/base_facility_3d/components/env_base99_wall_plain_5x12/env_base99_wall_plain_5x12_visual_top3d.glb | E6: art_source/environments/base_facility_3d/source/wall_height12/env_base99_wall_plain_5x12_source_v002.blend | F6: 5米网格墙视觉；逻辑高12米，可见高11.9米；共享色盘由Godot导入后处理绑定 | G6: src/world3d/DungeonRoom3D.gd | H6: 开 | I6: 外部脚本 | J6: BoxShape3D | K6: 5×12×0.36m逻辑外廓；11.9m可见墙；无自带碰撞 | L6: bottom_center；-Z | M6: 99/100层基地普通直墙 | N6: 正式美术已接入 | O6: v002 | P6: 根节点=基地99层普通墙体5x12米(Node3D)；PaletteUV共享色盘；碰撞归DungeonRoom3D
A7: ENV-BASE-WORLD-KIT-3D | B7: 入口基地3D环境套件 | C7: assets/art/environments/base_world_3d/env_base_world_kit_top3d.tscn | F7: Godot原生场景结构Prefab；由关卡脚本按模块实例化 | G7: src/base3d/BaseWorld3DEnvironment.gd | H7: 开 | I7: Prefab自身 | J7: 脚本生成 | K7: 约1:100迁移/程序几何 | L7: 未声明 | M7: 入口基地地图 | N7: 原型已接入 | O7: v001 | P7: 根节点=BaseWorld3DEnvironment(Node3D)
A8: ENV-DUNGEON-RUNTIME-3D | B8: 3D随机关卡通用房间套件 | C8: assets/art/environments/dungeon_3d/env_dungeon_runtime_kit_top3d.tscn | F8: Godot原生场景结构Prefab；由关卡脚本按模块实例化 | G8: src/world3d/DungeonRoom3D.gd | H8: 开 | I8: Prefab自身 | J8: 脚本生成 | K8: PackedScene/三档程序几何 | L8: 未声明 | M8: 四主题副本/随机房间 | N8: 原型已接入 | O8: v001 | P8: 根节点=DungeonRoom3D(Node3D)
A9: ENV-TRAINING-RANGE-KIT-3D | B9: 独立3D训练靶场套件 | C9: assets/art/environments/training_range_3d/env_training_range_kit_top3d.tscn | F9: Godot原生场景结构Prefab；由关卡脚本按模块实例化 | G9: src/training3d/TrainingRangeEnvironment3D.gd | H9: 开 | I9: Prefab自身 | J9: 脚本生成 | K9: PackedScene/程序环境 | L9: 未声明 | M9: 独立训练地图 | N9: 原型已接入 | O9: v001 | P9: 根节点=TrainingRangeEnvironment3D(Node3D)
A10: ENV-TOWER-CORNER-L-5M | B10: 塔楼L型转角5米 | C10: assets/art/environments/base_facility_3d/runtime/env_base99_corner_l_5m/env_base99_corner_l_5m_collision_top3d.tscn | D10: assets/art/environments/base_facility_3d/components/env_base99_corner_l_5m/env_base99_corner_l_5m_visual_top3d.glb | E10: art_source/environments/base_facility_3d/source/wall_height12/env_base99_corner_l_5m_source_v002.blend | F10: 基地转角视觉包；逻辑高12米，可见高11.9米；共享色盘由Godot导入后处理绑定 | G10: src/world3d/DungeonRoom3D.gd | H10: 开 | I10: 外部脚本 | J10: BoxShape3D双墙臂 | K10: 5×5×12m逻辑体；11.9m可见墙 | L10: inside_corner_floor；-Z | M10: 99层基地内外围转角 | N10: 正式美术已接入 | O10: v004 | P10: 稳定AssetID；视觉包无重复碰撞；12m双臂碰撞归DungeonRoom3D；PaletteUV共享色盘
A11: ENV-TOWER-CORNER-L-PARAPET-5M | B11: 塔楼L型女儿墙转角5米 | C11: assets/art/props/dungeon_3d/prp_corner_L_parapet_5m.tscn | F11: Godot原生场景结构Prefab；由关卡脚本按模块实例化 | G11: src/world3d/TowerFloorStage3D.gd | H11: 开 | I11: Prefab自身 | J11: BoxShape3D | K11: 未声明 | L11: 未声明 | M11: 场景通用组件 | N11: 程序占位 | O11: v001 | P11: 根节点=PrpCornerLParapet5m(Node3D)；2026-08-18扫描补登记资产主表
A12: ENV-TOWER-CORNER-T-5M | B12: 塔楼T型转角5米 | C12: assets/art/props/dungeon_3d/prp_corner_T_5m.tscn | F12: Godot原生场景结构Prefab；由关卡脚本按模块实例化 | G12: src/world3d/DungeonRoom3D.gd | H12: 开 | I12: Prefab自身 | J12: BoxShape3D | K12: 未声明 | L12: 未声明 | M12: 场景通用组件 | N12: 程序占位 | O12: v001 | P12: 根节点=PrpCornerT5m(Node3D)；2026-08-18扫描补登记资产主表
A13: ENV-TOWER-CORNER-X-5M | B13: 塔楼十字转角5米 | C13: assets/art/props/dungeon_3d/prp_corner_X_5m.tscn | F13: Godot原生场景结构Prefab；由关卡脚本按模块实例化 | G13: src/world3d/DungeonRoom3D.gd | H13: 开 | I13: Prefab自身 | J13: BoxShape3D | K13: 未声明 | L13: 未声明 | M13: 场景通用组件 | N13: 程序占位 | O13: v001 | P13: 根节点=PrpCornerX5m(Node3D)；2026-08-18扫描补登记资产主表
A14: ENV-DUNGEON-CORRIDOR-CEILING-SEGMENT | B14: 地牢走廊天花段 | C14: assets/art/props/dungeon_3d/prp_corridor_ceiling_segment.tscn | F14: Godot原生场景结构Prefab；由关卡脚本按模块实例化 | G14: src/world3d/DungeonRoom3D.gd | H14: 开 | I14: Prefab自身 | J14: BoxShape3D | K14: 未声明 | L14: 未声明 | M14: 场景通用组件 | N14: 程序占位 | O14: v001 | P14: 根节点=PrpCorridorCeilingSegment(Node3D)；2026-08-18扫描补登记资产主表
A15: ENV-DUNGEON-CORRIDOR-FLOOR-SEGMENT | B15: 地牢走廊地板段 | C15: assets/art/props/dungeon_3d/prp_corridor_floor_segment.tscn | F15: Godot原生场景结构Prefab；由关卡脚本按模块实例化 | G15: src/world3d/DungeonRoom3D.gd | H15: 开 | I15: Prefab自身 | J15: BoxShape3D | K15: 未声明 | L15: 未声明 | M15: 场景通用组件 | N15: 程序占位 | O15: v001 | P15: 根节点=PrpCorridorFloorSegment(Node3D)；2026-08-18扫描补登记资产主表
A16: ENV-DUNGEON-CORRIDOR-STAIR-TREAD | B16: 地牢走廊楼梯踏步 | C16: assets/art/props/dungeon_3d/prp_corridor_stair_tread.tscn | F16: Godot原生场景结构Prefab；由关卡脚本按模块实例化 | G16: src/world3d/DungeonRoom3D.gd | H16: 无 | I16: 无 | J16: 无 | K16: 未声明 | L16: 未声明 | M16: 场景通用组件 | N16: 程序占位 | O16: v001 | P16: 根节点=PrpCorridorStairTread(Node3D)；2026-08-18扫描补登记资产主表
A17: ENV-DUNGEON-CORRIDOR-WALL-SEGMENT | B17: 地牢走廊墙段 | C17: assets/art/props/dungeon_3d/prp_corridor_wall_segment.tscn | F17: Godot原生场景结构Prefab；由关卡脚本按模块实例化 | G17: src/world3d/DungeonRoom3D.gd | H17: 开 | I17: Prefab自身 | J17: BoxShape3D | K17: 未声明 | L17: 未声明 | M17: 场景通用组件 | N17: 程序占位 | O17: v001 | P17: 根节点=PrpCorridorWallSegment(Node3D)；2026-08-18扫描补登记资产主表
A18: ENV-DUNGEON-ROOM-ACCESS-STEP | B18: 房间接入台阶 | C18: assets/art/props/dungeon_3d/prp_room_access_step.tscn | F18: Godot原生场景结构Prefab；由关卡脚本按模块实例化 | G18: src/world3d/DungeonRoom3D.gd | H18: 无 | I18: 无 | J18: 无 | K18: 未声明 | L18: 未声明 | M18: 场景通用组件 | N18: 程序占位 | O18: v001 | P18: 根节点=PrpRoomAccessStep(Node3D)；2026-08-18扫描补登记资产主表
A19: ENV-DUNGEON-ROOM-CORNER-POST | B19: 房间转角立柱 | C19: assets/art/props/dungeon_3d/prp_room_corner_post.tscn | F19: Godot原生场景结构Prefab；由关卡脚本按模块实例化 | G19: src/world3d/DungeonRoom3D.gd | H19: 开 | I19: Prefab自身 | J19: BoxShape3D | K19: 未声明 | L19: 未声明 | M19: 场景通用组件 | N19: 程序占位 | O19: v001 | P19: 根节点=PrpRoomCornerPost(Node3D)；2026-08-18扫描补登记资产主表
A20: ENV-DUNGEON-ROOM-DOOR-LINTEL | B20: 房间门楣 | C20: assets/art/props/dungeon_3d/prp_room_door_lintel.tscn | F20: Godot原生场景结构Prefab；由关卡脚本按模块实例化 | G20: src/world3d/DungeonRoom3D.gd | H20: 无 | I20: 无 | J20: 无 | K20: 未声明 | L20: 未声明 | M20: 场景通用组件 | N20: 程序占位 | O20: v001 | P20: 根节点=PrpRoomDoorLintel(Node3D)；2026-08-18扫描补登记资产主表
A21: ENV-DUNGEON-FACILITY-WALL-DOOR-SIDE | B21: 基地设施门墙侧柱 | C21: assets/art/props/dungeon_3d/prp_room_facility_base_wall_door_side.tscn | F21: Godot原生场景结构Prefab；由关卡脚本按模块实例化 | G21: src/world3d/DungeonRoom3D.gd | H21: 开 | I21: Prefab自身 | J21: BoxShape3D | K21: 未声明 | L21: 未声明 | M21: 场景通用组件 | N21: 程序占位 | O21: v001 | P21: 根节点=PrpRoomFacilityBaseWallDoorSide(Node3D)；2026-08-18扫描补登记资产主表
A22: ENV-DUNGEON-FACILITY-WALL-LINTEL | B22: 基地设施墙门楣 | C22: assets/art/props/dungeon_3d/prp_room_facility_base_wall_lintel.tscn | F22: Godot原生场景结构Prefab；由关卡脚本按模块实例化 | G22: src/world3d/DungeonRoom3D.gd | H22: 开 | I22: Prefab自身 | J22: BoxShape3D | K22: 未声明 | L22: 未声明 | M22: 场景通用组件 | N22: 程序占位 | O22: v001 | P22: 根节点=PrpRoomFacilityBaseWallLintel(Node3D)；2026-08-18扫描补登记资产主表
... A41: ENV-DUNGEON-ROOM-WALL-SEGMENT | B41: 房间普通墙段 | C41: assets/art/props/dungeon_3d/prp_room_wall_segment.tscn | F41: Godot原生场景结构Prefab；由关卡脚本按模块实例化 | G41: src/world3d/DungeonRoom3D.gd | H41: 开 | I41: Prefab自身 | J41: BoxShape3D | K41: 未声明 | L41: 未声明 | M41: 场景通用组件 | N41: 程序占位 | O41: v001 | P41: 根节点=PrpRoomWallSegment(Node3D)；2026-08-18扫描补登记资产主表
A42: ENV-TOWER-FLOOR-TILE-5M | B42: 塔楼5米地砖模块 | C42: assets/art/props/dungeon_3d/prp_tower_floor_tile_5m.tscn | D42: assets/art/environments/tower_descent_3d/components/floor_tile_5m/env_tower_floor_tile_5m_top3d.glb | E42: ../ShellStorm2-backup/2026-10-11_slimming/original_tree/art_source/environments/tower_descent_3d/source/floor_tile_5m/env_tower_floor_tile_5m_source_v002.blend | F42: Godot原生场景结构Prefab；由关卡脚本按模块实例化 | G42: src/world3d/TowerFloorStage3D.gd | H42: 开 | I42: TowerFloorStage3D.FloorSupport | J42: BoxShape3D 5×0.30×5m，由 FloorSupport 按槽位生成（Prefab 不再自带碰撞） | K42: GLB / 5×5×0.3005m / 共享Mesh / MultiMesh平铺 | L42: centered_slab（板厚居中；可视顶面与承重面 Y=0 对齐） | M42: 塔楼六个物理层楼板/335m MultiMesh网格/动态水平通道 | N42: 正式美术已接入 | O42: v002 | P42: 2026-09-17：占位 BoxMesh 替换为正式美术 env_tower_floor_tile_5m_top3d_v002.glb（与 100F/98F 同源同版）。根节点=PrpTowerFloorTile5m(Node3D)，下挂 ImportedModel 引用该 GLB；Prefab 原 FloorTileCollision 已移除，承重碰撞由 TowerFloorStage3D.FloorSupport 生成。资产声明 preserve_authored_palette=true，运行时不再用暖色 A/B 主题地砖材质覆盖，保留美术自带双表面 PaletteUV。原点契约 centered_slab，运行时按 -FLOOR_THICKNESS*0.5 偏移对齐承重面 Y=0。
A43: ENV-TOWER-STAIRWELL-GENERIC-12M | B43: 楼梯B（99→98通用） | C43: assets/art/environments/tower_descent_3d/runtime/env_tower_stairwell_generic_12m/env_tower_stairwell_generic_12m_root_top3d.tscn | D43: assets/art/environments/tower_descent_3d/components/env_tower_stairwell_generic_12m_top3d.glb | E43: art_source/environments/tower_descent_3d/source/stairs_12m/stairwell_art_v021/env_tower_stairwell_dual_art_source_v021.blend | F43: Blocks/Stairs/Stair_B；PackedScene v002实例化3个优化网格，保持v021完整视觉与楼层接口 | G43: src/world3d/TowerDescent3D.gd | H43: 开 | I43: TowerDescent3D运行时包装 | J43: ConcavePolygonShape3D（1个Walkable + 1个EnclosureWall） | K43: 15×30m占地 / 12m层差 / v021完整墙地楼梯与装饰 | L43: v002；Z-up；米制；楼层合同原点 | M43: 塔楼跨层楼梯间 | N43: 正式美术已接入 | O43: v002 | P43: 2026-09-15：v021正式美术已导出、共享色盘导入并替换临时资产；3网格运行优化，结构/流程/真实渲染验收通过；v001保留回滚。
A44: ENV-TOWER-STAIRWELL-ROOFTOP-12M | B44: 楼梯A（100→99天台） | C44: assets/art/environments/tower_descent_3d/runtime/env_tower_stairwell_rooftop_12m/env_tower_stairwell_rooftop_12m_root_top3d.tscn | D44: assets/art/environments/tower_descent_3d/components/env_tower_stairwell_rooftop_12m_top3d.glb | E44: art_source/environments/tower_descent_3d/source/stairs_12m/stairwell_art_v021/env_tower_stairwell_dual_art_source_v021.blend | F44: Blocks/Stairs/Stair_A；PackedScene v002实例化3个优化网格，保持v021完整视觉与楼层接口 | G44: src/world3d/TowerDescent3D.gd | H44: 开 | I44: TowerDescent3D运行时包装 | J44: ConcavePolygonShape3D（1个Walkable + 1个EnclosureWall） | K44: 15×30m占地 / 12m层差 / v021完整墙地楼梯与装饰 | L44: v002；Z-up；米制；楼层合同原点 | M44: 塔楼跨层楼梯间 | N44: 正式美术已接入 | O44: v002 | P44: 2026-09-15：v021正式美术已导出、共享色盘导入并替换临时资产；3网格运行优化，结构/流程/真实渲染验收通过；v001保留回滚。
A45: ENV-TOWER-WALL-DOOR-5M | B45: 塔楼5米带门墙模块 | C45: assets/art/props/dungeon_3d/prp_tower_wall_door_5m.tscn | D45: assets/art/environments/tower_descent_3d/components/env_tower_wall_door_5m_top3d.glb | E45: ../ShellStorm2-backup/2026-10-11_slimming/original_tree/art_source/environments/tower_descent_3d/source/wall_height12/env_tower_wall_door_5m_source_v003.blend | F45: Godot原生场景结构Prefab；由关卡脚本按模块实例化 | G45: src/world3d/DungeonRoom3D.gd | H45: 开 | I45: Prefab自身（3×BoxShape3D 代理）+ DungeonRoom3D | J45: 3×BoxShape3D：左/右门柱 1.4×12×0.30（x=∓1.8）+ 门楣 2.2×9.5×0.30（y 底=2.5），门洞镂空可通行 | K45: 5×0.30×11.9m可见墙；12m逻辑碰撞；2.2×2.5m净开口 | L45: bottom_center（几何 Y=0..11.9）；朝 +Z | M45: 5m墙位/2.2m净宽/2.5m净高/独立门扇 | N45: 正式美术已接入 | O45: v003 | P45: 2026-09-17：占位 BoxMesh 替换为正式美术 env_tower_wall_door_5m_top3d_v003.glb。根节点=PrpTowerWallDoor5m(Node3D)，下挂 ImportedModel；美术自带静态门扇 DoorLeaf_OPEN 置 visible=false，门扇改由运行时 RoomDoor3D.DoorPanel 提供（与基地99层带门墙同规范，GLB 只作墙体/门框）。保留原 3×BoxShape3D 碰撞代理（门柱 2 + 门楣 1，门洞镂空可通行）。资产声明 preserve_authored_palette=true，保留美术自带材质，不再用塔楼暖色 A/B 主题覆盖。
A46: ENV-TOWER-WALL-PARAPET-5M | B46: 塔楼5米楼顶女儿墙模块 | C46: assets/art/props/dungeon_3d/prp_tower_wall_parapet_5m.tscn | D46: assets/art/environments/tower_descent_3d/components/env_tower_wall_parapet_5m_top3d.glb | E46: 10C_MOD_WALL_PARAPET_5M_U01（Blender 集合）；export_env_tower_5m_modules_v001.py | F46: Godot原生场景结构Prefab；由关卡脚本按模块实例化 | G46: src/world3d/TowerFloorStage3D.gd | H46: 开 | I46: TowerFloorStage3D | J46: BoxShape3D 5×1.5×0.30，由 OuterBoundaryCollision 按槽位生成（Prefab 不再自带碰撞） | K46: GLB / 5×0.30×1.50m / 共享Mesh | L46: bottom_center（几何 Y=0..1.50）；朝 +Z | M46: 335m楼顶四周边界/268段MultiMesh围栏 | N46: 正式美术已接入 | O46: v001 | P46: 2026-09-17：占位 BoxMesh 替换为正式美术 env_tower_wall_parapet_5m_top3d_v001.glb。根节点=PrpTowerWallParapet5m(Node3D)，下挂 ImportedModel；Prefab 视觉专用（visual_only），楼顶四周边界碰撞由 TowerFloorStage3D.OuterBoundaryCollision 按 0.30m 代理生成。资产声明 preserve_authored_palette=true，保留美术自带 PaletteUV，不再用塔楼暖色 A/B 主题覆盖。原点契约 bottom_center（几何 Y=0..1.50）。
A47: ENV-TOWER-WALL-PARAPET-DOOR-5M | B47: 塔楼带门女儿墙5米 | C47: assets/art/props/dungeon_3d/prp_tower_wall_parapet_door_5m.tscn | F47: Godot原生场景结构Prefab；由关卡脚本按模块实例化 | G47: src/world3d/TowerFloorStage3D.gd | H47: 开 | I47: Prefab自身 | J47: BoxShape3D | K47: 未声明 | L47: 未声明 | M47: 场景通用组件 | N47: 程序占位 | O47: v001 | P47: 根节点=PrpTowerWallParapetDoor5m(Node3D)；2026-08-18扫描补登记资产主表
A48: ENV-TOWER-WALL-SOLID-5M | B48: 塔楼5米满高实墙模块 | C48: assets/art/props/dungeon_3d/prp_tower_wall_solid_5m.tscn | D48: assets/art/environments/tower_descent_3d/components/env_tower_wall_solid_5m_top3d.glb | E48: art_source/environments/tower_descent_3d/source/wall_height12/env_tower_wall_solid_5m_source_v004.blend（派生自 art_source/environments/tower_zones/battle/source/common_components/v007/env_battle_common_components_source_v007.blend） | F48: Godot原生场景结构Prefab；由关卡脚本按模块实例化 | G48: src/world3d/DungeonRoom3D.gd | H48: 开 | I48: DungeonRoom3D + TowerFloorStage3D | J48: DungeonRoom3D TowerWallCollision_*_Run 0.30m 代理；视觉走 MultiMesh，Prefab 不再自带碰撞 | K48: GLB / 可视包络 5×11.9×0.4675m（结构阻挡 0.30m）/ 12m逻辑碰撞 / 共享Mesh | L48: bottom_center（几何 Y=0..11.9）；朝 +Z | M48: 整层外墙/65m核心/探索房内墙/5m正交走廊 | N48: 正式美术已接入 | O48: v004 | P48: 2026-09-17：占位 BoxMesh 替换为正式美术（与 100F/98F 同源同版）。根节点=PrpTowerWallSolid5m(Node3D)，下挂 ImportedModel；Prefab 视觉专用（visual_only），结构碰撞由 DungeonRoom3D.TowerWallCollision_*_Run 与 TowerFloorStage3D.OuterBoundaryCollision_* 按 0.30m 代理生成。资产声明 preserve_authored_palette=true——塔楼 MultiMesh 不再套 WALL_SOLID_MATERIAL_A/B 单色主题，保留美术自带 PaletteUV（共享色盘角色 01_精工金属_紫色骨架 / 02_细腻哑光_青绿大面 / 04_柔和自发光_UI灯光）。原点契约 bottom_center（几何 Y=0..11.9），运行时按 -mesh.get_aabb().position.y 反算贴合楼面。 2026-09-19：升 v004。GLB 原地覆盖稳定路径（文件名去版本号，节点名统一 ENV_TOWER_WALL_SOLID_5M，根变换为单位矩阵）。结构包络与可视包络分离：bounds_size_m 仍 5×11.9×0.30（结构阻挡），visual_bounds_size_m=5×11.9×0.4675（正面装甲凸到 +Z 0.3175，背面 -0.15）。跨套朝向：Blender 侧 +Y 为厚度轴，B 套（battle/common_components，含 v007）装饰面在 -Y，导出前烘焙 180° 使装饰面落 Godot +Z，与 A 套 prp_tower_* 的 forward_axis="+Z" 对齐。该 GLB 除本 Prefab 外还被 TowerDescent3D 直接 preload（_get_corridor_wall_module_mesh / _build_stair_approach_corridor），故根节点变换必须为单位矩阵。
A49: ENV-BASE99-WALL-DOOR-5X12 | B49: 基地99层带门墙体5×12米 | C49: assets/art/environments/base_facility_3d/runtime/env_base99_wall_door_5x12/env_base99_wall_door_5x12_root_top3d.tscn | D49: assets/art/environments/base_facility_3d/components/env_base99_wall_door_5x12/env_base99_wall_door_5x12_visual_top3d.glb | E49: art_source/environments/base_facility_3d/source/wall_height12/env_base99_wall_door_5x12_source_v004.blend | F49: 仅表现；墙体由DungeonRoom3D按5米槽位组合 | G49: src/world3d/DungeonRoom3D.gd | H49: 开 | I49: 外部脚本 | J49: DungeonRoom3D BoxShape3D | K49: 5×12m逻辑外廓；11.9m可见墙；2.2×2.5m门洞 | L49: bottom_center；-Z | M49: 99层基地 | N49: 正式美术已接入 | O49: v004；GLB无玩法碰撞；DungeonRoom3D持有12m阻挡 | P49: GLB无玩法碰撞；cast_and_receive；替换同路径GLB不改变功能。
A50: ENV-BASE99-FLOOR-PLAIN-5M | B50: 基地99层普通地板5×5米 | C50: assets/art/environments/base_facility_3d/runtime/env_base99_floor_plain_5m/env_base99_floor_plain_5m_root_top3d.tscn | D50: assets/art/environments/base_facility_3d/components/env_base99_floor_plain_5m/env_base99_floor_plain_5m_visual_top3d.glb | E50: ../ShellStorm2-backup/2026-10-11_slimming/original_tree/art_source/environments/base_facility_3d/source/env_base99_modular_room/env_base99_modular_room_assets_clean_v001.blend | F50: 仅表现；5米网格由DungeonRoom3D组合 | G50: src/world3d/DungeonRoom3D.gd | H50: 开 | I50: 外部脚本 | J50: TowerFloorStage BoxShape3D | K50: 5×5×0.30m；平面中心/结构底面原点 | L50: bottom_center；-Z | M50: 99层基地 | N50: 正式美术已接入 | O50: v001 | P50: GLB无玩法碰撞；cast_and_receive；替换同路径GLB不改变功能。
A51: ENV-BASE99-FLOOR-RIVET-5M | B51: 基地99层铆钉铁皮带地板5×5米 | C51: assets/art/environments/base_facility_3d/runtime/env_base99_floor_rivet_5m/env_base99_floor_rivet_5m_root_top3d.tscn | D51: assets/art/environments/base_facility_3d/components/env_base99_floor_rivet_5m/env_base99_floor_rivet_5m_visual_top3d.glb | E51: ../ShellStorm2-backup/2026-10-11_slimming/original_tree/art_source/environments/base_facility_3d/source/env_base99_modular_room/env_base99_modular_room_assets_clean_v001.blend | F51: 仅表现；5米网格由DungeonRoom3D组合 | G51: src/world3d/DungeonRoom3D.gd | H51: 开 | I51: 外部脚本 | J51: TowerFloorStage BoxShape3D | K51: 5×5×0.395m视觉外廓；0.30m结构板+0.095m装饰凸起 | L51: bottom_center；-Z | M51: 99层基地 | N51: 正式美术已接入 | O51: v001 | P51: GLB无玩法碰撞；cast_and_receive；替换同路径GLB不改变功能。
A52: ENV-BASE99-WALL-WINDOW-5X12 | B52: 基地99层带窗墙体5×12米 | C52: assets/art/environments/base_facility_3d/runtime/env_base99_wall_window_5x12/env_base99_wall_window_5x12_root_top3d.tscn | D52: assets/art/environments/base_facility_3d/components/env_base99_wall_window_5x12/env_base99_wall_window_5x12_visual_top3d.glb | E52: art_source/environments/base_facility_3d/source/wall_height12/env_base99_wall_window_5x12_source_v002.blend | F52: 100层上层围护表现；99层禁止实例化 | H52: 开 | I52: 外部脚本 | J52: 上层围护独立结构碰撞 | K52: 5×12m逻辑外廓；11.9m可见墙；底边中心原点 | L52: bottom_center；-Z | M52: 100层基地 | N52: 正式美术已接入 | O52: v002；GLB仅表现；上层围护持有12m阻挡 | P52: GLB仅表现；cast_and_receive；99层使用数量必须为0。
A53: ENV-BASE99-MEZZANINE-20X10-Z7 | B53: 基地99层7米楼中楼楼板 | C53: assets/art/environments/base_facility_3d/runtime/env_base99_mezzanine_20x10_z7/env_base99_mezzanine_20x10_z7_root_top3d.tscn | D53: assets/art/environments/base_facility_3d/components/env_base99_mezzanine_20x10_z7/env_base99_mezzanine_20x10_z7_visual_top3d.glb | E53: ../ShellStorm2-backup/2026-10-11_slimming/original_tree/art_source/environments/base_facility_3d/source/env_base99_modular_room/env_base99_modular_room_assets_clean_v001.blend | F53: 可编辑可行走结构；含底部摄像机净空语义 | G53: src/world3d/Base99WalkableModule3D.gd | H53: 开 | I53: Prefab脚本 | J53: 简化Box楼板面 + camera_stair_slab | K53: 约20.25×10.25m外廓；完成面7m；底部中心原点 | L53: bottom_center；-Z | M53: 99层基地 | N53: 正式美术已接入 | O53: v001 | P53: 在基地布局tscn直接移动；模型、碰撞和摄像机语义随实例同步。
A54: ENV-BASE99-STAIR-L-Z7 | B54: 基地99层7米L型楼梯 | C54: assets/art/environments/base_facility_3d/runtime/env_base99_stair_l_z7/env_base99_stair_l_z7_root_top3d.tscn | D54: assets/art/environments/base_facility_3d/components/env_base99_stair_l_z7/env_base99_stair_l_z7_visual_top3d.glb | E54: ../ShellStorm2-backup/2026-10-11_slimming/original_tree/art_source/environments/base_facility_3d/source/env_base99_modular_room/env_base99_modular_room_assets_clean_v001.blend | F54: 可编辑可行走结构；含底部摄像机净空语义 | G54: src/world3d/Base99WalkableModule3D.gd | H54: 开 | I54: Prefab脚本 | J54: 两段Box斜坡+转角平台 + camera_stair_slab | K54: 约9.22×10.54×7.94m外廓；一楼至7m楼板 | L54: bottom_center；-Z | M54: 99层基地 | N54: 正式美术已接入 | O54: v001 | P54: 不使用踏步Trimesh；坡面低于角色44度上限；位置由布局tscn管理。
A55: ENV-BASE99-STAIR-EXTERIOR-H2 | B55: 基地99层二楼外门2米小楼梯 | C55: assets/art/environments/base_facility_3d/runtime/env_base99_stair_exterior_h2/env_base99_stair_exterior_h2_root_top3d.tscn | D55: assets/art/environments/base_facility_3d/components/env_base99_stair_exterior_h2/env_base99_stair_exterior_h2_visual_top3d.glb | E55: ../ShellStorm2-backup/2026-10-11_slimming/original_tree/art_source/environments/base_facility_3d/source/env_base99_modular_room/env_base99_modular_room_assets_clean_v001.blend | F55: 可编辑可行走结构；含底部摄像机净空语义 | G55: src/world3d/Base99WalkableModule3D.gd | H55: 开 | I55: Prefab脚本 | J55: 简化Box斜坡 + camera_stair_slab | K55: 4.515×2.80×2.00m；7m楼板至9m外门门槛 | L55: bottom_center；-Z | M55: 99层基地 | N55: 正式美术已接入 | O55: v001 | P55: 不使用踏步Trimesh；位置和旋转由布局tscn管理。
A56: ENV-BASE100-UPPER-SHELL-30X30-H9 | B56: 基地100层上层围护与18米封顶 | C56: assets/art/environments/base_facility_3d/runtime/env_base100_upper_shell_30x30_h9/env_base100_upper_shell_30x30_h9_root_top3d.tscn | E56: art_source/environments/base_facility_3d/source/env_base99_modular_room/env_base99_modular_room_source_v001.blend | F56: 可编辑组合Prefab；24块围护墙与36块封顶模块；统一挡光并投影 | G56: src/world3d/Base100UpperShell3D.gd | H56: 开 | I56: Prefab脚本 | J56: 9个BoxShape3D（连续墙/东侧门洞框/屋顶） | K56: 30×30×9m上层围护；墙底9m；屋顶底18m；东门洞2.2×2.5m | L56: room_center；local -Z为北；根缩放1 | M56: 基地100层及18米屋顶 | N56: 正式美术已接入 | O56: v001 | P56: 子Prefab=60；北墙两端普通+中间4窗；其余19普通墙，东侧1门墙；复用现有墙/地板资产，cast_and_receive；18米屋顶阻挡室外光；不恢复99/100层中间36块。
A57: ENV-BASE99-MEZZANINE-20X10-Z5 | B57: 基地99层5米楼中楼结构与护栏（复用V020二层地板） | C57: assets/art/environments/base_facility_3d/runtime/env_base99_mezzanine_20x10_z5/env_base99_mezzanine_20x10_z5_root_top3d.tscn | D57: assets/art/environments/base_facility_3d/components/env_base99_mezzanine_20x10_z5/env_base99_mezzanine_20x10_z5_visual_top3d.glb | E57: art_source/environments/base_facility_3d/source/env_base99_modular_room/env_base99_modular_room_assets_clean_v006.blend（v006；资产v004） | F57: 5米承重平台与连续栏杆；移除9个旧地砖/甲板网格，二层表现复用V020地板；真实投影 | G57: src/world3d/Base99WalkableModule3D.gd | H57: 开 | I57: Prefab自身 | J57: 连续Box楼板+独立栏杆Box；西侧入口为L梯留空 | K57: 20.2475×10.2475×5.93m；台面5m；552三角面 | L57: 底面中心；Blender -Y / Godot -Z | M57: 99层基地楼中楼 | N57: 正式美术已接入；优化完成 | O57: 已完成，未接入 | P57: Blender母版v005；660/660面PaletteUV有效；边缘共面数0；视觉/碰撞/功能分离。2026-09-04：旧阁楼架实例从基地布局撤下，资产文件保留回滚。
A58: ENV-BASE99-STAIR-L-Z5 | B58: 基地99层5米L型楼梯 | C58: assets/art/environments/base_facility_3d/runtime/env_base99_stair_l_z5/env_base99_stair_l_z5_root_top3d.tscn | D58: assets/art/environments/base_facility_3d/components/env_base99_stair_l_z5/env_base99_stair_l_z5_visual_top3d.glb | E58: ../ShellStorm2-backup/2026-10-11_slimming/original_tree/art_source/environments/base_facility_3d/source/env_base99_modular_room/env_base99_modular_room_assets_clean_v004.blend | F58: 0→2.5→5米完整双跑L梯；转角扶手收口；真实投影与阻挡 | G58: src/world3d/Base99WalkableModule3D.gd | H58: 开 | I58: Prefab自身 | J58: 单一StaticBody：斜坡+平台+斜坡；独立连续扶手Box | K58: 9.2176×10.538×5.91015m；终点5m | L58: 底面中心；Blender -Y / Godot -Z | M58: 99层基地一楼至楼中楼 | N58: 正式美术已接入；沿用已验收V004 | O58: 已完成，未接入 | P58: 由91个可编辑源组件重建；踏步/斜梁/平台/导光条齐全；转角扶手不穿插；三段行走形状接缝齐平并重叠0.04m。2026-09-04：旧L型楼梯实例从基地布局撤下，资产文件保留回滚。
A59: ENV-BASE99-STAIR-EXTERIOR-H4 | B59: 基地99至100层4米外门楼梯 | C59: assets/art/environments/base_facility_3d/runtime/env_base99_stair_exterior_h4/env_base99_stair_exterior_h4_root_top3d.tscn | D59: assets/art/environments/base_facility_3d/components/env_base99_stair_exterior_h4/env_base99_stair_exterior_h4_visual_top3d.glb | E59: ../ShellStorm2-backup/2026-10-11_slimming/original_tree/art_source/environments/base_facility_3d/source/env_base99_modular_room/env_base99_modular_room_assets_clean_v002.blend | F59: 平台5米至100层9米；两段原生楼梯组合；真实投影 | G59: src/world3d/Base99WalkableModule3D.gd | H59: 开 | I59: Prefab自身 | J59: 覆盖8.515米包络的连续斜坡+双侧护栏 | K59: 8.515×2.8×4m；高差4m | L59: 底面中心；Blender -Y / Godot -Z | M59: 基地楼中楼至100层出口 | N59: 正式美术已接入 | O59: v002 | P59: 不做纵向拉伸；替代H2版本
A60: ENV-BASE99-MEZZANINE-UNDERDECK-BLOCKER | B60: 基地99层楼中楼下方工业仓库横向门板 | C60: assets/art/environments/base_facility_3d/runtime/env_base99_mezzanine_underdeck_blocker/env_base99_mezzanine_underdeck_blocker_root_top3d.tscn | D60: assets/art/environments/base_facility_3d/components/env_base99_mezzanine_underdeck_blocker/env_base99_mezzanine_underdeck_blocker_visual_top3d.glb | E60: art_source/environments/base_facility_3d/source/env_base99_mezzanine_underdeck_blocker/env_base99_mezzanine_underdeck_blocker_source_v003.blend | F60: 三面冷灰横向门板；0.55米内收；显式永久阻挡；真实投影 | G60: src/world3d/Base99MezzanineUnderdeckBlocker3D.gd | H60: 开 | I60: Prefab自身 | J60: 南/西/东三块与模型对齐的BoxShape3D；process always | K60: 19.31×9.11×4.65m视觉；碰撞顶4.95m | L60: 底面中心；Blender -Y / Godot -Z | M60: 99层基地楼中楼下方 | N60: 未在正式基地布局实例化（保留回滚） | O60: 已完成，未接入 | P60: Blender源文件重导；六条高低位物理射线命中；北侧由基地外墙封闭；v002保留回滚。2026-09-04：下方工业铁门实例及其永久碰撞从基地布局撤下，资产文件保留回滚。
A61: ENV-BASE99-FLOOR-DETAILS-V017 | B61: 基地99层完整地板替换 V021 | C61: assets/art/environments/base_facility_3d/runtime/env_base99_floor_full_replacement/env_base99_floor_full_replacement_root_top3d.tscn | D61: assets/art/environments/base_facility_3d/components/env_base99_floor_full_replacement/env_base99_floor_full_replacement_visual_top3d.glb | E61: art_source/design/blender/base_facility_layout/base_facility_runtime_layout_hq_v020.blend（v020） | F61: 完整36块新地板表现替换旧普通/铆钉MultiMesh；FloorSupport承重规格不变。 | G61: src/world3d/DungeonRoom3D.gd | H61: 无 | I61: TowerFloorStage3D | J61: 无；仅视觉 | K61: 30×30m；6×6×5m；2网格；4材质表面；498,920三角面；无内置碰撞 | L61: layout_origin；Blender +Y北 / Godot -Z北；根Y=0 | M61: 99层基地一层 | N61: 正式美术已接入 | O61: v003 | P61: Blender源文件=base_facility_runtime_layout_hq_v020.blend；Blender版本=v020；完整36块结构砖与深化内容导入；旧普通/铆钉MultiMesh视觉已移除；FloorSupport碰撞保持Y=0、30×30m、6×6×5m；共面重叠0、朝下三角面0；verify_base99_floor_visuals_v021与verify_base99_floor_player_collision_flow通过。
A62: ENV-BASE99-LOFT-FLOOR-FINISH-V017 | B62: 基地99层二层地板面层 V020 | C62: assets/art/environments/base_facility_3d/runtime/env_base99_loft_floor_finish/env_base99_loft_floor_finish_root_top3d.tscn | D62: assets/art/environments/base_facility_3d/components/env_base99_loft_floor_finish/env_base99_loft_floor_finish_visual_top3d.glb | E62: art_source/design/blender/base_facility_layout/base_facility_runtime_layout_hq_v020.blend（v020） | F62: 仅表现；Blender V020新增二楼地板面层保持不动，并作为V004阁楼结构唯一甲板表现。 | G62: src/world3d/DungeonRoom3D.gd | H62: 无 | I62: 无；仅视觉 | J62: 无；仅视觉 | K62: 19.6×9.6×0.108m；1网格；2材质表面；206三角面；无内置碰撞 | L62: layout_origin；装配层Y=-1m，将Blender Z=6对齐Godot Y=5 | M62: 99层基地北侧20×10米楼中楼 | N62: 正式美术已接入 | O62: v002 | P62: Blender源文件=base_facility_runtime_layout_hq_v020.blend；Blender版本=v020；二楼新增地板保持不动，不新增碰撞；共面重叠0、朝下三角面0；tests/verification/verify_base99_floor_visuals_v021.tscn通过。
A63: ENV-BASE99-FLOOR-VISUAL-LAYOUT-V017 | B63: 基地99层完整地板表现装配 V021 | C63: assets/art/environments/base_facility_3d/runtime/env_base99_floor_visuals/env_base99_floor_visuals_root_top3d.tscn | E63: art_source/design/blender/base_facility_layout/base_facility_runtime_layout_hq_v020.blend（v020） | F63: 完整一层新地板、V020二层面层、V004阁楼/楼梯与V021非门墙面内容的运行时装配；由基地美术布局直接实例化。 | G63: src/world3d/DungeonRoom3D.gd | H63: 无 | I63: 既有TowerFloorStage3D与楼中楼Prefab | J63: 无；仅视觉布局装配 | K63: 一层30×30m；二层20×10m；无内置碰撞 | L63: layout_origin；二层面层Y=-1m；V021墙面内容保持Blender烘焙坐标 | M63: 99层基地美术布局 | N63: 正式美术已接入 | O63: v003 | P63: Blender源文件=base_facility_runtime_layout_hq_v020.blend；Blender版本=v020；一层替换旧MultiMesh，二层保留V020面层；FloorSupport碰撞保持不变。2026-09-04：旧5米阁楼架、L型楼梯和下方工业铁门已从基地布局撤下；tests/verification/verify_base99_mezzanine_placement_removal.tscn通过。
A64: ENV-BASE99-WALL-CONTENTS-V021 | B64: 基地99层非门墙面内容资产包 | C64: assets/art/environments/base_facility_3d/runtime/env_base99_wall_contents/env_base99_wall_contents_root_top3d.tscn | D64: assets/art/environments/base_facility_3d/components/env_base99_wall_contents（18个GLB） | E64: art_source/design/blender/base_facility_layout/v021/base_facility_runtime_layout_hq_v021_wall_contents.blend（v021；derived from base_facility_runtime_layout_hq_v017.blend v017） | F64: 仅表现；18个非门墙面内容包，根节点保持原点并复用Blender烘焙摆放；排除门、门框、结构墙、墙板和挡板。 | G64: 无 | H64: 无 | I64: 无；visual_only_no_collision | J64: 无；visual_only_no_collision | K64: 18运行时网格；86,538三角面；向下表面已删除并抽稀 | L64: layout_origin；Blender +Y北 / Godot -Z北 | M64: 99层基地墙面内容 | N64: 正式美术已接入；优化完成
A65: ENV-BASE99-REMAINING-FACILITIES-V021 | B65: 基地99层剩余非门非墙独立设施资产包 | C65: assets/art/environments/base_facility_3d/runtime/env_base99_remaining_facilities/env_base99_remaining_facilities_root_top3d.tscn | D65: assets/art/environments/base_facility_3d/components/env_base99_remaining_facilities（45个GLB） | E65: art_source/design/blender/base_facility_layout/v021/base_facility_runtime_layout_hq_v021_remaining_facilities.blend（v021；derived from base_facility_runtime_layout_hq_v017.blend v017） | F65: 仓储、阁楼家具、独立设备与环境支持；排除门、门禁随属件、结构墙、墙面内容、地板、阁楼和楼梯。Blender烘焙摆放保持不变。 | G65: 无 | H65: 开 | I65: 每包独立Prefab | J65: 34包逐源物件BoxShape3D；11包仅视觉 | K65: 45运行时网格；84,274三角面；向下表面删除21,604；45/45公共色盘导入契约 | L65: layout_origin；Blender +Y北 / Godot -Z北 | M65: 99层基地剩余设施 | N65: 正式美术已接入；优化完成
A66: ENV-TOWER-STAIR-FLOOR-LOWER | B66: 楼梯间下层楼板 | E66: art_source/design/whitebox/tower_zones/v015/blender/whitebox_tower_stairs_v015.blend | F66: 3Dgame-design白盒可拖放组件 | H66: 无 | I66: 3Dgame-design | J66: 无；白盒编辑 | K66: 每间下层18块5×5×0.3m固定地砖，完成面+0.1m | L66: 组件中心；Blender Z-up | M66: 楼梯区专用 | N66: 白盒组件 | O66: v001 | P66: v015原位拼装，详细尺寸和实例位置见组件JSON；禁止缩放。
A67: ENV-TOWER-STAIR-FLOOR-MID | B67: 楼梯间中层楼板 | E67: art_source/design/whitebox/tower_zones/v015/blender/whitebox_tower_stairs_v015.blend | F67: 3Dgame-design白盒可拖放组件 | H67: 无 | I67: 3Dgame-design | J67: 无；白盒编辑 | K67: 每间中层6块固定拼接件，沿原平台边界收边 | L67: 组件中心；Blender Z-up | M67: 楼梯区专用 | N67: 白盒组件 | O67: v001 | P67: v015原位拼装，详细尺寸和实例位置见组件JSON；禁止缩放。
A68: ENV-TOWER-STAIR-FLOOR-UPPER | B68: 楼梯间上层楼板 | E68: art_source/design/whitebox/tower_zones/v015/blender/whitebox_tower_stairs_v015.blend | F68: 3Dgame-design白盒可拖放组件 | H68: 无 | I68: 3Dgame-design | J68: 无；白盒编辑 | K68: 每间上层6块固定拼接件，另有2块门口连接板 | L68: 组件中心；Blender Z-up | M68: 楼梯区专用 | N68: 白盒组件 | O68: v001 | P68: v015原位拼装，详细尺寸和实例位置见组件JSON；禁止缩放。
A69: ENV-TOWER-STAIR-FLIGHT-ADJUSTABLE | B69: 楼梯间可调直梯母组件 | E69: art_source/design/whitebox/tower_zones/v015/blender/whitebox_tower_stairs_v015.blend | F69: 3Dgame-design白盒可拖放组件 | H69: 无 | I69: 3Dgame-design | J69: 无；白盒编辑 | K69: 单母组件；每跑6m高/15m水平长度/21.8014°；20级；另一跑180°；高度/角度可调 | L69: 组件中心；Blender Z-up | M69: 楼梯区专用 | N69: 白盒组件 | O69: v002 | P69: v015原位拼装，详细尺寸和实例位置见组件JSON；禁止缩放。
A70: ENV-TOWER-CORNER-COLUMN-05M | B70: 塔楼通用拐角柱 | E70: tools/3Dgame-design/src/main.js | F70: 3Dgame-design白盒可拖放组件 | H70: 无 | I70: 3Dgame-design | J70: 无；白盒编辑 | K70: 0.5×0.5×12.9m | L70: 组件中心；Blender Z-up | M70: 全区块通用 | N70: 白盒组件 | O70: v001 | P70: 3Dgame-design通用组件；未重新导入Godot。
A71: ENV-BATTLE-L01-ROOM-MAIN-01-HUB | B71: 局内关卡01 主路内容房01 hub 30×25m 白模 | C71: 未制作 | D71: 未制作 | E71: art_source/design/whitebox/tower_zones/battle_level01/v003/blender/局内关卡01_白模_主路内容房_01_hub_30x25m_v003.blend | F71: 战局01白模v003；墙体按固定5m槽位拼装，带门墙完整占用5m槽并保留左右柱与门楣。 | G71: 未接入 | H71: 无 | I71: 无 | J71: 无 | K71: 30×25×11.9m | L71: 房间局部坐标：X/Y居中；底面Z=0；Godot -Z | M71: 局内关卡01 / Battle | N71: 白模源已完成；QA PASS | O71: v003 | P71: 2026-09-16：普通墙改为5m标准件；32个带门墙槽均为完整5m模块，保留左右柱与门楣；非整模数边缘使用2.5m固定收边。门中心、房间包络和地板组件与v002一致，Scale=1，无超过5m墙件。组件={"door_wall":2,"floor_slab":1,"floor_tile":30,"wall":24}。SHA256=29b9180a6de49af8f21daa2e3bfe074dcf01c5f45a845dc05f83c16106c61661。未导出GLB或接入Godot。
A72: ENV-BATTLE-L01-ROOM-MAIN-02 | B72: 局内关卡01 主路内容房02 数据机房 30×25m | C72: 未制作 | D72: 未制作 | E72: art_source/environments/tower_zones/battle/source/room_instances/main_room_02/v003/env_battle_l01_main_02_data_room_layout_source_v003.blend | F72: 基于v002白盒的参考图机房包装；82个独立资产包，墙/地砖/机柜/终端/跨设施支持分别归类。 | G72: 未接入 | H72: 无 | I72: 无 | J72: 无 | K72: 30×25×11.9m | L72: 房间局部坐标：X/Y居中；底面Z=0；Godot -Z | M72: 局内关卡01 / Battle | N72: Blender美术源已完成；源文件已规范迁移；未接入Godot | O72: v003 | P72: 2026-09-16：39件白盒结构及39件原制作源几何/变换保留；30×25m、墙11.9×0.3m、地面Z=0.3、东西门洞2.2×2.5m。82包磁盘镜像；四材质、共享外链色盘、全网格逐面PaletteUV验收通过。SHA256=5dcbd3f9c036c4f94b04a7d81a193a9b4c390d1aeec6b846507d08013cba1143。当前规范源=art_source/environments/tower_zones/battle/source/room_instances/main_room_02/v003/env_battle_l01_main_02_data_room_layout_source_v003.blend；原白盒=../ShellStorm2-backup/2026-10-11_slimming/original_tree/source/art/whitebox/tower_zones/battle_level01/v002/blender/局内关卡01_白模_主路内容房_02_30x25m_v002.blend。2026-09-18：仅规范迁移Blender过程源路径与英文命名；AssetID、Prefab/GLB运行时稳定路径及玩法规则未变，未重新导出GLB/Prefab。
A73: ENV-BATTLE-L01-ROOM-MAIN-03 | B73: 局内关卡01 主路内容房03 30×25m 白模 | C73: 未制作 | D73: 未制作 | E73: art_source/design/whitebox/tower_zones/battle_level01/v003/blender/局内关卡01_白模_主路内容房_03_30x25m_v003.blend | F73: 战局01白模v003；墙体按固定5m槽位拼装，带门墙完整占用5m槽并保留左右柱与门楣。 | G73: 未接入 | H73: 无 | I73: 无 | J73: 无 | K73: 30×25×11.9m | L73: 房间局部坐标：X/Y居中；底面Z=0；Godot -Z | M73: 局内关卡01 / Battle | N73: 白模源已完成；QA PASS | O73: v003 | P73: 2026-09-16：普通墙改为5m标准件；32个带门墙槽均为完整5m模块，保留左右柱与门楣；非整模数边缘使用2.5m固定收边。门中心、房间包络和地板组件与v002一致，Scale=1，无超过5m墙件。组件={"door_wall":3,"floor_slab":1,"floor_tile":30,"wall":27}。SHA256=f61200942b2907d8cd8fb1773979172d570c1a885bafdb32909ebe624b617590。未导出GLB或接入Godot。
A74: ENV-BATTLE-L01-ROOM-MAIN-04 | B74: 局内关卡01 主路内容房04 30×25m 白模 | C74: 未制作 | D74: 未制作 | E74: art_source/design/whitebox/tower_zones/battle_level01/v003/blender/局内关卡01_白模_主路内容房_04_30x25m_v003.blend | F74: 战局01白模v003；墙体按固定5m槽位拼装，带门墙完整占用5m槽并保留左右柱与门楣。 | G74: 未接入 | H74: 无 | I74: 无 | J74: 无 | K74: 30×25×11.9m | L74: 房间局部坐标：X/Y居中；底面Z=0；Godot -Z | M74: 局内关卡01 / Battle | N74: 白模源已完成；QA PASS | O74: v003 | P74: 2026-09-16：普通墙改为5m标准件；32个带门墙槽均为完整5m模块，保留左右柱与门楣；非整模数边缘使用2.5m固定收边。门中心、房间包络和地板组件与v002一致，Scale=1，无超过5m墙件。组件={"door_wall":2,"floor_slab":1,"floor_tile":30,"wall":26}。SHA256=0c67ec35481b555804ee2b618f1884e6e290af4e2a2065671ff16d04555e6d30。未导出GLB或接入Godot。
A75: ENV-BATTLE-L01-ROOM-MAIN-05 | B75: 局内关卡01 主路内容房05 30×40m 白模 | C75: 未制作 | D75: 未制作 | E75: art_source/design/whitebox/tower_zones/battle_level01/v003/blender/局内关卡01_白模_主路内容房_05_30x40m_v003.blend | F75: 战局01白模v003；墙体按固定5m槽位拼装，带门墙完整占用5m槽并保留左右柱与门楣。 | G75: 未接入 | H75: 无 | I75: 无 | J75: 无 | K75: 30×40×11.9m | L75: 房间局部坐标：X/Y居中；底面Z=0；Godot -Z | M75: 局内关卡01 / Battle | N75: 白模源已完成；QA PASS | O75: v003 | P75: 2026-09-16：普通墙改为5m标准件；32个带门墙槽均为完整5m模块，保留左右柱与门楣；非整模数边缘使用2.5m固定收边。门中心、房间包络和地板组件与v002一致，Scale=1，无超过5m墙件。组件={"door_wall":2,"floor_slab":1,"floor_tile":48,"wall":32}。SHA256=5657ac7120e2a7ed6a19f9fe5436b389dd489e88641ed01bd11e31284850cc0b。未导出GLB或接入Godot。
A76: ENV-BATTLE-L01-ROOM-MAIN-06 | B76: 局内关卡01 主路内容房06 30×25m 白模 | C76: 未制作 | D76: 未制作 | E76: art_source/design/whitebox/tower_zones/battle_level01/v003/blender/局内关卡01_白模_主路内容房_06_30x25m_v003.blend | F76: 战局01白模v003；墙体按固定5m槽位拼装，带门墙完整占用5m槽并保留左右柱与门楣。 | G76: 未接入 | H76: 无 | I76: 无 | J76: 无 | K76: 30×25×11.9m | L76: 房间局部坐标：X/Y居中；底面Z=0；Godot -Z | M76: 局内关卡01 / Battle | N76: 白模源已完成；QA PASS | O76: v003 | P76: 2026-09-16：普通墙改为5m标准件；32个带门墙槽均为完整5m模块，保留左右柱与门楣；非整模数边缘使用2.5m固定收边。门中心、房间包络和地板组件与v002一致，Scale=1，无超过5m墙件。组件={"door_wall":2,"floor_slab":1,"floor_tile":30,"wall":25}。SHA256=f01cad5d06fbc1e7ba9cbefe602603f8dc4edc4b7f96b81d58348655a3ff4010。未导出GLB或接入Godot。
A77: ENV-BATTLE-L01-ROOM-MAIN-07 | B77: 局内关卡01 主路内容房07 30×25m 白模 | C77: 未制作 | D77: 未制作 | E77: art_source/design/whitebox/tower_zones/battle_level01/v003/blender/局内关卡01_白模_主路内容房_07_30x25m_v003.blend | F77: 战局01白模v003；墙体按固定5m槽位拼装，带门墙完整占用5m槽并保留左右柱与门楣。 | G77: 未接入 | H77: 无 | I77: 无 | J77: 无 | K77: 30×25×11.9m | L77: 房间局部坐标：X/Y居中；底面Z=0；Godot -Z | M77: 局内关卡01 / Battle | N77: 白模源已完成；QA PASS | O77: v003 | P77: 2026-09-16：普通墙改为5m标准件；32个带门墙槽均为完整5m模块，保留左右柱与门楣；非整模数边缘使用2.5m固定收边。门中心、房间包络和地板组件与v002一致，Scale=1，无超过5m墙件。组件={"door_wall":2,"floor_slab":1,"floor_tile":30,"wall":24}。SHA256=98c199eb70a821ecca36519e5f653f6eab8804c34131c3e8c60988e22d8545df。未导出GLB或接入Godot。
A78: ENV-BATTLE-L01-ROOM-MAIN-08 | B78: 局内关卡01 主路内容房08 35×30m 白模 | C78: 未制作 | D78: 未制作 | E78: art_source/design/whitebox/tower_zones/battle_level01/v003/blender/局内关卡01_白模_主路内容房_08_35x30m_v003.blend | F78: 战局01白模v003；墙体按固定5m槽位拼装，带门墙完整占用5m槽并保留左右柱与门楣。 | G78: 未接入 | H78: 无 | I78: 无 | J78: 无 | K78: 35×30×11.9m | L78: 房间局部坐标：X/Y居中；底面Z=0；Godot -Z | M78: 局内关卡01 / Battle | N78: 白模源已完成；QA PASS | O78: v003 | P78: 2026-09-16：普通墙改为5m标准件；32个带门墙槽均为完整5m模块，保留左右柱与门楣；非整模数边缘使用2.5m固定收边。门中心、房间包络和地板组件与v002一致，Scale=1，无超过5m墙件。组件={"door_wall":2,"floor_slab":1,"floor_tile":42,"wall":30}。SHA256=35588e1e0b232944fe4d8a742df3824f1d9e3878bc6b4d52112fe149437f5dc5。未导出GLB或接入Godot。
A79: ENV-BATTLE-L01-ROOM-MAIN-09 | B79: 局内关卡01 主路内容房09 40×25m 白模 | C79: 未制作 | D79: 未制作 | E79: art_source/design/whitebox/tower_zones/battle_level01/v003/blender/局内关卡01_白模_主路内容房_09_40x25m_v003.blend | F79: 战局01白模v003；墙体按固定5m槽位拼装，带门墙完整占用5m槽并保留左右柱与门楣。 | G79: 未接入 | H79: 无 | I79: 无 | J79: 无 | K79: 40×25×11.9m | L79: 房间局部坐标：X/Y居中；底面Z=0；Godot -Z | M79: 局内关卡01 / Battle | N79: 白模源已完成；QA PASS | O79: v003 | P79: 2026-09-16：普通墙改为5m标准件；32个带门墙槽均为完整5m模块，保留左右柱与门楣；非整模数边缘使用2.5m固定收边。门中心、房间包络和地板组件与v002一致，Scale=1，无超过5m墙件。组件={"door_wall":3,"floor_slab":1,"floor_tile":40,"wall":30}。SHA256=593ed390ac3e54d4b7f7666f2bb9795e61d75112ddfd8636a10303e2b74f8280。未导出GLB或接入Godot。
A80: ENV-BATTLE-L01-ROOM-MAIN-10 | B80: 局内关卡01 主路内容房10 30×25m 白模 | C80: 未制作 | D80: 未制作 | E80: art_source/design/whitebox/tower_zones/battle_level01/v003/blender/局内关卡01_白模_主路内容房_10_30x25m_v003.blend | F80: 战局01白模v003；墙体按固定5m槽位拼装，带门墙完整占用5m槽并保留左右柱与门楣。 | G80: 未接入 | H80: 无 | I80: 无 | J80: 无 | K80: 30×25×11.9m | L80: 房间局部坐标：X/Y居中；底面Z=0；Godot -Z | M80: 局内关卡01 / Battle | N80: 白模源已完成；QA PASS | O80: v003 | P80: 2026-09-16：普通墙改为5m标准件；32个带门墙槽均为完整5m模块，保留左右柱与门楣；非整模数边缘使用2.5m固定收边。门中心、房间包络和地板组件与v002一致，Scale=1，无超过5m墙件。组件={"door_wall":2,"floor_slab":1,"floor_tile":30,"wall":25}。SHA256=906da8b7224bd6010efc9af9ea298aff6f4aa282c49aa774b1ec72a36c16affe。未导出GLB或接入Godot。
A81: ENV-BATTLE-L01-ROOM-BRANCH-01 | B81: 局内关卡01 支路内容房01 30×25m 白模 | C81: 未制作 | D81: 未制作 | E81: art_source/design/whitebox/tower_zones/battle_level01/v003/blender/局内关卡01_白模_支路内容房_01_30x25m_v003.blend | F81: 战局01白模v003；墙体按固定5m槽位拼装，带门墙完整占用5m槽并保留左右柱与门楣。 | G81: 未接入 | H81: 无 | I81: 无 | J81: 无 | K81: 30×25×11.9m | L81: 房间局部坐标：X/Y居中；底面Z=0；Godot -Z | M81: 局内关卡01 / Battle | N81: 白模源已完成；QA PASS | O81: v003 | P81: 2026-09-16：普通墙改为5m标准件；32个带门墙槽均为完整5m模块，保留左右柱与门楣；非整模数边缘使用2.5m固定收边。门中心、房间包络和地板组件与v002一致，Scale=1，无超过5m墙件。组件={"door_wall":2,"floor_slab":1,"floor_tile":30,"wall":25}。SHA256=13e4a206e23cff87878fb1b6fff433ba8c2ec782d2449333589a34b867465e6a。未导出GLB或接入Godot。
A82: ENV-BATTLE-L01-ROOM-BRANCH-02 | B82: 局内关卡01 支路内容房02 30×25m 白模 | C82: 未制作 | D82: 未制作 | E82: art_source/design/whitebox/tower_zones/battle_level01/v003/blender/局内关卡01_白模_支路内容房_02_30x25m_v003.blend | F82: 战局01白模v003；墙体按固定5m槽位拼装，带门墙完整占用5m槽并保留左右柱与门楣。 | G82: 未接入 | H82: 无 | I82: 无 | J82: 无 | K82: 30×25×11.9m | L82: 房间局部坐标：X/Y居中；底面Z=0；Godot -Z | M82: 局内关卡01 / Battle | N82: 白模源已完成；QA PASS | O82: v003 | P82: 2026-09-16：普通墙改为5m标准件；32个带门墙槽均为完整5m模块，保留左右柱与门楣；非整模数边缘使用2.5m固定收边。门中心、房间包络和地板组件与v002一致，Scale=1，无超过5m墙件。组件={"door_wall":1,"floor_slab":1,"floor_tile":30,"wall":23}。SHA256=5826151dfc9a615c1c632a29f9bdc8f69e0e9cd82ea6544e81586e40df3925ce。未导出GLB或接入Godot。
... A95: ENV-BATTLE-COMMON-DOOR-5M | B95: 战局通用门扇 2.2×0.18×2.5m | C95: assets/art/environments/tower_zones/battle/runtime/common_components/door_5m/door_5m_root_top3d.tscn | D95: assets/art/environments/tower_zones/battle/components/common_components/door_5m/door_5m_visual_top3d.glb | E95: ../ShellStorm2-backup/2026-10-11_slimming/original_tree/art_source/environments/tower_zones/battle/source/common_components/v006/env_battle_common_components_source_v006.blend（集合 door_5m_通用包） | F95: 战局01通用组件库 10_门组件；门扇本体，底边中心原点、开门为垂直升起（范式B：自包含 prefab + 自带碰撞） | G95: 无 | H95: 开 | I95: 本组件（PackedScene 自带） | J95: BoxShape3D 2.2×2.5×0.18，中心 y=1.25，底边中心原点 | K95: 2.2×0.18×2.5m | L95: 底边中心（Godot 底面 Y=0、XZ 居中）；朝 -Z | M95: 局内关卡01 / Battle（安全房 v007 已接入） | N95: 组件已完成；已接入；源文件已规范迁移至v006（未重导） | O95: v006 | P95: 2026-09-17：v004 复核本组件无需变更——门扇几何 2.2×0.18×2.5 与碰撞盒（中心 y=1.25）与 v003 一致，仍与 wall_door_5m 门洞严格配对。本次仅随库升版重新导出并复验。接入 RoomDoor3D 时只取其 ImportedModel 子树（或直接传 GLB PackedScene 作 panel visual），并先与本组件内嵌碰撞去重，避免与 DoorCollision 重复。GLB 不内嵌色盘，导入经 scene_facility_shared_palette_post_import.gd 绑公共色盘。Godot 契约断言通过（tests/verification/verify_common_wall_door_components_v004.tscn 与 verify_common_floor_tile_components_v004.tscn）。2026-09-17：已由入口/出口安全房 v007 在运行时直接引用（DungeonRoom3D preload 本组件 PackedScene）；其余战局房间尚未接入。2026-09-18：过程源迁移至 common_components/v006/env_battle_common_components_source_v006.blend；版本字段按源版本对齐为v006，现有Prefab/GLB、碰撞与玩法契约不变，未重导。
A96: ENV-ROOFTOP-REFERENCE-COMPONENT-LIBRARY | B96: 天台区块 参考组件库 | E96: art_source/environments/tower_zones/rooftop/source/reference_components/v002/天台区块_参考组件库_v002.blend | F96: 47独立包（10类）；女儿墙已改方案A 0.80m 并含3件破损变种；11 类装饰（空调/通风口/水管/藤蔓/花圃盆栽）已导出并接入 100F 装饰布局。 | H96: 未创建 | I96: 未来由Godot包装持有 | J96: 未创建 | K96: 外墙5×0.30×11.9m；逻辑12m | L96: XY居中、底面Z=0；正面-Y | M96: Rooftop / 100F；组件库，非正式布局替换 | N96: Blender源已完成 | O96: v002 | P96: 2026-09-20 方案A 0.80m 写回主库；2026-09-21 库内 47 包，16 件已导出，其中 11 件装饰已接入运行时；其余包仍为 Blender 源状态（未导出 GLB）。
A97: ENV-ROOFTOP-REF-FLOOR-FULL | B97: 完整地砖 | C97: assets/art/props/dungeon_3d/prp_rooftop_floor_5m.tscn | D97: assets/art/environments/tower_zones/rooftop/components/env_rooftop_ref_floor_full_top3d.glb | E97: art_source/environments/tower_zones/rooftop/source/reference_components/v002/天台区块_参考组件库_v002.blend#完整地砖_资产包 | F97: 独立资产包；01_地面系统 | H97: 开 | I97: TowerFloorStage3D | J97: BoxShape3D，由 TowerFloorStage3D 的 FloorSupport 按楼层轮廓铺满（Prefab 不再自带碰撞） | K97: 5.000×5.000×0.300 m | L97: bottom_center（几何 Y=0..0.30，顶面对齐 Y=0）；+Z 为行方向 | M97: 100F天台地面 / 266块5m地砖满铺（替代 POLISHED_FLOOR） | N97: 正式美术已接入 | O97: v002 | P97: 父库=ENV-ROOFTOP-REFERENCE-COMPONENT-LIBRARY；manifest=art_source/environments/tower_zones/rooftop/source/reference_components/v002/component_packages_v002/01/floor_full/asset_manifest.json；外墙植物包络不进入阻挡；未导入Godot。 2026-09-19：由「仅 Blender 源」升为运行时正式资产，本行不新增 AssetID。用户要求「天台的地板，帮我导出做一个新的 prefab，替代掉现在的地板，方法是新作一个 prefab，然后天台的生成代码从指向原来的改成这个」。导出 GLB assets/art/environments/tower_zones/rooftop/components/env_rooftop_ref_floor_full_top3d.glb（导出脚本 art_source/environments/tower_zones/rooftop/source/export_env_rooftop_ref_floor_facade_v001.py），建立 prefab assets/art/props/dungeon_3d/prp_rooftop_floor_5m.tscn；TowerFloorStage3D.ROOFTOP_FLOOR_SCENE 接管天台地面，替代原 POLISHED_FLOOR_SCENE。⚠️ 原点契约与旧地板不同：新件 bottom_center（几何 Y=0..0.30），旧件为几何中心；_build_floor 改用 _floor_visual_origin_y(mesh) = -AABB.end.y 把顶面对齐到 Y=0，不再用 -FLOOR_THICKNESS*0.5。实测 234 块 5m 地砖。Godot 契约断言 tests/verification/verify_rooftop_floor_facade_components.tscn 与 verify_rooftop_32x32_contract.tscn 通过。
A98: ENV-ROOFTOP-REF-FLOOR-HALF | B98: 半块地砖 | E98: art_source/environments/tower_zones/rooftop/source/reference_components/v002/天台区块_参考组件库_v002.blend#半块地砖_资产包 | F98: 独立资产包；01_地面系统 | H98: 未创建 | I98: 独立包运行包装 | J98: 未创建 | K98: 2.500×5.000×0.300 m | L98: XY中心/底面0；-Y | M98: 天台参考组件库 / floor_half | N98: Blender源已完成 | O98: v002 | P98: 父库=ENV-ROOFTOP-REFERENCE-COMPONENT-LIBRARY；manifest=art_source/environments/tower_zones/rooftop/source/reference_components/v002/component_packages_v002/01/floor_half/asset_manifest.json；外墙植物包络不进入阻挡；未导入Godot。
A99: ENV-ROOFTOP-REF-FLOOR-CORNER | B99: 角块地砖 | E99: art_source/environments/tower_zones/rooftop/source/reference_components/v002/天台区块_参考组件库_v002.blend#角块地砖_资产包 | F99: 独立资产包；01_地面系统 | H99: 未创建 | I99: 独立包运行包装 | J99: 未创建 | K99: 2.500×2.500×0.300 m | L99: XY中心/底面0；-Y | M99: 天台参考组件库 / floor_corner | N99: Blender源已完成 | O99: v002 | P99: 父库=ENV-ROOFTOP-REFERENCE-COMPONENT-LIBRARY；manifest=art_source/environments/tower_zones/rooftop/source/reference_components/v002/component_packages_v002/01/floor_corner/asset_manifest.json；外墙植物包络不进入阻挡；未导入Godot。
A100: ENV-ROOFTOP-REF-FLOOR-EDGE | B100: 边缘地砖 | E100: art_source/environments/tower_zones/rooftop/source/reference_components/v002/天台区块_参考组件库_v002.blend#边缘地砖_资产包 | F100: 独立资产包；01_地面系统 | H100: 未创建 | I100: 独立包运行包装 | J100: 未创建 | K100: 5.000×5.000×0.300 m | L100: XY中心/底面0；-Y | M100: 天台参考组件库 / floor_edge | N100: Blender源已完成 | O100: v002 | P100: 父库=ENV-ROOFTOP-REFERENCE-COMPONENT-LIBRARY；manifest=art_source/environments/tower_zones/rooftop/source/reference_components/v002/component_packages_v002/01/floor_edge/asset_manifest.json；外墙植物包络不进入阻挡；未导入Godot。
A101: ENV-ROOFTOP-REF-FLOOR-INNER | B101: 内角地砖 | E101: art_source/environments/tower_zones/rooftop/source/reference_components/v002/天台区块_参考组件库_v002.blend#内角地砖_资产包 | F101: 独立资产包；01_地面系统 | H101: 未创建 | I101: 独立包运行包装 | J101: 未创建 | K101: 5.000×5.000×0.300 m | L101: XY中心/底面0；-Y | M101: 天台参考组件库 / floor_inner | N101: Blender源已完成 | O101: v002 | P101: 父库=ENV-ROOFTOP-REFERENCE-COMPONENT-LIBRARY；manifest=art_source/environments/tower_zones/rooftop/source/reference_components/v002/component_packages_v002/01/floor_inner/asset_manifest.json；外墙植物包络不进入阻挡；未导入Godot。
A102: ENV-ROOFTOP-REF-PARAPET | B102: 女儿墙直段 | C102: assets/art/props/dungeon_3d/prp_rooftop_parapet_5m.tscn | D102: assets/art/environments/tower_zones/rooftop/components/env_rooftop_ref_parapet_top3d.glb | E102: art_source/environments/tower_zones/rooftop/source/reference_components/v002/天台区块_参考组件库_v002.blend#女儿墙直段_资产包；导出脚本 art_source/environments/tower_zones/rooftop/source/export_env_rooftop_parapet_v001.py 2026-09-20：改由 source/author_env_rooftop_parapet_v003.py 在 source/parapet_v003_work.blend 上重建 0.80m 方案A 平整墙板，再由 source/export_env_rooftop_parapet_v001.py 导出 GLB（source/reference_components/v002 保持只读，不改动）。 | F102: Godot原生场景结构Prefab；100F天台四周边界直段，由 TowerFloorStage3D 按 MultiMesh 摆 64 槽位 | G102: src/world3d/TowerFloorStage3D.gd | H102: 开 | I102: TowerFloorStage3D | J102: BoxShape3D 5×0.80×0.50，由 OuterBoundaryCollision 按槽位生成（Prefab 不再自带碰撞） | K102: GLB / 5×0.50×0.80m / 共享Mesh | L102: bottom_center（几何 Y=0..0.80）；朝 +Z | M102: 100F天台四周边界/64段MultiMesh | N102: 正式美术已接入 | O102: v003 | P102: 父库=ENV-ROOFTOP-REFERENCE-COMPONENT-LIBRARY；manifest=art_source/environments/tower_zones/rooftop/source/reference_components/v002/component_packages_v002/02/parapet/asset_manifest.json；外墙植物包络不进入阻挡；未导入Godot。 2026-09-19：由「仅 Blender 源」升为运行时正式资产，本行不新增 AssetID。用户要求「把天台那两组围栏组件导入 Godot、做成 prefab、坐标对齐、让天台生成围栏的代码指向它们」。导出：art_source/environments/tower_zones/rooftop/source/export_env_rooftop_parapet_v001.py（headless Blender，把网格 rebase 到包内 根_ 空物体后丢弃变换，得到 XY 居中 / 底面 Z=0 的原点契约，再 export_scene.gltf 导 GLB）。实测 GLB 72,632 B / sha256 30d77d64…，AABB=(-2.5,-0.25,0)~(2.5,0.25,1.8)（Blender Z-up，即 5×0.50×1.80）。.import 已绑 tools/asset_pipeline/scene_facility_shared_palette_post_import.gd，Godot 探针实测 palette_texture_bound=true（材质角色 02_细腻哑光_青绿大面）。 接线：TowerFloorStage3D.PARAPET_SCENE 由 prp_tower_wall_parapet_5m.tscn（塔楼 A 套 5×0.30×1.50m）改指本 prefab；ROOFTOP_PARAPET_HEIGHT 0.75 → 1.80、新增 ROOFTOP_PARAPET_THICKNESS=0.50 与按层取值的 _outer_wall_thickness()/_outer_wall_inset()（普通层仍 0.30m），并删掉历史上「1.50m 几何 × 0.5 纵向缩放凑 0.75m」的补偿——现在视觉包络 = 碰撞高度 = 1.80m（远征层被误缩半高的问题一并消掉）。每边 90−5=85m / 80−5=75m 正好整格，故直段 2×(17+15)=64 段、四角让位给 2.5m 转角件。注意旧 prefab prp_tower_wall_parapet_5m.tscn 仍被 DungeonRoom3D 引用且在 6 件 PREFAB_CONTRACT清单内，故本行是并行新身份、旧行(ENV-TOWER-WALL-PARAPET-5M)不动。 实测（probe_rooftop_parapet_alignment，须带窗口跑：MultiMesh 实例变换存在 RenderingServer 侧，dummy 渲染器一律回读成单位阵）：直段 61 + 门洞补位墙 3 + 转角件 4 = 68 件；四条边 coverage=全长 / gap=0.000 / overlap=0.000；四个转角件各 2.500×2.500 精确落座。门禁：ROOFTOP_WEST_EXPANSION_CONTRACT_PASS（verify_rooftop_32x32_contract，outer_segment_count=64 / outer_corner_count=4 / outer_wall_thickness=0.5 / outer_wall_height=1.8）；ROOFTOP_RAILING_OK / TOWER_LEVEL_BLOCKS_OK / TOWER_GRID_COMPONENT_ALIGNMENT_OK / EXPEDITION_LEVEL01_FLOW_OK / TEST_LEVEL_99_FLOW_OK 全绿。 2026-09-20：用户「改成 0.8 米的，变体也要一起改，然后中间的竖杠太密了 不好看，横杆在两边即可」。原 v002 配方是 22 块（基座 + 0.036m 分隔带 + 10 块墙身 + 10 块压顶），运行时表现为密集竖杠；本次重建为方案A 平整墙板，块数 22→3：基座带 5.0×0.50×0.10（z0..0.10）+ 墙板 5.0×0.43×0.64（z0.08..0.72）+ 压顶带 5.0×0.50×0.10（z0.70..0.80），合计**含压顶总高 0.80m**（用户选定口径）。厚度仍 0.50m ⇒ 边界内缩 _outer_wall_inset() 不变，四边/西侧碰撞位置与槽位相位不动。asset_version v002→v003；GLB 同路径覆盖重导（11,752 B）。TowerFloorStage3D.ROOFTOP_PARAPET_HEIGHT 1.80→0.80；_outer_wall_height()、OuterBoundaryCollision_* 高度、楼梯口矮墙缩放（ROOFTOP_PARAPET_HEIGHT / ROOFTOP_PARAPET_DOOR_BASE_HEIGHT = 0.80/1.50）自动跟随。⚠️ Player3D 无跳跃、无台阶攀爬，0.80m 与 1.80m 碰撞对玩法等价（都只是「走不出去」），差异仅在视觉高度、越过墙顶的相机视线与 0.80m 以上的弹道。实测 probe_rooftop_parapet_components：AABB=(5.0,0.80,0.50)、底面 Y=0、色盘已绑；门禁 ROOFTOP_WEST_EXPANSION_CONTRACT_PASS（外墙上限高度改断言为常量口径，不再硬编码 1.8）。
A103: ENV-ROOFTOP-REF-PARAPET-IVY | B103: 女儿墙挂藤 | E103: art_source/environments/tower_zones/rooftop/source/reference_components/v002/天台区块_参考组件库_v002.blend#女儿墙挂藤_资产包 | F103: 独立资产包；02_女儿墙 | H103: 未创建 | I103: 独立包运行包装 | J103: 未创建 | K103: 5.004×0.814×2.009 m | L103: XY中心/底面0；-Y | M103: 天台参考组件库 / parapet_ivy | N103: Blender源已完成 | O103: v002 | P103: 父库=ENV-ROOFTOP-REFERENCE-COMPONENT-LIBRARY；manifest=art_source/environments/tower_zones/rooftop/source/reference_components/v002/component_packages_v002/02/parapet_ivy/asset_manifest.json；外墙植物包络不进入阻挡；未导入Godot。
A104: ENV-ROOFTOP-REF-PARAPET-OUTER | B104: 女儿墙外角 | C104: assets/art/props/dungeon_3d/prp_rooftop_parapet_outer_2p5m.tscn | D104: assets/art/environments/tower_zones/rooftop/components/env_rooftop_ref_parapet_outer_top3d.glb | E104: art_source/environments/tower_zones/rooftop/source/reference_components/v002/天台区块_参考组件库_v002.blend#女儿墙外角_资产包；导出脚本 art_source/environments/tower_zones/rooftop/source/export_env_rooftop_parapet_v001.py 2026-09-20：改由 source/author_env_rooftop_parapet_v003.py 在 source/parapet_v003_work.blend 上重建 0.80m 方案A 平整墙板，再由 source/export_env_rooftop_parapet_v001.py 导出 GLB（source/reference_components/v002 保持只读，不改动）。 | F104: Godot原生场景结构Prefab；100F天台四角的阳角转角件，由 TowerFloorStage3D 单独实例化 4 件 | G104: src/world3d/TowerFloorStage3D.gd | H104: 开 | I104: TowerFloorStage3D | J104: 四角 2.5×2.5 槽位由四边连续的 BoundaryCollision 代理覆盖（Prefab 不再自带碰撞） | K104: GLB / 2.5×2.5×0.80m 包络（两臂中心线在局部 x=-1.0 与 z=+1.0，臂厚 0.50m）/ 共享Mesh | L104: bottom_center（几何 Y=0..0.80）；朝 +Z；外角两臂在局部 −X 与 +Z | M104: 100F天台四角（SW/SE/NE/NW） | N104: 正式美术已接入 | O104: v003 | P104: 父库=ENV-ROOFTOP-REFERENCE-COMPONENT-LIBRARY；manifest=art_source/environments/tower_zones/rooftop/source/reference_components/v002/component_packages_v002/02/parapet_outer/asset_manifest.json；外墙植物包络不进入阻挡；未导入Godot。 2026-09-19：由「仅 Blender 源」升为运行时正式资产，本行不新增 AssetID（asset_version 仍 v002，与参考组件库同版）。实测 GLB 70,140 B / sha256 2bc924b4…，AABB=(-1.25,-1.25,0)~(1.25,1.25,1.8)（Blender Z-up，即 2.5×2.5×1.80）；顶点按象限统计 -X-Z:540 / -X+Z:888 / +X-Z:0 / +X+Z:540，即两臂落在 −X 与 +Z 边、开口朝 +X/−Z，臂中心线 x=−1.0 / z=+1.0。.import 同样绑共享色盘后处理，palette_texture_bound=true。 只用「外角」一件：100F 天台轮廓是 100×80m 矩形（2026-09-22 起；此前 90×80m）、四个角全是阳角，无内凹，所以ENV-ROOFTOP-REF-PARAPET-INNER 不在本次范围内（保持未导入）。 放位：转角件包络 2.5×2.5，摆在该角 2.5m 让位区的中心，按角旋转 90° 整数倍——SW=(−48.75, 0, 43.75) rot 0 / SE=(38.75, 0, 43.75) rot π/2 / NE=(38.75, 0, −33.75) rot π / NW=(−48.75, 0, −33.75) rot 3π/2（俯视逆时针）。这套放位让两条臂的中心线正好落在相邻两边的 boundary 上，包络端点与相邻直段无缝相接。这替掉了原来「两根直段在角上交叉」的旧画法。碰撞仍是四边连续体，本 prefab 只产生视觉节点（visual_only / collision_owner=TowerFloorStage3D.OuterBoundaryCollision）。 实测：probe_rooftop_parapet_alignment 四个转角件 span 尺寸均 2.500×2.500 且 position 与四个2.5m 让位区角点相等；corner_arm_centerlines / corner_open_facing 等朝向口径已写入 prefab 的metadata，供后续换件时核对。门禁 ROOFTOP_WEST_EXPANSION_CONTRACT_PASS 断言 outer_corner_count=4 与四件的位置/朝向（按 wrapf(actual-expected,-π,π) 比角）。 2026-09-20：随直段一起改为 0.80m（同一套三块式配方）。asset_version v002→v003；GLB 同路径覆盖重导（21,768 B），AABB=2.5×2.5×0.80、底面中心、两臂中心线 x=−1.0 / z=+1.0 与开口朝向均不变；四角落座位置（SW/SE/NE/NW）不动。实测 probe_rooftop_parapet_alignment：转角件 4 件 span 均 2.500×2.500，四条边 coverage=全长 / gap=0.000 / overlap=0.000。
A105: ENV-ROOFTOP-REF-PARAPET-INNER | B105: 女儿墙内角 | E105: art_source/environments/tower_zones/rooftop/source/reference_components/v002/天台区块_参考组件库_v002.blend#女儿墙内角_资产包 | F105: 独立资产包；02_女儿墙 | H105: 未创建 | I105: 独立包运行包装 | J105: 未创建 | K105: 2.500×2.500×1.800 m | L105: XY中心/底面0；-Y | M105: 天台参考组件库 / parapet_inner | N105: Blender源已完成 | O105: v002 | P105: 父库=ENV-ROOFTOP-REFERENCE-COMPONENT-LIBRARY；manifest=art_source/environments/tower_zones/rooftop/source/reference_components/v002/component_packages_v002/02/parapet_inner/asset_manifest.json；外墙植物包络不进入阻挡；未导入Godot。
A106: ENV-ROOFTOP-REF-ROOM-WALL | B106: 房间标准墙 | C106: assets/art/props/dungeon_3d/prp_rooftop_room_wall_5x12.tscn | D106: assets/art/environments/tower_zones/rooftop/components/env_rooftop_ref_room_wall_top3d.glb | E106: art_source/environments/tower_zones/rooftop/source/reference_components/v002/天台区块_参考组件库_v002.blend#房间标准墙_资产包 | F106: 独立资产包；03_房间墙体 | G106: src/world3d/Base100UpperShell3D.gd | H106: 开 | I106: Base100UpperShell3D | J106: BoxShape3D；由 Base100UpperShell3D._build_structure_collision() 生成 30×30 连续结构层代理，Prefab 自身不带碰撞节点（内嵌会与结构层重复阻挡） | K106: 5.000×11.900×0.300 m（逻辑高 12.000，顶面留 0.10 给 24m 封顶） | L106: bottom_center（几何 Y=0 起）；+Z 朝外。⚠️ 与 99F 系（ENV-BASE99-*，-Z 朝外）差 180°：同一条边 base99 用 -90°、本套件用 +90°。 | M106: 100F 上层围护东西南三面 17 块（南 6 / 西 6 / 东 5，东面 z=-7.5 门洞槽除外） | N106: 正式美术已接入 | O106: v002 | P106: 父库=ENV-ROOFTOP-REFERENCE-COMPONENT-LIBRARY；manifest=art_source/environments/tower_zones/rooftop/source/reference_components/v002/component_packages_v002/03/room_wall/asset_manifest.json；外墙植物包络不进入阻挡；未导入Godot。 2026-09-20：由「仅 Blender 源」升为运行时正式资产，本行不新增 AssetID。用户要求「把天台参考组件库里的房间墙体与房顶做成正规 prefab，替换 100F 上层围护的东西南三面，北面大窗不动」。导出 GLB 后建立 prefab prp_rooftop_room_wall_5x12.tscn；场景 env_base100_upper_shell_30x30_h12_root_top3d.tscn 用 17 个实例承接，rotation_y = 0（南）/ -90°（西）/ +90°（东）；北面 2 普通墙 + 4 窗墙与东面 1 门墙仍为 base99。碰撞交 Base100UpperShell3D 连续结构层（9 片不变）。验收 verify_base99_wall_visual_replacement（含 base100_rooftop_room_wall_count=17）。
A107: ENV-ROOFTOP-REF-ROOM-WINDOW | B107: 房间窗墙 | C107: assets/art/props/dungeon_3d/prp_rooftop_room_window_5x12.tscn | D107: assets/art/environments/tower_zones/rooftop/components/env_rooftop_ref_room_window_top3d.glb | E107: art_source/environments/tower_zones/rooftop/source/reference_components/v002/天台区块_参考组件库_v002.blend#房间窗墙_资产包 | F107: 独立资产包；03_房间墙体 | H107: 未创建 | I107: Base100UpperShell3D | J107: Prefab 已声明 collision_owner；尚未在 100F 上层围护场景实例化 | K107: 5.000×11.900×0.300 m（逻辑高 12.000） | L107: bottom_center（几何 Y=0 起）；+Z 朝外。⚠️ 与 99F 系（ENV-BASE99-*，-Z 朝外）差 180°：同一条边 base99 用 -90°、本套件用 +90°。 | M107: 已制作并登记；100F 上层围护**未使用**（北面 4 大窗仍用 base99 窗墙） | N107: 正式美术已接入 | O107: v002 | P107: 父库=ENV-ROOFTOP-REFERENCE-COMPONENT-LIBRARY；manifest=art_source/environments/tower_zones/rooftop/source/reference_components/v002/component_packages_v002/03/room_window/asset_manifest.json；外墙植物包络不进入阻挡；未导入Godot。 2026-09-20：随房间墙体套件一并导出 GLB 并建立 prefab；本批场景未摆放 —— 用户口径是「北面大窗不动」，北面 4 块沿用 base99 窗墙。留作后续把北面大窗换成天台 v002 窗墙时直接引用。
A108: ENV-ROOFTOP-REF-ROOM-DOORWALL | B108: 房间门洞墙 | C108: assets/art/props/dungeon_3d/prp_rooftop_room_doorwall_5x12.tscn | D108: assets/art/environments/tower_zones/rooftop/components/env_rooftop_ref_room_doorwall_top3d.glb | E108: art_source/environments/tower_zones/rooftop/source/reference_components/v002/天台区块_参考组件库_v002.blend#房间门洞墙_资产包 | F108: 独立资产包；03_房间墙体 | H108: 未创建 | I108: Base100UpperShell3D | J108: Prefab 已声明 collision_owner；尚未在 100F 上层围护场景实例化 | K108: 5.000×11.900×0.300 m；门洞净空 3.80×6.80 m（两侧垛各 0.60 m） | L108: bottom_center（几何 Y=0 起）；+Z 朝外。⚠️ 与 99F 系（ENV-BASE99-*，-Z 朝外）差 180°：同一条边 base99 用 -90°、本套件用 +90°。 | M108: 已制作并登记；100F 上层围护**未使用**（东面门洞槽仍用 base99 门墙） | N108: 正式美术已接入 | O108: v002 | P108: 父库=ENV-ROOFTOP-REFERENCE-COMPONENT-LIBRARY；manifest=art_source/environments/tower_zones/rooftop/source/reference_components/v002/component_packages_v002/03/room_doorwall/asset_manifest.json；外墙植物包络不进入阻挡；未导入Godot。 2026-09-20：随房间墙体套件一并导出 GLB 并建立 prefab；本批场景未摆放。原因：东面 z=-7.5 门洞槽是 100F 唯一的外梯过场门位，由 TowerDescent3D._install_base_rooftop_transit_door() 挂 RoomDoor3D，其净尺寸写死 TOWER_GEOMETRY.DOOR_CLEAR_WIDTH_M/HEIGHT_M = 2.2×2.5；换成本件的 3.80×6.80 洞等于改全游戏所有门的尺寸与碰撞。用户决策「东门不动，新门只入库」。
A109: ENV-ROOFTOP-REF-ROOF-FULL | B109: 房顶完整板 | C109: assets/art/props/dungeon_3d/prp_rooftop_roof_full_5m.tscn | D109: assets/art/environments/tower_zones/rooftop/components/env_rooftop_ref_roof_full_top3d.glb | E109: art_source/environments/tower_zones/rooftop/source/reference_components/v002/天台区块_参考组件库_v002.blend#房顶完整板_资产包 | F109: 独立资产包；04_房顶模块 | G109: src/world3d/Base100UpperShell3D.gd | H109: 开 | I109: Base100UpperShell3D | J109: BoxShape3D；由 Base100UpperShell3D._build_structure_collision() 生成 30×30 连续结构层代理，Prefab 自身不带碰撞节点（内嵌会与结构层重复阻挡） | K109: 5.000×5.000×0.300 m（底面原点到顶面 0.30，摆 y=24 占 24.00..24.30） | L109: bottom_center（几何 Y=0 起）；+Z 朝外。⚠️ 与 99F 系（ENV-BASE99-*，-Z 朝外）差 180°：同一条边 base99 用 -90°、本套件用 +90°。 | M109: 100F 24m 封顶 6×6 网格的 16 个内圈格 | N109: 正式美术已接入 | O109: v002 | P109: 父库=ENV-ROOFTOP-REFERENCE-COMPONENT-LIBRARY；manifest=art_source/environments/tower_zones/rooftop/source/reference_components/v002/component_packages_v002/04/roof_full/asset_manifest.json；外墙植物包络不进入阻挡；未导入Godot。 2026-09-20：由「仅 Blender 源」升为运行时正式资产，本行不新增 AssetID。用户要求「36 格 base99 地砖换成新房顶模块」。prefab prp_rooftop_roof_full_5m.tscn 只铺 6×6 的 16 个内圈格（rotation_y=0）。
A110: ENV-ROOFTOP-REF-ROOF-EDGE | B110: 房顶边缘板 | C110: assets/art/props/dungeon_3d/prp_rooftop_roof_edge_5m.tscn | D110: assets/art/environments/tower_zones/rooftop/components/env_rooftop_ref_roof_edge_top3d.glb | E110: art_source/environments/tower_zones/rooftop/source/reference_components/v002/天台区块_参考组件库_v002.blend#房顶边缘板_资产包 | F110: 独立资产包；04_房顶模块 | G110: src/world3d/Base100UpperShell3D.gd | H110: 开 | I110: Base100UpperShell3D | J110: BoxShape3D；由 Base100UpperShell3D._build_structure_collision() 生成 30×30 连续结构层代理，Prefab 自身不带碰撞节点（内嵌会与结构层重复阻挡） | K110: 5.000×5.000×0.300 m（收口线脚在板厚之内，不外扩包络） | L110: bottom_center（几何 Y=0 起）；+Z 朝外。⚠️ 与 99F 系（ENV-BASE99-*，-Z 朝外）差 180°：同一条边 base99 用 -90°、本套件用 +90°。 | M110: 100F 24m 封顶 6×6 网格的 16 个外圈非角格 | N110: 正式美术已接入 | O110: v002 | P110: 父库=ENV-ROOFTOP-REFERENCE-COMPONENT-LIBRARY；manifest=art_source/environments/tower_zones/rooftop/source/reference_components/v002/component_packages_v002/04/roof_edge/asset_manifest.json；外墙植物包络不进入阻挡；未导入Godot。 2026-09-20：由「仅 Blender 源」升为运行时正式资产，本行不新增 AssetID。收口侧 = 局部 +Z 朝外，按边取 rotation：max z→0° / min z→180° / max x→+90° / min x→-90°。
A111: ENV-ROOFTOP-REF-ROOF-CORNER | B111: 房顶角板 | C111: assets/art/props/dungeon_3d/prp_rooftop_roof_corner_5m.tscn | D111: assets/art/environments/tower_zones/rooftop/components/env_rooftop_ref_roof_corner_top3d.glb | E111: art_source/environments/tower_zones/rooftop/source/reference_components/v002/天台区块_参考组件库_v002.blend#房顶角板_资产包 | F111: 独立资产包；04_房顶模块 | G111: src/world3d/Base100UpperShell3D.gd | H111: 开 | I111: Base100UpperShell3D | J111: BoxShape3D；由 Base100UpperShell3D._build_structure_collision() 生成 30×30 连续结构层代理，Prefab 自身不带碰撞节点（内嵌会与结构层重复阻挡） | K111: 5.000×5.000×0.300 m；2 个表面（骨架收口线脚 + 青绿大面） | L111: bottom_center（几何 Y=0 起）；+Z 朝外。⚠️ 与 99F 系（ENV-BASE99-*，-Z 朝外）差 180°：同一条边 base99 用 -90°、本套件用 +90°。 | M111: 100F 24m 封顶 6×6 网格的 4 个角格 | N111: 正式美术已接入 | O111: v002 | P111: 父库=ENV-ROOFTOP-REFERENCE-COMPONENT-LIBRARY；manifest=art_source/environments/tower_zones/rooftop/source/reference_components/v002/component_packages_v002/04/roof_corner/asset_manifest.json；外墙植物包络不进入阻挡；未导入Godot。 2026-09-20：由「仅 Blender 源」升为运行时正式资产，本行不新增 AssetID。⚠️ 本件收口在**局部 +Z 与 -X 两侧**（不是对称角板），由 reference_assembly.json 四个角格的 rotation_z 反解验证：(min x,max z)→0° / (max x,max z)→+90° / (max x,min z)→180° / (min x,min z)→-90°。
A112: ENV-ROOFTOP-REF-HVAC-LARGE | B112: 大型空调机组 | E112: art_source/environments/tower_zones/rooftop/source/reference_components/v002/天台区块_参考组件库_v002.blend#大型空调机组_资产包 | F112: 独立资产包；05_空调与设备 | H112: 未创建 | I112: 独立包运行包装 | J112: 未创建 | K112: 4.700×2.565×2.420 m | L112: XY中心/底面0；-Y | M112: 天台参考组件库 / hvac_large | N112: Blender源已完成 | O112: v002 | P112: 父库=ENV-ROOFTOP-REFERENCE-COMPONENT-LIBRARY；manifest=art_source/environments/tower_zones/rooftop/source/reference_components/v002/component_packages_v002/05/hvac_large/asset_manifest.json；外墙植物包络不进入阻挡；未导入Godot。
A113: ENV-ROOFTOP-REF-HVAC-SMALL | B113: 小型空调机组 | C113: assets/art/environments/tower_zones/rooftop/runtime/hvac_small.tscn | D113: assets/art/environments/tower_zones/rooftop/components/env_rooftop_ref_hvac_small_top3d.glb | E113: art_source/environments/tower_zones/rooftop/source/reference_components/v002/天台区块_参考组件库_v002.blend | F113: Godot视觉装饰PackedScene；100F天台房屋四向外墙墙面（避开门洞）（布局内 4 个实例），由 TowerFloorStage3D 按装饰布局清单实例化 | G113: src/world3d/TowerFloorStage3D.gd | H113: 无 | I113: 引擎（visual_only） | J113: 未创建 | K113: 2.500×2.365×1.870 m | L113: XY中心/底面0；-Y | M113: 100F天台装饰布局 / hvac_small | N113: 正式美术已接入 | O113: v002 | P113: 父库=ENV-ROOFTOP-REFERENCE-COMPONENT-LIBRARY；2026-09-21 从 v002 主库导出 GLB(a6c115780b91) 并生成 runtime PackedScene；接入 100F 装饰布局＝120实例/6组（绿化20件blocking，其余visual_only）；布局源=art_source/environments/tower_zones/rooftop/source/layouts/100f_decorated_v001/rooftop_100f_decorated_layout_v001.json
A114: ENV-ROOFTOP-REF-HVAC-FAN | B114: 顶置通风扇 | E114: art_source/environments/tower_zones/rooftop/source/reference_components/v002/天台区块_参考组件库_v002.blend#顶置通风扇_资产包 | F114: 独立资产包；05_空调与设备 | H114: 未创建 | I114: 独立包运行包装 | J114: 未创建 | K114: 2.200×2.275×0.720 m | L114: XY中心/底面0；-Y | M114: 天台参考组件库 / hvac_fan | N114: Blender源已完成 | O114: v002 | P114: 父库=ENV-ROOFTOP-REFERENCE-COMPONENT-LIBRARY；manifest=art_source/environments/tower_zones/rooftop/source/reference_components/v002/component_packages_v002/05/hvac_fan/asset_manifest.json；外墙植物包络不进入阻挡；未导入Godot。
A115: ENV-ROOFTOP-REF-HVAC-VENT | B115: 小通风口 | C115: assets/art/environments/tower_zones/rooftop/runtime/hvac_vent.tscn | D115: assets/art/environments/tower_zones/rooftop/components/env_rooftop_ref_hvac_vent_top3d.glb | E115: art_source/environments/tower_zones/rooftop/source/reference_components/v002/天台区块_参考组件库_v002.blend | F115: Godot视觉装饰PackedScene；100F天台房屋南北墙高处（布局内 2 个实例），由 TowerFloorStage3D 按装饰布局清单实例化 | G115: src/world3d/TowerFloorStage3D.gd | H115: 无 | I115: 引擎（visual_only） | J115: 未创建 | K115: 1.400×1.165×0.850 m | L115: XY中心/底面0；-Y | M115: 100F天台装饰布局 / hvac_vent | N115: 正式美术已接入 | O115: v002 | P115: 父库=ENV-ROOFTOP-REFERENCE-COMPONENT-LIBRARY；2026-09-21 从 v002 主库导出 GLB(7bf9c80cf1c2) 并生成 runtime PackedScene；接入 100F 装饰布局＝120实例/6组（绿化20件blocking，其余visual_only）；布局源=art_source/environments/tower_zones/rooftop/source/layouts/100f_decorated_v001/rooftop_100f_decorated_layout_v001.json
A116: ENV-ROOFTOP-REF-HVAC-CABINET | B116: 机电箱 | E116: art_source/environments/tower_zones/rooftop/source/reference_components/v002/天台区块_参考组件库_v002.blend#机电箱_资产包 | F116: 独立资产包；05_空调与设备 | H116: 未创建 | I116: 独立包运行包装 | J116: 未创建 | K116: 2.400×1.160×2.100 m | L116: XY中心/底面0；-Y | M116: 天台参考组件库 / hvac_cabinet | N116: Blender源已完成 | O116: v002 | P116: 父库=ENV-ROOFTOP-REFERENCE-COMPONENT-LIBRARY；manifest=art_source/environments/tower_zones/rooftop/source/reference_components/v002/component_packages_v002/05/hvac_cabinet/asset_manifest.json；外墙植物包络不进入阻挡；未导入Godot。
A117: ENV-ROOFTOP-REF-HVAC-ELECTRIC | B117: 配电箱 | E117: art_source/environments/tower_zones/rooftop/source/reference_components/v002/天台区块_参考组件库_v002.blend#配电箱_资产包 | F117: 独立资产包；05_空调与设备 | H117: 未创建 | I117: 独立包运行包装 | J117: 未创建 | K117: 1.500×0.910×2.400 m | L117: XY中心/底面0；-Y | M117: 天台参考组件库 / hvac_electric | N117: Blender源已完成 | O117: v002 | P117: 父库=ENV-ROOFTOP-REFERENCE-COMPONENT-LIBRARY；manifest=art_source/environments/tower_zones/rooftop/source/reference_components/v002/component_packages_v002/05/hvac_electric/asset_manifest.json；外墙植物包络不进入阻挡；未导入Godot。
A118: ENV-ROOFTOP-REF-PIPE-STRAIGHT | B118: 直管段 | C118: assets/art/environments/tower_zones/rooftop/runtime/pipe_straight.tscn | D118: assets/art/environments/tower_zones/rooftop/components/env_rooftop_ref_pipe_straight_top3d.glb | E118: art_source/environments/tower_zones/rooftop/source/reference_components/v002/天台区块_参考组件库_v002.blend | F118: Godot视觉装饰PackedScene；100F天台房屋四周闭环水管（布局内 32 个实例），由 TowerFloorStage3D 按装饰布局清单实例化 | G118: src/world3d/TowerFloorStage3D.gd | H118: 无 | I118: 引擎（visual_only） | J118: 未创建 | K118: 2.640×0.410×0.410 m | L118: XY中心/底面0；-Y | M118: 100F天台装饰布局 / pipe_straight | N118: 正式美术已接入 | O118: v002 | P118: 父库=ENV-ROOFTOP-REFERENCE-COMPONENT-LIBRARY；2026-09-21 从 v002 主库导出 GLB(3138e3414ffb) 并生成 runtime PackedScene；接入 100F 装饰布局＝120实例/6组（绿化20件blocking，其余visual_only）；布局源=art_source/environments/tower_zones/rooftop/source/layouts/100f_decorated_v001/rooftop_100f_decorated_layout_v001.json
A119: ENV-ROOFTOP-REF-PIPE-ELBOW | B119: 转角弯管 | C119: assets/art/environments/tower_zones/rooftop/runtime/pipe_elbow.tscn | D119: assets/art/environments/tower_zones/rooftop/components/env_rooftop_ref_pipe_elbow_top3d.glb | E119: art_source/environments/tower_zones/rooftop/source/reference_components/v002/天台区块_参考组件库_v002.blend | F119: Godot视觉装饰PackedScene；100F天台闭环水管四角（布局内 4 个实例），由 TowerFloorStage3D 按装饰布局清单实例化 | G119: src/world3d/TowerFloorStage3D.gd | H119: 无 | I119: 引擎（visual_only） | J119: 未创建 | K119: 1.575×0.410×1.275 m | L119: XY中心/底面0；-Y | M119: 100F天台装饰布局 / pipe_elbow | N119: 正式美术已接入 | O119: v002 | P119: 父库=ENV-ROOFTOP-REFERENCE-COMPONENT-LIBRARY；2026-09-21 从 v002 主库导出 GLB(1f5e1a101fba) 并生成 runtime PackedScene；接入 100F 装饰布局＝120实例/6组（绿化20件blocking，其余visual_only）；布局源=art_source/environments/tower_zones/rooftop/source/layouts/100f_decorated_v001/rooftop_100f_decorated_layout_v001.json
A120: ENV-ROOFTOP-REF-PIPE-TEE | B120: 三通管 | C120: assets/art/environments/tower_zones/rooftop/runtime/pipe_tee.tscn | D120: assets/art/environments/tower_zones/rooftop/components/env_rooftop_ref_pipe_tee_top3d.glb | E120: art_source/environments/tower_zones/rooftop/source/reference_components/v002/天台区块_参考组件库_v002.blend | F120: Godot视觉装饰PackedScene；100F天台闭环水管灌溉分支（布局内 2 个实例），由 TowerFloorStage3D 按装饰布局清单实例化 | G120: src/world3d/TowerFloorStage3D.gd | H120: 无 | I120: 引擎（visual_only） | J120: 未创建 | K120: 2.640×0.410×1.355 m | L120: XY中心/底面0；-Y | M120: 100F天台装饰布局 / pipe_tee | N120: 正式美术已接入 | O120: v002 | P120: 父库=ENV-ROOFTOP-REFERENCE-COMPONENT-LIBRARY；2026-09-21 从 v002 主库导出 GLB(3ea17b1e98a6) 并生成 runtime PackedScene；接入 100F 装饰布局＝120实例/6组（绿化20件blocking，其余visual_only）；布局源=art_source/environments/tower_zones/rooftop/source/layouts/100f_decorated_v001/rooftop_100f_decorated_layout_v001.json
A121: ENV-ROOFTOP-REF-PIPE-RISER | B121: 立管下水管 | C121: assets/art/environments/tower_zones/rooftop/runtime/pipe_riser.tscn | D121: assets/art/environments/tower_zones/rooftop/components/env_rooftop_ref_pipe_riser_top3d.glb | E121: art_source/environments/tower_zones/rooftop/source/reference_components/v002/天台区块_参考组件库_v002.blend | F121: Godot视觉装饰PackedScene；100F天台闭环水管至地面立管（布局内 4 个实例），由 TowerFloorStage3D 按装饰布局清单实例化 | G121: src/world3d/TowerFloorStage3D.gd | H121: 无 | I121: 引擎（visual_only） | J121: 未创建 | K121: 0.795×0.485×4.945 m | L121: XY中心/底面0；-Y | M121: 100F天台装饰布局 / pipe_riser | N121: 正式美术已接入 | O121: v002 | P121: 父库=ENV-ROOFTOP-REFERENCE-COMPONENT-LIBRARY；2026-09-21 从 v002 主库导出 GLB(e815f0626f41) 并生成 runtime PackedScene；接入 100F 装饰布局＝120实例/6组（绿化20件blocking，其余visual_only）；布局源=art_source/environments/tower_zones/rooftop/source/layouts/100f_decorated_v001/rooftop_100f_decorated_layout_v001.json
A122: ENV-ROOFTOP-REF-PIPE-BRACKET | B122: 管道支架 | C122: assets/art/environments/tower_zones/rooftop/runtime/pipe_bracket.tscn | D122: assets/art/environments/tower_zones/rooftop/components/env_rooftop_ref_pipe_bracket_top3d.glb | E122: art_source/environments/tower_zones/rooftop/source/reference_components/v002/天台区块_参考组件库_v002.blend | F122: Godot视觉装饰PackedScene；100F天台立管墙面固定（布局内 4 个实例），由 TowerFloorStage3D 按装饰布局清单实例化 | G122: src/world3d/TowerFloorStage3D.gd | H122: 无 | I122: 引擎（visual_only） | J122: 未创建 | K122: 0.480×0.876×3.640 m | L122: XY中心/底面0；-Y | M122: 100F天台装饰布局 / pipe_bracket | N122: 正式美术已接入 | O122: v002 | P122: 父库=ENV-ROOFTOP-REFERENCE-COMPONENT-LIBRARY；2026-09-21 从 v002 主库导出 GLB(50f208d92e99) 并生成 runtime PackedScene；接入 100F 装饰布局＝120实例/6组（绿化20件blocking，其余visual_only）；布局源=art_source/environments/tower_zones/rooftop/source/layouts/100f_decorated_v001/rooftop_100f_decorated_layout_v001.json
A123: ENV-ROOFTOP-REF-DOOR-LAMP | B123: 门与暖灯 | E123: art_source/environments/tower_zones/rooftop/source/reference_components/v002/天台区块_参考组件库_v002.blend#门与暖灯_资产包 | F123: 厚门柱1.10m、门楣1.16m、门槛1.55m；门扇内凹；独立输出。 | H123: 未创建 | I123: 独立包运行包装 | J123: 未创建 | K123: 4.900×1.555×7.570 m | L123: XY中心/底面0；-Y | M123: 天台参考组件库 / door_lamp | N123: Blender源已完成 | O123: v002 | P123: 父库=ENV-ROOFTOP-REFERENCE-COMPONENT-LIBRARY；manifest=art_source/environments/tower_zones/rooftop/source/reference_components/v002/component_packages_v002/07/door_lamp/asset_manifest.json；外墙植物包络不进入阻挡；未导入Godot。
A124: ENV-ROOFTOP-REF-CANOPY | B124: 支撑雨棚 | E124: art_source/environments/tower_zones/rooftop/source/reference_components/v002/天台区块_参考组件库_v002.blend#支撑雨棚_资产包 | F124: 独立资产包；07_门与雨棚 | H124: 未创建 | I124: 独立包运行包装 | J124: 未创建 | K124: 5.000×2.800×2.186 m | L124: XY中心/底面0；-Y | M124: 天台参考组件库 / canopy | N124: Blender源已完成 | O124: v002 | P124: 父库=ENV-ROOFTOP-REFERENCE-COMPONENT-LIBRARY；manifest=art_source/environments/tower_zones/rooftop/source/reference_components/v002/component_packages_v002/07/canopy/asset_manifest.json；外墙植物包络不进入阻挡；未导入Godot。
A125: ENV-ROOFTOP-REF-IVY | B125: 墙面攀爬藤蔓 | C125: assets/art/environments/tower_zones/rooftop/runtime/ivy.tscn | D125: assets/art/environments/tower_zones/rooftop/components/env_rooftop_ref_ivy_top3d.glb | E125: art_source/environments/tower_zones/rooftop/source/reference_components/v002/天台区块_参考组件库_v002.blend | F125: Godot视觉装饰PackedScene；100F天台房屋墙面分段挂藤（布局内 11 个实例），由 TowerFloorStage3D 按装饰布局清单实例化 | G125: src/world3d/TowerFloorStage3D.gd | H125: 无 | I125: 引擎（visual_only） | J125: 未创建 | K125: 4.256×0.819×3.802 m | L125: XY中心/底面0；-Y | M125: 100F天台装饰布局 / ivy | N125: 正式美术已接入 | O125: v002 | P125: 父库=ENV-ROOFTOP-REFERENCE-COMPONENT-LIBRARY；2026-09-21 从 v002 主库导出 GLB(8c54feeec0f7) 并生成 runtime PackedScene；接入 100F 装饰布局＝120实例/6组（绿化20件blocking，其余visual_only）；布局源=art_source/environments/tower_zones/rooftop/source/layouts/100f_decorated_v001/rooftop_100f_decorated_layout_v001.json
A126: ENV-ROOFTOP-REF-FLOWERBOX | B126: 长条花箱 | C126: assets/art/environments/tower_zones/rooftop/runtime/flowerbox.tscn | D126: assets/art/environments/tower_zones/rooftop/components/env_rooftop_ref_flowerbox_top3d.glb | E126: art_source/environments/tower_zones/rooftop/source/reference_components/v002/天台区块_参考组件库_v002.blend | F126: Godot视觉装饰PackedScene；100F天台房屋四周贴墙长条花箱（布局内 6 个实例），由 TowerFloorStage3D 按装饰布局清单实例化 | G126: src/world3d/TowerFloorStage3D.gd | H126: 无 | I126: 引擎（visual_only） | J126: 未创建 | K126: 4.500×1.185×2.134 m | L126: XY中心/底面0；-Y | M126: 100F天台装饰布局 / flowerbox | N126: 正式美术已接入 | O126: v002 | P126: 父库=ENV-ROOFTOP-REFERENCE-COMPONENT-LIBRARY；2026-09-21 从 v002 主库导出 GLB(8e7f91af2221) 并生成 runtime PackedScene；接入 100F 装饰布局＝120实例/6组（绿化20件blocking，其余visual_only）；布局源=art_source/environments/tower_zones/rooftop/source/layouts/100f_decorated_v001/rooftop_100f_decorated_layout_v001.json
A127: ENV-ROOFTOP-REF-PLANT-LARGE | B127: 大盆栽 | C127: assets/art/environments/tower_zones/rooftop/runtime/plant_large.tscn | D127: assets/art/environments/tower_zones/rooftop/components/env_rooftop_ref_plant_large_top3d.glb | E127: art_source/environments/tower_zones/rooftop/source/reference_components/v002/天台区块_参考组件库_v002.blend | F127: Godot视觉装饰PackedScene；100F天台房屋周边高点盆栽（布局内 6 个实例），由 TowerFloorStage3D 按装饰布局清单实例化 | G127: src/world3d/TowerFloorStage3D.gd | H127: 无 | I127: 引擎（visual_only） | J127: 未创建 | K127: 1.547×1.745×2.772 m | L127: XY中心/底面0；-Y | M127: 100F天台装饰布局 / plant_large | N127: 正式美术已接入 | O127: v002 | P127: 父库=ENV-ROOFTOP-REFERENCE-COMPONENT-LIBRARY；2026-09-21 从 v002 主库导出 GLB(138135d836c3) 并生成 runtime PackedScene；接入 100F 装饰布局＝120实例/6组（绿化20件blocking，其余visual_only）；布局源=art_source/environments/tower_zones/rooftop/source/layouts/100f_decorated_v001/rooftop_100f_decorated_layout_v001.json
A128: ENV-ROOFTOP-REF-PLANT-SMALL | B128: 小盆栽 | C128: assets/art/environments/tower_zones/rooftop/runtime/plant_small.tscn | D128: assets/art/environments/tower_zones/rooftop/components/env_rooftop_ref_plant_small_top3d.glb | E128: art_source/environments/tower_zones/rooftop/source/reference_components/v002/天台区块_参考组件库_v002.blend | F128: Godot视觉装饰PackedScene；100F天台房屋周边低点盆栽（布局内 6 个实例），由 TowerFloorStage3D 按装饰布局清单实例化 | G128: src/world3d/TowerFloorStage3D.gd | H128: 无 | I128: 引擎（visual_only） | J128: 未创建 | K128: 1.096×1.095×1.482 m | L128: XY中心/底面0；-Y | M128: 100F天台装饰布局 / plant_small | N128: 正式美术已接入 | O128: v002 | P128: 父库=ENV-ROOFTOP-REFERENCE-COMPONENT-LIBRARY；2026-09-21 从 v002 主库导出 GLB(917d1ee05228) 并生成 runtime PackedScene；接入 100F 装饰布局＝120实例/6组（绿化20件blocking，其余visual_only）；布局源=art_source/environments/tower_zones/rooftop/source/layouts/100f_decorated_v001/rooftop_100f_decorated_layout_v001.json
A129: ENV-ROOFTOP-REF-DETAIL-MAT | B129: 编织门垫 | E129: art_source/environments/tower_zones/rooftop/source/reference_components/v002/天台区块_参考组件库_v002.blend#编织门垫_资产包 | F129: 独立资产包；09_细节附件 | H129: 未创建 | I129: 独立包运行包装 | J129: 未创建 | K129: 3.000×1.650×0.100 m | L129: XY中心/底面0；-Y | M129: 天台参考组件库 / detail_mat | N129: Blender源已完成 | O129: v002 | P129: 父库=ENV-ROOFTOP-REFERENCE-COMPONENT-LIBRARY；manifest=art_source/environments/tower_zones/rooftop/source/reference_components/v002/component_packages_v002/09/detail_mat/asset_manifest.json；外墙植物包络不进入阻挡；未导入Godot。
A130: ENV-ROOFTOP-REF-DETAIL-DRAIN | B130: 排水格栅 | E130: art_source/environments/tower_zones/rooftop/source/reference_components/v002/天台区块_参考组件库_v002.blend#排水格栅_资产包 | F130: 独立资产包；09_细节附件 | H130: 未创建 | I130: 独立包运行包装 | J130: 未创建 | K130: 1.200×1.200×0.200 m | L130: XY中心/底面0；-Y | M130: 天台参考组件库 / detail_drain | N130: Blender源已完成 | O130: v002 | P130: 父库=ENV-ROOFTOP-REFERENCE-COMPONENT-LIBRARY；manifest=art_source/environments/tower_zones/rooftop/source/reference_components/v002/component_packages_v002/09/detail_drain/asset_manifest.json；外墙植物包络不进入阻挡；未导入Godot。
A131: ENV-ROOFTOP-REF-DETAIL-VENT | B131: 墙面通风箱 | E131: art_source/environments/tower_zones/rooftop/source/reference_components/v002/天台区块_参考组件库_v002.blend#墙面通风箱_资产包 | F131: 独立资产包；09_细节附件 | H131: 未创建 | I131: 独立包运行包装 | J131: 未创建 | K131: 1.800×0.890×1.440 m | L131: XY中心/底面0；-Y | M131: 天台参考组件库 / detail_vent | N131: Blender源已完成 | O131: v002 | P131: 父库=ENV-ROOFTOP-REFERENCE-COMPONENT-LIBRARY；manifest=art_source/environments/tower_zones/rooftop/source/reference_components/v002/component_packages_v002/09/detail_vent/asset_manifest.json；外墙植物包络不进入阻挡；未导入Godot。
...

Sheet 3D-设施
A1: ShellStorm2 · 设施组件 3D Prefab
A2: 门扇、终端、工作台、储物与服务设施；设施模型统一引用 assets/art/shared/palette/设施低亮多巴胺色盘_10x10_512.png。
A4: AssetID | B4: 中文名 | C4: Prefab路径 | D4: GLB模型路径 | E4: Blender源文件 | F4: 功能说明 | G4: 功能脚本路径 | H4: 碰撞开关 | I4: 碰撞归属 | J4: 碰撞方式 | K4: 标准尺寸 | L4: 原点与朝向 | M4: 使用位置 | N4: 制作状态 | O4: 版本 | P4: 备注
A5: PRP-BASE-FACILITY-3D | B5: 基地设施3D通用模块 | C5: assets/art/props/base_world_3d/prp_base_facility_root_top3d_v001.tscn | F5: 设施或交互Prefab；保留自身脚本、碰撞和状态接口 | G5: src/base3d/BaseFacility3D.gd | H5: 开 | I5: Prefab自身 | J5: BoxShape3D | K5: PackedScene/材质变体/名称与实时摘要共用Label3D | L5: 未声明 | M5: 8类基地设施/统一状态牌 | N5: 原型已接入 | O5: v001 | P5: 根节点=BaseFacility3D(Area3D)
A6: PRP-BASE-VENDING-MACHINE-3D | B6: 基地科幻自动贩卖机 | C6: assets/art/props/base_world_3d/prp_base_vending_machine_root_top3d_v001.tscn | E6: ../ShellStorm2-backup/2026-10-11_slimming/original_tree/art_source/props/base_world_3d/source/vending_machine/prp_base_vending_machine_source_v001.blend | F6: 设施或交互Prefab；保留自身脚本、碰撞和状态接口 | G6: src/base3d/BaseFacility3D.gd | H6: 开 | I6: Prefab自身 | J6: BoxShape3D | K6: 4材质；主体/自发光分离；独立GLB/PackedScene | L6: 未声明 | M6: BaseWorld3D/TowerDescent99F | N6: 正式美术已接入 | O6: v002 | P6: 根节点=BaseVendingMachine3D(Area3D)；资产主表当前Prefab=assets/art/props/base_world_3d/runtime/vending_machine/prp_base_vending_machine_root_top3d_v002.tscn；旧版Prefab保留用于回滚；正式版本为v002
A7: PRP-DUNGEON-GATE-3D | B7: 地下城入口3D模块 | C7: assets/art/props/base_world_3d/prp_dungeon_gate_root_top3d_v001.tscn | F7: 设施或交互Prefab；保留自身脚本、碰撞和状态接口 | G7: src/base3d/DungeonEntrance3D.gd | H7: 开 | I7: Prefab自身 | J7: BoxShape3D | K7: PackedScene/材质变体 | L7: 未声明 | M7: 4个地下城入口 | N7: 原型已接入 | O7: v001 | P7: 根节点=DungeonEntrance3D(Area3D)
